Workbook

Sheet 📋 Параметры
A1: 🏢 КАЛЬКУЛЯТОР БЮДЖЕТА ЖК — Параметры объекта
A3: Жёлтый | B3: Ввод данных (заполните) | C3: Голубой | D3: Формула (не трогайте) | E3: Зелёный | F3: Итоговый результат
A5: А. ОСНОВНАЯ ИНФОРМАЦИЯ ОБ ОБЪЕКТЕ
A6: Название ЖК | B6: Новый объект
A7: Город / регион | B7: Санкт-Петербург
A8: Количество корпусов | B8: 4
A9: Общая площадь МОП, м² | B9: 12000
A10: Площадь территории, м² | B10: 8000
A11: Площадь УДС, м² | B11: 5000
A12: Количество квартир | B12: 500
A13: Этажность (средняя) | B13: 17
A14: Дата начала контракта | B14: 01.07.2026
A15: Срок контракта, лет | B15: 1
A17: Б. НАПРАВЛЕНИЯ УСЛУГ (отметьте ДА/НЕТ)
A18: МОП — уборка МКД | B18: ДА
A19: ПТ — территория, озеленение | B19: ДА
A20: УДС — уборка дорог/проездов | B20: НЕТ
A21: Снегоуборка | B21: ДА
A22: Доп. услуги | B22: НЕТ
A24: В. НАЛОГИ И СТАВКИ
A25: Режим налогообложения | B25: УСН 6%
A26: Ставка НДС | B26: 0.05
A27: Ставка УСН (% от выручки) | B27: 0.015
A28: Ставка НДФЛ | B28: 0.13
A29: Ставка страх. взносов (РФ, до МРОТ×2) | B29: 0.3
A30: Ставка страх. взносов (выше МРОТ×2) | B30: 0.15
A31: Ставка страх. взносов (СНГ) | B31: 0.243
A32: Налог на прибыль (в КП) | B32: 0.15
A34: Г. КОММЕРЧЕСКИЕ ПАРАМЕТРЫ (структура КП)
A35: Накладные расходы (% от себест.) | B35: 0.15
A36: Целевая прибыль (% от себест.) | B36: 0.2
A37: Целевая рент. чистой прибыли | B37: 0.2
A38: Расходы бэк-офиса (% от выручки) | B38: 0.08
A39: Расходы управления (% от выручки) | B39: 0.04
A41: Д. СЕЗОННОСТЬ
A42: Летние месяцы (апр–сен) | B42: 6 | C42: мес.
A43: Зимние месяцы (окт–мар) | B43: 6 | C43: мес.
A44: Месяцев снегоуборки | B44: 5 | C44: мес.
A47: 📌 КАК ПОЛЬЗОВАТЬСЯ: 1. Заполните жёлтые ячейки на этом листе 2. Перейдите на лист «👥 Расчёт ФОТ» — укажите штат сотрудников 3. На листе «📊 Смета + КП» проверьте себестоимость и цену контракта 4. Лист «💰 П&Л» покажет помесячный P&L (как в ПланФакте) 5. Итоги на листе «🎯 Итоги»

Sheet 👥 Расчёт ФОТ
A1: 👥 РАСЧЁТ ФОТ ПО НАПРАВЛЕНИЯМ
A3: Ставки (из листа Параметры):
A4: НДФЛ: | B4: ='📋 Параметры'!B28
A5: СВ РФ (до порога): | B5: ='📋 Параметры'!B29
A6: СВ (выше порога): | B6: ='📋 Параметры'!B30
A7: СВ СНГ: | B7: ='📋 Параметры'!B31
A9: Должность | B9: Кол-во (лето) | C9: Кол-во (зима) | D9: ЗП на руки (1 чел.) | E9: ЗП gross (1 чел.) | F9: НДФЛ (1 чел.) | G9: Ставка СВ% | H9: СВ (1 чел.) | I9: Расход/мес (лето) | J9: Расход/мес (зима)
A10: МОП — УБОРКА МКД
A11: Уборщик производственных помещений | B11: 4 | C11: 4 | D11: 60000 | E11: =IF(D11=0,0,D11/(1-B4)) | F11: =IF(E11=0,0,E11*B4) | G11: =B5 | H11: =IF(E11=0,0,E11*G11) | I11: =IF(B11=0,0,(E11+H11)*B11) | J11: =IF(C11=0,0,(E11+H11)*C11)
A12: Уборщик (сменный) | D12: 60000 | E12: =IF(D12=0,0,D12/(1-B4)) | F12: =IF(E12=0,0,E12*B4) | G12: =B5 | H12: =IF(E12=0,0,E12*G12) | I12: =IF(B12=0,0,(E12+H12)*B12) | J12: =IF(C12=0,0,(E12+H12)*C12)
A13: Уборщик холлов и лифтов | D13: 55000 | E13: =IF(D13=0,0,D13/(1-B4)) | F13: =IF(E13=0,0,E13*B4) | G13: =B5 | H13: =IF(E13=0,0,E13*G13) | I13: =IF(B13=0,0,(E13+H13)*B13) | J13: =IF(C13=0,0,(E13+H13)*C13)
A14: ОПМ (оператор профмашины) | D14: 65000 | E14: =IF(D14=0,0,D14/(1-B4)) | F14: =IF(E14=0,0,E14*B4) | G14: =B5 | H14: =IF(E14=0,0,E14*G14) | I14: =IF(B14=0,0,(E14+H14)*B14) | J14: =IF(C14=0,0,(E14+H14)*C14)
A15: Администратор/старший смены | B15: 1 | C15: 1 | D15: 80000 | E15: =IF(D15=0,0,D15/(1-B4)) | F15: =IF(E15=0,0,E15*B4) | G15: =B5 | H15: =IF(E15=0,0,E15*G15) | I15: =IF(B15=0,0,(E15+H15)*B15) | J15: =IF(C15=0,0,(E15+H15)*C15)
A16: ИТОГО МОП | B16: =SUM(B11,B12,B13,B14,B15) | C16: =SUM(C11,C12,C13,C14,C15) | I16: =SUM(I11,I12,I13,I14,I15) | J16: =SUM(J11,J12,J13,J14,J15)
A18: ПТ — ТЕРРИТОРИЯ И ОЗЕЛЕНЕНИЕ
A19: Дворник | B19: 3 | C19: 4 | D19: 80000 | E19: =IF(D19=0,0,D19/(1-B4)) | F19: =IF(E19=0,0,E19*B4) | G19: =B5 | H19: =IF(E19=0,0,E19*G19) | I19: =IF(B19=0,0,(E19+H19)*B19) | J19: =IF(C19=0,0,(E19+H19)*C19)
A20: Дворник-тракторист | D20: 90000 | E20: =IF(D20=0,0,D20/(1-B4)) | F20: =IF(E20=0,0,E20*B4) | G20: =B5 | H20: =IF(E20=0,0,E20*G20) | I20: =IF(B20=0,0,(E20+H20)*B20) | J20: =IF(C20=0,0,(E20+H20)*C20)
A21: Бригадир | B21: 1 | C21: 1 | D21: 80000 | E21: =IF(D21=0,0,D21/(1-B4)) | F21: =IF(E21=0,0,E21*B4) | G21: =B5 | H21: =IF(E21=0,0,E21*G21) | I21: =IF(B21=0,0,(E21+H21)*B21) | J21: =IF(C21=0,0,(E21+H21)*C21)
A22: Садовник | D22: 70000 | E22: =IF(D22=0,0,D22/(1-B4)) | F22: =IF(E22=0,0,E22*B4) | G22: =B5 | H22: =IF(E22=0,0,E22*G22) | I22: =IF(B22=0,0,(E22+H22)*B22) | J22: =IF(C22=0,0,(E22+H22)*C22)
A23: Администратор | D23: 120000 | E23: =IF(D23=0,0,D23/(1-B4)) | F23: =IF(E23=0,0,E23*B4) | G23: =B5 | H23: =IF(E23=0,0,E23*G23) | I23: =IF(B23=0,0,(E23+H23)*B23) | J23: =IF(C23=0,0,(E23+H23)*C23)
A24: ИТОГО ПТ | B24: =SUM(B19,B20,B21,B22,B23) | C24: =SUM(C19,C20,C21,C22,C23) | I24: =SUM(I19,I20,I21,I22,I23) | J24: =SUM(J19,J20,J21,J22,J23)
A26: УДС — УБОРКА ДОРОГ И ПРОЕЗДОВ
A27: Дворник | D27: 80000 | E27: =IF(D27=0,0,D27/(1-B4)) | F27: =IF(E27=0,0,E27*B4) | G27: =B5 | H27: =IF(E27=0,0,E27*G27) | I27: =IF(B27=0,0,(E27+H27)*B27) | J27: =IF(C27=0,0,(E27+H27)*C27)
A28: Тракторист | D28: 90000 | E28: =IF(D28=0,0,D28/(1-B4)) | F28: =IF(E28=0,0,E28*B4) | G28: =B5 | H28: =IF(E28=0,0,E28*G28) | I28: =IF(B28=0,0,(E28+H28)*B28) | J28: =IF(C28=0,0,(E28+H28)*C28)
A29: Бригадир | D29: 80000 | E29: =IF(D29=0,0,D29/(1-B4)) | F29: =IF(E29=0,0,E29*B4) | G29: =B5 | H29: =IF(E29=0,0,E29*G29) | I29: =IF(B29=0,0,(E29+H29)*B29) | J29: =IF(C29=0,0,(E29+H29)*C29)
A30: Администратор | D30: 120000 | E30: =IF(D30=0,0,D30/(1-B4)) | F30: =IF(E30=0,0,E30*B4) | G30: =B5 | H30: =IF(E30=0,0,E30*G30) | I30: =IF(B30=0,0,(E30+H30)*B30) | J30: =IF(C30=0,0,(E30+H30)*C30)
A31: ИТОГО УДС | B31: =SUM(B27,B28,B29,B30) | C31: =SUM(C27,C28,C29,C30) | I31: =SUM(I27,I28,I29,I30) | J31: =SUM(J27,J28,J29,J30)
A33: АУП — УПРАВЛЕНИЕ ОБЪЕКТОМ
A34: Менеджер объекта | B34: 1 | C34: 1 | D34: 80000 | E34: =IF(D34=0,0,D34/(1-B4)) | F34: =IF(E34=0,0,E34*B4) | G34: =B5 | H34: =IF(E34=0,0,E34*G34) | I34: =IF(B34=0,0,(E34+H34)*B34) | J34: =IF(C34=0,0,(E34+H34)*C34)
A35: Менеджер разъездной (доля) | D35: 120000 | E35: =IF(D35=0,0,D35/(1-B4)) | F35: =IF(E35=0,0,E35*B4) | G35: =B5 | H35: =IF(E35=0,0,E35*G35) | I35: =IF(B35=0,0,(E35+H35)*B35) | J35: =IF(C35=0,0,(E35+H35)*C35)
A36: ИТОГО АУП | B36: =SUM(B34,B35) | C36: =SUM(C34,C35) | I36: =SUM(I34,I35) | J36: =SUM(J34,J35)
A38: ИТОГО ФОТ ПО ВСЕМ НАПРАВЛЕНИЯМ (с налогами)
A39: Всего ФОТ — ЛЕТНИЙ месяц | I39: =I16+I24+I31+I36
A40: Всего ФОТ — ЗИМНИЙ месяц | J40: =J16+J24+J31+J36
A41: Среднегодовой ФОТ/мес | I41: =(I39*'📋 Параметры'!B42+J40*'📋 Параметры'!B43)/12
A43: Итого ЗП на руки / мес (лето) | B43: =SUMPRODUCT(B10:B36,D10:D36)
A44: Итого ЗП на руки / мес (зима) | B44: =SUMPRODUCT(C10:C36,D10:D36)

Sheet 📊 Смета + КП
A1: 📊 СМЕТА И РАСЧЁТ ЦЕНЫ КОНТРАКТА
A3: Статья затрат | B3: Лето/мес | C3: Зима/мес | D3: Среднегод./мес | E3: % от себест.
A4: А. ФОТ (из листа «Расчёт ФОТ»)
A5: ⚠️ Заполните ячейки «Лето/мес» и «Зима/мес» вручную из листа «👥 Расчёт ФОТ» (строки ИТОГО по направлениям), ИЛИ удалите значения — тогда используйте формулы ниже.
A6: ФОТ МОП (с налогами) | B6: 0 | C6: 0 | D6: =(B6*'📋 Параметры'!B42+C6*'📋 Параметры'!B43)/12
A7: ФОТ ПТ (с налогами) | B7: 0 | C7: 0 | D7: =(B7*'📋 Параметры'!B42+C7*'📋 Параметры'!B43)/12
A8: ФОТ УДС (с налогами) | B8: 0 | C8: 0 | D8: =(B8*'📋 Параметры'!B42+C8*'📋 Параметры'!B43)/12
A9: ФОТ АУП (с налогами) | B9: 0 | C9: 0 | D9: =(B9*'📋 Параметры'!B42+C9*'📋 Параметры'!B43)/12
A10: ИТОГО ФОТ | B10: =SUM(B6,B7,B8,B9) | C10: =SUM(C6,C7,C8,C9) | D10: =SUM(D6,D7,D8,D9)
A12: Б. ПРОЧИЕ ПРЯМЫЕ ЗАТРАТЫ
A13: Расходные материалы и моющие средства | B13: 20000 | C13: 20000 | D13: =(B13*'📋 Параметры'!B42+C13*'📋 Параметры'!B43)/12
A14: Сыпучие материалы (ПТ, сезонно) | B14: 10000 | C14: 30000 | D14: =(B14*'📋 Параметры'!B42+C14*'📋 Параметры'!B43)/12
A15: Малый инвентарь (лопаты, грабли, мётлы) | B15: 5000 | C15: 5000 | D15: =(B15*'📋 Параметры'!B42+C15*'📋 Параметры'!B43)/12
A16: Обслуживание и ремонт техники | B16: 5000 | C16: 5000 | D16: =(B16*'📋 Параметры'!B42+C16*'📋 Параметры'!B43)/12
A17: Спецодежда и обувь (в мес.) | B17: 3000 | C17: 4000 | D17: =(B17*'📋 Параметры'!B42+C17*'📋 Параметры'!B43)/12
A18: Вывоз мусора | D18: =(B18*'📋 Параметры'!B42+C18*'📋 Параметры'!B43)/12
A19: Прочие прямые расходы | D19: =(B19*'📋 Параметры'!B42+C19*'📋 Параметры'!B43)/12
A20: ИТОГО прочие прямые | B20: =SUM(B13+B14+B15+B16+B17+B18+B19) | C20: =SUM(C13+C14+C15+C16+C17+C18+C19) | D20: =SUM(D13,D14,D15,D16,D17,D18,D19)
A22: В. СЕБЕСТОИМОСТЬ
A23: ИТОГО СЕБЕСТОИМОСТЬ | B23: =B10+B20 | C23: =C10+C20 | D23: =D10+D20 | E23: 100%
A25: Г. РАСЧЁТ ЦЕНЫ КОНТРАКТА (по методологии Опенбук)
A26: Накладные расходы (%) | D26: =D23*'📋 Параметры'!B35 | E26: ='📋 Параметры'!B35
A27: Прибыль (%) | D27: =D23*'📋 Параметры'!B37 | E27: ='📋 Параметры'!B28
A28: Налог на прибыль (15%) | D28: =D23*'📋 Параметры'!B36*'📋 Параметры'!B32 | E28: 15%
A29: Стоимость контракта БЕЗ НДС/мес | D29: =D23+D26+D27+D28
A30: НДС 5%/мес | D30: =D29*'📋 Параметры'!B26
A31: ★ СТОИМОСТЬ КОНТРАКТА С НДС/мес | D31: =D29+D30
A33: Д. КЛЮЧЕВЫЕ ПОКАЗАТЕЛИ
A34: Себестоимость/мес (среднегод.) | D34: =D23
A35: Цена контракта/мес (с НДС) | D35: =D31
A36: Чистая прибыль/мес (до КП-метода) | D36: =D31-D23-D30-D23*'📋 Параметры'!B36*'📋 Параметры'!B32
A37: Рентабельность ЧП (от цены без НДС) | D37: =IFERROR((D29-D23)/ D29,0)
A38: ФОТ / Выручка | D38: =IFERROR(D10/D31,0)

Sheet 💰 П&Л
A1: 💰 П&Л — ОТЧЁТ О ПРИБЫЛЯХ И УБЫТКАХ (по месяцам)
A3: Статья | B3: Янв | C3: Фев | D3: Мар | E3: Апр | F3: Май | G3: Июн | H3: Июл | I3: Авг | J3: Сен | K3: Окт | L3: Ноя | M3: Дек | N3: Итого
A4: ВЫРУЧКА
A5: Контракт МОП (с НДС) | B5: 0 | C5: 0 | D5: 0 | E5: 0 | F5: 0 | G5: 0 | H5: 0 | I5: 0 | J5: 0 | K5: 0 | L5: 0 | M5: 0 | N5: =SUM(B5,C5,D5,E5,F5,G5,H5,I5,J5,K5,L5,M5)
A6: Контракт ПТ (с НДС) | B6: 0 | C6: 0 | D6: 0 | E6: 0 | F6: 0 | G6: 0 | H6: 0 | I6: 0 | J6: 0 | K6: 0 | L6: 0 | M6: 0 | N6: =SUM(B6,C6,D6,E6,F6,G6,H6,I6,J6,K6,L6,M6)
A7: Контракт УДС (с НДС) | B7: 0 | C7: 0 | D7: 0 | E7: 0 | F7: 0 | G7: 0 | H7: 0 | I7: 0 | J7: 0 | K7: 0 | L7: 0 | M7: 0 | N7: =SUM(B7,C7,D7,E7,F7,G7,H7,I7,J7,K7,L7,M7)
A8: Доп. услуги / снег | B8: 0 | C8: 0 | D8: 0 | E8: 0 | F8: 0 | G8: 0 | H8: 0 | I8: 0 | J8: 0 | K8: 0 | L8: 0 | M8: 0 | N8: =SUM(B8,C8,D8,E8,F8,G8,H8,I8,J8,K8,L8,M8)
A9: ИТОГО ВЫРУЧКА | B9: =SUM(B5,B6,B7,B8) | C9: =SUM(C5,C6,C7,C8) | D9: =SUM(D5,D6,D7,D8) | E9: =SUM(E5,E6,E7,E8) | F9: =SUM(F5,F6,F7,F8) | G9: =SUM(G5,G6,G7,G8) | H9: =SUM(H5,H6,H7,H8) | I9: =SUM(I5,I6,I7,I8) | ... N9: =SUM(N5,N6,N7,N8)
A11: ПРЯМЫЕ РАСХОДЫ
A12: ФОТ МОП (с налогами) | B12: 0 | C12: 0 | D12: 0 | E12: 0 | F12: 0 | G12: 0 | H12: 0 | I12: 0 | J12: 0 | K12: 0 | L12: 0 | M12: 0 | N12: =SUM(B12,C12,D12,E12,F12,G12,H12,I12,J12,K12,L12,M12)
A13: ФОТ ПТ (с налогами) | B13: 0 | C13: 0 | D13: 0 | E13: 0 | F13: 0 | G13: 0 | H13: 0 | I13: 0 | J13: 0 | K13: 0 | L13: 0 | M13: 0 | N13: =SUM(B13,C13,D13,E13,F13,G13,H13,I13,J13,K13,L13,M13)
A14: ФОТ УДС (с налогами) | B14: 0 | C14: 0 | D14: 0 | E14: 0 | F14: 0 | G14: 0 | H14: 0 | I14: 0 | J14: 0 | K14: 0 | L14: 0 | M14: 0 | N14: =SUM(B14,C14,D14,E14,F14,G14,H14,I14,J14,K14,L14,M14)
A15: ФОТ АУП | B15: 0 | C15: 0 | D15: 0 | E15: 0 | F15: 0 | G15: 0 | H15: 0 | I15: 0 | J15: 0 | K15: 0 | L15: 0 | M15: 0 | N15: =SUM(B15,C15,D15,E15,F15,G15,H15,I15,J15,K15,L15,M15)
A16: Переменные (материалы, расходники) | B16: 0 | C16: 0 | D16: 0 | E16: 0 | F16: 0 | G16: 0 | H16: 0 | I16: 0 | J16: 0 | K16: 0 | L16: 0 | M16: 0 | N16: =SUM(B16,C16,D16,E16,F16,G16,H16,I16,J16,K16,L16,M16)
A17: Обслуживание техники | B17: 0 | C17: 0 | D17: 0 | E17: 0 | F17: 0 | G17: 0 | H17: 0 | I17: 0 | J17: 0 | K17: 0 | L17: 0 | M17: 0 | N17: =SUM(B17,C17,D17,E17,F17,G17,H17,I17,J17,K17,L17,M17)
A18: Спецодежда / инвентарь | B18: 0 | C18: 0 | D18: 0 | E18: 0 | F18: 0 | G18: 0 | H18: 0 | I18: 0 | J18: 0 | K18: 0 | L18: 0 | M18: 0 | N18: =SUM(B18,C18,D18,E18,F18,G18,H18,I18,J18,K18,L18,M18)
A19: Прочие прямые расходы | B19: 0 | C19: 0 | D19: 0 | E19: 0 | F19: 0 | G19: 0 | H19: 0 | I19: 0 | J19: 0 | K19: 0 | L19: 0 | M19: 0 | N19: =SUM(B19,C19,D19,E19,F19,G19,H19,I19,J19,K19,L19,M19)
A20: ИТОГО ПРЯМЫЕ РАСХОДЫ | B20: =SUM(B12,B13,B14,B15,B16,B17,B18,B19) | C20: =SUM(C12,C13,C14,C15,C16,C17,C18,C19) | D20: =SUM(D12,D13,D14,D15,D16,D17,D18,D19) | E20: =SUM(E12,E13,E14,E15,E16,E17,E18,E19) | F20: =SUM(F12,F13,F14,F15,F16,F17,F18,F19) | G20: =SUM(G12,G13,G14,G15,G16,G17,G18,G19) | H20: =SUM(H12,H13,H14,H15,H16,H17,H18,H19) | I20: =SUM(I12,I13,I14,I15,I16,I17,I18,I19) | ... N20: =SUM(N12,N13,N14,N15,N16,N17,N18,N19)
A21: ВАЛОВАЯ ПРИБЫЛЬ | B21: =B9-B20 | C21: =C9-C20 | D21: =D9-D20 | E21: =E9-E20 | F21: =F9-F20 | G21: =G9-G20 | H21: =H9-H20 | I21: =I9-I20 | ... N21: =N9-N20
A22: Валовая рентабельность | B22: =IFERROR(B21/B9,0) | C22: =IFERROR(C21/C9,0) | D22: =IFERROR(D21/D9,0) | E22: =IFERROR(E21/E9,0) | F22: =IFERROR(F21/F9,0) | G22: =IFERROR(G21/G9,0) | H22: =IFERROR(H21/H9,0) | I22: =IFERROR(I21/I9,0) | ... N22: =IFERROR(N21/N9,0)
A24: КОСВЕННЫЕ РАСХОДЫ (Бэк-офис + Управление)
A25: Расходы Бэк-Офис (% от выручки) | B25: =B9*'📋 Параметры'!B38 | C25: =C9*'📋 Параметры'!B38 | D25: =D9*'📋 Параметры'!B38 | E25: =E9*'📋 Параметры'!B38 | F25: =F9*'📋 Параметры'!B38 | G25: =G9*'📋 Параметры'!B38 | H25: =H9*'📋 Параметры'!B38 | I25: =I9*'📋 Параметры'!B38 | J25: =J9*'📋 Параметры'!B38 | K25: =K9*'📋 Параметры'!B38 | L25: =L9*'📋 Параметры'!B38 | M25: =M9*'📋 Параметры'!B38 | N25: =SUM(B25,C25,D25,E25,F25,G25,H25,I25,J25,K25,L25,M25)
A26: Расходы управления (% от выручки) | B26: =B9*'📋 Параметры'!B39 | C26: =C9*'📋 Параметры'!B39 | D26: =D9*'📋 Параметры'!B39 | E26: =E9*'📋 Параметры'!B39 | F26: =F9*'📋 Параметры'!B39 | G26: =G9*'📋 Параметры'!B39 | H26: =H9*'📋 Параметры'!B39 | I26: =I9*'📋 Параметры'!B39 | J26: =J9*'📋 Параметры'!B39 | K26: =K9*'📋 Параметры'!B39 | L26: =L9*'📋 Параметры'!B39 | M26: =M9*'📋 Параметры'!B39 | N26: =SUM(B26,C26,D26,E26,F26,G26,H26,I26,J26,K26,L26,M26)
A27: Прочие административные | B27: 0 | C27: 0 | D27: 0 | E27: 0 | F27: 0 | G27: 0 | H27: 0 | I27: 0 | J27: 0 | K27: 0 | L27: 0 | M27: 0 | N27: =SUM(B27,C27,D27,E27,F27,G27,H27,I27,J27,K27,L27,M27)
A28: ИТОГО КОСВЕННЫЕ | B28: =SUM(B25,B26,B27) | C28: =SUM(C25,C26,C27) | D28: =SUM(D25,D26,D27) | E28: =SUM(E25,E26,E27) | F28: =SUM(F25,F26,F27) | G28: =SUM(G25,G26,G27) | H28: =SUM(H25,H26,H27) | I28: =SUM(I25,I26,I27) | ... N28: =SUM(N25,N26,N27)
A29: ОПЕРАЦИОННАЯ ПРИБЫЛЬ | B29: =B21-B28 | C29: =C21-C28 | D29: =D21-D28 | E29: =E21-E28 | F29: =F21-F28 | G29: =G21-G28 | H29: =H21-H28 | I29: =I21-I28 | ... N29: =N21-N28
A30: Операционная рентабельность | B30: =IFERROR(B29/B9,0) | C30: =IFERROR(C29/C9,0) | D30: =IFERROR(D29/D9,0) | E30: =IFERROR(E29/E9,0) | F30: =IFERROR(F29/F9,0) | G30: =IFERROR(G29/G9,0) | H30: =IFERROR(H29/H9,0) | I30: =IFERROR(I29/I9,0) | ... N30: =IFERROR(N29/N9,0)
A32: НАЛОГИ
A33: НДС 5% (от выручки) | B33: =B9*'📋 Параметры'!B26 | C33: =C9*'📋 Параметры'!B26 | D33: =D9*'📋 Параметры'!B26 | E33: =E9*'📋 Параметры'!B26 | F33: =F9*'📋 Параметры'!B26 | G33: =G9*'📋 Параметры'!B26 | H33: =H9*'📋 Параметры'!B26 | I33: =I9*'📋 Параметры'!B26 | J33: =J9*'📋 Параметры'!B26 | K33: =K9*'📋 Параметры'!B26 | L33: =L9*'📋 Параметры'!B26 | M33: =M9*'📋 Параметры'!B26 | N33: =SUM(B33,C33,D33,E33,F33,G33,H33,I33,J33,K33,L33,M33)
A34: УСН | B34: =B9*'📋 Параметры'!B27 | C34: =C9*'📋 Параметры'!B27 | D34: =D9*'📋 Параметры'!B27 | E34: =E9*'📋 Параметры'!B27 | F34: =F9*'📋 Параметры'!B27 | G34: =G9*'📋 Параметры'!B27 | H34: =H9*'📋 Параметры'!B27 | I34: =I9*'📋 Параметры'!B27 | J34: =J9*'📋 Параметры'!B27 | K34: =K9*'📋 Параметры'!B27 | L34: =L9*'📋 Параметры'!B27 | M34: =M9*'📋 Параметры'!B27 | N34: =SUM(B34,C34,D34,E34,F34,G34,H34,I34,J34,K34,L34,M34)
A35: Амортизация | B35: 0 | C35: 0 | D35: 0 | E35: 0 | F35: 0 | G35: 0 | H35: 0 | I35: 0 | J35: 0 | K35: 0 | L35: 0 | M35: 0 | N35: =SUM(B35,C35,D35,E35,F35,G35,H35,I35,J35,K35,L35,M35)
A36: ИТОГО НАЛОГИ | B36: =SUM(B33,B34,B35) | C36: =SUM(C33,C34,C35) | D36: =SUM(D33,D34,D35) | E36: =SUM(E33,E34,E35) | F36: =SUM(F33,F34,F35) | G36: =SUM(G33,G34,G35) | H36: =SUM(H33,H34,H35) | I36: =SUM(I33,I34,I35) | ... N36: =SUM(N33,N34,N35)
A37: ✅ ЧИСТАЯ ПРИБЫЛЬ | B37: =B29-B36 | C37: =C29-C36 | D37: =D29-D36 | E37: =E29-E36 | F37: =F29-F36 | G37: =G29-G36 | H37: =H29-H36 | I37: =I29-I36 | ... N37: =N29-N36
A38: Рентабельность чистой прибыли | B38: =IFERROR(B37/B9,0) | C38: =IFERROR(C37/C9,0) | D38: =IFERROR(D37/D9,0) | E38: =IFERROR(E37/E9,0) | F38: =IFERROR(F37/F9,0) | G38: =IFERROR(G37/G9,0) | H38: =IFERROR(H37/H9,0) | I38: =IFERROR(I37/I9,0) | ... N38: =IFERROR(N37/N9,0)

Sheet 🎯 Итоги
A1: 🎯 ИТОГОВЫЙ ДАШБОРД — НОВЫЙ ОБЪЕКТ
A3: Объект: | B3: ='📋 Параметры'!B7 | C3: Город: | D3: ='📋 Параметры'!B8
A5: 📋 ЦЕНА КОНТРАКТА (из Сметы)
A6: Себестоимость/мес (среднегод.) | B6: ='📊 Смета + КП'!D32
A7: Цена без НДС/мес | B7: ='📊 Смета + КП'!D39
A8: НДС 5%/мес | B8: ='📊 Смета + КП'!D40
A9: ★ Цена контракта с НДС/мес | B9: ='📊 Смета + КП'!D41
A10: ★ Цена контракта с НДС/год | B10: ='📊 Смета + КП'!D41*12
A12: 💰 П&Л (из листа П&Л, ИТОГО за год)
B13: Лето/мес | C13: Зима/мес | D13: Год (Итого)
A14: Выручка | D14: ='💰 П&Л'!O8
A15: Прямые расходы | D15: ='💰 П&Л'!O11
A16: Валовая прибыль | D16: ='💰 П&Л'!O12
A17: Косвенные расходы | D17: ='💰 П&Л'!O16
A18: Операционная прибыль | D18: ='💰 П&Л'!O17
A19: Налоги | D19: ='💰 П&Л'!O19
A20: ✅ Чистая прибыль | D20: ='💰 П&Л'!O21
A22: 📈 РЕНТАБЕЛЬНОСТЬ
A23: Валовая рентабельность | B23: =IFERROR('💰 П&Л'!O10/'💰 П&Л'!O5,0)
A24: Операционная рентабельность | B24: =IFERROR('💰 П&Л'!O15/'💰 П&Л'!O5,0)
A25: ★ Чистая рентабельность | B25: =IFERROR('💰 П&Л'!O19/'💰 П&Л'!O5,0)
A26: ФОТ / Выручка | B26: ='📊 Смета + КП'!D46
A28: 🚦 ПРОВЕРКА ЦЕЛЕЙ
A29: Цель рент. ЧП ≥ 20% | B29: Цель: | C29: ='📋 Параметры'!B28 | D29: =IFERROR('💰 П&Л'!O19/'💰 П&Л'!O5,0)
A30: ФОТ / Выручка ≤ 65% | B30: Цель: | C30: 65% | D30: ='📊 Смета + КП'!D46
A33: ⚠️ Примечание: значения из П&Л рассчитываются автоматически только после заполнения всех жёлтых ячеек на листах «📋 Параметры», «👥 Расчёт ФОТ» и «💰 П&Л».
