Workbook

Sheet Сводный бюджет СПб 2
A1: ПланФакт | B1: Создано с помощью сервиса ПланФакт | I1: =HYPERLINK("https://app.planfact.io/?from=Pf_BDR", "Перейти в сервис")
B2: Итого | C2: июнь` 26 | D2: июль` 26 | E2: август` 26 | F2: сентябрь` 26 | G2: октябрь` 26 | H2: ноябрь` 26 | I2: декабрь` 26
A3: Сводный бюджет СПб 2 | B3: план | C3: план | D3: план | E3: план | F3: план | G3: план | H3: план | I3: план
A4: Выручка | B4: =SUM(B5,B6) | C4: =SUM(C5,C6) | D4: =SUM(D5,D6) | E4: =SUM(E5,E6) | F4: =SUM(F5,F6) | G4: =SUM(G5,G6) | H4: - | I4: =SUM(I5,I6)
A5: Нераспределенный доход | B5: =SUM(C5,D5,E5,F5) | C5: =SUM('Астрид'!C5,'Курортный'!C5,'Новое Колпино'!C5,'Таллинский парк'!C5) | D5: =SUM('Астрид'!D5,'Курортный'!D5,'Новое Колпино'!D5,'Таллинский парк'!D5) | E5: =SUM('Астрид'!E5,'Курортный'!E5,'Новое Колпино'!E5,'Таллинский парк'!E5) | F5: =SUM('Астрид'!F5,'Курортный'!F5,'Новое Колпино'!F5,'Таллинский парк'!F5) | G5: =SUM('Астрид'!G5,'Курортный'!G5,'Новое Колпино'!G5,'Таллинский парк'!G5) | H5: - | I5: =SUM('Астрид'!I5,'Курортный'!I5,'Новое Колпино'!I5,'Таллинский парк'!I5)
A6: Выручка | B6: =SUM(B7,B8,B9) | C6: =SUM(C7,C8,C9) | D6: =SUM(D7,D8,D9) | E6: =SUM(E7,E8,E9) | F6: =SUM(F7,F8,F9) | G6: =SUM(G7,G8,G9) | H6: - | I6: =SUM(I7,I8,I9)
A7: Реализация услуг Клининг (ОД) | B7: =SUM(C7,D7,E7,F7) | C7: =SUM('Астрид'!C7,'Курортный'!C7,'Новое Колпино'!C7,'Таллинский парк'!C7) | D7: =SUM('Астрид'!D7,'Курортный'!D7,'Новое Колпино'!D7,'Таллинский парк'!D7) | E7: =SUM('Астрид'!E7,'Курортный'!E7,'Новое Колпино'!E7,'Таллинский парк'!E7) | F7: =SUM('Астрид'!F7,'Курортный'!F7,'Новое Колпино'!F7,'Таллинский парк'!F7) | G7: =SUM('Астрид'!G7,'Курортный'!G7,'Новое Колпино'!G7,'Таллинский парк'!G7) | H7: - | I7: =SUM('Астрид'!I7,'Курортный'!I7,'Новое Колпино'!I7,'Таллинский парк'!I7)
A8: Реализация услуг Клининг (Доп.услуги) | B8: =SUM(C8,D8,E8,F8) | C8: =SUM('Астрид'!C8,'Курортный'!C8,'Новое Колпино'!C8,'Таллинский парк'!C8) | D8: =SUM('Астрид'!D8,'Курортный'!D8,'Новое Колпино'!D8,'Таллинский парк'!D8) | E8: =SUM('Астрид'!E8,'Курортный'!E8,'Новое Колпино'!E8,'Таллинский парк'!E8) | F8: =SUM('Астрид'!F8,'Курортный'!F8,'Новое Колпино'!F8,'Таллинский парк'!F8) | G8: =SUM('Астрид'!G8,'Курортный'!G8,'Новое Колпино'!G8,'Таллинский парк'!G8) | H8: - | I8: =SUM('Астрид'!I8,'Курортный'!I8,'Новое Колпино'!I8,'Таллинский парк'!I8)
A9: Реализация услуг Клининг (снег) | B9: =SUM(C9,D9,E9,F9) | C9: =SUM('Астрид'!C9,'Курортный'!C9,'Новое Колпино'!C9,'Таллинский парк'!C9) | D9: =SUM('Астрид'!D9,'Курортный'!D9,'Новое Колпино'!D9,'Таллинский парк'!D9) | E9: =SUM('Астрид'!E9,'Курортный'!E9,'Новое Колпино'!E9,'Таллинский парк'!E9) | F9: =SUM('Астрид'!F9,'Курортный'!F9,'Новое Колпино'!F9,'Таллинский парк'!F9) | G9: =SUM('Астрид'!G9,'Курортный'!G9,'Новое Колпино'!G9,'Таллинский парк'!G9) | H9: - | I9: =SUM('Астрид'!I9,'Курортный'!I9,'Новое Колпино'!I9,'Таллинский парк'!I9)
A10: Прямые расходы | B10: =SUM(B11,B12,B13,B21,B22,B23,B24,B25,B26,B27,B28,B29,B30,B31,B32,B33,B34) | C10: =SUM(C11,C12,C13,C21,C22,C23,C24,C25,C26,C27,C28,C29,C30,C31,C32,C33,C34) | D10: =SUM(D11,D12,D13,D21,D22,D23,D24,D25,D26,D27,D28,D29,D30,D31,D32,D33,D34) | E10: =SUM(E11,E12,E13,E21,E22,E23,E24,E25,E26,E27,E28,E29,E30,E31,E32,E33,E34) | F10: =SUM(F11,F12,F13,F21,F22,F23,F24,F25,F26,F27,F28,F29,F30,F31,F32,F33,F34) | G10: =SUM(G11,G12,G13,G21,G22,G23,G24,G25,G26,G27,G28,G29,G30,G31,G32,G33,G34) | H10: - | I10: =SUM(I11,I12,I13,I21,I22,I23,I24,I25,I26,I27,I28,I29,I30,I31,I32,I33,I34)
A11: Нераспределенный расход | B11: =SUM(C11,D11,E11,F11) | C11: =SUM('Астрид'!C11,'Курортный'!C11,'Новое Колпино'!C11,'Таллинский парк'!C11) | D11: =SUM('Астрид'!D11,'Курортный'!D11,'Новое Колпино'!D11,'Таллинский парк'!D11) | E11: =SUM('Астрид'!E11,'Курортный'!E11,'Новое Колпино'!E11,'Таллинский парк'!E11) | F11: =SUM('Астрид'!F11,'Курортный'!F11,'Новое Колпино'!F11,'Таллинский парк'!F11) | G11: =SUM('Астрид'!G11,'Курортный'!G11,'Новое Колпино'!G11,'Таллинский парк'!G11) | H11: - | I11: =SUM('Астрид'!I11,'Курортный'!I11,'Новое Колпино'!I11,'Таллинский парк'!I11)
A12: Транспортные расходы | B12: =SUM(C12,D12,E12,F12) | C12: =SUM('Астрид'!C12,'Курортный'!C12,'Новое Колпино'!C12,'Таллинский парк'!C12) | D12: =SUM('Астрид'!D12,'Курортный'!D12,'Новое Колпино'!D12,'Таллинский парк'!D12) | E12: =SUM('Астрид'!E12,'Курортный'!E12,'Новое Колпино'!E12,'Таллинский парк'!E12) | F12: =SUM('Астрид'!F12,'Курортный'!F12,'Новое Колпино'!F12,'Таллинский парк'!F12) | G12: =SUM('Астрид'!G12,'Курортный'!G12,'Новое Колпино'!G12,'Таллинский парк'!G12) | H12: - | I12: =SUM('Астрид'!I12,'Курортный'!I12,'Новое Колпино'!I12,'Таллинский парк'!I12)
A13: Переменные | B13: =SUM(B14,B15,B16,B17,B18,B19,B20) | C13: =SUM(C14,C15,C16,C17,C18,C19,C20) | D13: =SUM(D14,D15,D16,D17,D18,D19,D20) | E13: =SUM(E14,E15,E16,E17,E18,E19,E20) | F13: =SUM(F14,F15,F16,F17,F18,F19,F20) | G13: =SUM(G14,G15,G16,G17,G18,G19,G20) | H13: - | I13: =SUM(I14,I15,I16,I17,I18,I19,I20)
A14: Услуги техниги для уборки снега (ПТ) | B14: =SUM(C14,D14,E14,F14) | C14: =SUM('Астрид'!C14,'Курортный'!C14,'Новое Колпино'!C14,'Таллинский парк'!C14) | D14: =SUM('Астрид'!D14,'Курортный'!D14,'Новое Колпино'!D14,'Таллинский парк'!D14) | E14: =SUM('Астрид'!E14,'Курортный'!E14,'Новое Колпино'!E14,'Таллинский парк'!E14) | F14: =SUM('Астрид'!F14,'Курортный'!F14,'Новое Колпино'!F14,'Таллинский парк'!F14) | G14: =SUM('Астрид'!G14,'Курортный'!G14,'Новое Колпино'!G14,'Таллинский парк'!G14) | H14: - | I14: =SUM('Астрид'!I14,'Курортный'!I14,'Новое Колпино'!I14,'Таллинский парк'!I14)
A15: Услуги садовника (ПТ) | B15: =SUM(C15,D15,E15,F15) | C15: =SUM('Астрид'!C15,'Курортный'!C15,'Новое Колпино'!C15,'Таллинский парк'!C15) | D15: =SUM('Астрид'!D15,'Курортный'!D15,'Новое Колпино'!D15,'Таллинский парк'!D15) | E15: =SUM('Астрид'!E15,'Курортный'!E15,'Новое Колпино'!E15,'Таллинский парк'!E15) | F15: =SUM('Астрид'!F15,'Курортный'!F15,'Новое Колпино'!F15,'Таллинский парк'!F15) | G15: =SUM('Астрид'!G15,'Курортный'!G15,'Новое Колпино'!G15,'Таллинский парк'!G15) | H15: - | I15: =SUM('Астрид'!I15,'Курортный'!I15,'Новое Колпино'!I15,'Таллинский парк'!I15)
A16: Сыпучие материалы (ПТ) | B16: =SUM(C16,D16,E16,F16) | C16: =SUM('Астрид'!C16,'Курортный'!C16,'Новое Колпино'!C16,'Таллинский парк'!C16) | D16: =SUM('Астрид'!D16,'Курортный'!D16,'Новое Колпино'!D16,'Таллинский парк'!D16) | E16: =SUM('Астрид'!E16,'Курортный'!E16,'Новое Колпино'!E16,'Таллинский парк'!E16) | F16: =SUM('Астрид'!F16,'Курортный'!F16,'Новое Колпино'!F16,'Таллинский парк'!F16) | G16: =SUM('Астрид'!G16,'Курортный'!G16,'Новое Колпино'!G16,'Таллинский парк'!G16) | H16: - | I16: =SUM('Астрид'!I16,'Курортный'!I16,'Новое Колпино'!I16,'Таллинский парк'!I16)
A17: Расходные материалы и инстументы (МОП) | B17: =SUM(C17,D17,E17,F17) | C17: =SUM('Астрид'!C17,'Курортный'!C17,'Новое Колпино'!C17,'Таллинский парк'!C17) | D17: =SUM('Астрид'!D17,'Курортный'!D17,'Новое Колпино'!D17,'Таллинский парк'!D17) | E17: =SUM('Астрид'!E17,'Курортный'!E17,'Новое Колпино'!E17,'Таллинский парк'!E17) | F17: =SUM('Астрид'!F17,'Курортный'!F17,'Новое Колпино'!F17,'Таллинский парк'!F17) | G17: =SUM('Астрид'!G17,'Курортный'!G17,'Новое Колпино'!G17,'Таллинский парк'!G17) | H17: - | I17: =SUM('Астрид'!I17,'Курортный'!I17,'Новое Колпино'!I17,'Таллинский парк'!I17)
A18: Расходные материалы и инстументы (ПТ) | B18: =SUM(C18,D18,E18,F18) | C18: =SUM('Астрид'!C18,'Курортный'!C18,'Новое Колпино'!C18,'Таллинский парк'!C18) | D18: =SUM('Астрид'!D18,'Курортный'!D18,'Новое Колпино'!D18,'Таллинский парк'!D18) | E18: =SUM('Астрид'!E18,'Курортный'!E18,'Новое Колпино'!E18,'Таллинский парк'!E18) | F18: =SUM('Астрид'!F18,'Курортный'!F18,'Новое Колпино'!F18,'Таллинский парк'!F18) | G18: =SUM('Астрид'!G18,'Курортный'!G18,'Новое Колпино'!G18,'Таллинский парк'!G18) | H18: - | I18: =SUM('Астрид'!I18,'Курортный'!I18,'Новое Колпино'!I18,'Таллинский парк'!I18)
A19: Арена оборудования (ПТ) | B19: =SUM(C19,D19,E19,F19) | C19: =SUM('Астрид'!C19,'Курортный'!C19,'Новое Колпино'!C19,'Таллинский парк'!C19) | D19: =SUM('Астрид'!D19,'Курортный'!D19,'Новое Колпино'!D19,'Таллинский парк'!D19) | E19: =SUM('Астрид'!E19,'Курортный'!E19,'Новое Колпино'!E19,'Таллинский парк'!E19) | F19: =SUM('Астрид'!F19,'Курортный'!F19,'Новое Колпино'!F19,'Таллинский парк'!F19) | G19: =SUM('Астрид'!G19,'Курортный'!G19,'Новое Колпино'!G19,'Таллинский парк'!G19) | H19: - | I19: =SUM('Астрид'!I19,'Курортный'!I19,'Новое Колпино'!I19,'Таллинский парк'!I19)
A20: Арена оборудования (МОП) | B20: =SUM(C20,D20,E20,F20) | C20: =SUM('Астрид'!C20,'Курортный'!C20,'Новое Колпино'!C20,'Таллинский парк'!C20) | D20: =SUM('Астрид'!D20,'Курортный'!D20,'Новое Колпино'!D20,'Таллинский парк'!D20) | E20: =SUM('Астрид'!E20,'Курортный'!E20,'Новое Колпино'!E20,'Таллинский парк'!E20) | F20: =SUM('Астрид'!F20,'Курортный'!F20,'Новое Колпино'!F20,'Таллинский парк'!F20) | G20: =SUM('Астрид'!G20,'Курортный'!G20,'Новое Колпино'!G20,'Таллинский парк'!G20) | H20: - | I20: =SUM('Астрид'!I20,'Курортный'!I20,'Новое Колпино'!I20,'Таллинский парк'!I20)
A21: Заработная плата (МОП) | B21: =SUM(C21,D21,E21,F21) | C21: =SUM('Астрид'!C21,'Курортный'!C21,'Новое Колпино'!C21,'Таллинский парк'!C21) | D21: =SUM('Астрид'!D21,'Курортный'!D21,'Новое Колпино'!D21,'Таллинский парк'!D21) | E21: =SUM('Астрид'!E21,'Курортный'!E21,'Новое Колпино'!E21,'Таллинский парк'!E21) | F21: =SUM('Астрид'!F21,'Курортный'!F21,'Новое Колпино'!F21,'Таллинский парк'!F21) | G21: =SUM('Астрид'!G21,'Курортный'!G21,'Новое Колпино'!G21,'Таллинский парк'!G21) | H21: - | I21: =SUM('Астрид'!I21,'Курортный'!I21,'Новое Колпино'!I21,'Таллинский парк'!I21)
A22: Заработная плата (ПТ) | B22: =SUM(C22,D22,E22,F22) | C22: =SUM('Астрид'!C22,'Курортный'!C22,'Новое Колпино'!C22,'Таллинский парк'!C22) | D22: =SUM('Астрид'!D22,'Курортный'!D22,'Новое Колпино'!D22,'Таллинский парк'!D22) | E22: =SUM('Астрид'!E22,'Курортный'!E22,'Новое Колпино'!E22,'Таллинский парк'!E22) | F22: =SUM('Астрид'!F22,'Курортный'!F22,'Новое Колпино'!F22,'Таллинский парк'!F22) | G22: =SUM('Астрид'!G22,'Курортный'!G22,'Новое Колпино'!G22,'Таллинский парк'!G22) | H22: - | I22: =SUM('Астрид'!I22,'Курортный'!I22,'Новое Колпино'!I22,'Таллинский парк'!I22)
A23: Налоги с ФОТ (МОП) | B23: =SUM(C23,D23,E23,F23) | C23: =SUM('Астрид'!C23,'Курортный'!C23,'Новое Колпино'!C23,'Таллинский парк'!C23) | D23: =SUM('Астрид'!D23,'Курортный'!D23,'Новое Колпино'!D23,'Таллинский парк'!D23) | E23: =SUM('Астрид'!E23,'Курортный'!E23,'Новое Колпино'!E23,'Таллинский парк'!E23) | F23: =SUM('Астрид'!F23,'Курортный'!F23,'Новое Колпино'!F23,'Таллинский парк'!F23) | G23: =SUM('Астрид'!G23,'Курортный'!G23,'Новое Колпино'!G23,'Таллинский парк'!G23) | H23: - | I23: =SUM('Астрид'!I23,'Курортный'!I23,'Новое Колпино'!I23,'Таллинский парк'!I23)
A24: Налоги с ФОТ (ПТ) | B24: =SUM(C24,D24,E24,F24) | C24: =SUM('Астрид'!C24,'Курортный'!C24,'Новое Колпино'!C24,'Таллинский парк'!C24) | D24: =SUM('Астрид'!D24,'Курортный'!D24,'Новое Колпино'!D24,'Таллинский парк'!D24) | E24: =SUM('Астрид'!E24,'Курортный'!E24,'Новое Колпино'!E24,'Таллинский парк'!E24) | F24: =SUM('Астрид'!F24,'Курортный'!F24,'Новое Колпино'!F24,'Таллинский парк'!F24) | G24: =SUM('Астрид'!G24,'Курортный'!G24,'Новое Колпино'!G24,'Таллинский парк'!G24) | H24: - | I24: =SUM('Астрид'!I24,'Курортный'!I24,'Новое Колпино'!I24,'Таллинский парк'!I24)
A25: Премми (МОП) | B25: =SUM(C25,D25,E25,F25) | C25: =SUM('Астрид'!C25,'Курортный'!C25,'Новое Колпино'!C25,'Таллинский парк'!C25) | D25: =SUM('Астрид'!D25,'Курортный'!D25,'Новое Колпино'!D25,'Таллинский парк'!D25) | E25: =SUM('Астрид'!E25,'Курортный'!E25,'Новое Колпино'!E25,'Таллинский парк'!E25) | F25: =SUM('Астрид'!F25,'Курортный'!F25,'Новое Колпино'!F25,'Таллинский парк'!F25) | G25: =SUM('Астрид'!G25,'Курортный'!G25,'Новое Колпино'!G25,'Таллинский парк'!G25) | H25: - | I25: =SUM('Астрид'!I25,'Курортный'!I25,'Новое Колпино'!I25,'Таллинский парк'!I25)
... A33: Расходы к удержанию | B33: =SUM(C33,D33,E33,F33) | C33: =SUM('Астрид'!C33,'Курортный'!C33,'Новое Колпино'!C33,'Таллинский парк'!C33) | D33: =SUM('Астрид'!D33,'Курортный'!D33,'Новое Колпино'!D33,'Таллинский парк'!D33) | E33: =SUM('Астрид'!E33,'Курортный'!E33,'Новое Колпино'!E33,'Таллинский парк'!E33) | F33: =SUM('Астрид'!F33,'Курортный'!F33,'Новое Колпино'!F33,'Таллинский парк'!F33) | G33: =SUM('Астрид'!G33,'Курортный'!G33,'Новое Колпино'!G33,'Таллинский парк'!G33) | H33: - | I33: =SUM('Астрид'!I33,'Курортный'!I33,'Новое Колпино'!I33,'Таллинский парк'!I33)
A34: Общехозяйственные | B34: =SUM(B35,B36,B37,B38,B39,B40,B41,B42) | C34: =SUM(C35,C36,C37,C38,C39,C40,C41,C42) | D34: =SUM(D35,D36,D37,D38,D39,D40,D41,D42) | E34: =SUM(E35,E36,E37,E38,E39,E40,E41,E42) | F34: =SUM(F35,F36,F37,F38,F39,F40,F41,F42) | G34: =SUM(G35,G36,G37,G38,G39,G40,G41,G42) | H34: - | I34: =SUM(I35,I36,I37,I38,I39,I40,I41,I42)
A35: Аутсорс (направления) | B35: =SUM(C35,D35,E35,F35) | C35: =SUM('Астрид'!C35,'Курортный'!C35,'Новое Колпино'!C35,'Таллинский парк'!C35) | D35: =SUM('Астрид'!D35,'Курортный'!D35,'Новое Колпино'!D35,'Таллинский парк'!D35) | E35: =SUM('Астрид'!E35,'Курортный'!E35,'Новое Колпино'!E35,'Таллинский парк'!E35) | F35: =SUM('Астрид'!F35,'Курортный'!F35,'Новое Колпино'!F35,'Таллинский парк'!F35) | G35: =SUM('Астрид'!G35,'Курортный'!G35,'Новое Колпино'!G35,'Таллинский парк'!G35) | H35: - | I35: =SUM('Астрид'!I35,'Курортный'!I35,'Новое Колпино'!I35,'Таллинский парк'!I35)
A36: Заработная плата МО АУП | B36: =SUM(C36,D36,E36,F36) | C36: =SUM('Астрид'!C36,'Курортный'!C36,'Новое Колпино'!C36,'Таллинский парк'!C36) | D36: =SUM('Астрид'!D36,'Курортный'!D36,'Новое Колпино'!D36,'Таллинский парк'!D36) | E36: =SUM('Астрид'!E36,'Курортный'!E36,'Новое Колпино'!E36,'Таллинский парк'!E36) | F36: =SUM('Астрид'!F36,'Курортный'!F36,'Новое Колпино'!F36,'Таллинский парк'!F36) | G36: =SUM('Астрид'!G36,'Курортный'!G36,'Новое Колпино'!G36,'Таллинский парк'!G36) | H36: - | I36: =SUM('Астрид'!I36,'Курортный'!I36,'Новое Колпино'!I36,'Таллинский парк'!I36)
A37: Инструменты: ГСМ | B37: =SUM(C37,D37,E37,F37) | C37: =SUM('Астрид'!C37,'Курортный'!C37,'Новое Колпино'!C37,'Таллинский парк'!C37) | D37: =SUM('Астрид'!D37,'Курортный'!D37,'Новое Колпино'!D37,'Таллинский парк'!D37) | E37: =SUM('Астрид'!E37,'Курортный'!E37,'Новое Колпино'!E37,'Таллинский парк'!E37) | F37: =SUM('Астрид'!F37,'Курортный'!F37,'Новое Колпино'!F37,'Таллинский парк'!F37) | G37: =SUM('Астрид'!G37,'Курортный'!G37,'Новое Колпино'!G37,'Таллинский парк'!G37) | H37: - | I37: =SUM('Астрид'!I37,'Курортный'!I37,'Новое Колпино'!I37,'Таллинский парк'!I37)
A38: Медосмотры | B38: =SUM(C38,D38,E38,F38) | C38: =SUM('Астрид'!C38,'Курортный'!C38,'Новое Колпино'!C38,'Таллинский парк'!C38) | D38: =SUM('Астрид'!D38,'Курортный'!D38,'Новое Колпино'!D38,'Таллинский парк'!D38) | E38: =SUM('Астрид'!E38,'Курортный'!E38,'Новое Колпино'!E38,'Таллинский парк'!E38) | F38: =SUM('Астрид'!F38,'Курортный'!F38,'Новое Колпино'!F38,'Таллинский парк'!F38) | G38: =SUM('Астрид'!G38,'Курортный'!G38,'Новое Колпино'!G38,'Таллинский парк'!G38) | H38: - | I38: =SUM('Астрид'!I38,'Курортный'!I38,'Новое Колпино'!I38,'Таллинский парк'!I38)
A39: Налоги с ФОТ (ИП) | B39: =SUM(C39,D39,E39,F39) | C39: =SUM('Астрид'!C39,'Курортный'!C39,'Новое Колпино'!C39,'Таллинский парк'!C39) | D39: =SUM('Астрид'!D39,'Курортный'!D39,'Новое Колпино'!D39,'Таллинский парк'!D39) | E39: =SUM('Астрид'!E39,'Курортный'!E39,'Новое Колпино'!E39,'Таллинский парк'!E39) | F39: =SUM('Астрид'!F39,'Курортный'!F39,'Новое Колпино'!F39,'Таллинский парк'!F39) | G39: =SUM('Астрид'!G39,'Курортный'!G39,'Новое Колпино'!G39,'Таллинский парк'!G39) | H39: - | I39: =SUM('Астрид'!I39,'Курортный'!I39,'Новое Колпино'!I39,'Таллинский парк'!I39)
A40: Приобритение мебели, бытовой техники | B40: =SUM(C40,D40,E40,F40) | C40: =SUM('Астрид'!C40,'Курортный'!C40,'Новое Колпино'!C40,'Таллинский парк'!C40) | D40: =SUM('Астрид'!D40,'Курортный'!D40,'Новое Колпино'!D40,'Таллинский парк'!D40) | E40: =SUM('Астрид'!E40,'Курортный'!E40,'Новое Колпино'!E40,'Таллинский парк'!E40) | F40: =SUM('Астрид'!F40,'Курортный'!F40,'Новое Колпино'!F40,'Таллинский парк'!F40) | G40: =SUM('Астрид'!G40,'Курортный'!G40,'Новое Колпино'!G40,'Таллинский парк'!G40) | H40: - | I40: =SUM('Астрид'!I40,'Курортный'!I40,'Новое Колпино'!I40,'Таллинский парк'!I40)
A41: Комиссия за перевод ЗП | B41: =SUM(C41,D41,E41,F41) | C41: =SUM('Астрид'!C41,'Курортный'!C41,'Новое Колпино'!C41,'Таллинский парк'!C41) | D41: =SUM('Астрид'!D41,'Курортный'!D41,'Новое Колпино'!D41,'Таллинский парк'!D41) | E41: =SUM('Астрид'!E41,'Курортный'!E41,'Новое Колпино'!E41,'Таллинский парк'!E41) | F41: =SUM('Астрид'!F41,'Курортный'!F41,'Новое Колпино'!F41,'Таллинский парк'!F41) | G41: =SUM('Астрид'!G41,'Курортный'!G41,'Новое Колпино'!G41,'Таллинский парк'!G41) | H41: - | I41: =SUM('Астрид'!I41,'Курортный'!I41,'Новое Колпино'!I41,'Таллинский парк'!I41)
A42: Аренда квартиры (включая коммуналку) | B42: =SUM(C42,D42,E42,F42) | C42: =SUM('Астрид'!C42,'Курортный'!C42,'Новое Колпино'!C42,'Таллинский парк'!C42) | D42: =SUM('Астрид'!D42,'Курортный'!D42,'Новое Колпино'!D42,'Таллинский парк'!D42) | E42: =SUM('Астрид'!E42,'Курортный'!E42,'Новое Колпино'!E42,'Таллинский парк'!E42) | F42: =SUM('Астрид'!F42,'Курортный'!F42,'Новое Колпино'!F42,'Таллинский парк'!F42) | G42: =SUM('Астрид'!G42,'Курортный'!G42,'Новое Колпино'!G42,'Таллинский парк'!G42) | H42: - | I42: =SUM('Астрид'!I42,'Курортный'!I42,'Новое Колпино'!I42,'Таллинский парк'!I42)
A43: Валовая прибыль | B43: =B4-B10 | C43: =C4-C10 | D43: =D4-D10 | E43: =E4-E10 | F43: =F4-F10 | G43: =G4-G10 | H43: - | I43: =I4-I10
A44: Валовая рентабельность | B44: =IFERROR(IF(B4=0,"-",B43/B4),"-") | C44: =IFERROR(IF(C4=0,"-",C43/C4),"-") | D44: =IFERROR(IF(D4=0,"-",D43/D4),"-") | E44: =IFERROR(IF(E4=0,"-",E43/E4),"-") | F44: =IFERROR(IF(F4=0,"-",F43/F4),"-") | G44: =IFERROR(IF(G4=0,"-",G43/G4),"-") | H44: - | I44: =IFERROR(IF(I4=0,"-",I43/I4),"-")
A45: Косвенные расходы | B45: =SUM(B46,B47,B48,B52,B56,B57,B58,B59,B60,B63,B64,B65,B66,B67,B68,B69,B70,B71,B72,B73,B74,B75,B76,B77,B78,B79) | C45: =SUM(C46,C47,C48,C52,C56,C57,C58,C59,C60,C63,C64,C65,C66,C67,C68,C69,C70,C71,C72,C73,C74,C75,C76,C77,C78,C79) | D45: =SUM(D46,D47,D48,D52,D56,D57,D58,D59,D60,D63,D64,D65,D66,D67,D68,D69,D70,D71,D72,D73,D74,D75,D76,D77,D78,D79) | E45: =SUM(E46,E47,E48,E52,E56,E57,E58,E59,E60,E63,E64,E65,E66,E67,E68,E69,E70,E71,E72,E73,E74,E75,E76,E77,E78,E79) | F45: =SUM(F46,F47,F48,F52,F56,F57,F58,F59,F60,F63,F64,F65,F66,F67,F68,F69,F70,F71,F72,F73,F74,F75,F76,F77,F78,F79) | G45: =SUM(G46,G47,G48,G52,G56,G57,G58,G59,G60,G63,G64,G65,G66,G67,G68,G69,G70,G71,G72,G73,G74,G75,G76,G77,G78,G79) | H45: - | I45: =SUM(I46,I47,I48,I52,I56,I57,I58,I59,I60,I63,I64,I65,I66,I67,I68,I69,I70,I71,I72,I73,I74,I75,I76,I77,I78,I79)
A46: Расход БЭК-ОФИС | B46: =SUM(C46,D46,E46,F46) | C46: =SUM('Астрид'!C46,'Курортный'!C46,'Новое Колпино'!C46,'Таллинский парк'!C46) | D46: =SUM('Астрид'!D46,'Курортный'!D46,'Новое Колпино'!D46,'Таллинский парк'!D46) | E46: =SUM('Астрид'!E46,'Курортный'!E46,'Новое Колпино'!E46,'Таллинский парк'!E46) | F46: =SUM('Астрид'!F46,'Курортный'!F46,'Новое Колпино'!F46,'Таллинский парк'!F46) | G46: =SUM('Астрид'!G46,'Курортный'!G46,'Новое Колпино'!G46,'Таллинский парк'!G46) | H46: - | I46: =SUM('Астрид'!I46,'Курортный'!I46,'Новое Колпино'!I46,'Таллинский парк'!I46)
A47: Расходы на бэк-офис | B47: =SUM(C47,D47,E47,F47) | C47: =SUM('Астрид'!C47,'Курортный'!C47,'Новое Колпино'!C47,'Таллинский парк'!C47) | D47: =SUM('Астрид'!D47,'Курортный'!D47,'Новое Колпино'!D47,'Таллинский парк'!D47) | E47: =SUM('Астрид'!E47,'Курортный'!E47,'Новое Колпино'!E47,'Таллинский парк'!E47) | F47: =SUM('Астрид'!F47,'Курортный'!F47,'Новое Колпино'!F47,'Таллинский парк'!F47) | G47: =SUM('Астрид'!G47,'Курортный'!G47,'Новое Колпино'!G47,'Таллинский парк'!G47) | H47: - | I47: =SUM('Астрид'!I47,'Курортный'!I47,'Новое Колпино'!I47,'Таллинский парк'!I47)
A48: Автомобиль | B48: =SUM(B49,B50,B51) | C48: =SUM(C49,C50,C51) | D48: =SUM(D49,D50,D51) | E48: =SUM(E49,E50,E51) | F48: =SUM(F49,F50,F51) | G48: =SUM(G49,G50,G51) | H48: - | I48: =SUM(I49,I50,I51)
A49: Автомобиль: ГСМ | B49: =SUM(C49,D49,E49,F49) | C49: =SUM('Астрид'!C49,'Курортный'!C49,'Новое Колпино'!C49,'Таллинский парк'!C49) | D49: =SUM('Астрид'!D49,'Курортный'!D49,'Новое Колпино'!D49,'Таллинский парк'!D49) | E49: =SUM('Астрид'!E49,'Курортный'!E49,'Новое Колпино'!E49,'Таллинский парк'!E49) | F49: =SUM('Астрид'!F49,'Курортный'!F49,'Новое Колпино'!F49,'Таллинский парк'!F49) | G49: =SUM('Астрид'!G49,'Курортный'!G49,'Новое Колпино'!G49,'Таллинский парк'!G49) | H49: - | I49: =SUM('Астрид'!I49,'Курортный'!I49,'Новое Колпино'!I49,'Таллинский парк'!I49)
A50: Автомобиль: страхование | B50: =SUM(C50,D50,E50,F50) | C50: =SUM('Астрид'!C50,'Курортный'!C50,'Новое Колпино'!C50,'Таллинский парк'!C50) | D50: =SUM('Астрид'!D50,'Курортный'!D50,'Новое Колпино'!D50,'Таллинский парк'!D50) | E50: =SUM('Астрид'!E50,'Курортный'!E50,'Новое Колпино'!E50,'Таллинский парк'!E50) | F50: =SUM('Астрид'!F50,'Курортный'!F50,'Новое Колпино'!F50,'Таллинский парк'!F50) | G50: =SUM('Астрид'!G50,'Курортный'!G50,'Новое Колпино'!G50,'Таллинский парк'!G50) | H50: - | I50: =SUM('Астрид'!I50,'Курортный'!I50,'Новое Колпино'!I50,'Таллинский парк'!I50)
A51: Автомобиль: ТО | B51: =SUM(C51,D51,E51,F51) | C51: =SUM('Астрид'!C51,'Курортный'!C51,'Новое Колпино'!C51,'Таллинский парк'!C51) | D51: =SUM('Астрид'!D51,'Курортный'!D51,'Новое Колпино'!D51,'Таллинский парк'!D51) | E51: =SUM('Астрид'!E51,'Курортный'!E51,'Новое Колпино'!E51,'Таллинский парк'!E51) | F51: =SUM('Астрид'!F51,'Курортный'!F51,'Новое Колпино'!F51,'Таллинский парк'!F51) | G51: =SUM('Астрид'!G51,'Курортный'!G51,'Новое Колпино'!G51,'Таллинский парк'!G51) | H51: - | I51: =SUM('Астрид'!I51,'Курортный'!I51,'Новое Колпино'!I51,'Таллинский парк'!I51)
A52: Офисные расходы | B52: =SUM(B53,B54,B55) | C52: =SUM(C53,C54,C55) | D52: =SUM(D53,D54,D55) | E52: =SUM(E53,E54,E55) | F52: =SUM(F53,F54,F55) | G52: =SUM(G53,G54,G55) | H52: - | I52: =SUM(I53,I54,I55)
A53: Аренда офиса | B53: =SUM(C53,D53,E53,F53) | C53: =SUM('Астрид'!C53,'Курортный'!C53,'Новое Колпино'!C53,'Таллинский парк'!C53) | D53: =SUM('Астрид'!D53,'Курортный'!D53,'Новое Колпино'!D53,'Таллинский парк'!D53) | E53: =SUM('Астрид'!E53,'Курортный'!E53,'Новое Колпино'!E53,'Таллинский парк'!E53) | F53: =SUM('Астрид'!F53,'Курортный'!F53,'Новое Колпино'!F53,'Таллинский парк'!F53) | G53: =SUM('Астрид'!G53,'Курортный'!G53,'Новое Колпино'!G53,'Таллинский парк'!G53) | H53: - | I53: =SUM('Астрид'!I53,'Курортный'!I53,'Новое Колпино'!I53,'Таллинский парк'!I53)
A54: Канцелярия и обслуживание | B54: =SUM(C54,D54,E54,F54) | C54: =SUM('Астрид'!C54,'Курортный'!C54,'Новое Колпино'!C54,'Таллинский парк'!C54) | D54: =SUM('Астрид'!D54,'Курортный'!D54,'Новое Колпино'!D54,'Таллинский парк'!D54) | E54: =SUM('Астрид'!E54,'Курортный'!E54,'Новое Колпино'!E54,'Таллинский парк'!E54) | F54: =SUM('Астрид'!F54,'Курортный'!F54,'Новое Колпино'!F54,'Таллинский парк'!F54) | G54: =SUM('Астрид'!G54,'Курортный'!G54,'Новое Колпино'!G54,'Таллинский парк'!G54) | H54: - | I54: =SUM('Астрид'!I54,'Курортный'!I54,'Новое Колпино'!I54,'Таллинский парк'!I54)
A55: Интернет и связь | B55: =SUM(C55,D55,E55,F55) | C55: =SUM('Астрид'!C55,'Курортный'!C55,'Новое Колпино'!C55,'Таллинский парк'!C55) | D55: =SUM('Астрид'!D55,'Курортный'!D55,'Новое Колпино'!D55,'Таллинский парк'!D55) | E55: =SUM('Астрид'!E55,'Курортный'!E55,'Новое Колпино'!E55,'Таллинский парк'!E55) | F55: =SUM('Астрид'!F55,'Курортный'!F55,'Новое Колпино'!F55,'Таллинский парк'!F55) | G55: =SUM('Астрид'!G55,'Курортный'!G55,'Новое Колпино'!G55,'Таллинский парк'!G55) | H55: - | I55: =SUM('Астрид'!I55,'Курортный'!I55,'Новое Колпино'!I55,'Таллинский парк'!I55)
A56: Банковские услуги | B56: =SUM(C56,D56,E56,F56) | C56: =SUM('Астрид'!C56,'Курортный'!C56,'Новое Колпино'!C56,'Таллинский парк'!C56) | D56: =SUM('Астрид'!D56,'Курортный'!D56,'Новое Колпино'!D56,'Таллинский парк'!D56) | E56: =SUM('Астрид'!E56,'Курортный'!E56,'Новое Колпино'!E56,'Таллинский парк'!E56) | F56: =SUM('Астрид'!F56,'Курортный'!F56,'Новое Колпино'!F56,'Таллинский парк'!F56) | G56: =SUM('Астрид'!G56,'Курортный'!G56,'Новое Колпино'!G56,'Таллинский парк'!G56) | H56: - | I56: =SUM('Астрид'!I56,'Курортный'!I56,'Новое Колпино'!I56,'Таллинский парк'!I56)
A57: Заработная плата АУП (БО) | B57: =SUM(C57,D57,E57,F57) | C57: =SUM('Астрид'!C57,'Курортный'!C57,'Новое Колпино'!C57,'Таллинский парк'!C57) | D57: =SUM('Астрид'!D57,'Курортный'!D57,'Новое Колпино'!D57,'Таллинский парк'!D57) | E57: =SUM('Астрид'!E57,'Курортный'!E57,'Новое Колпино'!E57,'Таллинский парк'!E57) | F57: =SUM('Астрид'!F57,'Курортный'!F57,'Новое Колпино'!F57,'Таллинский парк'!F57) | G57: =SUM('Астрид'!G57,'Курортный'!G57,'Новое Колпино'!G57,'Таллинский парк'!G57) | H57: - | I57: =SUM('Астрид'!I57,'Курортный'!I57,'Новое Колпино'!I57,'Таллинский парк'!I57)
A58: Заработная плата бухгалтерии (БО) | B58: =SUM(C58,D58,E58,F58) | C58: =SUM('Астрид'!C58,'Курортный'!C58,'Новое Колпино'!C58,'Таллинский парк'!C58) | D58: =SUM('Астрид'!D58,'Курортный'!D58,'Новое Колпино'!D58,'Таллинский парк'!D58) | E58: =SUM('Астрид'!E58,'Курортный'!E58,'Новое Колпино'!E58,'Таллинский парк'!E58) | F58: =SUM('Астрид'!F58,'Курортный'!F58,'Новое Колпино'!F58,'Таллинский парк'!F58) | G58: =SUM('Астрид'!G58,'Курортный'!G58,'Новое Колпино'!G58,'Таллинский парк'!G58) | H58: - | I58: =SUM('Астрид'!I58,'Курортный'!I58,'Новое Колпино'!I58,'Таллинский парк'!I58)
A59: Заработная плата СБ (БО) | B59: =SUM(C59,D59,E59,F59) | C59: =SUM('Астрид'!C59,'Курортный'!C59,'Новое Колпино'!C59,'Таллинский парк'!C59) | D59: =SUM('Астрид'!D59,'Курортный'!D59,'Новое Колпино'!D59,'Таллинский парк'!D59) | E59: =SUM('Астрид'!E59,'Курортный'!E59,'Новое Колпино'!E59,'Таллинский парк'!E59) | F59: =SUM('Астрид'!F59,'Курортный'!F59,'Новое Колпино'!F59,'Таллинский парк'!F59) | G59: =SUM('Астрид'!G59,'Курортный'!G59,'Новое Колпино'!G59,'Таллинский парк'!G59) | H59: - | I59: =SUM('Астрид'!I59,'Курортный'!I59,'Новое Колпино'!I59,'Таллинский парк'!I59)
A60: Командировочные расходы | B60: =SUM(B61,B62) | C60: =SUM(C61,C62) | D60: =SUM(D61,D62) | E60: =SUM(E61,E62) | F60: =SUM(F61,F62) | G60: =SUM(G61,G62) | H60: - | I60: =SUM(I61,I62)
A61: Командировнчеы расходы: билеты (БО) | B61: =SUM(C61,D61,E61,F61) | C61: =SUM('Астрид'!C61,'Курортный'!C61,'Новое Колпино'!C61,'Таллинский парк'!C61) | D61: =SUM('Астрид'!D61,'Курортный'!D61,'Новое Колпино'!D61,'Таллинский парк'!D61) | E61: =SUM('Астрид'!E61,'Курортный'!E61,'Новое Колпино'!E61,'Таллинский парк'!E61) | F61: =SUM('Астрид'!F61,'Курортный'!F61,'Новое Колпино'!F61,'Таллинский парк'!F61) | G61: =SUM('Астрид'!G61,'Курортный'!G61,'Новое Колпино'!G61,'Таллинский парк'!G61) | H61: - | I61: =SUM('Астрид'!I61,'Курортный'!I61,'Новое Колпино'!I61,'Таллинский парк'!I61)
A62: Командировнчеы расходы: проживание (БО) | B62: =SUM(C62,D62,E62,F62) | C62: =SUM('Астрид'!C62,'Курортный'!C62,'Новое Колпино'!C62,'Таллинский парк'!C62) | D62: =SUM('Астрид'!D62,'Курортный'!D62,'Новое Колпино'!D62,'Таллинский парк'!D62) | E62: =SUM('Астрид'!E62,'Курортный'!E62,'Новое Колпино'!E62,'Таллинский парк'!E62) | F62: =SUM('Астрид'!F62,'Курортный'!F62,'Новое Колпино'!F62,'Таллинский парк'!F62) | G62: =SUM('Астрид'!G62,'Курортный'!G62,'Новое Колпино'!G62,'Таллинский парк'!G62) | H62: - | I62: =SUM('Астрид'!I62,'Курортный'!I62,'Новое Колпино'!I62,'Таллинский парк'!I62)
A63: Комиссия УК ДОМ | B63: =SUM(C63,D63,E63,F63) | C63: =SUM('Астрид'!C63,'Курортный'!C63,'Новое Колпино'!C63,'Таллинский парк'!C63) | D63: =SUM('Астрид'!D63,'Курортный'!D63,'Новое Колпино'!D63,'Таллинский парк'!D63) | E63: =SUM('Астрид'!E63,'Курортный'!E63,'Новое Колпино'!E63,'Таллинский парк'!E63) | F63: =SUM('Астрид'!F63,'Курортный'!F63,'Новое Колпино'!F63,'Таллинский парк'!F63) | G63: =SUM('Астрид'!G63,'Курортный'!G63,'Новое Колпино'!G63,'Таллинский парк'!G63) | H63: - | I63: =SUM('Астрид'!I63,'Курортный'!I63,'Новое Колпино'!I63,'Таллинский парк'!I63)
A64: Налоги с ФОТ (ИП)_БО | B64: =SUM(C64,D64,E64,F64) | C64: =SUM('Астрид'!C64,'Курортный'!C64,'Новое Колпино'!C64,'Таллинский парк'!C64) | D64: =SUM('Астрид'!D64,'Курортный'!D64,'Новое Колпино'!D64,'Таллинский парк'!D64) | E64: =SUM('Астрид'!E64,'Курортный'!E64,'Новое Колпино'!E64,'Таллинский парк'!E64) | F64: =SUM('Астрид'!F64,'Курортный'!F64,'Новое Колпино'!F64,'Таллинский парк'!F64) | G64: =SUM('Астрид'!G64,'Курортный'!G64,'Новое Колпино'!G64,'Таллинский парк'!G64) | H64: - | I64: =SUM('Астрид'!I64,'Курортный'!I64,'Новое Колпино'!I64,'Таллинский парк'!I64)
A65: Налоги с ФОТ (НДФЛ) БО | B65: =SUM(C65,D65,E65,F65) | C65: =SUM('Астрид'!C65,'Курортный'!C65,'Новое Колпино'!C65,'Таллинский парк'!C65) | D65: =SUM('Астрид'!D65,'Курортный'!D65,'Новое Колпино'!D65,'Таллинский парк'!D65) | E65: =SUM('Астрид'!E65,'Курортный'!E65,'Новое Колпино'!E65,'Таллинский парк'!E65) | F65: =SUM('Астрид'!F65,'Курортный'!F65,'Новое Колпино'!F65,'Таллинский парк'!F65) | G65: =SUM('Астрид'!G65,'Курортный'!G65,'Новое Колпино'!G65,'Таллинский парк'!G65) | H65: - | I65: =SUM('Астрид'!I65,'Курортный'!I65,'Новое Колпино'!I65,'Таллинский парк'!I65)
A66: Налоги с ФОТ (страховые взносы) БО | B66: =SUM(C66,D66,E66,F66) | C66: =SUM('Астрид'!C66,'Курортный'!C66,'Новое Колпино'!C66,'Таллинский парк'!C66) | D66: =SUM('Астрид'!D66,'Курортный'!D66,'Новое Колпино'!D66,'Таллинский парк'!D66) | E66: =SUM('Астрид'!E66,'Курортный'!E66,'Новое Колпино'!E66,'Таллинский парк'!E66) | F66: =SUM('Астрид'!F66,'Курортный'!F66,'Новое Колпино'!F66,'Таллинский парк'!F66) | G66: =SUM('Астрид'!G66,'Курортный'!G66,'Новое Колпино'!G66,'Таллинский парк'!G66) | H66: - | I66: =SUM('Астрид'!I66,'Курортный'!I66,'Новое Колпино'!I66,'Таллинский парк'!I66)
A67: Нотариальные услуги | B67: =SUM(C67,D67,E67,F67) | C67: =SUM('Астрид'!C67,'Курортный'!C67,'Новое Колпино'!C67,'Таллинский парк'!C67) | D67: =SUM('Астрид'!D67,'Курортный'!D67,'Новое Колпино'!D67,'Таллинский парк'!D67) | E67: =SUM('Астрид'!E67,'Курортный'!E67,'Новое Колпино'!E67,'Таллинский парк'!E67) | F67: =SUM('Астрид'!F67,'Курортный'!F67,'Новое Колпино'!F67,'Таллинский парк'!F67) | G67: =SUM('Астрид'!G67,'Курортный'!G67,'Новое Колпино'!G67,'Таллинский парк'!G67) | H67: - | I67: =SUM('Астрид'!I67,'Курортный'!I67,'Новое Колпино'!I67,'Таллинский парк'!I67)
A68: Обслуживание техники (БО) | B68: =SUM(C68,D68,E68,F68) | C68: =SUM('Астрид'!C68,'Курортный'!C68,'Новое Колпино'!C68,'Таллинский парк'!C68) | D68: =SUM('Астрид'!D68,'Курортный'!D68,'Новое Колпино'!D68,'Таллинский парк'!D68) | E68: =SUM('Астрид'!E68,'Курортный'!E68,'Новое Колпино'!E68,'Таллинский парк'!E68) | F68: =SUM('Астрид'!F68,'Курортный'!F68,'Новое Колпино'!F68,'Таллинский парк'!F68) | G68: =SUM('Астрид'!G68,'Курортный'!G68,'Новое Колпино'!G68,'Таллинский парк'!G68) | H68: - | I68: =SUM('Астрид'!I68,'Курортный'!I68,'Новое Колпино'!I68,'Таллинский парк'!I68)
A69: Программное обеспечение (БО) | B69: =SUM(C69,D69,E69,F69) | C69: =SUM('Астрид'!C69,'Курортный'!C69,'Новое Колпино'!C69,'Таллинский парк'!C69) | D69: =SUM('Астрид'!D69,'Курортный'!D69,'Новое Колпино'!D69,'Таллинский парк'!D69) | E69: =SUM('Астрид'!E69,'Курортный'!E69,'Новое Колпино'!E69,'Таллинский парк'!E69) | F69: =SUM('Астрид'!F69,'Курортный'!F69,'Новое Колпино'!F69,'Таллинский парк'!F69) | G69: =SUM('Астрид'!G69,'Курортный'!G69,'Новое Колпино'!G69,'Таллинский парк'!G69) | H69: - | I69: =SUM('Астрид'!I69,'Курортный'!I69,'Новое Колпино'!I69,'Таллинский парк'!I69)
A70: ПланФакт | B70: =SUM(C70,D70,E70,F70) | C70: =SUM('Астрид'!C70,'Курортный'!C70,'Новое Колпино'!C70,'Таллинский парк'!C70) | D70: =SUM('Астрид'!D70,'Курортный'!D70,'Новое Колпино'!D70,'Таллинский парк'!D70) | E70: =SUM('Астрид'!E70,'Курортный'!E70,'Новое Колпино'!E70,'Таллинский парк'!E70) | F70: =SUM('Астрид'!F70,'Курортный'!F70,'Новое Колпино'!F70,'Таллинский парк'!F70) | G70: =SUM('Астрид'!G70,'Курортный'!G70,'Новое Колпино'!G70,'Таллинский парк'!G70) | H70: - | I70: =SUM('Астрид'!I70,'Курортный'!I70,'Новое Колпино'!I70,'Таллинский парк'!I70)
A71: ТБ | B71: =SUM(C71,D71,E71,F71) | C71: =SUM('Астрид'!C71,'Курортный'!C71,'Новое Колпино'!C71,'Таллинский парк'!C71) | D71: =SUM('Астрид'!D71,'Курортный'!D71,'Новое Колпино'!D71,'Таллинский парк'!D71) | E71: =SUM('Астрид'!E71,'Курортный'!E71,'Новое Колпино'!E71,'Таллинский парк'!E71) | F71: =SUM('Астрид'!F71,'Курортный'!F71,'Новое Колпино'!F71,'Таллинский парк'!F71) | G71: =SUM('Астрид'!G71,'Курортный'!G71,'Новое Колпино'!G71,'Таллинский парк'!G71) | H71: - | I71: =SUM('Астрид'!I71,'Курортный'!I71,'Новое Колпино'!I71,'Таллинский парк'!I71)
A72: Контур | B72: =SUM(C72,D72,E72,F72) | C72: =SUM('Астрид'!C72,'Курортный'!C72,'Новое Колпино'!C72,'Таллинский парк'!C72) | D72: =SUM('Астрид'!D72,'Курортный'!D72,'Новое Колпино'!D72,'Таллинский парк'!D72) | E72: =SUM('Астрид'!E72,'Курортный'!E72,'Новое Колпино'!E72,'Таллинский парк'!E72) | F72: =SUM('Астрид'!F72,'Курортный'!F72,'Новое Колпино'!F72,'Таллинский парк'!F72) | G72: =SUM('Астрид'!G72,'Курортный'!G72,'Новое Колпино'!G72,'Таллинский парк'!G72) | H72: - | I72: =SUM('Астрид'!I72,'Курортный'!I72,'Новое Колпино'!I72,'Таллинский парк'!I72)
... A79: HR (аутсорс) | B79: =SUM(C79,D79,E79,F79) | C79: =SUM('Астрид'!C79,'Курортный'!C79,'Новое Колпино'!C79,'Таллинский парк'!C79) | D79: =SUM('Астрид'!D79,'Курортный'!D79,'Новое Колпино'!D79,'Таллинский парк'!D79) | E79: =SUM('Астрид'!E79,'Курортный'!E79,'Новое Колпино'!E79,'Таллинский парк'!E79) | F79: =SUM('Астрид'!F79,'Курортный'!F79,'Новое Колпино'!F79,'Таллинский парк'!F79) | G79: =SUM('Астрид'!G79,'Курортный'!G79,'Новое Колпино'!G79,'Таллинский парк'!G79) | H79: - | I79: =SUM('Астрид'!I79,'Курортный'!I79,'Новое Колпино'!I79,'Таллинский парк'!I79)
A80: Операционная прибыль | B80: =B43-B45 | C80: =C43-C45 | D80: =D43-D45 | E80: =E43-E45 | F80: =F43-F45 | G80: =G43-G45 | H80: - | I80: =I43-I45
A81: Операционная рентабельность | B81: =IFERROR(IF(B4=0,"-",B80/B4),"-") | C81: =IFERROR(IF(C4=0,"-",C80/C4),"-") | D81: =IFERROR(IF(D4=0,"-",D80/D4),"-") | E81: =IFERROR(IF(E4=0,"-",E80/E4),"-") | F81: =IFERROR(IF(F4=0,"-",F80/F4),"-") | G81: =IFERROR(IF(G4=0,"-",G80/G4),"-") | H81: - | I81: =IFERROR(IF(I4=0,"-",I80/I4),"-")
A82: Прочие доходы | B82: =SUM(B83,B84,B85,B86) | C82: =SUM(C83,C84,C85,C86) | D82: =SUM(D83,D84,D85,D86) | E82: =SUM(E83,E84,E85,E86) | F82: =SUM(F83,F84,F85,F86) | G82: =SUM(G83,G84,G85,G86) | H82: - | I82: =SUM(I83,I84,I85,I86)
A83: Доход БЭК-ОФИС | B83: =SUM(C83,D83,E83,F83) | C83: =SUM('Астрид'!C83,'Курортный'!C83,'Новое Колпино'!C83,'Таллинский парк'!C83) | D83: =SUM('Астрид'!D83,'Курортный'!D83,'Новое Колпино'!D83,'Таллинский парк'!D83) | E83: =SUM('Астрид'!E83,'Курортный'!E83,'Новое Колпино'!E83,'Таллинский парк'!E83) | F83: =SUM('Астрид'!F83,'Курортный'!F83,'Новое Колпино'!F83,'Таллинский парк'!F83) | G83: =SUM('Астрид'!G83,'Курортный'!G83,'Новое Колпино'!G83,'Таллинский парк'!G83) | H83: - | I83: =SUM('Астрид'!I83,'Курортный'!I83,'Новое Колпино'!I83,'Таллинский парк'!I83)
A84: Пополненин бэк-офис | B84: =SUM(C84,D84,E84,F84) | C84: =SUM('Астрид'!C84,'Курортный'!C84,'Новое Колпино'!C84,'Таллинский парк'!C84) | D84: =SUM('Астрид'!D84,'Курортный'!D84,'Новое Колпино'!D84,'Таллинский парк'!D84) | E84: =SUM('Астрид'!E84,'Курортный'!E84,'Новое Колпино'!E84,'Таллинский парк'!E84) | F84: =SUM('Астрид'!F84,'Курортный'!F84,'Новое Колпино'!F84,'Таллинский парк'!F84) | G84: =SUM('Астрид'!G84,'Курортный'!G84,'Новое Колпино'!G84,'Таллинский парк'!G84) | H84: - | I84: =SUM('Астрид'!I84,'Курортный'!I84,'Новое Колпино'!I84,'Таллинский парк'!I84)
A85: Проценты по вкладам | B85: =SUM(C85,D85,E85,F85) | C85: =SUM('Астрид'!C85,'Курортный'!C85,'Новое Колпино'!C85,'Таллинский парк'!C85) | D85: =SUM('Астрид'!D85,'Курортный'!D85,'Новое Колпино'!D85,'Таллинский парк'!D85) | E85: =SUM('Астрид'!E85,'Курортный'!E85,'Новое Колпино'!E85,'Таллинский парк'!E85) | F85: =SUM('Астрид'!F85,'Курортный'!F85,'Новое Колпино'!F85,'Таллинский парк'!F85) | G85: =SUM('Астрид'!G85,'Курортный'!G85,'Новое Колпино'!G85,'Таллинский парк'!G85) | H85: - | I85: =SUM('Астрид'!I85,'Курортный'!I85,'Новое Колпино'!I85,'Таллинский парк'!I85)
A86: Курсовая разница (+) | B86: =SUM(C86,D86,E86,F86) | C86: =SUM('Астрид'!C86,'Курортный'!C86,'Новое Колпино'!C86,'Таллинский парк'!C86) | D86: =SUM('Астрид'!D86,'Курортный'!D86,'Новое Колпино'!D86,'Таллинский парк'!D86) | E86: =SUM('Астрид'!E86,'Курортный'!E86,'Новое Колпино'!E86,'Таллинский парк'!E86) | F86: =SUM('Астрид'!F86,'Курортный'!F86,'Новое Колпино'!F86,'Таллинский парк'!F86) | G86: =SUM('Астрид'!G86,'Курортный'!G86,'Новое Колпино'!G86,'Таллинский парк'!G86) | H86: - | I86: =SUM('Астрид'!I86,'Курортный'!I86,'Новое Колпино'!I86,'Таллинский парк'!I86)
A87: Прочие расходы | B87: =SUM(B88) | C87: =SUM(C88) | D87: =SUM(D88) | E87: =SUM(E88) | F87: =SUM(F88) | G87: =SUM(G88) | H87: - | I87: =SUM(I88)
A88: Курсовая разница (-) | B88: =SUM(C88,D88,E88,F88) | C88: =SUM('Астрид'!C88,'Курортный'!C88,'Новое Колпино'!C88,'Таллинский парк'!C88) | D88: =SUM('Астрид'!D88,'Курортный'!D88,'Новое Колпино'!D88,'Таллинский парк'!D88) | E88: =SUM('Астрид'!E88,'Курортный'!E88,'Новое Колпино'!E88,'Таллинский парк'!E88) | F88: =SUM('Астрид'!F88,'Курортный'!F88,'Новое Колпино'!F88,'Таллинский парк'!F88) | G88: =SUM('Астрид'!G88,'Курортный'!G88,'Новое Колпино'!G88,'Таллинский парк'!G88) | H88: - | I88: =SUM('Астрид'!I88,'Курортный'!I88,'Новое Колпино'!I88,'Таллинский парк'!I88)
A89: EBITDA | B89: =B80+IFERROR(B82*1,0)-IFERROR(B87*1,0) | C89: =C80+IFERROR(C82*1,0)-IFERROR(C87*1,0) | D89: =D80+IFERROR(D82*1,0)-IFERROR(D87*1,0) | E89: =E80+IFERROR(E82*1,0)-IFERROR(E87*1,0) | F89: =F80+IFERROR(F82*1,0)-IFERROR(F87*1,0) | G89: =G80+IFERROR(G82*1,0)-IFERROR(G87*1,0) | H89: - | I89: =I80+IFERROR(I82*1,0)-IFERROR(I87*1,0)
A90: Рентабельность по EBITDA | B90: =IFERROR(IF(B4=0,"-",B89/B4),"-") | C90: =IFERROR(IF(C4=0,"-",C89/C4),"-") | D90: =IFERROR(IF(D4=0,"-",D89/D4),"-") | E90: =IFERROR(IF(E4=0,"-",E89/E4),"-") | F90: =IFERROR(IF(F4=0,"-",F89/F4),"-") | G90: =IFERROR(IF(G4=0,"-",G89/G4),"-") | H90: - | I90: =IFERROR(IF(I4=0,"-",I89/I4),"-")
A91: Амортизация | B91: =SUM(B92,B93) | C91: =SUM(C92,C93) | D91: =SUM(D92,D93) | E91: =SUM(E92,E93) | F91: =SUM(F92,F93) | G91: =SUM(G92,G93) | H91: - | I91: =SUM(I92,I93)
A92: Амортизация ОС (ПТ) | B92: =SUM(C92,D92,E92,F92) | C92: =SUM('Астрид'!C92,'Курортный'!C92,'Новое Колпино'!C92,'Таллинский парк'!C92) | D92: =SUM('Астрид'!D92,'Курортный'!D92,'Новое Колпино'!D92,'Таллинский парк'!D92) | E92: =SUM('Астрид'!E92,'Курортный'!E92,'Новое Колпино'!E92,'Таллинский парк'!E92) | F92: =SUM('Астрид'!F92,'Курортный'!F92,'Новое Колпино'!F92,'Таллинский парк'!F92) | G92: =SUM('Астрид'!G92,'Курортный'!G92,'Новое Колпино'!G92,'Таллинский парк'!G92) | H92: - | I92: =SUM('Астрид'!I92,'Курортный'!I92,'Новое Колпино'!I92,'Таллинский парк'!I92)
A93: Амортизация ОС (МОП) | B93: =SUM(C93,D93,E93,F93) | C93: =SUM('Астрид'!C93,'Курортный'!C93,'Новое Колпино'!C93,'Таллинский парк'!C93) | D93: =SUM('Астрид'!D93,'Курортный'!D93,'Новое Колпино'!D93,'Таллинский парк'!D93) | E93: =SUM('Астрид'!E93,'Курортный'!E93,'Новое Колпино'!E93,'Таллинский парк'!E93) | F93: =SUM('Астрид'!F93,'Курортный'!F93,'Новое Колпино'!F93,'Таллинский парк'!F93) | G93: =SUM('Астрид'!G93,'Курортный'!G93,'Новое Колпино'!G93,'Таллинский парк'!G93) | H93: - | I93: =SUM('Астрид'!I93,'Курортный'!I93,'Новое Колпино'!I93,'Таллинский парк'!I93)
A94: Проценты по кредитам и займам | B94: =SUM(C94,D94,E94,F94) | C94: =SUM('Астрид'!C94,'Курортный'!C94,'Новое Колпино'!C94,'Таллинский парк'!C94) | D94: =SUM('Астрид'!D94,'Курортный'!D94,'Новое Колпино'!D94,'Таллинский парк'!D94) | E94: =SUM('Астрид'!E94,'Курортный'!E94,'Новое Колпино'!E94,'Таллинский парк'!E94) | F94: =SUM('Астрид'!F94,'Курортный'!F94,'Новое Колпино'!F94,'Таллинский парк'!F94) | G94: =SUM('Астрид'!G94,'Курортный'!G94,'Новое Колпино'!G94,'Таллинский парк'!G94) | H94: - | I94: =SUM('Астрид'!I94,'Курортный'!I94,'Новое Колпино'!I94,'Таллинский парк'!I94)
A95: Налог на прибыль | B95: =SUM(B96,B97) | C95: =SUM(C96,C97) | D95: =SUM(D96,D97) | E95: =SUM(E96,E97) | F95: =SUM(F96,F97) | G95: =SUM(G96,G97) | H95: - | I95: =SUM(I96,I97)
A96: Налоги УСН | B96: =SUM(C96,D96,E96,F96) | C96: =SUM('Астрид'!C96,'Курортный'!C96,'Новое Колпино'!C96,'Таллинский парк'!C96) | D96: =SUM('Астрид'!D96,'Курортный'!D96,'Новое Колпино'!D96,'Таллинский парк'!D96) | E96: =SUM('Астрид'!E96,'Курортный'!E96,'Новое Колпино'!E96,'Таллинский парк'!E96) | F96: =SUM('Астрид'!F96,'Курортный'!F96,'Новое Колпино'!F96,'Таллинский парк'!F96) | G96: =SUM('Астрид'!G96,'Курортный'!G96,'Новое Колпино'!G96,'Таллинский парк'!G96) | H96: - | I96: =SUM('Астрид'!I96,'Курортный'!I96,'Новое Колпино'!I96,'Таллинский парк'!I96)
A97: Налоги НДС 5% | B97: =SUM(C97,D97,E97,F97) | C97: =SUM('Астрид'!C97,'Курортный'!C97,'Новое Колпино'!C97,'Таллинский парк'!C97) | D97: =SUM('Астрид'!D97,'Курортный'!D97,'Новое Колпино'!D97,'Таллинский парк'!D97) | E97: =SUM('Астрид'!E97,'Курортный'!E97,'Новое Колпино'!E97,'Таллинский парк'!E97) | F97: =SUM('Астрид'!F97,'Курортный'!F97,'Новое Колпино'!F97,'Таллинский парк'!F97) | G97: =SUM('Астрид'!G97,'Курортный'!G97,'Новое Колпино'!G97,'Таллинский парк'!G97) | H97: - | I97: =SUM('Астрид'!I97,'Курортный'!I97,'Новое Колпино'!I97,'Таллинский парк'!I97)
A98: Чистая прибыль (убыток) | B98: =IFERROR(B89*1,0)-IFERROR(B91*1,0)-IFERROR(B94*1,0)-IFERROR(B95*1,0) | C98: =IFERROR(C89*1,0)-IFERROR(C91*1,0)-IFERROR(C94*1,0)-IFERROR(C95*1,0) | D98: =IFERROR(D89*1,0)-IFERROR(D91*1,0)-IFERROR(D94*1,0)-IFERROR(D95*1,0) | E98: =IFERROR(E89*1,0)-IFERROR(E91*1,0)-IFERROR(E94*1,0)-IFERROR(E95*1,0) | F98: =IFERROR(F89*1,0)-IFERROR(F91*1,0)-IFERROR(F94*1,0)-IFERROR(F95*1,0) | G98: =IFERROR(G89*1,0)-IFERROR(G91*1,0)-IFERROR(G94*1,0)-IFERROR(G95*1,0) | H98: - | I98: =IFERROR(I89*1,0)-IFERROR(I91*1,0)-IFERROR(I94*1,0)-IFERROR(I95*1,0)
A99: Рентабельность чистой прибыли | B99: =IFERROR(IF(B4=0,"-",B98/B4),"-") | C99: =IFERROR(IF(C4=0,"-",C98/C4),"-") | D99: =IFERROR(IF(D4=0,"-",D98/D4),"-") | E99: =IFERROR(IF(E4=0,"-",E98/E4),"-") | F99: =IFERROR(IF(F4=0,"-",F98/F4),"-") | G99: =IFERROR(IF(G4=0,"-",G98/G4),"-") | H99: - | I99: =IFERROR(IF(I4=0,"-",I98/I4),"-")

Sheet Астрид
A1: ПланФакт | B1: Создано с помощью сервиса ПланФакт | I1: =HYPERLINK("https://app.planfact.io/?from=Pf_BDR", "Перейти в сервис")
B2: Итого | C2: июнь` 26 | D2: июль` 26 | E2: август` 26 | F2: сентябрь` 26 | G2: октябрь` 26 | H2: ноябрь` 26 | I2: декабрь` 26
A3: Астрид | B3: план | C3: план | D3: план | E3: план | F3: план | G3: план | H3: план | I3: план
A4: Выручка | B4: =SUM(B5,B6) | C4: =SUM(C5,C6) | D4: =SUM(D5,D6) | E4: =SUM(E5,E6) | F4: =SUM(F5,F6) | G4: =SUM(G5,G6) | H4: - | I4: =SUM(I5,I6)
A5: Нераспределенный доход | B5: =SUM(C5,D5,E5,F5) | C5: - | D5: - | E5: - | F5: - | G5: - | H5: - | I5: -
A6: Выручка | B6: =SUM(B7,B8,B9) | C6: =SUM(C7,C8,C9) | D6: =SUM(D7,D8,D9) | E6: =SUM(E7,E8,E9) | F6: =SUM(F7,F8,F9) | G6: =SUM(G7,G8,G9) | H6: - | I6: =SUM(I7,I8,I9)
A7: Реализация услуг Клининг (ОД) | B7: =SUM(C7,D7,E7,F7) | C7: 228370.58 | D7: 653960.57 | E7: 228370.58 | F7: 653960.57 | G7: - | H7: - | I7: -
A8: Реализация услуг Клининг (Доп.услуги) | B8: =SUM(C8,D8,E8,F8) | C8: - | D8: 470000 | E8: - | F8: - | G8: - | H8: - | I8: -
A9: Реализация услуг Клининг (снег) | B9: =SUM(C9,D9,E9,F9) | C9: - | D9: - | E9: - | F9: - | G9: - | H9: - | I9: -
A10: Прямые расходы | B10: =SUM(B11,B12,B13,B21,B22,B23,B24,B25,B26,B27,B28,B29,B30,B31,B32,B33,B34) | C10: =SUM(C11,C12,C13,C21,C22,C23,C24,C25,C26,C27,C28,C29,C30,C31,C32,C33,C34) | D10: =SUM(D11,D12,D13,D21,D22,D23,D24,D25,D26,D27,D28,D29,D30,D31,D32,D33,D34) | E10: =SUM(E11,E12,E13,E21,E22,E23,E24,E25,E26,E27,E28,E29,E30,E31,E32,E33,E34) | F10: =SUM(F11,F12,F13,F21,F22,F23,F24,F25,F26,F27,F28,F29,F30,F31,F32,F33,F34) | G10: =SUM(G11,G12,G13,G21,G22,G23,G24,G25,G26,G27,G28,G29,G30,G31,G32,G33,G34) | H10: - | I10: =SUM(I11,I12,I13,I21,I22,I23,I24,I25,I26,I27,I28,I29,I30,I31,I32,I33,I34)
A11: Нераспределенный расход | B11: =SUM(C11,D11,E11,F11) | C11: - | D11: - | E11: - | F11: - | G11: - | H11: - | I11: -
A12: Транспортные расходы | B12: =SUM(C12,D12,E12,F12) | C12: - | D12: - | E12: - | F12: - | G12: - | H12: - | I12: -
A13: Переменные | B13: =SUM(B14,B15,B16,B17,B18,B19,B20) | C13: =SUM(C14,C15,C16,C17,C18,C19,C20) | D13: =SUM(D14,D15,D16,D17,D18,D19,D20) | E13: =SUM(E14,E15,E16,E17,E18,E19,E20) | F13: =SUM(F14,F15,F16,F17,F18,F19,F20) | G13: =SUM(G14,G15,G16,G17,G18,G19,G20) | H13: - | I13: =SUM(I14,I15,I16,I17,I18,I19,I20)
A14: Услуги техниги для уборки снега (ПТ) | B14: =SUM(C14,D14,E14,F14) | C14: - | D14: - | E14: - | F14: - | G14: - | H14: - | I14: -
A15: Услуги садовника (ПТ) | B15: =SUM(C15,D15,E15,F15) | C15: - | D15: - | E15: - | F15: - | G15: - | H15: - | I15: -
A16: Сыпучие материалы (ПТ) | B16: =SUM(C16,D16,E16,F16) | C16: - | D16: - | E16: - | F16: - | G16: - | H16: - | I16: -
A17: Расходные материалы и инстументы (МОП) | B17: =SUM(C17,D17,E17,F17) | C17: 10587.92 | D17: 21587.92 | E17: 10587.92 | F17: 10000 | G17: - | H17: - | I17: -
A18: Расходные материалы и инстументы (ПТ) | B18: =SUM(C18,D18,E18,F18) | C18: - | D18: 5000 | E18: - | F18: 5000 | G18: - | H18: - | I18: -
A19: Арена оборудования (ПТ) | B19: =SUM(C19,D19,E19,F19) | C19: - | D19: - | E19: - | F19: - | G19: - | H19: - | I19: -
A20: Арена оборудования (МОП) | B20: =SUM(C20,D20,E20,F20) | C20: - | D20: - | E20: - | F20: - | G20: - | H20: - | I20: -
A21: Заработная плата (МОП) | B21: =SUM(C21,D21,E21,F21) | C21: 209688.53 | D21: 210030 | E21: 209688.53 | F21: 210030 | G21: - | H21: - | I21: -
A22: Заработная плата (ПТ) | B22: =SUM(C22,D22,E22,F22) | C22: 294494.09 | D22: 258000 | E22: 294494.09 | F22: 258000 | G22: - | H22: - | I22: -
A23: Налоги с ФОТ (МОП) | B23: =SUM(C23,D23,E23,F23) | C23: 19188.5 | D23: 64800 | E23: 19188.5 | F23: 42000 | G23: - | H23: - | I23: -
A24: Налоги с ФОТ (ПТ) | B24: =SUM(C24,D24,E24,F24) | C24: 13380.59 | D24: 5012.59 | E24: 13380.59 | F24: - | G24: - | H24: - | I24: -
A25: Премми (МОП) | B25: =SUM(C25,D25,E25,F25) | C25: - | D25: - | E25: - | F25: - | G25: - | H25: - | I25: -
A26: Премми (ПТ) | B26: =SUM(C26,D26,E26,F26) | C26: - | D26: - | E26: - | F26: - | G26: - | H26: - | I26: -
A27: Униформа (МОП) | B27: =SUM(C27,D27,E27,F27) | C27: - | D27: - | E27: - | F27: - | G27: - | H27: - | I27: -
A28: Униформа (ПТ) | B28: =SUM(C28,D28,E28,F28) | C28: - | D28: - | E28: - | F28: - | G28: - | H28: - | I28: -
A29: Ремонт оборудования (МОП) | B29: =SUM(C29,D29,E29,F29) | C29: - | D29: - | E29: - | F29: - | G29: - | H29: - | I29: -
A30: Ремонт оборудования (ПТ) | B30: =SUM(C30,D30,E30,F30) | C30: 1019 | D30: - | E30: 1019 | F30: - | G30: - | H30: - | I30: -
A31: Вывоз мусора | B31: =SUM(C31,D31,E31,F31) | C31: - | D31: - | E31: - | F31: - | G31: - | H31: - | I31: -
A32: Штрафы, пени, неустойки | B32: =SUM(C32,D32,E32,F32) | C32: - | D32: - | E32: - | F32: - | G32: - | H32: - | I32: -
A33: Расходы к удержанию | B33: =SUM(C33,D33,E33,F33) | C33: - | D33: - | E33: - | F33: - | G33: - | H33: - | I33: -
A34: Общехозяйственные | B34: =SUM(B35,B36,B37,B38,B39,B40,B41,B42) | C34: =SUM(C35,C36,C37,C38,C39,C40,C41,C42) | D34: =SUM(D35,D36,D37,D38,D39,D40,D41,D42) | E34: =SUM(E35,E36,E37,E38,E39,E40,E41,E42) | F34: =SUM(F35,F36,F37,F38,F39,F40,F41,F42) | G34: =SUM(G35,G36,G37,G38,G39,G40,G41,G42) | H34: - | I34: =SUM(I35,I36,I37,I38,I39,I40,I41,I42)
A35: Аутсорс (направления) | B35: =SUM(C35,D35,E35,F35) | C35: 10000 | D35: 7500 | E35: 10000 | F35: 2500 | G35: - | H35: - | I35: -
A36: Заработная плата МО АУП | B36: =SUM(C36,D36,E36,F36) | C36: 60000 | D36: 60000 | E36: 60000 | F36: 60000 | G36: - | H36: - | I36: -
A37: Инструменты: ГСМ | B37: =SUM(C37,D37,E37,F37) | C37: 2000 | D37: 1000 | E37: 2000 | F37: 1000 | G37: - | H37: - | I37: -
A38: Медосмотры | B38: =SUM(C38,D38,E38,F38) | C38: - | D38: - | E38: - | F38: - | G38: - | H38: - | I38: -
A39: Налоги с ФОТ (ИП) | B39: =SUM(C39,D39,E39,F39) | C39: 26500 | D39: 36960 | E39: 26500 | F39: 36960 | G39: - | H39: - | I39: -
A40: Приобритение мебели, бытовой техники | B40: =SUM(C40,D40,E40,F40) | C40: - | D40: - | E40: - | F40: - | G40: - | H40: - | I40: -
A41: Комиссия за перевод ЗП | B41: =SUM(C41,D41,E41,F41) | C41: 1000 | D41: - | E41: 1000 | F41: - | G41: - | H41: - | I41: -
A42: Аренда квартиры (включая коммуналку) | B42: =SUM(C42,D42,E42,F42) | C42: - | D42: - | E42: - | F42: - | G42: - | H42: - | I42: -
A43: Валовая прибыль | B43: =B4-B10 | C43: =C4-C10 | D43: =D4-D10 | E43: =E4-E10 | F43: =F4-F10 | G43: =G4-G10 | H43: - | I43: =I4-I10
A44: Валовая рентабельность | B44: =IFERROR(IF(B4=0,"-",B43/B4),"-") | C44: =IFERROR(IF(C4=0,"-",C43/C4),"-") | D44: =IFERROR(IF(D4=0,"-",D43/D4),"-") | E44: =IFERROR(IF(E4=0,"-",E43/E4),"-") | F44: =IFERROR(IF(F4=0,"-",F43/F4),"-") | G44: =IFERROR(IF(G4=0,"-",G43/G4),"-") | H44: - | I44: =IFERROR(IF(I4=0,"-",I43/I4),"-")
A45: Косвенные расходы | B45: =SUM(B46,B47,B48,B52,B56,B57,B58,B59,B60,B63,B64,B65,B66,B67,B68,B69,B70,B71,B72,B73,B74,B75,B76,B77,B78,B79) | C45: =SUM(C46,C47,C48,C52,C56,C57,C58,C59,C60,C63,C64,C65,C66,C67,C68,C69,C70,C71,C72,C73,C74,C75,C76,C77,C78,C79) | D45: =SUM(D46,D47,D48,D52,D56,D57,D58,D59,D60,D63,D64,D65,D66,D67,D68,D69,D70,D71,D72,D73,D74,D75,D76,D77,D78,D79) | E45: =SUM(E46,E47,E48,E52,E56,E57,E58,E59,E60,E63,E64,E65,E66,E67,E68,E69,E70,E71,E72,E73,E74,E75,E76,E77,E78,E79) | F45: =SUM(F46,F47,F48,F52,F56,F57,F58,F59,F60,F63,F64,F65,F66,F67,F68,F69,F70,F71,F72,F73,F74,F75,F76,F77,F78,F79) | G45: =SUM(G46,G47,G48,G52,G56,G57,G58,G59,G60,G63,G64,G65,G66,G67,G68,G69,G70,G71,G72,G73,G74,G75,G76,G77,G78,G79) | H45: - | I45: =SUM(I46,I47,I48,I52,I56,I57,I58,I59,I60,I63,I64,I65,I66,I67,I68,I69,I70,I71,I72,I73,I74,I75,I76,I77,I78,I79)
A46: Расход БЭК-ОФИС | B46: =SUM(C46,D46,E46,F46) | C46: 55821.21 | D46: 84919.2 | E46: 55821.21 | F46: 84919.2 | G46: - | H46: - | I46: -
A47: Расходы на бэк-офис | B47: =SUM(C47,D47,E47,F47) | C47: - | D47: - | E47: - | F47: - | G47: - | H47: - | I47: -
A48: Автомобиль | B48: =SUM(B49,B50,B51) | C48: =SUM(C49,C50,C51) | D48: =SUM(D49,D50,D51) | E48: =SUM(E49,E50,E51) | F48: =SUM(F49,F50,F51) | G48: =SUM(G49,G50,G51) | H48: - | I48: =SUM(I49,I50,I51)
A49: Автомобиль: ГСМ | B49: =SUM(C49,D49,E49,F49) | C49: - | D49: - | E49: - | F49: - | G49: - | H49: - | I49: -
A50: Автомобиль: страхование | B50: =SUM(C50,D50,E50,F50) | C50: - | D50: - | E50: - | F50: - | G50: - | H50: - | I50: -
A51: Автомобиль: ТО | B51: =SUM(C51,D51,E51,F51) | C51: - | D51: - | E51: - | F51: - | G51: - | H51: - | I51: -
A52: Офисные расходы | B52: =SUM(B53,B54,B55) | C52: =SUM(C53,C54,C55) | D52: =SUM(D53,D54,D55) | E52: =SUM(E53,E54,E55) | F52: =SUM(F53,F54,F55) | G52: =SUM(G53,G54,G55) | H52: - | I52: =SUM(I53,I54,I55)
A53: Аренда офиса | B53: =SUM(C53,D53,E53,F53) | C53: - | D53: - | E53: - | F53: - | G53: - | H53: - | I53: -
A54: Канцелярия и обслуживание | B54: =SUM(C54,D54,E54,F54) | C54: - | D54: - | E54: - | F54: - | G54: - | H54: - | I54: -
A55: Интернет и связь | B55: =SUM(C55,D55,E55,F55) | C55: - | D55: - | E55: - | F55: - | G55: - | H55: - | I55: -
A56: Банковские услуги | B56: =SUM(C56,D56,E56,F56) | C56: - | D56: - | E56: - | F56: - | G56: - | H56: - | I56: -
A57: Заработная плата АУП (БО) | B57: =SUM(C57,D57,E57,F57) | C57: - | D57: - | E57: - | F57: - | G57: - | H57: - | I57: -
A58: Заработная плата бухгалтерии (БО) | B58: =SUM(C58,D58,E58,F58) | C58: - | D58: - | E58: - | F58: - | G58: - | H58: - | I58: -
A59: Заработная плата СБ (БО) | B59: =SUM(C59,D59,E59,F59) | C59: - | D59: - | E59: - | F59: - | G59: - | H59: - | I59: -
A60: Командировочные расходы | B60: =SUM(B61,B62) | C60: =SUM(C61,C62) | D60: =SUM(D61,D62) | E60: =SUM(E61,E62) | F60: =SUM(F61,F62) | G60: =SUM(G61,G62) | H60: - | I60: =SUM(I61,I62)
A61: Командировнчеы расходы: билеты (БО) | B61: =SUM(C61,D61,E61,F61) | C61: - | D61: - | E61: - | F61: - | G61: - | H61: - | I61: -
A62: Командировнчеы расходы: проживание (БО) | B62: =SUM(C62,D62,E62,F62) | C62: - | D62: - | E62: - | F62: - | G62: - | H62: - | I62: -
A63: Комиссия УК ДОМ | B63: =SUM(C63,D63,E63,F63) | C63: - | D63: - | E63: - | F63: - | G63: - | H63: - | I63: -
A64: Налоги с ФОТ (ИП)_БО | B64: =SUM(C64,D64,E64,F64) | C64: - | D64: - | E64: - | F64: - | G64: - | H64: - | I64: -
A65: Налоги с ФОТ (НДФЛ) БО | B65: =SUM(C65,D65,E65,F65) | C65: - | D65: - | E65: - | F65: - | G65: - | H65: - | I65: -
A66: Налоги с ФОТ (страховые взносы) БО | B66: =SUM(C66,D66,E66,F66) | C66: - | D66: - | E66: - | F66: - | G66: - | H66: - | I66: -
A67: Нотариальные услуги | B67: =SUM(C67,D67,E67,F67) | C67: - | D67: - | E67: - | F67: - | G67: - | H67: - | I67: -
A68: Обслуживание техники (БО) | B68: =SUM(C68,D68,E68,F68) | C68: - | D68: - | E68: - | F68: - | G68: - | H68: - | I68: -
A69: Программное обеспечение (БО) | B69: =SUM(C69,D69,E69,F69) | C69: - | D69: - | E69: - | F69: - | G69: - | H69: - | I69: -
A70: ПланФакт | B70: =SUM(C70,D70,E70,F70) | C70: - | D70: - | E70: - | F70: - | G70: - | H70: - | I70: -
A71: ТБ | B71: =SUM(C71,D71,E71,F71) | C71: - | D71: - | E71: - | F71: - | G71: - | H71: - | I71: -
A72: Контур | B72: =SUM(C72,D72,E72,F72) | C72: - | D72: - | E72: - | F72: - | G72: - | H72: - | I72: -
... A79: HR (аутсорс) | B79: =SUM(C79,D79,E79,F79) | C79: - | D79: - | E79: - | F79: - | G79: - | H79: - | I79: -
A80: Операционная прибыль | B80: =B43-B45 | C80: =C43-C45 | D80: =D43-D45 | E80: =E43-E45 | F80: =F43-F45 | G80: =G43-G45 | H80: - | I80: =I43-I45
A81: Операционная рентабельность | B81: =IFERROR(IF(B4=0,"-",B80/B4),"-") | C81: =IFERROR(IF(C4=0,"-",C80/C4),"-") | D81: =IFERROR(IF(D4=0,"-",D80/D4),"-") | E81: =IFERROR(IF(E4=0,"-",E80/E4),"-") | F81: =IFERROR(IF(F4=0,"-",F80/F4),"-") | G81: =IFERROR(IF(G4=0,"-",G80/G4),"-") | H81: - | I81: =IFERROR(IF(I4=0,"-",I80/I4),"-")
A82: Прочие доходы | B82: =SUM(B83,B84,B85,B86) | C82: =SUM(C83,C84,C85,C86) | D82: =SUM(D83,D84,D85,D86) | E82: =SUM(E83,E84,E85,E86) | F82: =SUM(F83,F84,F85,F86) | G82: =SUM(G83,G84,G85,G86) | H82: - | I82: =SUM(I83,I84,I85,I86)
A83: Доход БЭК-ОФИС | B83: =SUM(C83,D83,E83,F83) | C83: - | D83: - | E83: - | F83: - | G83: - | H83: - | I83: -
A84: Пополненин бэк-офис | B84: =SUM(C84,D84,E84,F84) | C84: - | D84: - | E84: - | F84: - | G84: - | H84: - | I84: -
A85: Проценты по вкладам | B85: =SUM(C85,D85,E85,F85) | C85: - | D85: - | E85: - | F85: - | G85: - | H85: - | I85: -
A86: Курсовая разница (+) | B86: =SUM(C86,D86,E86,F86) | C86: - | D86: - | E86: - | F86: - | G86: - | H86: - | I86: -
A87: Прочие расходы | B87: =SUM(B88) | C87: =SUM(C88) | D87: =SUM(D88) | E87: =SUM(E88) | F87: =SUM(F88) | G87: =SUM(G88) | H87: - | I87: =SUM(I88)
A88: Курсовая разница (-) | B88: =SUM(C88,D88,E88,F88) | C88: - | D88: - | E88: - | F88: - | G88: - | H88: - | I88: -
A89: EBITDA | B89: =B80+IFERROR(B82*1,0)-IFERROR(B87*1,0) | C89: =C80+IFERROR(C82*1,0)-IFERROR(C87*1,0) | D89: =D80+IFERROR(D82*1,0)-IFERROR(D87*1,0) | E89: =E80+IFERROR(E82*1,0)-IFERROR(E87*1,0) | F89: =F80+IFERROR(F82*1,0)-IFERROR(F87*1,0) | G89: =G80+IFERROR(G82*1,0)-IFERROR(G87*1,0) | H89: - | I89: =I80+IFERROR(I82*1,0)-IFERROR(I87*1,0)
A90: Рентабельность по EBITDA | B90: =IFERROR(IF(B4=0,"-",B89/B4),"-") | C90: =IFERROR(IF(C4=0,"-",C89/C4),"-") | D90: =IFERROR(IF(D4=0,"-",D89/D4),"-") | E90: =IFERROR(IF(E4=0,"-",E89/E4),"-") | F90: =IFERROR(IF(F4=0,"-",F89/F4),"-") | G90: =IFERROR(IF(G4=0,"-",G89/G4),"-") | H90: - | I90: =IFERROR(IF(I4=0,"-",I89/I4),"-")
A91: Амортизация | B91: =SUM(B92,B93) | C91: =SUM(C92,C93) | D91: =SUM(D92,D93) | E91: =SUM(E92,E93) | F91: =SUM(F92,F93) | G91: =SUM(G92,G93) | H91: - | I91: =SUM(I92,I93)
A92: Амортизация ОС (ПТ) | B92: =SUM(C92,D92,E92,F92) | C92: - | D92: - | E92: - | F92: - | G92: - | H92: - | I92: -
A93: Амортизация ОС (МОП) | B93: =SUM(C93,D93,E93,F93) | C93: - | D93: - | E93: - | F93: - | G93: - | H93: - | I93: -
A94: Проценты по кредитам и займам | B94: =SUM(C94,D94,E94,F94) | C94: - | D94: - | E94: - | F94: - | G94: - | H94: - | I94: -
A95: Налог на прибыль | B95: =SUM(B96,B97) | C95: =SUM(C96,C97) | D95: =SUM(D96,D97) | E95: =SUM(E96,E97) | F95: =SUM(F96,F97) | G95: =SUM(G96,G97) | H95: - | I95: =SUM(I96,I97)
A96: Налоги УСН | B96: =SUM(C96,D96,E96,F96) | C96: - | D96: 10000 | E96: - | F96: 10000 | G96: - | H96: - | I96: -
A97: Налоги НДС 5% | B97: =SUM(C97,D97,E97,F97) | C97: 38678.65 | D97: 31140.99 | E97: 38678.65 | F97: 31140.99 | G97: - | H97: - | I97: -
A98: Чистая прибыль (убыток) | B98: =IFERROR(B89*1,0)-IFERROR(B91*1,0)-IFERROR(B94*1,0)-IFERROR(B95*1,0) | C98: =IFERROR(C89*1,0)-IFERROR(C91*1,0)-IFERROR(C94*1,0)-IFERROR(C95*1,0) | D98: =IFERROR(D89*1,0)-IFERROR(D91*1,0)-IFERROR(D94*1,0)-IFERROR(D95*1,0) | E98: =IFERROR(E89*1,0)-IFERROR(E91*1,0)-IFERROR(E94*1,0)-IFERROR(E95*1,0) | F98: =IFERROR(F89*1,0)-IFERROR(F91*1,0)-IFERROR(F94*1,0)-IFERROR(F95*1,0) | G98: =IFERROR(G89*1,0)-IFERROR(G91*1,0)-IFERROR(G94*1,0)-IFERROR(G95*1,0) | H98: - | I98: =IFERROR(I89*1,0)-IFERROR(I91*1,0)-IFERROR(I94*1,0)-IFERROR(I95*1,0)
A99: Рентабельность чистой прибыли | B99: =IFERROR(IF(B4=0,"-",B98/B4),"-") | C99: =IFERROR(IF(C4=0,"-",C98/C4),"-") | D99: =IFERROR(IF(D4=0,"-",D98/D4),"-") | E99: =IFERROR(IF(E4=0,"-",E98/E4),"-") | F99: =IFERROR(IF(F4=0,"-",F98/F4),"-") | G99: =IFERROR(IF(G4=0,"-",G98/G4),"-") | H99: - | I99: =IFERROR(IF(I4=0,"-",I98/I4),"-")

Sheet Курортный
A1: ПланФакт | B1: Создано с помощью сервиса ПланФакт | I1: =HYPERLINK("https://app.planfact.io/?from=Pf_BDR", "Перейти в сервис")
B2: Итого | C2: июнь` 26 | D2: июль` 26 | E2: август` 26 | F2: сентябрь` 26 | G2: октябрь` 26 | H2: ноябрь` 26 | I2: декабрь` 26
A3: Курортный | B3: план | C3: план | D3: план | E3: план | F3: план | G3: план | H3: план | I3: план
A4: Выручка | B4: =SUM(B5,B6) | C4: =SUM(C5,C6) | D4: =SUM(D5,D6) | E4: =SUM(E5,E6) | F4: =SUM(F5,F6) | G4: =SUM(G5,G6) | H4: - | I4: =SUM(I5,I6)
A5: Нераспределенный доход | B5: =SUM(C5,D5,E5,F5) | C5: - | D5: - | E5: - | F5: - | G5: - | H5: - | I5: -
A6: Выручка | B6: =SUM(B7,B8,B9) | C6: =SUM(C7,C8,C9) | D6: =SUM(D7,D8,D9) | E6: =SUM(E7,E8,E9) | F6: =SUM(F7,F8,F9) | G6: =SUM(G7,G8,G9) | H6: - | I6: =SUM(I7,I8,I9)
A7: Реализация услуг Клининг (ОД) | B7: =SUM(C7,D7,E7,F7) | C7: 1299347.8 | D7: 1299347.8 | E7: 1299347.8 | F7: 1299347.8 | G7: - | H7: - | I7: -
A8: Реализация услуг Клининг (Доп.услуги) | B8: =SUM(C8,D8,E8,F8) | C8: 772382 | D8: 661260 | E8: 661260.69 | F8: 661260.69 | G8: - | H8: - | I8: -
A9: Реализация услуг Клининг (снег) | B9: =SUM(C9,D9,E9,F9) | C9: - | D9: - | E9: - | F9: - | G9: - | H9: - | I9: -
A10: Прямые расходы | B10: =SUM(B11,B12,B13,B21,B22,B23,B24,B25,B26,B27,B28,B29,B30,B31,B32,B33,B34) | C10: =SUM(C11,C12,C13,C21,C22,C23,C24,C25,C26,C27,C28,C29,C30,C31,C32,C33,C34) | D10: =SUM(D11,D12,D13,D21,D22,D23,D24,D25,D26,D27,D28,D29,D30,D31,D32,D33,D34) | E10: =SUM(E11,E12,E13,E21,E22,E23,E24,E25,E26,E27,E28,E29,E30,E31,E32,E33,E34) | F10: =SUM(F11,F12,F13,F21,F22,F23,F24,F25,F26,F27,F28,F29,F30,F31,F32,F33,F34) | G10: =SUM(G11,G12,G13,G21,G22,G23,G24,G25,G26,G27,G28,G29,G30,G31,G32,G33,G34) | H10: - | I10: =SUM(I11,I12,I13,I21,I22,I23,I24,I25,I26,I27,I28,I29,I30,I31,I32,I33,I34)
A11: Нераспределенный расход | B11: =SUM(C11,D11,E11,F11) | C11: - | D11: - | E11: - | F11: - | G11: - | H11: - | I11: -
A12: Транспортные расходы | B12: =SUM(C12,D12,E12,F12) | C12: - | D12: - | E12: - | F12: - | G12: - | H12: - | I12: -
A13: Переменные | B13: =SUM(B14,B15,B16,B17,B18,B19,B20) | C13: =SUM(C14,C15,C16,C17,C18,C19,C20) | D13: =SUM(D14,D15,D16,D17,D18,D19,D20) | E13: =SUM(E14,E15,E16,E17,E18,E19,E20) | F13: =SUM(F14,F15,F16,F17,F18,F19,F20) | G13: =SUM(G14,G15,G16,G17,G18,G19,G20) | H13: - | I13: =SUM(I14,I15,I16,I17,I18,I19,I20)
A14: Услуги техниги для уборки снега (ПТ) | B14: =SUM(C14,D14,E14,F14) | C14: - | D14: - | E14: - | F14: - | G14: - | H14: - | I14: -
A15: Услуги садовника (ПТ) | B15: =SUM(C15,D15,E15,F15) | C15: - | D15: - | E15: - | F15: - | G15: - | H15: - | I15: -
A16: Сыпучие материалы (ПТ) | B16: =SUM(C16,D16,E16,F16) | C16: - | D16: - | E16: - | F16: - | G16: - | H16: - | I16: -
A17: Расходные материалы и инстументы (МОП) | B17: =SUM(C17,D17,E17,F17) | C17: 10000 | D17: 10000 | E17: 10000 | F17: 10000 | G17: - | H17: - | I17: -
A18: Расходные материалы и инстументы (ПТ) | B18: =SUM(C18,D18,E18,F18) | C18: 7999 | D18: 5000 | E18: 5000 | F18: 5000 | G18: - | H18: - | I18: -
A19: Арена оборудования (ПТ) | B19: =SUM(C19,D19,E19,F19) | C19: - | D19: - | E19: - | F19: - | G19: - | H19: - | I19: -
A20: Арена оборудования (МОП) | B20: =SUM(C20,D20,E20,F20) | C20: - | D20: - | E20: - | F20: - | G20: - | H20: - | I20: -
A21: Заработная плата (МОП) | B21: =SUM(C21,D21,E21,F21) | C21: 695034.97 | D21: 665000 | E21: 665000 | F21: 665000 | G21: - | H21: - | I21: -
A22: Заработная плата (ПТ) | B22: =SUM(C22,D22,E22,F22) | C22: 600000 | D22: 600000 | E22: 600000 | F22: 600000 | G22: - | H22: - | I22: -
A23: Налоги с ФОТ (МОП) | B23: =SUM(C23,D23,E23,F23) | C23: 60061 | D23: 79913 | E23: 79913 | F23: 79913 | G23: - | H23: - | I23: -
A24: Налоги с ФОТ (ПТ) | B24: =SUM(C24,D24,E24,F24) | C24: 28000 | D24: 28000 | E24: 28000 | F24: 28000 | G24: - | H24: - | I24: -
A25: Премми (МОП) | B25: =SUM(C25,D25,E25,F25) | C25: - | D25: - | E25: - | F25: - | G25: - | H25: - | I25: -
A26: Премми (ПТ) | B26: =SUM(C26,D26,E26,F26) | C26: - | D26: - | E26: - | F26: - | G26: - | H26: - | I26: -
A27: Униформа (МОП) | B27: =SUM(C27,D27,E27,F27) | C27: - | D27: - | E27: - | F27: - | G27: - | H27: - | I27: -
A28: Униформа (ПТ) | B28: =SUM(C28,D28,E28,F28) | C28: 7069 | D28: - | E28: - | F28: - | G28: - | H28: - | I28: -
A29: Ремонт оборудования (МОП) | B29: =SUM(C29,D29,E29,F29) | C29: - | D29: - | E29: - | F29: - | G29: - | H29: - | I29: -
A30: Ремонт оборудования (ПТ) | B30: =SUM(C30,D30,E30,F30) | C30: 3000 | D30: 3000 | E30: 3000 | F30: 3000 | G30: - | H30: - | I30: -
A31: Вывоз мусора | B31: =SUM(C31,D31,E31,F31) | C31: - | D31: - | E31: - | F31: - | G31: - | H31: - | I31: -
A32: Штрафы, пени, неустойки | B32: =SUM(C32,D32,E32,F32) | C32: - | D32: - | E32: - | F32: - | G32: - | H32: - | I32: -
A33: Расходы к удержанию | B33: =SUM(C33,D33,E33,F33) | C33: - | D33: - | E33: - | F33: - | G33: - | H33: - | I33: -
A34: Общехозяйственные | B34: =SUM(B35,B36,B37,B38,B39,B40,B41,B42) | C34: =SUM(C35,C36,C37,C38,C39,C40,C41,C42) | D34: =SUM(D35,D36,D37,D38,D39,D40,D41,D42) | E34: =SUM(E35,E36,E37,E38,E39,E40,E41,E42) | F34: =SUM(F35,F36,F37,F38,F39,F40,F41,F42) | G34: =SUM(G35,G36,G37,G38,G39,G40,G41,G42) | H34: - | I34: =SUM(I35,I36,I37,I38,I39,I40,I41,I42)
A35: Аутсорс (направления) | B35: =SUM(C35,D35,E35,F35) | C35: 2500 | D35: 2500 | E35: 2500 | F35: 2500 | G35: - | H35: - | I35: -
A36: Заработная плата МО АУП | B36: =SUM(C36,D36,E36,F36) | C36: 110000 | D36: 110000 | E36: 110000 | F36: 110000 | G36: - | H36: - | I36: -
A37: Инструменты: ГСМ | B37: =SUM(C37,D37,E37,F37) | C37: 3504.04 | D37: 3500 | E37: 3500 | F37: 3500 | G37: - | H37: - | I37: -
A38: Медосмотры | B38: =SUM(C38,D38,E38,F38) | C38: - | D38: - | E38: - | F38: - | G38: - | H38: - | I38: -
A39: Налоги с ФОТ (ИП) | B39: =SUM(C39,D39,E39,F39) | C39: 95550 | D39: 95550 | E39: 95550 | F39: 95550 | G39: - | H39: - | I39: -
A40: Приобритение мебели, бытовой техники | B40: =SUM(C40,D40,E40,F40) | C40: - | D40: - | E40: - | F40: - | G40: - | H40: - | I40: -
A41: Комиссия за перевод ЗП | B41: =SUM(C41,D41,E41,F41) | C41: 4000 | D41: 4000 | E41: 4000 | F41: 4000 | G41: - | H41: - | I41: -
A42: Аренда квартиры (включая коммуналку) | B42: =SUM(C42,D42,E42,F42) | C42: 44440.43 | D42: 45000 | E42: 45000 | F42: 45000 | G42: - | H42: - | I42: -
A43: Валовая прибыль | B43: =B4-B10 | C43: =C4-C10 | D43: =D4-D10 | E43: =E4-E10 | F43: =F4-F10 | G43: =G4-G10 | H43: - | I43: =I4-I10
A44: Валовая рентабельность | B44: =IFERROR(IF(B4=0,"-",B43/B4),"-") | C44: =IFERROR(IF(C4=0,"-",C43/C4),"-") | D44: =IFERROR(IF(D4=0,"-",D43/D4),"-") | E44: =IFERROR(IF(E4=0,"-",E43/E4),"-") | F44: =IFERROR(IF(F4=0,"-",F43/F4),"-") | G44: =IFERROR(IF(G4=0,"-",G43/G4),"-") | H44: - | I44: =IFERROR(IF(I4=0,"-",I43/I4),"-")
A45: Косвенные расходы | B45: =SUM(B46,B47,B48,B52,B56,B57,B58,B59,B60,B63,B64,B65,B66,B67,B68,B69,B70,B71,B72,B73,B74,B75,B76,B77,B78,B79) | C45: =SUM(C46,C47,C48,C52,C56,C57,C58,C59,C60,C63,C64,C65,C66,C67,C68,C69,C70,C71,C72,C73,C74,C75,C76,C77,C78,C79) | D45: =SUM(D46,D47,D48,D52,D56,D57,D58,D59,D60,D63,D64,D65,D66,D67,D68,D69,D70,D71,D72,D73,D74,D75,D76,D77,D78,D79) | E45: =SUM(E46,E47,E48,E52,E56,E57,E58,E59,E60,E63,E64,E65,E66,E67,E68,E69,E70,E71,E72,E73,E74,E75,E76,E77,E78,E79) | F45: =SUM(F46,F47,F48,F52,F56,F57,F58,F59,F60,F63,F64,F65,F66,F67,F68,F69,F70,F71,F72,F73,F74,F75,F76,F77,F78,F79) | G45: =SUM(G46,G47,G48,G52,G56,G57,G58,G59,G60,G63,G64,G65,G66,G67,G68,G69,G70,G71,G72,G73,G74,G75,G76,G77,G78,G79) | H45: - | I45: =SUM(I46,I47,I48,I52,I56,I57,I58,I59,I60,I63,I64,I65,I66,I67,I68,I69,I70,I71,I72,I73,I74,I75,I76,I77,I78,I79)
A46: Расход БЭК-ОФИС | B46: =SUM(C46,D46,E46,F46) | C46: 139048.12 | D46: 139048.12 | E46: 139048.12 | F46: 139048.12 | G46: - | H46: - | I46: -
A47: Расходы на бэк-офис | B47: =SUM(C47,D47,E47,F47) | C47: - | D47: - | E47: - | F47: - | G47: - | H47: - | I47: -
A48: Автомобиль | B48: =SUM(B49,B50,B51) | C48: =SUM(C49,C50,C51) | D48: =SUM(D49,D50,D51) | E48: =SUM(E49,E50,E51) | F48: =SUM(F49,F50,F51) | G48: =SUM(G49,G50,G51) | H48: - | I48: =SUM(I49,I50,I51)
A49: Автомобиль: ГСМ | B49: =SUM(C49,D49,E49,F49) | C49: - | D49: - | E49: - | F49: - | G49: - | H49: - | I49: -
A50: Автомобиль: страхование | B50: =SUM(C50,D50,E50,F50) | C50: - | D50: - | E50: - | F50: - | G50: - | H50: - | I50: -
A51: Автомобиль: ТО | B51: =SUM(C51,D51,E51,F51) | C51: - | D51: - | E51: - | F51: - | G51: - | H51: - | I51: -
A52: Офисные расходы | B52: =SUM(B53,B54,B55) | C52: =SUM(C53,C54,C55) | D52: =SUM(D53,D54,D55) | E52: =SUM(E53,E54,E55) | F52: =SUM(F53,F54,F55) | G52: =SUM(G53,G54,G55) | H52: - | I52: =SUM(I53,I54,I55)
A53: Аренда офиса | B53: =SUM(C53,D53,E53,F53) | C53: - | D53: - | E53: - | F53: - | G53: - | H53: - | I53: -
A54: Канцелярия и обслуживание | B54: =SUM(C54,D54,E54,F54) | C54: - | D54: - | E54: - | F54: - | G54: - | H54: - | I54: -
A55: Интернет и связь | B55: =SUM(C55,D55,E55,F55) | C55: - | D55: - | E55: - | F55: - | G55: - | H55: - | I55: -
A56: Банковские услуги | B56: =SUM(C56,D56,E56,F56) | C56: - | D56: - | E56: - | F56: - | G56: - | H56: - | I56: -
A57: Заработная плата АУП (БО) | B57: =SUM(C57,D57,E57,F57) | C57: - | D57: - | E57: - | F57: - | G57: - | H57: - | I57: -
A58: Заработная плата бухгалтерии (БО) | B58: =SUM(C58,D58,E58,F58) | C58: - | D58: - | E58: - | F58: - | G58: - | H58: - | I58: -
A59: Заработная плата СБ (БО) | B59: =SUM(C59,D59,E59,F59) | C59: - | D59: - | E59: - | F59: - | G59: - | H59: - | I59: -
A60: Командировочные расходы | B60: =SUM(B61,B62) | C60: =SUM(C61,C62) | D60: =SUM(D61,D62) | E60: =SUM(E61,E62) | F60: =SUM(F61,F62) | G60: =SUM(G61,G62) | H60: - | I60: =SUM(I61,I62)
A61: Командировнчеы расходы: билеты (БО) | B61: =SUM(C61,D61,E61,F61) | C61: - | D61: - | E61: - | F61: - | G61: - | H61: - | I61: -
A62: Командировнчеы расходы: проживание (БО) | B62: =SUM(C62,D62,E62,F62) | C62: - | D62: - | E62: - | F62: - | G62: - | H62: - | I62: -
A63: Комиссия УК ДОМ | B63: =SUM(C63,D63,E63,F63) | C63: - | D63: - | E63: - | F63: - | G63: - | H63: - | I63: -
A64: Налоги с ФОТ (ИП)_БО | B64: =SUM(C64,D64,E64,F64) | C64: - | D64: - | E64: - | F64: - | G64: - | H64: - | I64: -
A65: Налоги с ФОТ (НДФЛ) БО | B65: =SUM(C65,D65,E65,F65) | C65: - | D65: - | E65: - | F65: - | G65: - | H65: - | I65: -
A66: Налоги с ФОТ (страховые взносы) БО | B66: =SUM(C66,D66,E66,F66) | C66: - | D66: - | E66: - | F66: - | G66: - | H66: - | I66: -
A67: Нотариальные услуги | B67: =SUM(C67,D67,E67,F67) | C67: - | D67: - | E67: - | F67: - | G67: - | H67: - | I67: -
A68: Обслуживание техники (БО) | B68: =SUM(C68,D68,E68,F68) | C68: - | D68: - | E68: - | F68: - | G68: - | H68: - | I68: -
A69: Программное обеспечение (БО) | B69: =SUM(C69,D69,E69,F69) | C69: - | D69: - | E69: - | F69: - | G69: - | H69: - | I69: -
A70: ПланФакт | B70: =SUM(C70,D70,E70,F70) | C70: - | D70: - | E70: - | F70: - | G70: - | H70: - | I70: -
A71: ТБ | B71: =SUM(C71,D71,E71,F71) | C71: - | D71: - | E71: - | F71: - | G71: - | H71: - | I71: -
A72: Контур | B72: =SUM(C72,D72,E72,F72) | C72: - | D72: - | E72: - | F72: - | G72: - | H72: - | I72: -
... A79: HR (аутсорс) | B79: =SUM(C79,D79,E79,F79) | C79: - | D79: - | E79: - | F79: - | G79: - | H79: - | I79: -
A80: Операционная прибыль | B80: =B43-B45 | C80: =C43-C45 | D80: =D43-D45 | E80: =E43-E45 | F80: =F43-F45 | G80: =G43-G45 | H80: - | I80: =I43-I45
A81: Операционная рентабельность | B81: =IFERROR(IF(B4=0,"-",B80/B4),"-") | C81: =IFERROR(IF(C4=0,"-",C80/C4),"-") | D81: =IFERROR(IF(D4=0,"-",D80/D4),"-") | E81: =IFERROR(IF(E4=0,"-",E80/E4),"-") | F81: =IFERROR(IF(F4=0,"-",F80/F4),"-") | G81: =IFERROR(IF(G4=0,"-",G80/G4),"-") | H81: - | I81: =IFERROR(IF(I4=0,"-",I80/I4),"-")
A82: Прочие доходы | B82: =SUM(B83,B84,B85,B86) | C82: =SUM(C83,C84,C85,C86) | D82: =SUM(D83,D84,D85,D86) | E82: =SUM(E83,E84,E85,E86) | F82: =SUM(F83,F84,F85,F86) | G82: =SUM(G83,G84,G85,G86) | H82: - | I82: =SUM(I83,I84,I85,I86)
A83: Доход БЭК-ОФИС | B83: =SUM(C83,D83,E83,F83) | C83: - | D83: - | E83: - | F83: - | G83: - | H83: - | I83: -
A84: Пополненин бэк-офис | B84: =SUM(C84,D84,E84,F84) | C84: - | D84: - | E84: - | F84: - | G84: - | H84: - | I84: -
A85: Проценты по вкладам | B85: =SUM(C85,D85,E85,F85) | C85: - | D85: - | E85: - | F85: - | G85: - | H85: - | I85: -
A86: Курсовая разница (+) | B86: =SUM(C86,D86,E86,F86) | C86: - | D86: - | E86: - | F86: - | G86: - | H86: - | I86: -
A87: Прочие расходы | B87: =SUM(B88) | C87: =SUM(C88) | D87: =SUM(D88) | E87: =SUM(E88) | F87: =SUM(F88) | G87: =SUM(G88) | H87: - | I87: =SUM(I88)
A88: Курсовая разница (-) | B88: =SUM(C88,D88,E88,F88) | C88: - | D88: - | E88: - | F88: - | G88: - | H88: - | I88: -
A89: EBITDA | B89: =B80+IFERROR(B82*1,0)-IFERROR(B87*1,0) | C89: =C80+IFERROR(C82*1,0)-IFERROR(C87*1,0) | D89: =D80+IFERROR(D82*1,0)-IFERROR(D87*1,0) | E89: =E80+IFERROR(E82*1,0)-IFERROR(E87*1,0) | F89: =F80+IFERROR(F82*1,0)-IFERROR(F87*1,0) | G89: =G80+IFERROR(G82*1,0)-IFERROR(G87*1,0) | H89: - | I89: =I80+IFERROR(I82*1,0)-IFERROR(I87*1,0)
A90: Рентабельность по EBITDA | B90: =IFERROR(IF(B4=0,"-",B89/B4),"-") | C90: =IFERROR(IF(C4=0,"-",C89/C4),"-") | D90: =IFERROR(IF(D4=0,"-",D89/D4),"-") | E90: =IFERROR(IF(E4=0,"-",E89/E4),"-") | F90: =IFERROR(IF(F4=0,"-",F89/F4),"-") | G90: =IFERROR(IF(G4=0,"-",G89/G4),"-") | H90: - | I90: =IFERROR(IF(I4=0,"-",I89/I4),"-")
A91: Амортизация | B91: =SUM(B92,B93) | C91: =SUM(C92,C93) | D91: =SUM(D92,D93) | E91: =SUM(E92,E93) | F91: =SUM(F92,F93) | G91: =SUM(G92,G93) | H91: - | I91: =SUM(I92,I93)
A92: Амортизация ОС (ПТ) | B92: =SUM(C92,D92,E92,F92) | C92: - | D92: - | E92: - | F92: - | G92: - | H92: - | I92: -
A93: Амортизация ОС (МОП) | B93: =SUM(C93,D93,E93,F93) | C93: - | D93: - | E93: - | F93: - | G93: - | H93: - | I93: -
A94: Проценты по кредитам и займам | B94: =SUM(C94,D94,E94,F94) | C94: - | D94: - | E94: - | F94: - | G94: - | H94: - | I94: -
A95: Налог на прибыль | B95: =SUM(B96,B97) | C95: =SUM(C96,C97) | D95: =SUM(D96,D97) | E95: =SUM(E96,E97) | F95: =SUM(F96,F97) | G95: =SUM(G96,G97) | H95: - | I95: =SUM(I96,I97)
A96: Налоги УСН | B96: =SUM(C96,D96,E96,F96) | C96: 28000 | D96: 28000 | E96: 28000 | F96: 28000 | G96: - | H96: - | I96: -
A97: Налоги НДС 5% | B97: =SUM(C97,D97,E97,F97) | C97: 94590.32 | D97: 94590.32 | E97: 94590.32 | F97: 94590.32 | G97: - | H97: - | I97: -
A98: Чистая прибыль (убыток) | B98: =IFERROR(B89*1,0)-IFERROR(B91*1,0)-IFERROR(B94*1,0)-IFERROR(B95*1,0) | C98: =IFERROR(C89*1,0)-IFERROR(C91*1,0)-IFERROR(C94*1,0)-IFERROR(C95*1,0) | D98: =IFERROR(D89*1,0)-IFERROR(D91*1,0)-IFERROR(D94*1,0)-IFERROR(D95*1,0) | E98: =IFERROR(E89*1,0)-IFERROR(E91*1,0)-IFERROR(E94*1,0)-IFERROR(E95*1,0) | F98: =IFERROR(F89*1,0)-IFERROR(F91*1,0)-IFERROR(F94*1,0)-IFERROR(F95*1,0) | G98: =IFERROR(G89*1,0)-IFERROR(G91*1,0)-IFERROR(G94*1,0)-IFERROR(G95*1,0) | H98: - | I98: =IFERROR(I89*1,0)-IFERROR(I91*1,0)-IFERROR(I94*1,0)-IFERROR(I95*1,0)
A99: Рентабельность чистой прибыли | B99: =IFERROR(IF(B4=0,"-",B98/B4),"-") | C99: =IFERROR(IF(C4=0,"-",C98/C4),"-") | D99: =IFERROR(IF(D4=0,"-",D98/D4),"-") | E99: =IFERROR(IF(E4=0,"-",E98/E4),"-") | F99: =IFERROR(IF(F4=0,"-",F98/F4),"-") | G99: =IFERROR(IF(G4=0,"-",G98/G4),"-") | H99: - | I99: =IFERROR(IF(I4=0,"-",I98/I4),"-")

Sheet Новое Колпино
A1: ПланФакт | B1: Создано с помощью сервиса ПланФакт | I1: =HYPERLINK("https://app.planfact.io/?from=Pf_BDR", "Перейти в сервис")
B2: Итого | C2: июнь` 26 | D2: июль` 26 | E2: август` 26 | F2: сентябрь` 26 | G2: октябрь` 26 | H2: ноябрь` 26 | I2: декабрь` 26
A3: Новое Колпино | B3: план | C3: план | D3: план | E3: план | F3: план | G3: план | H3: план | I3: план
A4: Выручка | B4: =SUM(B5,B6) | C4: =SUM(C5,C6) | D4: =SUM(D5,D6) | E4: =SUM(E5,E6) | F4: =SUM(F5,F6) | G4: =SUM(G5,G6) | H4: - | I4: =SUM(I5,I6)
A5: Нераспределенный доход | B5: =SUM(C5,D5,E5,F5) | C5: - | D5: - | E5: - | F5: - | G5: - | H5: - | I5: -
A6: Выручка | B6: =SUM(B7,B8,B9) | C6: =SUM(C7,C8,C9) | D6: =SUM(D7,D8,D9) | E6: =SUM(E7,E8,E9) | F6: =SUM(F7,F8,F9) | G6: =SUM(G7,G8,G9) | H6: - | I6: =SUM(I7,I8,I9)
A7: Реализация услуг Клининг (ОД) | B7: =SUM(C7,D7,E7,F7) | C7: 2759092 | D7: 2472043.9 | E7: 2472043.9 | F7: 2472043.9 | G7: - | H7: - | I7: -
A8: Реализация услуг Клининг (Доп.услуги) | B8: =SUM(C8,D8,E8,F8) | C8: - | D8: - | E8: - | F8: - | G8: - | H8: - | I8: -
A9: Реализация услуг Клининг (снег) | B9: =SUM(C9,D9,E9,F9) | C9: - | D9: - | E9: - | F9: - | G9: - | H9: - | I9: -
A10: Прямые расходы | B10: =SUM(B11,B12,B13,B21,B22,B23,B24,B25,B26,B27,B28,B29,B30,B31,B32,B33,B34) | C10: =SUM(C11,C12,C13,C21,C22,C23,C24,C25,C26,C27,C28,C29,C30,C31,C32,C33,C34) | D10: =SUM(D11,D12,D13,D21,D22,D23,D24,D25,D26,D27,D28,D29,D30,D31,D32,D33,D34) | E10: =SUM(E11,E12,E13,E21,E22,E23,E24,E25,E26,E27,E28,E29,E30,E31,E32,E33,E34) | F10: =SUM(F11,F12,F13,F21,F22,F23,F24,F25,F26,F27,F28,F29,F30,F31,F32,F33,F34) | G10: =SUM(G11,G12,G13,G21,G22,G23,G24,G25,G26,G27,G28,G29,G30,G31,G32,G33,G34) | H10: - | I10: =SUM(I11,I12,I13,I21,I22,I23,I24,I25,I26,I27,I28,I29,I30,I31,I32,I33,I34)
A11: Нераспределенный расход | B11: =SUM(C11,D11,E11,F11) | C11: - | D11: - | E11: - | F11: - | G11: - | H11: - | I11: -
A12: Транспортные расходы | B12: =SUM(C12,D12,E12,F12) | C12: - | D12: - | E12: - | F12: - | G12: - | H12: - | I12: -
A13: Переменные | B13: =SUM(B14,B15,B16,B17,B18,B19,B20) | C13: =SUM(C14,C15,C16,C17,C18,C19,C20) | D13: =SUM(D14,D15,D16,D17,D18,D19,D20) | E13: =SUM(E14,E15,E16,E17,E18,E19,E20) | F13: =SUM(F14,F15,F16,F17,F18,F19,F20) | G13: =SUM(G14,G15,G16,G17,G18,G19,G20) | H13: - | I13: =SUM(I14,I15,I16,I17,I18,I19,I20)
A14: Услуги техниги для уборки снега (ПТ) | B14: =SUM(C14,D14,E14,F14) | C14: - | D14: - | E14: - | F14: - | G14: - | H14: - | I14: -
A15: Услуги садовника (ПТ) | B15: =SUM(C15,D15,E15,F15) | C15: 88000 | D15: 88000 | E15: 88000 | F15: 88000 | G15: - | H15: - | I15: -
A16: Сыпучие материалы (ПТ) | B16: =SUM(C16,D16,E16,F16) | C16: - | D16: - | E16: - | F16: - | G16: - | H16: - | I16: -
A17: Расходные материалы и инстументы (МОП) | B17: =SUM(C17,D17,E17,F17) | C17: 43810.13 | D17: 30000 | E17: 30000 | F17: 30000 | G17: - | H17: - | I17: -
A18: Расходные материалы и инстументы (ПТ) | B18: =SUM(C18,D18,E18,F18) | C18: 5901.4 | D18: 60000 | E18: 10000 | F18: 10000 | G18: - | H18: - | I18: -
A19: Арена оборудования (ПТ) | B19: =SUM(C19,D19,E19,F19) | C19: - | D19: - | E19: - | F19: - | G19: - | H19: - | I19: -
A20: Арена оборудования (МОП) | B20: =SUM(C20,D20,E20,F20) | C20: - | D20: 30000 | E20: - | F20: - | G20: - | H20: - | I20: -
A21: Заработная плата (МОП) | B21: =SUM(C21,D21,E21,F21) | C21: 685000 | D21: 685000 | E21: 685000 | F21: 685000 | G21: - | H21: - | I21: -
A22: Заработная плата (ПТ) | B22: =SUM(C22,D22,E22,F22) | C22: 958084.67 | D22: 920000 | E22: 920000 | F22: 920000 | G22: - | H22: - | I22: -
A23: Налоги с ФОТ (МОП) | B23: =SUM(C23,D23,E23,F23) | C23: 28000 | D23: 28000 | E23: 28000 | F23: 28000 | G23: - | H23: - | I23: -
A24: Налоги с ФОТ (ПТ) | B24: =SUM(C24,D24,E24,F24) | C24: 143705 | D24: 143705 | E24: 143705 | F24: 143705 | G24: - | H24: - | I24: -
A25: Премми (МОП) | B25: =SUM(C25,D25,E25,F25) | C25: - | D25: - | E25: - | F25: - | G25: - | H25: - | I25: -
A26: Премми (ПТ) | B26: =SUM(C26,D26,E26,F26) | C26: - | D26: - | E26: - | F26: - | G26: - | H26: - | I26: -
A27: Униформа (МОП) | B27: =SUM(C27,D27,E27,F27) | C27: - | D27: - | E27: - | F27: - | G27: - | H27: - | I27: -
A28: Униформа (ПТ) | B28: =SUM(C28,D28,E28,F28) | C28: - | D28: - | E28: - | F28: - | G28: - | H28: - | I28: -
A29: Ремонт оборудования (МОП) | B29: =SUM(C29,D29,E29,F29) | C29: - | D29: - | E29: - | F29: - | G29: - | H29: - | I29: -
A30: Ремонт оборудования (ПТ) | B30: =SUM(C30,D30,E30,F30) | C30: 3000 | D30: 3000 | E30: 3000 | F30: 3000 | G30: - | H30: - | I30: -
A31: Вывоз мусора | B31: =SUM(C31,D31,E31,F31) | C31: - | D31: - | E31: - | F31: - | G31: - | H31: - | I31: -
A32: Штрафы, пени, неустойки | B32: =SUM(C32,D32,E32,F32) | C32: - | D32: - | E32: - | F32: - | G32: - | H32: - | I32: -
A33: Расходы к удержанию | B33: =SUM(C33,D33,E33,F33) | C33: - | D33: - | E33: - | F33: - | G33: - | H33: - | I33: -
A34: Общехозяйственные | B34: =SUM(B35,B36,B37,B38,B39,B40,B41,B42) | C34: =SUM(C35,C36,C37,C38,C39,C40,C41,C42) | D34: =SUM(D35,D36,D37,D38,D39,D40,D41,D42) | E34: =SUM(E35,E36,E37,E38,E39,E40,E41,E42) | F34: =SUM(F35,F36,F37,F38,F39,F40,F41,F42) | G34: =SUM(G35,G36,G37,G38,G39,G40,G41,G42) | H34: - | I34: =SUM(I35,I36,I37,I38,I39,I40,I41,I42)
A35: Аутсорс (направления) | B35: =SUM(C35,D35,E35,F35) | C35: 5000 | D35: 5000 | E35: 5000 | F35: 5000 | G35: - | H35: - | I35: -
A36: Заработная плата МО АУП | B36: =SUM(C36,D36,E36,F36) | C36: 100000 | D36: 100000 | E36: 100000 | F36: 100000 | G36: - | H36: - | I36: -
A37: Инструменты: ГСМ | B37: =SUM(C37,D37,E37,F37) | C37: 5000 | D37: 5000 | E37: 5000 | F37: 5000 | G37: - | H37: - | I37: -
A38: Медосмотры | B38: =SUM(C38,D38,E38,F38) | C38: - | D38: - | E38: - | F38: - | G38: - | H38: - | I38: -
A39: Налоги с ФОТ (ИП) | B39: =SUM(C39,D39,E39,F39) | C39: 119350 | D39: 119350 | E39: 119350 | F39: 119350 | G39: - | H39: - | I39: -
A40: Приобритение мебели, бытовой техники | B40: =SUM(C40,D40,E40,F40) | C40: - | D40: - | E40: - | F40: - | G40: - | H40: - | I40: -
A41: Комиссия за перевод ЗП | B41: =SUM(C41,D41,E41,F41) | C41: 2000 | D41: 2000 | E41: 2000 | F41: 2000 | G41: - | H41: - | I41: -
A42: Аренда квартиры (включая коммуналку) | B42: =SUM(C42,D42,E42,F42) | C42: - | D42: - | E42: - | F42: - | G42: - | H42: - | I42: -
A43: Валовая прибыль | B43: =B4-B10 | C43: =C4-C10 | D43: =D4-D10 | E43: =E4-E10 | F43: =F4-F10 | G43: =G4-G10 | H43: - | I43: =I4-I10
A44: Валовая рентабельность | B44: =IFERROR(IF(B4=0,"-",B43/B4),"-") | C44: =IFERROR(IF(C4=0,"-",C43/C4),"-") | D44: =IFERROR(IF(D4=0,"-",D43/D4),"-") | E44: =IFERROR(IF(E4=0,"-",E43/E4),"-") | F44: =IFERROR(IF(F4=0,"-",F43/F4),"-") | G44: =IFERROR(IF(G4=0,"-",G43/G4),"-") | H44: - | I44: =IFERROR(IF(I4=0,"-",I43/I4),"-")
A45: Косвенные расходы | B45: =SUM(B46,B47,B48,B52,B56,B57,B58,B59,B60,B63,B64,B65,B66,B67,B68,B69,B70,B71,B72,B73,B74,B75,B76,B77,B78,B79) | C45: =SUM(C46,C47,C48,C52,C56,C57,C58,C59,C60,C63,C64,C65,C66,C67,C68,C69,C70,C71,C72,C73,C74,C75,C76,C77,C78,C79) | D45: =SUM(D46,D47,D48,D52,D56,D57,D58,D59,D60,D63,D64,D65,D66,D67,D68,D69,D70,D71,D72,D73,D74,D75,D76,D77,D78,D79) | E45: =SUM(E46,E47,E48,E52,E56,E57,E58,E59,E60,E63,E64,E65,E66,E67,E68,E69,E70,E71,E72,E73,E74,E75,E76,E77,E78,E79) | F45: =SUM(F46,F47,F48,F52,F56,F57,F58,F59,F60,F63,F64,F65,F66,F67,F68,F69,F70,F71,F72,F73,F74,F75,F76,F77,F78,F79) | G45: =SUM(G46,G47,G48,G52,G56,G57,G58,G59,G60,G63,G64,G65,G66,G67,G68,G69,G70,G71,G72,G73,G74,G75,G76,G77,G78,G79) | H45: - | I45: =SUM(I46,I47,I48,I52,I56,I57,I58,I59,I60,I63,I64,I65,I66,I67,I68,I69,I70,I71,I72,I73,I74,I75,I76,I77,I78,I79)
A46: Расход БЭК-ОФИС | B46: =SUM(C46,D46,E46,F46) | C46: 295694.29 | D46: 295694.29 | E46: 295694.29 | F46: 295694.29 | G46: - | H46: - | I46: -
A47: Расходы на бэк-офис | B47: =SUM(C47,D47,E47,F47) | C47: - | D47: - | E47: - | F47: - | G47: - | H47: - | I47: -
A48: Автомобиль | B48: =SUM(B49,B50,B51) | C48: =SUM(C49,C50,C51) | D48: =SUM(D49,D50,D51) | E48: =SUM(E49,E50,E51) | F48: =SUM(F49,F50,F51) | G48: =SUM(G49,G50,G51) | H48: - | I48: =SUM(I49,I50,I51)
A49: Автомобиль: ГСМ | B49: =SUM(C49,D49,E49,F49) | C49: - | D49: - | E49: - | F49: - | G49: - | H49: - | I49: -
A50: Автомобиль: страхование | B50: =SUM(C50,D50,E50,F50) | C50: - | D50: - | E50: - | F50: - | G50: - | H50: - | I50: -
A51: Автомобиль: ТО | B51: =SUM(C51,D51,E51,F51) | C51: - | D51: - | E51: - | F51: - | G51: - | H51: - | I51: -
A52: Офисные расходы | B52: =SUM(B53,B54,B55) | C52: =SUM(C53,C54,C55) | D52: =SUM(D53,D54,D55) | E52: =SUM(E53,E54,E55) | F52: =SUM(F53,F54,F55) | G52: =SUM(G53,G54,G55) | H52: - | I52: =SUM(I53,I54,I55)
A53: Аренда офиса | B53: =SUM(C53,D53,E53,F53) | C53: - | D53: - | E53: - | F53: - | G53: - | H53: - | I53: -
A54: Канцелярия и обслуживание | B54: =SUM(C54,D54,E54,F54) | C54: - | D54: - | E54: - | F54: - | G54: - | H54: - | I54: -
A55: Интернет и связь | B55: =SUM(C55,D55,E55,F55) | C55: 3000 | D55: 3000 | E55: 3000 | F55: 3000 | G55: - | H55: - | I55: -
A56: Банковские услуги | B56: =SUM(C56,D56,E56,F56) | C56: - | D56: - | E56: - | F56: - | G56: - | H56: - | I56: -
A57: Заработная плата АУП (БО) | B57: =SUM(C57,D57,E57,F57) | C57: - | D57: - | E57: - | F57: - | G57: - | H57: - | I57: -
A58: Заработная плата бухгалтерии (БО) | B58: =SUM(C58,D58,E58,F58) | C58: - | D58: - | E58: - | F58: - | G58: - | H58: - | I58: -
A59: Заработная плата СБ (БО) | B59: =SUM(C59,D59,E59,F59) | C59: - | D59: - | E59: - | F59: - | G59: - | H59: - | I59: -
A60: Командировочные расходы | B60: =SUM(B61,B62) | C60: =SUM(C61,C62) | D60: =SUM(D61,D62) | E60: =SUM(E61,E62) | F60: =SUM(F61,F62) | G60: =SUM(G61,G62) | H60: - | I60: =SUM(I61,I62)
A61: Командировнчеы расходы: билеты (БО) | B61: =SUM(C61,D61,E61,F61) | C61: - | D61: - | E61: - | F61: - | G61: - | H61: - | I61: -
A62: Командировнчеы расходы: проживание (БО) | B62: =SUM(C62,D62,E62,F62) | C62: - | D62: - | E62: - | F62: - | G62: - | H62: - | I62: -
A63: Комиссия УК ДОМ | B63: =SUM(C63,D63,E63,F63) | C63: - | D63: - | E63: - | F63: - | G63: - | H63: - | I63: -
A64: Налоги с ФОТ (ИП)_БО | B64: =SUM(C64,D64,E64,F64) | C64: - | D64: - | E64: - | F64: - | G64: - | H64: - | I64: -
A65: Налоги с ФОТ (НДФЛ) БО | B65: =SUM(C65,D65,E65,F65) | C65: - | D65: - | E65: - | F65: - | G65: - | H65: - | I65: -
A66: Налоги с ФОТ (страховые взносы) БО | B66: =SUM(C66,D66,E66,F66) | C66: - | D66: - | E66: - | F66: - | G66: - | H66: - | I66: -
A67: Нотариальные услуги | B67: =SUM(C67,D67,E67,F67) | C67: - | D67: - | E67: - | F67: - | G67: - | H67: - | I67: -
A68: Обслуживание техники (БО) | B68: =SUM(C68,D68,E68,F68) | C68: - | D68: - | E68: - | F68: - | G68: - | H68: - | I68: -
A69: Программное обеспечение (БО) | B69: =SUM(C69,D69,E69,F69) | C69: - | D69: - | E69: - | F69: - | G69: - | H69: - | I69: -
A70: ПланФакт | B70: =SUM(C70,D70,E70,F70) | C70: - | D70: - | E70: - | F70: - | G70: - | H70: - | I70: -
A71: ТБ | B71: =SUM(C71,D71,E71,F71) | C71: - | D71: - | E71: - | F71: - | G71: - | H71: - | I71: -
A72: Контур | B72: =SUM(C72,D72,E72,F72) | C72: - | D72: - | E72: - | F72: - | G72: - | H72: - | I72: -
... A79: HR (аутсорс) | B79: =SUM(C79,D79,E79,F79) | C79: - | D79: - | E79: - | F79: - | G79: - | H79: - | I79: -
A80: Операционная прибыль | B80: =B43-B45 | C80: =C43-C45 | D80: =D43-D45 | E80: =E43-E45 | F80: =F43-F45 | G80: =G43-G45 | H80: - | I80: =I43-I45
A81: Операционная рентабельность | B81: =IFERROR(IF(B4=0,"-",B80/B4),"-") | C81: =IFERROR(IF(C4=0,"-",C80/C4),"-") | D81: =IFERROR(IF(D4=0,"-",D80/D4),"-") | E81: =IFERROR(IF(E4=0,"-",E80/E4),"-") | F81: =IFERROR(IF(F4=0,"-",F80/F4),"-") | G81: =IFERROR(IF(G4=0,"-",G80/G4),"-") | H81: - | I81: =IFERROR(IF(I4=0,"-",I80/I4),"-")
A82: Прочие доходы | B82: =SUM(B83,B84,B85,B86) | C82: =SUM(C83,C84,C85,C86) | D82: =SUM(D83,D84,D85,D86) | E82: =SUM(E83,E84,E85,E86) | F82: =SUM(F83,F84,F85,F86) | G82: =SUM(G83,G84,G85,G86) | H82: - | I82: =SUM(I83,I84,I85,I86)
A83: Доход БЭК-ОФИС | B83: =SUM(C83,D83,E83,F83) | C83: - | D83: - | E83: - | F83: - | G83: - | H83: - | I83: -
A84: Пополненин бэк-офис | B84: =SUM(C84,D84,E84,F84) | C84: - | D84: - | E84: - | F84: - | G84: - | H84: - | I84: -
A85: Проценты по вкладам | B85: =SUM(C85,D85,E85,F85) | C85: - | D85: - | E85: - | F85: - | G85: - | H85: - | I85: -
A86: Курсовая разница (+) | B86: =SUM(C86,D86,E86,F86) | C86: - | D86: - | E86: - | F86: - | G86: - | H86: - | I86: -
A87: Прочие расходы | B87: =SUM(B88) | C87: =SUM(C88) | D87: =SUM(D88) | E87: =SUM(E88) | F87: =SUM(F88) | G87: =SUM(G88) | H87: - | I87: =SUM(I88)
A88: Курсовая разница (-) | B88: =SUM(C88,D88,E88,F88) | C88: - | D88: - | E88: - | F88: - | G88: - | H88: - | I88: -
A89: EBITDA | B89: =B80+IFERROR(B82*1,0)-IFERROR(B87*1,0) | C89: =C80+IFERROR(C82*1,0)-IFERROR(C87*1,0) | D89: =D80+IFERROR(D82*1,0)-IFERROR(D87*1,0) | E89: =E80+IFERROR(E82*1,0)-IFERROR(E87*1,0) | F89: =F80+IFERROR(F82*1,0)-IFERROR(F87*1,0) | G89: =G80+IFERROR(G82*1,0)-IFERROR(G87*1,0) | H89: - | I89: =I80+IFERROR(I82*1,0)-IFERROR(I87*1,0)
A90: Рентабельность по EBITDA | B90: =IFERROR(IF(B4=0,"-",B89/B4),"-") | C90: =IFERROR(IF(C4=0,"-",C89/C4),"-") | D90: =IFERROR(IF(D4=0,"-",D89/D4),"-") | E90: =IFERROR(IF(E4=0,"-",E89/E4),"-") | F90: =IFERROR(IF(F4=0,"-",F89/F4),"-") | G90: =IFERROR(IF(G4=0,"-",G89/G4),"-") | H90: - | I90: =IFERROR(IF(I4=0,"-",I89/I4),"-")
A91: Амортизация | B91: =SUM(B92,B93) | C91: =SUM(C92,C93) | D91: =SUM(D92,D93) | E91: =SUM(E92,E93) | F91: =SUM(F92,F93) | G91: =SUM(G92,G93) | H91: - | I91: =SUM(I92,I93)
A92: Амортизация ОС (ПТ) | B92: =SUM(C92,D92,E92,F92) | C92: - | D92: - | E92: - | F92: - | G92: - | H92: - | I92: -
A93: Амортизация ОС (МОП) | B93: =SUM(C93,D93,E93,F93) | C93: - | D93: - | E93: - | F93: - | G93: - | H93: - | I93: -
A94: Проценты по кредитам и займам | B94: =SUM(C94,D94,E94,F94) | C94: - | D94: - | E94: - | F94: - | G94: - | H94: - | I94: -
A95: Налог на прибыль | B95: =SUM(B96,B97) | C95: =SUM(C96,C97) | D95: =SUM(D96,D97) | E95: =SUM(E96,E97) | F95: =SUM(F96,F97) | G95: =SUM(G96,G97) | H95: - | I95: =SUM(I96,I97)
A96: Налоги УСН | B96: =SUM(C96,D96,E96,F96) | C96: 42000 | D96: 42000 | E96: 42000 | F96: 42000 | G96: - | H96: - | I96: -
A97: Налоги НДС 5% | B97: =SUM(C97,D97,E97,F97) | C97: 117716.37 | D97: 117716.37 | E97: 117716.37 | F97: 117716.37 | G97: - | H97: - | I97: -
A98: Чистая прибыль (убыток) | B98: =IFERROR(B89*1,0)-IFERROR(B91*1,0)-IFERROR(B94*1,0)-IFERROR(B95*1,0) | C98: =IFERROR(C89*1,0)-IFERROR(C91*1,0)-IFERROR(C94*1,0)-IFERROR(C95*1,0) | D98: =IFERROR(D89*1,0)-IFERROR(D91*1,0)-IFERROR(D94*1,0)-IFERROR(D95*1,0) | E98: =IFERROR(E89*1,0)-IFERROR(E91*1,0)-IFERROR(E94*1,0)-IFERROR(E95*1,0) | F98: =IFERROR(F89*1,0)-IFERROR(F91*1,0)-IFERROR(F94*1,0)-IFERROR(F95*1,0) | G98: =IFERROR(G89*1,0)-IFERROR(G91*1,0)-IFERROR(G94*1,0)-IFERROR(G95*1,0) | H98: - | I98: =IFERROR(I89*1,0)-IFERROR(I91*1,0)-IFERROR(I94*1,0)-IFERROR(I95*1,0)
A99: Рентабельность чистой прибыли | B99: =IFERROR(IF(B4=0,"-",B98/B4),"-") | C99: =IFERROR(IF(C4=0,"-",C98/C4),"-") | D99: =IFERROR(IF(D4=0,"-",D98/D4),"-") | E99: =IFERROR(IF(E4=0,"-",E98/E4),"-") | F99: =IFERROR(IF(F4=0,"-",F98/F4),"-") | G99: =IFERROR(IF(G4=0,"-",G98/G4),"-") | H99: - | I99: =IFERROR(IF(I4=0,"-",I98/I4),"-")

Sheet Таллинский парк
A1: ПланФакт | B1: Создано с помощью сервиса ПланФакт | I1: =HYPERLINK("https://app.planfact.io/?from=Pf_BDR", "Перейти в сервис")
B2: Итого | C2: июнь` 26 | D2: июль` 26 | E2: август` 26 | F2: сентябрь` 26 | G2: октябрь` 26 | H2: ноябрь` 26 | I2: декабрь` 26
A3: Таллинский парк | B3: план | C3: план | D3: план | E3: план | F3: план | G3: план | H3: план | I3: план
A4: Выручка | B4: =SUM(B5,B6) | C4: =SUM(C5,C6) | D4: =SUM(D5,D6) | E4: =SUM(E5,E6) | F4: =SUM(F5,F6) | G4: =SUM(G5,G6) | H4: - | I4: =SUM(I5,I6)
A5: Нераспределенный доход | B5: =SUM(C5,D5,E5,F5) | C5: - | D5: - | E5: - | F5: - | G5: - | H5: - | I5: -
A6: Выручка | B6: =SUM(B7,B8,B9) | C6: =SUM(C7,C8,C9) | D6: =SUM(D7,D8,D9) | E6: =SUM(E7,E8,E9) | F6: =SUM(F7,F8,F9) | G6: =SUM(G7,G8,G9) | H6: - | I6: =SUM(I7,I8,I9)
A7: Реализация услуг Клининг (ОД) | B7: =SUM(C7,D7,E7,F7) | C7: 1599464.2 | D7: 1599464.2 | E7: 1599464.2 | F7: 1599464.2 | G7: - | H7: - | I7: -
A8: Реализация услуг Клининг (Доп.услуги) | B8: =SUM(C8,D8,E8,F8) | C8: - | D8: - | E8: - | F8: - | G8: - | H8: - | I8: -
A9: Реализация услуг Клининг (снег) | B9: =SUM(C9,D9,E9,F9) | C9: - | D9: - | E9: - | F9: - | G9: - | H9: - | I9: -
A10: Прямые расходы | B10: =SUM(B11,B12,B13,B21,B22,B23,B24,B25,B26,B27,B28,B29,B30,B31,B32,B33,B34) | C10: =SUM(C11,C12,C13,C21,C22,C23,C24,C25,C26,C27,C28,C29,C30,C31,C32,C33,C34) | D10: =SUM(D11,D12,D13,D21,D22,D23,D24,D25,D26,D27,D28,D29,D30,D31,D32,D33,D34) | E10: =SUM(E11,E12,E13,E21,E22,E23,E24,E25,E26,E27,E28,E29,E30,E31,E32,E33,E34) | F10: =SUM(F11,F12,F13,F21,F22,F23,F24,F25,F26,F27,F28,F29,F30,F31,F32,F33,F34) | G10: =SUM(G11,G12,G13,G21,G22,G23,G24,G25,G26,G27,G28,G29,G30,G31,G32,G33,G34) | H10: - | I10: =SUM(I11,I12,I13,I21,I22,I23,I24,I25,I26,I27,I28,I29,I30,I31,I32,I33,I34)
A11: Нераспределенный расход | B11: =SUM(C11,D11,E11,F11) | C11: - | D11: - | E11: - | F11: - | G11: - | H11: - | I11: -
A12: Транспортные расходы | B12: =SUM(C12,D12,E12,F12) | C12: 15000 | D12: - | E12: - | F12: - | G12: - | H12: - | I12: -
A13: Переменные | B13: =SUM(B14,B15,B16,B17,B18,B19,B20) | C13: =SUM(C14,C15,C16,C17,C18,C19,C20) | D13: =SUM(D14,D15,D16,D17,D18,D19,D20) | E13: =SUM(E14,E15,E16,E17,E18,E19,E20) | F13: =SUM(F14,F15,F16,F17,F18,F19,F20) | G13: =SUM(G14,G15,G16,G17,G18,G19,G20) | H13: - | I13: =SUM(I14,I15,I16,I17,I18,I19,I20)
A14: Услуги техниги для уборки снега (ПТ) | B14: =SUM(C14,D14,E14,F14) | C14: - | D14: - | E14: - | F14: - | G14: - | H14: - | I14: -
A15: Услуги садовника (ПТ) | B15: =SUM(C15,D15,E15,F15) | C15: - | D15: - | E15: - | F15: - | G15: - | H15: - | I15: -
A16: Сыпучие материалы (ПТ) | B16: =SUM(C16,D16,E16,F16) | C16: - | D16: - | E16: - | F16: - | G16: - | H16: - | I16: -
A17: Расходные материалы и инстументы (МОП) | B17: =SUM(C17,D17,E17,F17) | C17: 525 | D17: 3000 | E17: 3000 | F17: 3000 | G17: - | H17: - | I17: -
A18: Расходные материалы и инстументы (ПТ) | B18: =SUM(C18,D18,E18,F18) | C18: 33381 | D18: 5000 | E18: 5000 | F18: 5000 | G18: - | H18: - | I18: -
A19: Арена оборудования (ПТ) | B19: =SUM(C19,D19,E19,F19) | C19: 18000 | D19: - | E19: - | F19: - | G19: - | H19: - | I19: -
A20: Арена оборудования (МОП) | B20: =SUM(C20,D20,E20,F20) | C20: - | D20: - | E20: - | F20: - | G20: - | H20: - | I20: -
A21: Заработная плата (МОП) | B21: =SUM(C21,D21,E21,F21) | C21: 264000 | D21: 264000 | E21: 264000 | F21: 264000 | G21: - | H21: - | I21: -
A22: Заработная плата (ПТ) | B22: =SUM(C22,D22,E22,F22) | C22: 532778 | D22: 350000 | E22: 350000 | F22: 350000 | G22: - | H22: - | I22: -
A23: Налоги с ФОТ (МОП) | B23: =SUM(C23,D23,E23,F23) | C23: 11052.57 | D23: 14000 | E23: 14000 | F23: 14000 | G23: - | H23: - | I23: -
A24: Налоги с ФОТ (ПТ) | B24: =SUM(C24,D24,E24,F24) | C24: - | D24: - | E24: - | F24: - | G24: - | H24: - | I24: -
A25: Премми (МОП) | B25: =SUM(C25,D25,E25,F25) | C25: - | D25: - | E25: - | F25: - | G25: - | H25: - | I25: -
A26: Премми (ПТ) | B26: =SUM(C26,D26,E26,F26) | C26: - | D26: - | E26: - | F26: - | G26: - | H26: - | I26: -
A27: Униформа (МОП) | B27: =SUM(C27,D27,E27,F27) | C27: - | D27: - | E27: - | F27: - | G27: - | H27: - | I27: -
A28: Униформа (ПТ) | B28: =SUM(C28,D28,E28,F28) | C28: - | D28: - | E28: - | F28: - | G28: - | H28: - | I28: -
A29: Ремонт оборудования (МОП) | B29: =SUM(C29,D29,E29,F29) | C29: - | D29: - | E29: - | F29: - | G29: - | H29: - | I29: -
A30: Ремонт оборудования (ПТ) | B30: =SUM(C30,D30,E30,F30) | C30: - | D30: - | E30: - | F30: - | G30: - | H30: - | I30: -
A31: Вывоз мусора | B31: =SUM(C31,D31,E31,F31) | C31: - | D31: - | E31: - | F31: - | G31: - | H31: - | I31: -
A32: Штрафы, пени, неустойки | B32: =SUM(C32,D32,E32,F32) | C32: - | D32: - | E32: - | F32: - | G32: - | H32: - | I32: -
A33: Расходы к удержанию | B33: =SUM(C33,D33,E33,F33) | C33: - | D33: - | E33: - | F33: - | G33: - | H33: - | I33: -
A34: Общехозяйственные | B34: =SUM(B35,B36,B37,B38,B39,B40,B41,B42) | C34: =SUM(C35,C36,C37,C38,C39,C40,C41,C42) | D34: =SUM(D35,D36,D37,D38,D39,D40,D41,D42) | E34: =SUM(E35,E36,E37,E38,E39,E40,E41,E42) | F34: =SUM(F35,F36,F37,F38,F39,F40,F41,F42) | G34: =SUM(G35,G36,G37,G38,G39,G40,G41,G42) | H34: - | I34: =SUM(I35,I36,I37,I38,I39,I40,I41,I42)
A35: Аутсорс (направления) | B35: =SUM(C35,D35,E35,F35) | C35: 12500 | D35: 10000 | E35: 5000 | F35: 5000 | G35: - | H35: - | I35: -
A36: Заработная плата МО АУП | B36: =SUM(C36,D36,E36,F36) | C36: 120000 | D36: 120000 | E36: 120000 | F36: 120000 | G36: - | H36: - | I36: -
A37: Инструменты: ГСМ | B37: =SUM(C37,D37,E37,F37) | C37: 2000 | D37: 2000 | E37: 2000 | F37: 2000 | G37: - | H37: - | I37: -
A38: Медосмотры | B38: =SUM(C38,D38,E38,F38) | C38: - | D38: - | E38: - | F38: - | G38: - | H38: - | I38: -
A39: Налоги с ФОТ (ИП) | B39: =SUM(C39,D39,E39,F39) | C39: 51450 | D39: 51450 | E39: 51450 | F39: 51450 | G39: - | H39: - | I39: -
A40: Приобритение мебели, бытовой техники | B40: =SUM(C40,D40,E40,F40) | C40: - | D40: - | E40: - | F40: - | G40: - | H40: - | I40: -
A41: Комиссия за перевод ЗП | B41: =SUM(C41,D41,E41,F41) | C41: 2000 | D41: 2000 | E41: 2000 | F41: 2000 | G41: - | H41: - | I41: -
A42: Аренда квартиры (включая коммуналку) | B42: =SUM(C42,D42,E42,F42) | C42: - | D42: - | E42: - | F42: - | G42: - | H42: - | I42: -
A43: Валовая прибыль | B43: =B4-B10 | C43: =C4-C10 | D43: =D4-D10 | E43: =E4-E10 | F43: =F4-F10 | G43: =G4-G10 | H43: - | I43: =I4-I10
A44: Валовая рентабельность | B44: =IFERROR(IF(B4=0,"-",B43/B4),"-") | C44: =IFERROR(IF(C4=0,"-",C43/C4),"-") | D44: =IFERROR(IF(D4=0,"-",D43/D4),"-") | E44: =IFERROR(IF(E4=0,"-",E43/E4),"-") | F44: =IFERROR(IF(F4=0,"-",F43/F4),"-") | G44: =IFERROR(IF(G4=0,"-",G43/G4),"-") | H44: - | I44: =IFERROR(IF(I4=0,"-",I43/I4),"-")
A45: Косвенные расходы | B45: =SUM(B46,B47,B48,B52,B56,B57,B58,B59,B60,B63,B64,B65,B66,B67,B68,B69,B70,B71,B72,B73,B74,B75,B76,B77,B78,B79) | C45: =SUM(C46,C47,C48,C52,C56,C57,C58,C59,C60,C63,C64,C65,C66,C67,C68,C69,C70,C71,C72,C73,C74,C75,C76,C77,C78,C79) | D45: =SUM(D46,D47,D48,D52,D56,D57,D58,D59,D60,D63,D64,D65,D66,D67,D68,D69,D70,D71,D72,D73,D74,D75,D76,D77,D78,D79) | E45: =SUM(E46,E47,E48,E52,E56,E57,E58,E59,E60,E63,E64,E65,E66,E67,E68,E69,E70,E71,E72,E73,E74,E75,E76,E77,E78,E79) | F45: =SUM(F46,F47,F48,F52,F56,F57,F58,F59,F60,F63,F64,F65,F66,F67,F68,F69,F70,F71,F72,F73,F74,F75,F76,F77,F78,F79) | G45: =SUM(G46,G47,G48,G52,G56,G57,G58,G59,G60,G63,G64,G65,G66,G67,G68,G69,G70,G71,G72,G73,G74,G75,G76,G77,G78,G79) | H45: - | I45: =SUM(I46,I47,I48,I52,I56,I57,I58,I59,I60,I63,I64,I65,I66,I67,I68,I69,I70,I71,I72,I73,I74,I75,I76,I77,I78,I79)
A46: Расход БЭК-ОФИС | B46: =SUM(C46,D46,E46,F46) | C46: 98555.62 | D46: 98555.62 | E46: 98555.62 | F46: 98555.62 | G46: - | H46: - | I46: -
A47: Расходы на бэк-офис | B47: =SUM(C47,D47,E47,F47) | C47: - | D47: - | E47: - | F47: - | G47: - | H47: - | I47: -
A48: Автомобиль | B48: =SUM(B49,B50,B51) | C48: =SUM(C49,C50,C51) | D48: =SUM(D49,D50,D51) | E48: =SUM(E49,E50,E51) | F48: =SUM(F49,F50,F51) | G48: =SUM(G49,G50,G51) | H48: - | I48: =SUM(I49,I50,I51)
A49: Автомобиль: ГСМ | B49: =SUM(C49,D49,E49,F49) | C49: - | D49: - | E49: - | F49: - | G49: - | H49: - | I49: -
A50: Автомобиль: страхование | B50: =SUM(C50,D50,E50,F50) | C50: - | D50: - | E50: - | F50: - | G50: - | H50: - | I50: -
A51: Автомобиль: ТО | B51: =SUM(C51,D51,E51,F51) | C51: - | D51: - | E51: - | F51: - | G51: - | H51: - | I51: -
A52: Офисные расходы | B52: =SUM(B53,B54,B55) | C52: =SUM(C53,C54,C55) | D52: =SUM(D53,D54,D55) | E52: =SUM(E53,E54,E55) | F52: =SUM(F53,F54,F55) | G52: =SUM(G53,G54,G55) | H52: - | I52: =SUM(I53,I54,I55)
A53: Аренда офиса | B53: =SUM(C53,D53,E53,F53) | C53: - | D53: - | E53: - | F53: - | G53: - | H53: - | I53: -
A54: Канцелярия и обслуживание | B54: =SUM(C54,D54,E54,F54) | C54: - | D54: - | E54: - | F54: - | G54: - | H54: - | I54: -
A55: Интернет и связь | B55: =SUM(C55,D55,E55,F55) | C55: - | D55: - | E55: - | F55: - | G55: - | H55: - | I55: -
A56: Банковские услуги | B56: =SUM(C56,D56,E56,F56) | C56: - | D56: - | E56: - | F56: - | G56: - | H56: - | I56: -
A57: Заработная плата АУП (БО) | B57: =SUM(C57,D57,E57,F57) | C57: - | D57: - | E57: - | F57: - | G57: - | H57: - | I57: -
A58: Заработная плата бухгалтерии (БО) | B58: =SUM(C58,D58,E58,F58) | C58: - | D58: - | E58: - | F58: - | G58: - | H58: - | I58: -
A59: Заработная плата СБ (БО) | B59: =SUM(C59,D59,E59,F59) | C59: - | D59: - | E59: - | F59: - | G59: - | H59: - | I59: -
A60: Командировочные расходы | B60: =SUM(B61,B62) | C60: =SUM(C61,C62) | D60: =SUM(D61,D62) | E60: =SUM(E61,E62) | F60: =SUM(F61,F62) | G60: =SUM(G61,G62) | H60: - | I60: =SUM(I61,I62)
A61: Командировнчеы расходы: билеты (БО) | B61: =SUM(C61,D61,E61,F61) | C61: - | D61: - | E61: - | F61: - | G61: - | H61: - | I61: -
A62: Командировнчеы расходы: проживание (БО) | B62: =SUM(C62,D62,E62,F62) | C62: - | D62: - | E62: - | F62: - | G62: - | H62: - | I62: -
A63: Комиссия УК ДОМ | B63: =SUM(C63,D63,E63,F63) | C63: - | D63: - | E63: - | F63: - | G63: - | H63: - | I63: -
A64: Налоги с ФОТ (ИП)_БО | B64: =SUM(C64,D64,E64,F64) | C64: - | D64: - | E64: - | F64: - | G64: - | H64: - | I64: -
A65: Налоги с ФОТ (НДФЛ) БО | B65: =SUM(C65,D65,E65,F65) | C65: - | D65: - | E65: - | F65: - | G65: - | H65: - | I65: -
A66: Налоги с ФОТ (страховые взносы) БО | B66: =SUM(C66,D66,E66,F66) | C66: - | D66: - | E66: - | F66: - | G66: - | H66: - | I66: -
A67: Нотариальные услуги | B67: =SUM(C67,D67,E67,F67) | C67: - | D67: - | E67: - | F67: - | G67: - | H67: - | I67: -
A68: Обслуживание техники (БО) | B68: =SUM(C68,D68,E68,F68) | C68: - | D68: - | E68: - | F68: - | G68: - | H68: - | I68: -
A69: Программное обеспечение (БО) | B69: =SUM(C69,D69,E69,F69) | C69: - | D69: - | E69: - | F69: - | G69: - | H69: - | I69: -
A70: ПланФакт | B70: =SUM(C70,D70,E70,F70) | C70: - | D70: - | E70: - | F70: - | G70: - | H70: - | I70: -
A71: ТБ | B71: =SUM(C71,D71,E71,F71) | C71: - | D71: - | E71: - | F71: - | G71: - | H71: - | I71: -
A72: Контур | B72: =SUM(C72,D72,E72,F72) | C72: - | D72: - | E72: - | F72: - | G72: - | H72: - | I72: -
... A79: HR (аутсорс) | B79: =SUM(C79,D79,E79,F79) | C79: - | D79: - | E79: - | F79: - | G79: - | H79: - | I79: -
A80: Операционная прибыль | B80: =B43-B45 | C80: =C43-C45 | D80: =D43-D45 | E80: =E43-E45 | F80: =F43-F45 | G80: =G43-G45 | H80: - | I80: =I43-I45
A81: Операционная рентабельность | B81: =IFERROR(IF(B4=0,"-",B80/B4),"-") | C81: =IFERROR(IF(C4=0,"-",C80/C4),"-") | D81: =IFERROR(IF(D4=0,"-",D80/D4),"-") | E81: =IFERROR(IF(E4=0,"-",E80/E4),"-") | F81: =IFERROR(IF(F4=0,"-",F80/F4),"-") | G81: =IFERROR(IF(G4=0,"-",G80/G4),"-") | H81: - | I81: =IFERROR(IF(I4=0,"-",I80/I4),"-")
A82: Прочие доходы | B82: =SUM(B83,B84,B85,B86) | C82: =SUM(C83,C84,C85,C86) | D82: =SUM(D83,D84,D85,D86) | E82: =SUM(E83,E84,E85,E86) | F82: =SUM(F83,F84,F85,F86) | G82: =SUM(G83,G84,G85,G86) | H82: - | I82: =SUM(I83,I84,I85,I86)
A83: Доход БЭК-ОФИС | B83: =SUM(C83,D83,E83,F83) | C83: - | D83: - | E83: - | F83: - | G83: - | H83: - | I83: -
A84: Пополненин бэк-офис | B84: =SUM(C84,D84,E84,F84) | C84: - | D84: - | E84: - | F84: - | G84: - | H84: - | I84: -
A85: Проценты по вкладам | B85: =SUM(C85,D85,E85,F85) | C85: - | D85: - | E85: - | F85: - | G85: - | H85: - | I85: -
A86: Курсовая разница (+) | B86: =SUM(C86,D86,E86,F86) | C86: - | D86: - | E86: - | F86: - | G86: - | H86: - | I86: -
A87: Прочие расходы | B87: =SUM(B88) | C87: =SUM(C88) | D87: =SUM(D88) | E87: =SUM(E88) | F87: =SUM(F88) | G87: =SUM(G88) | H87: - | I87: =SUM(I88)
A88: Курсовая разница (-) | B88: =SUM(C88,D88,E88,F88) | C88: - | D88: - | E88: - | F88: - | G88: - | H88: - | I88: -
A89: EBITDA | B89: =B80+IFERROR(B82*1,0)-IFERROR(B87*1,0) | C89: =C80+IFERROR(C82*1,0)-IFERROR(C87*1,0) | D89: =D80+IFERROR(D82*1,0)-IFERROR(D87*1,0) | E89: =E80+IFERROR(E82*1,0)-IFERROR(E87*1,0) | F89: =F80+IFERROR(F82*1,0)-IFERROR(F87*1,0) | G89: =G80+IFERROR(G82*1,0)-IFERROR(G87*1,0) | H89: - | I89: =I80+IFERROR(I82*1,0)-IFERROR(I87*1,0)
A90: Рентабельность по EBITDA | B90: =IFERROR(IF(B4=0,"-",B89/B4),"-") | C90: =IFERROR(IF(C4=0,"-",C89/C4),"-") | D90: =IFERROR(IF(D4=0,"-",D89/D4),"-") | E90: =IFERROR(IF(E4=0,"-",E89/E4),"-") | F90: =IFERROR(IF(F4=0,"-",F89/F4),"-") | G90: =IFERROR(IF(G4=0,"-",G89/G4),"-") | H90: - | I90: =IFERROR(IF(I4=0,"-",I89/I4),"-")
A91: Амортизация | B91: =SUM(B92,B93) | C91: =SUM(C92,C93) | D91: =SUM(D92,D93) | E91: =SUM(E92,E93) | F91: =SUM(F92,F93) | G91: =SUM(G92,G93) | H91: - | I91: =SUM(I92,I93)
A92: Амортизация ОС (ПТ) | B92: =SUM(C92,D92,E92,F92) | C92: - | D92: - | E92: - | F92: - | G92: - | H92: - | I92: -
A93: Амортизация ОС (МОП) | B93: =SUM(C93,D93,E93,F93) | C93: - | D93: - | E93: - | F93: - | G93: - | H93: - | I93: -
A94: Проценты по кредитам и займам | B94: =SUM(C94,D94,E94,F94) | C94: - | D94: - | E94: - | F94: - | G94: - | H94: - | I94: -
A95: Налог на прибыль | B95: =SUM(B96,B97) | C95: =SUM(C96,C97) | D95: =SUM(D96,D97) | E95: =SUM(E96,E97) | F95: =SUM(F96,F97) | G95: =SUM(G96,G97) | H95: - | I95: =SUM(I96,I97)
A96: Налоги УСН | B96: =SUM(C96,D96,E96,F96) | C96: 24000 | D96: 24000 | E96: 24000 | F96: 24000 | G96: - | H96: - | I96: -
A97: Налоги НДС 5% | B97: =SUM(C97,D97,E97,F97) | C97: 76164.98 | D97: 76164.98 | E97: 76164.98 | F97: 76164.98 | G97: - | H97: - | I97: -
A98: Чистая прибыль (убыток) | B98: =IFERROR(B89*1,0)-IFERROR(B91*1,0)-IFERROR(B94*1,0)-IFERROR(B95*1,0) | C98: =IFERROR(C89*1,0)-IFERROR(C91*1,0)-IFERROR(C94*1,0)-IFERROR(C95*1,0) | D98: =IFERROR(D89*1,0)-IFERROR(D91*1,0)-IFERROR(D94*1,0)-IFERROR(D95*1,0) | E98: =IFERROR(E89*1,0)-IFERROR(E91*1,0)-IFERROR(E94*1,0)-IFERROR(E95*1,0) | F98: =IFERROR(F89*1,0)-IFERROR(F91*1,0)-IFERROR(F94*1,0)-IFERROR(F95*1,0) | G98: =IFERROR(G89*1,0)-IFERROR(G91*1,0)-IFERROR(G94*1,0)-IFERROR(G95*1,0) | H98: - | I98: =IFERROR(I89*1,0)-IFERROR(I91*1,0)-IFERROR(I94*1,0)-IFERROR(I95*1,0)
A99: Рентабельность чистой прибыли | B99: =IFERROR(IF(B4=0,"-",B98/B4),"-") | C99: =IFERROR(IF(C4=0,"-",C98/C4),"-") | D99: =IFERROR(IF(D4=0,"-",D98/D4),"-") | E99: =IFERROR(IF(E4=0,"-",E98/E4),"-") | F99: =IFERROR(IF(F4=0,"-",F98/F4),"-") | G99: =IFERROR(IF(G4=0,"-",G98/G4),"-") | H99: - | I99: =IFERROR(IF(I4=0,"-",I98/I4),"-")
