Workbook

Sheet Сводный бюджет компании
A1: ПланФакт | B1: Создано с помощью сервиса ПланФакт | I1: =HYPERLINK("https://app.planfact.io/?from=Pf_BDR", "Перейти в сервис")
B2: Итого | C2: июнь` 26 | D2: июль` 26 | E2: август` 26 | F2: сентябрь` 26 | G2: октябрь` 26 | H2: ноябрь` 26 | I2: декабрь` 26
A3: Сводный бюджет компании | B3: план | C3: план | D3: план | E3: план | F3: план | G3: план | H3: план | I3: план
A4: Выручка | B4: =SUM(B5,B6) | C4: =SUM(C5,C6) | D4: =SUM(D5,D6) | E4: =SUM(E5,E6) | F4: =SUM(F5,F6) | G4: =SUM(G5,G6) | H4: =SUM(H5,H6) | I4: =SUM(I5,I6)
A5: Нераспределенный доход | B5: =SUM('Астон.Движение'!B5,'Астон.Реформа'!B5,'Дом Милый Дом'!B5,'River Park'!B5,'Астрид'!B5,'Живи в Курортном'!B5,'Новое Колпино'!B5,'Таллинский парк'!B5,'Твоя Привелегия'!B5,'Исеть Парк'!B5,'Космонавтов 11'!B5,'Утес'!B5) | C5: =SUM('Астон.Движение'!C5,'Астон.Реформа'!C5,'Дом Милый Дом'!C5,'River Park'!C5,'Астрид'!C5,'Живи в Курортном'!C5,'Новое Колпино'!C5,'Таллинский парк'!C5,'Твоя Привелегия'!C5,'Исеть Парк'!C5,'Космонавтов 11'!C5,'Утес'!C5) | D5: =SUM('Астон.Движение'!D5,'Астон.Реформа'!D5,'Дом Милый Дом'!D5,'River Park'!D5,'Астрид'!D5,'Живи в Курортном'!D5,'Новое Колпино'!D5,'Таллинский парк'!D5,'Твоя Привелегия'!D5,'Исеть Парк'!D5,'Космонавтов 11'!D5,'Утес'!D5) | E5: =SUM('Астон.Движение'!E5,'Астон.Реформа'!E5,'Дом Милый Дом'!E5,'River Park'!E5,'Астрид'!E5,'Живи в Курортном'!E5,'Новое Колпино'!E5,'Таллинский парк'!E5,'Твоя Привелегия'!E5,'Исеть Парк'!E5,'Космонавтов 11'!E5,'Утес'!E5) | F5: =SUM('Астон.Движение'!F5,'Астон.Реформа'!F5,'Дом Милый Дом'!F5,'River Park'!F5,'Астрид'!F5,'Живи в Курортном'!F5,'Новое Колпино'!F5,'Таллинский парк'!F5,'Твоя Привелегия'!F5,'Исеть Парк'!F5,'Космонавтов 11'!F5,'Утес'!F5) | G5: =SUM('Астон.Движение'!G5,'Астон.Реформа'!G5,'Дом Милый Дом'!G5,'River Park'!G5,'Астрид'!G5,'Живи в Курортном'!G5,'Новое Колпино'!G5,'Таллинский парк'!G5,'Твоя Привелегия'!G5,'Исеть Парк'!G5,'Космонавтов 11'!G5,'Утес'!G5) | H5: =SUM('Астон.Движение'!H5,'Астон.Реформа'!H5,'Дом Милый Дом'!H5,'River Park'!H5,'Астрид'!H5,'Живи в Курортном'!H5,'Новое Колпино'!H5,'Таллинский парк'!H5,'Твоя Привелегия'!H5,'Исеть Парк'!H5,'Космонавтов 11'!H5,'Утес'!H5) | I5: =SUM('Астон.Движение'!I5,'Астон.Реформа'!I5,'Дом Милый Дом'!I5,'River Park'!I5,'Астрид'!I5,'Живи в Курортном'!I5,'Новое Колпино'!I5,'Таллинский парк'!I5,'Твоя Привелегия'!I5,'Исеть Парк'!I5,'Космонавтов 11'!I5,'Утес'!I5)
A6: Выручка | B6: =SUM(B7,B8,B9) | C6: =SUM(C7,C8,C9) | D6: =SUM(D7,D8,D9) | E6: =SUM(E7,E8,E9) | F6: =SUM(F7,F8,F9) | G6: =SUM(G7,G8,G9) | H6: =SUM(H7,H8,H9) | I6: =SUM(I7,I8,I9)
A7: Реализация услуг Клининг (ОД) | B7: =SUM('Астон.Движение'!B7,'Астон.Реформа'!B7,'Дом Милый Дом'!B7,'River Park'!B7,'Астрид'!B7,'Живи в Курортном'!B7,'Новое Колпино'!B7,'Таллинский парк'!B7,'Твоя Привелегия'!B7,'Исеть Парк'!B7,'Космонавтов 11'!B7,'Утес'!B7) | C7: =SUM('Астон.Движение'!C7,'Астон.Реформа'!C7,'Дом Милый Дом'!C7,'River Park'!C7,'Астрид'!C7,'Живи в Курортном'!C7,'Новое Колпино'!C7,'Таллинский парк'!C7,'Твоя Привелегия'!C7,'Исеть Парк'!C7,'Космонавтов 11'!C7,'Утес'!C7) | D7: =SUM('Астон.Движение'!D7,'Астон.Реформа'!D7,'Дом Милый Дом'!D7,'River Park'!D7,'Астрид'!D7,'Живи в Курортном'!D7,'Новое Колпино'!D7,'Таллинский парк'!D7,'Твоя Привелегия'!D7,'Исеть Парк'!D7,'Космонавтов 11'!D7,'Утес'!D7) | E7: =SUM('Астон.Движение'!E7,'Астон.Реформа'!E7,'Дом Милый Дом'!E7,'River Park'!E7,'Астрид'!E7,'Живи в Курортном'!E7,'Новое Колпино'!E7,'Таллинский парк'!E7,'Твоя Привелегия'!E7,'Исеть Парк'!E7,'Космонавтов 11'!E7,'Утес'!E7) | F7: =SUM('Астон.Движение'!F7,'Астон.Реформа'!F7,'Дом Милый Дом'!F7,'River Park'!F7,'Астрид'!F7,'Живи в Курортном'!F7,'Новое Колпино'!F7,'Таллинский парк'!F7,'Твоя Привелегия'!F7,'Исеть Парк'!F7,'Космонавтов 11'!F7,'Утес'!F7) | G7: =SUM('Астон.Движение'!G7,'Астон.Реформа'!G7,'Дом Милый Дом'!G7,'River Park'!G7,'Астрид'!G7,'Живи в Курортном'!G7,'Новое Колпино'!G7,'Таллинский парк'!G7,'Твоя Привелегия'!G7,'Исеть Парк'!G7,'Космонавтов 11'!G7,'Утес'!G7) | H7: =SUM('Астон.Движение'!H7,'Астон.Реформа'!H7,'Дом Милый Дом'!H7,'River Park'!H7,'Астрид'!H7,'Живи в Курортном'!H7,'Новое Колпино'!H7,'Таллинский парк'!H7,'Твоя Привелегия'!H7,'Исеть Парк'!H7,'Космонавтов 11'!H7,'Утес'!H7) | I7: =SUM('Астон.Движение'!I7,'Астон.Реформа'!I7,'Дом Милый Дом'!I7,'River Park'!I7,'Астрид'!I7,'Живи в Курортном'!I7,'Новое Колпино'!I7,'Таллинский парк'!I7,'Твоя Привелегия'!I7,'Исеть Парк'!I7,'Космонавтов 11'!I7,'Утес'!I7)
A8: Реализация услуг Клининг (Доп.услуги) | B8: =SUM('Астон.Движение'!B8,'Астон.Реформа'!B8,'Дом Милый Дом'!B8,'River Park'!B8,'Астрид'!B8,'Живи в Курортном'!B8,'Новое Колпино'!B8,'Таллинский парк'!B8,'Твоя Привелегия'!B8,'Исеть Парк'!B8,'Космонавтов 11'!B8,'Утес'!B8) | C8: =SUM('Астон.Движение'!C8,'Астон.Реформа'!C8,'Дом Милый Дом'!C8,'River Park'!C8,'Астрид'!C8,'Живи в Курортном'!C8,'Новое Колпино'!C8,'Таллинский парк'!C8,'Твоя Привелегия'!C8,'Исеть Парк'!C8,'Космонавтов 11'!C8,'Утес'!C8) | D8: =SUM('Астон.Движение'!D8,'Астон.Реформа'!D8,'Дом Милый Дом'!D8,'River Park'!D8,'Астрид'!D8,'Живи в Курортном'!D8,'Новое Колпино'!D8,'Таллинский парк'!D8,'Твоя Привелегия'!D8,'Исеть Парк'!D8,'Космонавтов 11'!D8,'Утес'!D8) | E8: =SUM('Астон.Движение'!E8,'Астон.Реформа'!E8,'Дом Милый Дом'!E8,'River Park'!E8,'Астрид'!E8,'Живи в Курортном'!E8,'Новое Колпино'!E8,'Таллинский парк'!E8,'Твоя Привелегия'!E8,'Исеть Парк'!E8,'Космонавтов 11'!E8,'Утес'!E8) | F8: =SUM('Астон.Движение'!F8,'Астон.Реформа'!F8,'Дом Милый Дом'!F8,'River Park'!F8,'Астрид'!F8,'Живи в Курортном'!F8,'Новое Колпино'!F8,'Таллинский парк'!F8,'Твоя Привелегия'!F8,'Исеть Парк'!F8,'Космонавтов 11'!F8,'Утес'!F8) | G8: =SUM('Астон.Движение'!G8,'Астон.Реформа'!G8,'Дом Милый Дом'!G8,'River Park'!G8,'Астрид'!G8,'Живи в Курортном'!G8,'Новое Колпино'!G8,'Таллинский парк'!G8,'Твоя Привелегия'!G8,'Исеть Парк'!G8,'Космонавтов 11'!G8,'Утес'!G8) | H8: =SUM('Астон.Движение'!H8,'Астон.Реформа'!H8,'Дом Милый Дом'!H8,'River Park'!H8,'Астрид'!H8,'Живи в Курортном'!H8,'Новое Колпино'!H8,'Таллинский парк'!H8,'Твоя Привелегия'!H8,'Исеть Парк'!H8,'Космонавтов 11'!H8,'Утес'!H8) | I8: =SUM('Астон.Движение'!I8,'Астон.Реформа'!I8,'Дом Милый Дом'!I8,'River Park'!I8,'Астрид'!I8,'Живи в Курортном'!I8,'Новое Колпино'!I8,'Таллинский парк'!I8,'Твоя Привелегия'!I8,'Исеть Парк'!I8,'Космонавтов 11'!I8,'Утес'!I8)
A9: Реализация услуг Клининг (снег) | B9: =SUM('Астон.Движение'!B9,'Астон.Реформа'!B9,'Дом Милый Дом'!B9,'River Park'!B9,'Астрид'!B9,'Живи в Курортном'!B9,'Новое Колпино'!B9,'Таллинский парк'!B9,'Твоя Привелегия'!B9,'Исеть Парк'!B9,'Космонавтов 11'!B9,'Утес'!B9) | C9: =SUM('Астон.Движение'!C9,'Астон.Реформа'!C9,'Дом Милый Дом'!C9,'River Park'!C9,'Астрид'!C9,'Живи в Курортном'!C9,'Новое Колпино'!C9,'Таллинский парк'!C9,'Твоя Привелегия'!C9,'Исеть Парк'!C9,'Космонавтов 11'!C9,'Утес'!C9) | D9: =SUM('Астон.Движение'!D9,'Астон.Реформа'!D9,'Дом Милый Дом'!D9,'River Park'!D9,'Астрид'!D9,'Живи в Курортном'!D9,'Новое Колпино'!D9,'Таллинский парк'!D9,'Твоя Привелегия'!D9,'Исеть Парк'!D9,'Космонавтов 11'!D9,'Утес'!D9) | E9: =SUM('Астон.Движение'!E9,'Астон.Реформа'!E9,'Дом Милый Дом'!E9,'River Park'!E9,'Астрид'!E9,'Живи в Курортном'!E9,'Новое Колпино'!E9,'Таллинский парк'!E9,'Твоя Привелегия'!E9,'Исеть Парк'!E9,'Космонавтов 11'!E9,'Утес'!E9) | F9: =SUM('Астон.Движение'!F9,'Астон.Реформа'!F9,'Дом Милый Дом'!F9,'River Park'!F9,'Астрид'!F9,'Живи в Курортном'!F9,'Новое Колпино'!F9,'Таллинский парк'!F9,'Твоя Привелегия'!F9,'Исеть Парк'!F9,'Космонавтов 11'!F9,'Утес'!F9) | G9: =SUM('Астон.Движение'!G9,'Астон.Реформа'!G9,'Дом Милый Дом'!G9,'River Park'!G9,'Астрид'!G9,'Живи в Курортном'!G9,'Новое Колпино'!G9,'Таллинский парк'!G9,'Твоя Привелегия'!G9,'Исеть Парк'!G9,'Космонавтов 11'!G9,'Утес'!G9) | H9: =SUM('Астон.Движение'!H9,'Астон.Реформа'!H9,'Дом Милый Дом'!H9,'River Park'!H9,'Астрид'!H9,'Живи в Курортном'!H9,'Новое Колпино'!H9,'Таллинский парк'!H9,'Твоя Привелегия'!H9,'Исеть Парк'!H9,'Космонавтов 11'!H9,'Утес'!H9) | I9: =SUM('Астон.Движение'!I9,'Астон.Реформа'!I9,'Дом Милый Дом'!I9,'River Park'!I9,'Астрид'!I9,'Живи в Курортном'!I9,'Новое Колпино'!I9,'Таллинский парк'!I9,'Твоя Привелегия'!I9,'Исеть Парк'!I9,'Космонавтов 11'!I9,'Утес'!I9)
A10: Прямые расходы | B10: =SUM(B11,B12,B13,B21,B22,B23,B24,B25,B26,B27,B28,B29,B30,B31,B32,B33,B34) | C10: =SUM(C11,C12,C13,C21,C22,C23,C24,C25,C26,C27,C28,C29,C30,C31,C32,C33,C34) | D10: =SUM(D11,D12,D13,D21,D22,D23,D24,D25,D26,D27,D28,D29,D30,D31,D32,D33,D34) | E10: =SUM(E11,E12,E13,E21,E22,E23,E24,E25,E26,E27,E28,E29,E30,E31,E32,E33,E34) | F10: =SUM(F11,F12,F13,F21,F22,F23,F24,F25,F26,F27,F28,F29,F30,F31,F32,F33,F34) | G10: =SUM(G11,G12,G13,G21,G22,G23,G24,G25,G26,G27,G28,G29,G30,G31,G32,G33,G34) | H10: =SUM(H11,H12,H13,H21,H22,H23,H24,H25,H26,H27,H28,H29,H30,H31,H32,H33,H34) | I10: =SUM(I11,I12,I13,I21,I22,I23,I24,I25,I26,I27,I28,I29,I30,I31,I32,I33,I34)
A11: Нераспределенный расход | B11: =SUM('Астон.Движение'!B11,'Астон.Реформа'!B11,'Дом Милый Дом'!B11,'River Park'!B11,'Астрид'!B11,'Живи в Курортном'!B11,'Новое Колпино'!B11,'Таллинский парк'!B11,'Твоя Привелегия'!B11,'Исеть Парк'!B11,'Космонавтов 11'!B11,'Утес'!B11) | C11: =SUM('Астон.Движение'!C11,'Астон.Реформа'!C11,'Дом Милый Дом'!C11,'River Park'!C11,'Астрид'!C11,'Живи в Курортном'!C11,'Новое Колпино'!C11,'Таллинский парк'!C11,'Твоя Привелегия'!C11,'Исеть Парк'!C11,'Космонавтов 11'!C11,'Утес'!C11) | D11: =SUM('Астон.Движение'!D11,'Астон.Реформа'!D11,'Дом Милый Дом'!D11,'River Park'!D11,'Астрид'!D11,'Живи в Курортном'!D11,'Новое Колпино'!D11,'Таллинский парк'!D11,'Твоя Привелегия'!D11,'Исеть Парк'!D11,'Космонавтов 11'!D11,'Утес'!D11) | E11: =SUM('Астон.Движение'!E11,'Астон.Реформа'!E11,'Дом Милый Дом'!E11,'River Park'!E11,'Астрид'!E11,'Живи в Курортном'!E11,'Новое Колпино'!E11,'Таллинский парк'!E11,'Твоя Привелегия'!E11,'Исеть Парк'!E11,'Космонавтов 11'!E11,'Утес'!E11) | F11: =SUM('Астон.Движение'!F11,'Астон.Реформа'!F11,'Дом Милый Дом'!F11,'River Park'!F11,'Астрид'!F11,'Живи в Курортном'!F11,'Новое Колпино'!F11,'Таллинский парк'!F11,'Твоя Привелегия'!F11,'Исеть Парк'!F11,'Космонавтов 11'!F11,'Утес'!F11) | G11: =SUM('Астон.Движение'!G11,'Астон.Реформа'!G11,'Дом Милый Дом'!G11,'River Park'!G11,'Астрид'!G11,'Живи в Курортном'!G11,'Новое Колпино'!G11,'Таллинский парк'!G11,'Твоя Привелегия'!G11,'Исеть Парк'!G11,'Космонавтов 11'!G11,'Утес'!G11) | H11: =SUM('Астон.Движение'!H11,'Астон.Реформа'!H11,'Дом Милый Дом'!H11,'River Park'!H11,'Астрид'!H11,'Живи в Курортном'!H11,'Новое Колпино'!H11,'Таллинский парк'!H11,'Твоя Привелегия'!H11,'Исеть Парк'!H11,'Космонавтов 11'!H11,'Утес'!H11) | I11: =SUM('Астон.Движение'!I11,'Астон.Реформа'!I11,'Дом Милый Дом'!I11,'River Park'!I11,'Астрид'!I11,'Живи в Курортном'!I11,'Новое Колпино'!I11,'Таллинский парк'!I11,'Твоя Привелегия'!I11,'Исеть Парк'!I11,'Космонавтов 11'!I11,'Утес'!I11)
A12: Транспортные расходы | B12: =SUM('Астон.Движение'!B12,'Астон.Реформа'!B12,'Дом Милый Дом'!B12,'River Park'!B12,'Астрид'!B12,'Живи в Курортном'!B12,'Новое Колпино'!B12,'Таллинский парк'!B12,'Твоя Привелегия'!B12,'Исеть Парк'!B12,'Космонавтов 11'!B12,'Утес'!B12) | C12: =SUM('Астон.Движение'!C12,'Астон.Реформа'!C12,'Дом Милый Дом'!C12,'River Park'!C12,'Астрид'!C12,'Живи в Курортном'!C12,'Новое Колпино'!C12,'Таллинский парк'!C12,'Твоя Привелегия'!C12,'Исеть Парк'!C12,'Космонавтов 11'!C12,'Утес'!C12) | D12: =SUM('Астон.Движение'!D12,'Астон.Реформа'!D12,'Дом Милый Дом'!D12,'River Park'!D12,'Астрид'!D12,'Живи в Курортном'!D12,'Новое Колпино'!D12,'Таллинский парк'!D12,'Твоя Привелегия'!D12,'Исеть Парк'!D12,'Космонавтов 11'!D12,'Утес'!D12) | E12: =SUM('Астон.Движение'!E12,'Астон.Реформа'!E12,'Дом Милый Дом'!E12,'River Park'!E12,'Астрид'!E12,'Живи в Курортном'!E12,'Новое Колпино'!E12,'Таллинский парк'!E12,'Твоя Привелегия'!E12,'Исеть Парк'!E12,'Космонавтов 11'!E12,'Утес'!E12) | F12: =SUM('Астон.Движение'!F12,'Астон.Реформа'!F12,'Дом Милый Дом'!F12,'River Park'!F12,'Астрид'!F12,'Живи в Курортном'!F12,'Новое Колпино'!F12,'Таллинский парк'!F12,'Твоя Привелегия'!F12,'Исеть Парк'!F12,'Космонавтов 11'!F12,'Утес'!F12) | G12: =SUM('Астон.Движение'!G12,'Астон.Реформа'!G12,'Дом Милый Дом'!G12,'River Park'!G12,'Астрид'!G12,'Живи в Курортном'!G12,'Новое Колпино'!G12,'Таллинский парк'!G12,'Твоя Привелегия'!G12,'Исеть Парк'!G12,'Космонавтов 11'!G12,'Утес'!G12) | H12: =SUM('Астон.Движение'!H12,'Астон.Реформа'!H12,'Дом Милый Дом'!H12,'River Park'!H12,'Астрид'!H12,'Живи в Курортном'!H12,'Новое Колпино'!H12,'Таллинский парк'!H12,'Твоя Привелегия'!H12,'Исеть Парк'!H12,'Космонавтов 11'!H12,'Утес'!H12) | I12: =SUM('Астон.Движение'!I12,'Астон.Реформа'!I12,'Дом Милый Дом'!I12,'River Park'!I12,'Астрид'!I12,'Живи в Курортном'!I12,'Новое Колпино'!I12,'Таллинский парк'!I12,'Твоя Привелегия'!I12,'Исеть Парк'!I12,'Космонавтов 11'!I12,'Утес'!I12)
A13: Переменные | B13: =SUM(B14,B15,B16,B17,B18,B19,B20) | C13: =SUM(C14,C15,C16,C17,C18,C19,C20) | D13: =SUM(D14,D15,D16,D17,D18,D19,D20) | E13: =SUM(E14,E15,E16,E17,E18,E19,E20) | F13: =SUM(F14,F15,F16,F17,F18,F19,F20) | G13: =SUM(G14,G15,G16,G17,G18,G19,G20) | H13: =SUM(H14,H15,H16,H17,H18,H19,H20) | I13: =SUM(I14,I15,I16,I17,I18,I19,I20)
A14: Услуги техниги для уборки снега (ПТ) | B14: =SUM('Астон.Движение'!B14,'Астон.Реформа'!B14,'Дом Милый Дом'!B14,'River Park'!B14,'Астрид'!B14,'Живи в Курортном'!B14,'Новое Колпино'!B14,'Таллинский парк'!B14,'Твоя Привелегия'!B14,'Исеть Парк'!B14,'Космонавтов 11'!B14,'Утес'!B14) | C14: =SUM('Астон.Движение'!C14,'Астон.Реформа'!C14,'Дом Милый Дом'!C14,'River Park'!C14,'Астрид'!C14,'Живи в Курортном'!C14,'Новое Колпино'!C14,'Таллинский парк'!C14,'Твоя Привелегия'!C14,'Исеть Парк'!C14,'Космонавтов 11'!C14,'Утес'!C14) | D14: =SUM('Астон.Движение'!D14,'Астон.Реформа'!D14,'Дом Милый Дом'!D14,'River Park'!D14,'Астрид'!D14,'Живи в Курортном'!D14,'Новое Колпино'!D14,'Таллинский парк'!D14,'Твоя Привелегия'!D14,'Исеть Парк'!D14,'Космонавтов 11'!D14,'Утес'!D14) | E14: =SUM('Астон.Движение'!E14,'Астон.Реформа'!E14,'Дом Милый Дом'!E14,'River Park'!E14,'Астрид'!E14,'Живи в Курортном'!E14,'Новое Колпино'!E14,'Таллинский парк'!E14,'Твоя Привелегия'!E14,'Исеть Парк'!E14,'Космонавтов 11'!E14,'Утес'!E14) | F14: =SUM('Астон.Движение'!F14,'Астон.Реформа'!F14,'Дом Милый Дом'!F14,'River Park'!F14,'Астрид'!F14,'Живи в Курортном'!F14,'Новое Колпино'!F14,'Таллинский парк'!F14,'Твоя Привелегия'!F14,'Исеть Парк'!F14,'Космонавтов 11'!F14,'Утес'!F14) | G14: =SUM('Астон.Движение'!G14,'Астон.Реформа'!G14,'Дом Милый Дом'!G14,'River Park'!G14,'Астрид'!G14,'Живи в Курортном'!G14,'Новое Колпино'!G14,'Таллинский парк'!G14,'Твоя Привелегия'!G14,'Исеть Парк'!G14,'Космонавтов 11'!G14,'Утес'!G14) | H14: =SUM('Астон.Движение'!H14,'Астон.Реформа'!H14,'Дом Милый Дом'!H14,'River Park'!H14,'Астрид'!H14,'Живи в Курортном'!H14,'Новое Колпино'!H14,'Таллинский парк'!H14,'Твоя Привелегия'!H14,'Исеть Парк'!H14,'Космонавтов 11'!H14,'Утес'!H14) | I14: =SUM('Астон.Движение'!I14,'Астон.Реформа'!I14,'Дом Милый Дом'!I14,'River Park'!I14,'Астрид'!I14,'Живи в Курортном'!I14,'Новое Колпино'!I14,'Таллинский парк'!I14,'Твоя Привелегия'!I14,'Исеть Парк'!I14,'Космонавтов 11'!I14,'Утес'!I14)
A15: Услуги садовника (ПТ) | B15: =SUM('Астон.Движение'!B15,'Астон.Реформа'!B15,'Дом Милый Дом'!B15,'River Park'!B15,'Астрид'!B15,'Живи в Курортном'!B15,'Новое Колпино'!B15,'Таллинский парк'!B15,'Твоя Привелегия'!B15,'Исеть Парк'!B15,'Космонавтов 11'!B15,'Утес'!B15) | C15: =SUM('Астон.Движение'!C15,'Астон.Реформа'!C15,'Дом Милый Дом'!C15,'River Park'!C15,'Астрид'!C15,'Живи в Курортном'!C15,'Новое Колпино'!C15,'Таллинский парк'!C15,'Твоя Привелегия'!C15,'Исеть Парк'!C15,'Космонавтов 11'!C15,'Утес'!C15) | D15: =SUM('Астон.Движение'!D15,'Астон.Реформа'!D15,'Дом Милый Дом'!D15,'River Park'!D15,'Астрид'!D15,'Живи в Курортном'!D15,'Новое Колпино'!D15,'Таллинский парк'!D15,'Твоя Привелегия'!D15,'Исеть Парк'!D15,'Космонавтов 11'!D15,'Утес'!D15) | E15: =SUM('Астон.Движение'!E15,'Астон.Реформа'!E15,'Дом Милый Дом'!E15,'River Park'!E15,'Астрид'!E15,'Живи в Курортном'!E15,'Новое Колпино'!E15,'Таллинский парк'!E15,'Твоя Привелегия'!E15,'Исеть Парк'!E15,'Космонавтов 11'!E15,'Утес'!E15) | F15: =SUM('Астон.Движение'!F15,'Астон.Реформа'!F15,'Дом Милый Дом'!F15,'River Park'!F15,'Астрид'!F15,'Живи в Курортном'!F15,'Новое Колпино'!F15,'Таллинский парк'!F15,'Твоя Привелегия'!F15,'Исеть Парк'!F15,'Космонавтов 11'!F15,'Утес'!F15) | G15: =SUM('Астон.Движение'!G15,'Астон.Реформа'!G15,'Дом Милый Дом'!G15,'River Park'!G15,'Астрид'!G15,'Живи в Курортном'!G15,'Новое Колпино'!G15,'Таллинский парк'!G15,'Твоя Привелегия'!G15,'Исеть Парк'!G15,'Космонавтов 11'!G15,'Утес'!G15) | H15: =SUM('Астон.Движение'!H15,'Астон.Реформа'!H15,'Дом Милый Дом'!H15,'River Park'!H15,'Астрид'!H15,'Живи в Курортном'!H15,'Новое Колпино'!H15,'Таллинский парк'!H15,'Твоя Привелегия'!H15,'Исеть Парк'!H15,'Космонавтов 11'!H15,'Утес'!H15) | I15: =SUM('Астон.Движение'!I15,'Астон.Реформа'!I15,'Дом Милый Дом'!I15,'River Park'!I15,'Астрид'!I15,'Живи в Курортном'!I15,'Новое Колпино'!I15,'Таллинский парк'!I15,'Твоя Привелегия'!I15,'Исеть Парк'!I15,'Космонавтов 11'!I15,'Утес'!I15)
A16: Сыпучие материалы (ПТ) | B16: =SUM('Астон.Движение'!B16,'Астон.Реформа'!B16,'Дом Милый Дом'!B16,'River Park'!B16,'Астрид'!B16,'Живи в Курортном'!B16,'Новое Колпино'!B16,'Таллинский парк'!B16,'Твоя Привелегия'!B16,'Исеть Парк'!B16,'Космонавтов 11'!B16,'Утес'!B16) | C16: =SUM('Астон.Движение'!C16,'Астон.Реформа'!C16,'Дом Милый Дом'!C16,'River Park'!C16,'Астрид'!C16,'Живи в Курортном'!C16,'Новое Колпино'!C16,'Таллинский парк'!C16,'Твоя Привелегия'!C16,'Исеть Парк'!C16,'Космонавтов 11'!C16,'Утес'!C16) | D16: =SUM('Астон.Движение'!D16,'Астон.Реформа'!D16,'Дом Милый Дом'!D16,'River Park'!D16,'Астрид'!D16,'Живи в Курортном'!D16,'Новое Колпино'!D16,'Таллинский парк'!D16,'Твоя Привелегия'!D16,'Исеть Парк'!D16,'Космонавтов 11'!D16,'Утес'!D16) | E16: =SUM('Астон.Движение'!E16,'Астон.Реформа'!E16,'Дом Милый Дом'!E16,'River Park'!E16,'Астрид'!E16,'Живи в Курортном'!E16,'Новое Колпино'!E16,'Таллинский парк'!E16,'Твоя Привелегия'!E16,'Исеть Парк'!E16,'Космонавтов 11'!E16,'Утес'!E16) | F16: =SUM('Астон.Движение'!F16,'Астон.Реформа'!F16,'Дом Милый Дом'!F16,'River Park'!F16,'Астрид'!F16,'Живи в Курортном'!F16,'Новое Колпино'!F16,'Таллинский парк'!F16,'Твоя Привелегия'!F16,'Исеть Парк'!F16,'Космонавтов 11'!F16,'Утес'!F16) | G16: =SUM('Астон.Движение'!G16,'Астон.Реформа'!G16,'Дом Милый Дом'!G16,'River Park'!G16,'Астрид'!G16,'Живи в Курортном'!G16,'Новое Колпино'!G16,'Таллинский парк'!G16,'Твоя Привелегия'!G16,'Исеть Парк'!G16,'Космонавтов 11'!G16,'Утес'!G16) | H16: =SUM('Астон.Движение'!H16,'Астон.Реформа'!H16,'Дом Милый Дом'!H16,'River Park'!H16,'Астрид'!H16,'Живи в Курортном'!H16,'Новое Колпино'!H16,'Таллинский парк'!H16,'Твоя Привелегия'!H16,'Исеть Парк'!H16,'Космонавтов 11'!H16,'Утес'!H16) | I16: =SUM('Астон.Движение'!I16,'Астон.Реформа'!I16,'Дом Милый Дом'!I16,'River Park'!I16,'Астрид'!I16,'Живи в Курортном'!I16,'Новое Колпино'!I16,'Таллинский парк'!I16,'Твоя Привелегия'!I16,'Исеть Парк'!I16,'Космонавтов 11'!I16,'Утес'!I16)
A17: Расходные материалы и инстументы (МОП) | B17: =SUM('Астон.Движение'!B17,'Астон.Реформа'!B17,'Дом Милый Дом'!B17,'River Park'!B17,'Астрид'!B17,'Живи в Курортном'!B17,'Новое Колпино'!B17,'Таллинский парк'!B17,'Твоя Привелегия'!B17,'Исеть Парк'!B17,'Космонавтов 11'!B17,'Утес'!B17) | C17: =SUM('Астон.Движение'!C17,'Астон.Реформа'!C17,'Дом Милый Дом'!C17,'River Park'!C17,'Астрид'!C17,'Живи в Курортном'!C17,'Новое Колпино'!C17,'Таллинский парк'!C17,'Твоя Привелегия'!C17,'Исеть Парк'!C17,'Космонавтов 11'!C17,'Утес'!C17) | D17: =SUM('Астон.Движение'!D17,'Астон.Реформа'!D17,'Дом Милый Дом'!D17,'River Park'!D17,'Астрид'!D17,'Живи в Курортном'!D17,'Новое Колпино'!D17,'Таллинский парк'!D17,'Твоя Привелегия'!D17,'Исеть Парк'!D17,'Космонавтов 11'!D17,'Утес'!D17) | E17: =SUM('Астон.Движение'!E17,'Астон.Реформа'!E17,'Дом Милый Дом'!E17,'River Park'!E17,'Астрид'!E17,'Живи в Курортном'!E17,'Новое Колпино'!E17,'Таллинский парк'!E17,'Твоя Привелегия'!E17,'Исеть Парк'!E17,'Космонавтов 11'!E17,'Утес'!E17) | F17: =SUM('Астон.Движение'!F17,'Астон.Реформа'!F17,'Дом Милый Дом'!F17,'River Park'!F17,'Астрид'!F17,'Живи в Курортном'!F17,'Новое Колпино'!F17,'Таллинский парк'!F17,'Твоя Привелегия'!F17,'Исеть Парк'!F17,'Космонавтов 11'!F17,'Утес'!F17) | G17: =SUM('Астон.Движение'!G17,'Астон.Реформа'!G17,'Дом Милый Дом'!G17,'River Park'!G17,'Астрид'!G17,'Живи в Курортном'!G17,'Новое Колпино'!G17,'Таллинский парк'!G17,'Твоя Привелегия'!G17,'Исеть Парк'!G17,'Космонавтов 11'!G17,'Утес'!G17) | H17: =SUM('Астон.Движение'!H17,'Астон.Реформа'!H17,'Дом Милый Дом'!H17,'River Park'!H17,'Астрид'!H17,'Живи в Курортном'!H17,'Новое Колпино'!H17,'Таллинский парк'!H17,'Твоя Привелегия'!H17,'Исеть Парк'!H17,'Космонавтов 11'!H17,'Утес'!H17) | I17: =SUM('Астон.Движение'!I17,'Астон.Реформа'!I17,'Дом Милый Дом'!I17,'River Park'!I17,'Астрид'!I17,'Живи в Курортном'!I17,'Новое Колпино'!I17,'Таллинский парк'!I17,'Твоя Привелегия'!I17,'Исеть Парк'!I17,'Космонавтов 11'!I17,'Утес'!I17)
A18: Расходные материалы и инстументы (ПТ) | B18: =SUM('Астон.Движение'!B18,'Астон.Реформа'!B18,'Дом Милый Дом'!B18,'River Park'!B18,'Астрид'!B18,'Живи в Курортном'!B18,'Новое Колпино'!B18,'Таллинский парк'!B18,'Твоя Привелегия'!B18,'Исеть Парк'!B18,'Космонавтов 11'!B18,'Утес'!B18) | C18: =SUM('Астон.Движение'!C18,'Астон.Реформа'!C18,'Дом Милый Дом'!C18,'River Park'!C18,'Астрид'!C18,'Живи в Курортном'!C18,'Новое Колпино'!C18,'Таллинский парк'!C18,'Твоя Привелегия'!C18,'Исеть Парк'!C18,'Космонавтов 11'!C18,'Утес'!C18) | D18: =SUM('Астон.Движение'!D18,'Астон.Реформа'!D18,'Дом Милый Дом'!D18,'River Park'!D18,'Астрид'!D18,'Живи в Курортном'!D18,'Новое Колпино'!D18,'Таллинский парк'!D18,'Твоя Привелегия'!D18,'Исеть Парк'!D18,'Космонавтов 11'!D18,'Утес'!D18) | E18: =SUM('Астон.Движение'!E18,'Астон.Реформа'!E18,'Дом Милый Дом'!E18,'River Park'!E18,'Астрид'!E18,'Живи в Курортном'!E18,'Новое Колпино'!E18,'Таллинский парк'!E18,'Твоя Привелегия'!E18,'Исеть Парк'!E18,'Космонавтов 11'!E18,'Утес'!E18) | F18: =SUM('Астон.Движение'!F18,'Астон.Реформа'!F18,'Дом Милый Дом'!F18,'River Park'!F18,'Астрид'!F18,'Живи в Курортном'!F18,'Новое Колпино'!F18,'Таллинский парк'!F18,'Твоя Привелегия'!F18,'Исеть Парк'!F18,'Космонавтов 11'!F18,'Утес'!F18) | G18: =SUM('Астон.Движение'!G18,'Астон.Реформа'!G18,'Дом Милый Дом'!G18,'River Park'!G18,'Астрид'!G18,'Живи в Курортном'!G18,'Новое Колпино'!G18,'Таллинский парк'!G18,'Твоя Привелегия'!G18,'Исеть Парк'!G18,'Космонавтов 11'!G18,'Утес'!G18) | H18: =SUM('Астон.Движение'!H18,'Астон.Реформа'!H18,'Дом Милый Дом'!H18,'River Park'!H18,'Астрид'!H18,'Живи в Курортном'!H18,'Новое Колпино'!H18,'Таллинский парк'!H18,'Твоя Привелегия'!H18,'Исеть Парк'!H18,'Космонавтов 11'!H18,'Утес'!H18) | I18: =SUM('Астон.Движение'!I18,'Астон.Реформа'!I18,'Дом Милый Дом'!I18,'River Park'!I18,'Астрид'!I18,'Живи в Курортном'!I18,'Новое Колпино'!I18,'Таллинский парк'!I18,'Твоя Привелегия'!I18,'Исеть Парк'!I18,'Космонавтов 11'!I18,'Утес'!I18)
A19: Арена оборудования (ПТ) | B19: =SUM('Астон.Движение'!B19,'Астон.Реформа'!B19,'Дом Милый Дом'!B19,'River Park'!B19,'Астрид'!B19,'Живи в Курортном'!B19,'Новое Колпино'!B19,'Таллинский парк'!B19,'Твоя Привелегия'!B19,'Исеть Парк'!B19,'Космонавтов 11'!B19,'Утес'!B19) | C19: =SUM('Астон.Движение'!C19,'Астон.Реформа'!C19,'Дом Милый Дом'!C19,'River Park'!C19,'Астрид'!C19,'Живи в Курортном'!C19,'Новое Колпино'!C19,'Таллинский парк'!C19,'Твоя Привелегия'!C19,'Исеть Парк'!C19,'Космонавтов 11'!C19,'Утес'!C19) | D19: =SUM('Астон.Движение'!D19,'Астон.Реформа'!D19,'Дом Милый Дом'!D19,'River Park'!D19,'Астрид'!D19,'Живи в Курортном'!D19,'Новое Колпино'!D19,'Таллинский парк'!D19,'Твоя Привелегия'!D19,'Исеть Парк'!D19,'Космонавтов 11'!D19,'Утес'!D19) | E19: =SUM('Астон.Движение'!E19,'Астон.Реформа'!E19,'Дом Милый Дом'!E19,'River Park'!E19,'Астрид'!E19,'Живи в Курортном'!E19,'Новое Колпино'!E19,'Таллинский парк'!E19,'Твоя Привелегия'!E19,'Исеть Парк'!E19,'Космонавтов 11'!E19,'Утес'!E19) | F19: =SUM('Астон.Движение'!F19,'Астон.Реформа'!F19,'Дом Милый Дом'!F19,'River Park'!F19,'Астрид'!F19,'Живи в Курортном'!F19,'Новое Колпино'!F19,'Таллинский парк'!F19,'Твоя Привелегия'!F19,'Исеть Парк'!F19,'Космонавтов 11'!F19,'Утес'!F19) | G19: =SUM('Астон.Движение'!G19,'Астон.Реформа'!G19,'Дом Милый Дом'!G19,'River Park'!G19,'Астрид'!G19,'Живи в Курортном'!G19,'Новое Колпино'!G19,'Таллинский парк'!G19,'Твоя Привелегия'!G19,'Исеть Парк'!G19,'Космонавтов 11'!G19,'Утес'!G19) | H19: =SUM('Астон.Движение'!H19,'Астон.Реформа'!H19,'Дом Милый Дом'!H19,'River Park'!H19,'Астрид'!H19,'Живи в Курортном'!H19,'Новое Колпино'!H19,'Таллинский парк'!H19,'Твоя Привелегия'!H19,'Исеть Парк'!H19,'Космонавтов 11'!H19,'Утес'!H19) | I19: =SUM('Астон.Движение'!I19,'Астон.Реформа'!I19,'Дом Милый Дом'!I19,'River Park'!I19,'Астрид'!I19,'Живи в Курортном'!I19,'Новое Колпино'!I19,'Таллинский парк'!I19,'Твоя Привелегия'!I19,'Исеть Парк'!I19,'Космонавтов 11'!I19,'Утес'!I19)
A20: Арена оборудования (МОП) | B20: =SUM('Астон.Движение'!B20,'Астон.Реформа'!B20,'Дом Милый Дом'!B20,'River Park'!B20,'Астрид'!B20,'Живи в Курортном'!B20,'Новое Колпино'!B20,'Таллинский парк'!B20,'Твоя Привелегия'!B20,'Исеть Парк'!B20,'Космонавтов 11'!B20,'Утес'!B20) | C20: =SUM('Астон.Движение'!C20,'Астон.Реформа'!C20,'Дом Милый Дом'!C20,'River Park'!C20,'Астрид'!C20,'Живи в Курортном'!C20,'Новое Колпино'!C20,'Таллинский парк'!C20,'Твоя Привелегия'!C20,'Исеть Парк'!C20,'Космонавтов 11'!C20,'Утес'!C20) | D20: =SUM('Астон.Движение'!D20,'Астон.Реформа'!D20,'Дом Милый Дом'!D20,'River Park'!D20,'Астрид'!D20,'Живи в Курортном'!D20,'Новое Колпино'!D20,'Таллинский парк'!D20,'Твоя Привелегия'!D20,'Исеть Парк'!D20,'Космонавтов 11'!D20,'Утес'!D20) | E20: =SUM('Астон.Движение'!E20,'Астон.Реформа'!E20,'Дом Милый Дом'!E20,'River Park'!E20,'Астрид'!E20,'Живи в Курортном'!E20,'Новое Колпино'!E20,'Таллинский парк'!E20,'Твоя Привелегия'!E20,'Исеть Парк'!E20,'Космонавтов 11'!E20,'Утес'!E20) | F20: =SUM('Астон.Движение'!F20,'Астон.Реформа'!F20,'Дом Милый Дом'!F20,'River Park'!F20,'Астрид'!F20,'Живи в Курортном'!F20,'Новое Колпино'!F20,'Таллинский парк'!F20,'Твоя Привелегия'!F20,'Исеть Парк'!F20,'Космонавтов 11'!F20,'Утес'!F20) | G20: =SUM('Астон.Движение'!G20,'Астон.Реформа'!G20,'Дом Милый Дом'!G20,'River Park'!G20,'Астрид'!G20,'Живи в Курортном'!G20,'Новое Колпино'!G20,'Таллинский парк'!G20,'Твоя Привелегия'!G20,'Исеть Парк'!G20,'Космонавтов 11'!G20,'Утес'!G20) | H20: =SUM('Астон.Движение'!H20,'Астон.Реформа'!H20,'Дом Милый Дом'!H20,'River Park'!H20,'Астрид'!H20,'Живи в Курортном'!H20,'Новое Колпино'!H20,'Таллинский парк'!H20,'Твоя Привелегия'!H20,'Исеть Парк'!H20,'Космонавтов 11'!H20,'Утес'!H20) | I20: =SUM('Астон.Движение'!I20,'Астон.Реформа'!I20,'Дом Милый Дом'!I20,'River Park'!I20,'Астрид'!I20,'Живи в Курортном'!I20,'Новое Колпино'!I20,'Таллинский парк'!I20,'Твоя Привелегия'!I20,'Исеть Парк'!I20,'Космонавтов 11'!I20,'Утес'!I20)
A21: Заработная плата (МОП) | B21: =SUM('Астон.Движение'!B21,'Астон.Реформа'!B21,'Дом Милый Дом'!B21,'River Park'!B21,'Астрид'!B21,'Живи в Курортном'!B21,'Новое Колпино'!B21,'Таллинский парк'!B21,'Твоя Привелегия'!B21,'Исеть Парк'!B21,'Космонавтов 11'!B21,'Утес'!B21) | C21: =SUM('Астон.Движение'!C21,'Астон.Реформа'!C21,'Дом Милый Дом'!C21,'River Park'!C21,'Астрид'!C21,'Живи в Курортном'!C21,'Новое Колпино'!C21,'Таллинский парк'!C21,'Твоя Привелегия'!C21,'Исеть Парк'!C21,'Космонавтов 11'!C21,'Утес'!C21) | D21: =SUM('Астон.Движение'!D21,'Астон.Реформа'!D21,'Дом Милый Дом'!D21,'River Park'!D21,'Астрид'!D21,'Живи в Курортном'!D21,'Новое Колпино'!D21,'Таллинский парк'!D21,'Твоя Привелегия'!D21,'Исеть Парк'!D21,'Космонавтов 11'!D21,'Утес'!D21) | E21: =SUM('Астон.Движение'!E21,'Астон.Реформа'!E21,'Дом Милый Дом'!E21,'River Park'!E21,'Астрид'!E21,'Живи в Курортном'!E21,'Новое Колпино'!E21,'Таллинский парк'!E21,'Твоя Привелегия'!E21,'Исеть Парк'!E21,'Космонавтов 11'!E21,'Утес'!E21) | F21: =SUM('Астон.Движение'!F21,'Астон.Реформа'!F21,'Дом Милый Дом'!F21,'River Park'!F21,'Астрид'!F21,'Живи в Курортном'!F21,'Новое Колпино'!F21,'Таллинский парк'!F21,'Твоя Привелегия'!F21,'Исеть Парк'!F21,'Космонавтов 11'!F21,'Утес'!F21) | G21: =SUM('Астон.Движение'!G21,'Астон.Реформа'!G21,'Дом Милый Дом'!G21,'River Park'!G21,'Астрид'!G21,'Живи в Курортном'!G21,'Новое Колпино'!G21,'Таллинский парк'!G21,'Твоя Привелегия'!G21,'Исеть Парк'!G21,'Космонавтов 11'!G21,'Утес'!G21) | H21: =SUM('Астон.Движение'!H21,'Астон.Реформа'!H21,'Дом Милый Дом'!H21,'River Park'!H21,'Астрид'!H21,'Живи в Курортном'!H21,'Новое Колпино'!H21,'Таллинский парк'!H21,'Твоя Привелегия'!H21,'Исеть Парк'!H21,'Космонавтов 11'!H21,'Утес'!H21) | I21: =SUM('Астон.Движение'!I21,'Астон.Реформа'!I21,'Дом Милый Дом'!I21,'River Park'!I21,'Астрид'!I21,'Живи в Курортном'!I21,'Новое Колпино'!I21,'Таллинский парк'!I21,'Твоя Привелегия'!I21,'Исеть Парк'!I21,'Космонавтов 11'!I21,'Утес'!I21)
A22: Заработная плата (ПТ) | B22: =SUM('Астон.Движение'!B22,'Астон.Реформа'!B22,'Дом Милый Дом'!B22,'River Park'!B22,'Астрид'!B22,'Живи в Курортном'!B22,'Новое Колпино'!B22,'Таллинский парк'!B22,'Твоя Привелегия'!B22,'Исеть Парк'!B22,'Космонавтов 11'!B22,'Утес'!B22) | C22: =SUM('Астон.Движение'!C22,'Астон.Реформа'!C22,'Дом Милый Дом'!C22,'River Park'!C22,'Астрид'!C22,'Живи в Курортном'!C22,'Новое Колпино'!C22,'Таллинский парк'!C22,'Твоя Привелегия'!C22,'Исеть Парк'!C22,'Космонавтов 11'!C22,'Утес'!C22) | D22: =SUM('Астон.Движение'!D22,'Астон.Реформа'!D22,'Дом Милый Дом'!D22,'River Park'!D22,'Астрид'!D22,'Живи в Курортном'!D22,'Новое Колпино'!D22,'Таллинский парк'!D22,'Твоя Привелегия'!D22,'Исеть Парк'!D22,'Космонавтов 11'!D22,'Утес'!D22) | E22: =SUM('Астон.Движение'!E22,'Астон.Реформа'!E22,'Дом Милый Дом'!E22,'River Park'!E22,'Астрид'!E22,'Живи в Курортном'!E22,'Новое Колпино'!E22,'Таллинский парк'!E22,'Твоя Привелегия'!E22,'Исеть Парк'!E22,'Космонавтов 11'!E22,'Утес'!E22) | F22: =SUM('Астон.Движение'!F22,'Астон.Реформа'!F22,'Дом Милый Дом'!F22,'River Park'!F22,'Астрид'!F22,'Живи в Курортном'!F22,'Новое Колпино'!F22,'Таллинский парк'!F22,'Твоя Привелегия'!F22,'Исеть Парк'!F22,'Космонавтов 11'!F22,'Утес'!F22) | G22: =SUM('Астон.Движение'!G22,'Астон.Реформа'!G22,'Дом Милый Дом'!G22,'River Park'!G22,'Астрид'!G22,'Живи в Курортном'!G22,'Новое Колпино'!G22,'Таллинский парк'!G22,'Твоя Привелегия'!G22,'Исеть Парк'!G22,'Космонавтов 11'!G22,'Утес'!G22) | H22: =SUM('Астон.Движение'!H22,'Астон.Реформа'!H22,'Дом Милый Дом'!H22,'River Park'!H22,'Астрид'!H22,'Живи в Курортном'!H22,'Новое Колпино'!H22,'Таллинский парк'!H22,'Твоя Привелегия'!H22,'Исеть Парк'!H22,'Космонавтов 11'!H22,'Утес'!H22) | I22: =SUM('Астон.Движение'!I22,'Астон.Реформа'!I22,'Дом Милый Дом'!I22,'River Park'!I22,'Астрид'!I22,'Живи в Курортном'!I22,'Новое Колпино'!I22,'Таллинский парк'!I22,'Твоя Привелегия'!I22,'Исеть Парк'!I22,'Космонавтов 11'!I22,'Утес'!I22)
A23: Налоги с ФОТ (МОП) | B23: =SUM('Астон.Движение'!B23,'Астон.Реформа'!B23,'Дом Милый Дом'!B23,'River Park'!B23,'Астрид'!B23,'Живи в Курортном'!B23,'Новое Колпино'!B23,'Таллинский парк'!B23,'Твоя Привелегия'!B23,'Исеть Парк'!B23,'Космонавтов 11'!B23,'Утес'!B23) | C23: =SUM('Астон.Движение'!C23,'Астон.Реформа'!C23,'Дом Милый Дом'!C23,'River Park'!C23,'Астрид'!C23,'Живи в Курортном'!C23,'Новое Колпино'!C23,'Таллинский парк'!C23,'Твоя Привелегия'!C23,'Исеть Парк'!C23,'Космонавтов 11'!C23,'Утес'!C23) | D23: =SUM('Астон.Движение'!D23,'Астон.Реформа'!D23,'Дом Милый Дом'!D23,'River Park'!D23,'Астрид'!D23,'Живи в Курортном'!D23,'Новое Колпино'!D23,'Таллинский парк'!D23,'Твоя Привелегия'!D23,'Исеть Парк'!D23,'Космонавтов 11'!D23,'Утес'!D23) | E23: =SUM('Астон.Движение'!E23,'Астон.Реформа'!E23,'Дом Милый Дом'!E23,'River Park'!E23,'Астрид'!E23,'Живи в Курортном'!E23,'Новое Колпино'!E23,'Таллинский парк'!E23,'Твоя Привелегия'!E23,'Исеть Парк'!E23,'Космонавтов 11'!E23,'Утес'!E23) | F23: =SUM('Астон.Движение'!F23,'Астон.Реформа'!F23,'Дом Милый Дом'!F23,'River Park'!F23,'Астрид'!F23,'Живи в Курортном'!F23,'Новое Колпино'!F23,'Таллинский парк'!F23,'Твоя Привелегия'!F23,'Исеть Парк'!F23,'Космонавтов 11'!F23,'Утес'!F23) | G23: =SUM('Астон.Движение'!G23,'Астон.Реформа'!G23,'Дом Милый Дом'!G23,'River Park'!G23,'Астрид'!G23,'Живи в Курортном'!G23,'Новое Колпино'!G23,'Таллинский парк'!G23,'Твоя Привелегия'!G23,'Исеть Парк'!G23,'Космонавтов 11'!G23,'Утес'!G23) | H23: =SUM('Астон.Движение'!H23,'Астон.Реформа'!H23,'Дом Милый Дом'!H23,'River Park'!H23,'Астрид'!H23,'Живи в Курортном'!H23,'Новое Колпино'!H23,'Таллинский парк'!H23,'Твоя Привелегия'!H23,'Исеть Парк'!H23,'Космонавтов 11'!H23,'Утес'!H23) | I23: =SUM('Астон.Движение'!I23,'Астон.Реформа'!I23,'Дом Милый Дом'!I23,'River Park'!I23,'Астрид'!I23,'Живи в Курортном'!I23,'Новое Колпино'!I23,'Таллинский парк'!I23,'Твоя Привелегия'!I23,'Исеть Парк'!I23,'Космонавтов 11'!I23,'Утес'!I23)
A24: Налоги с ФОТ (ПТ) | B24: =SUM('Астон.Движение'!B24,'Астон.Реформа'!B24,'Дом Милый Дом'!B24,'River Park'!B24,'Астрид'!B24,'Живи в Курортном'!B24,'Новое Колпино'!B24,'Таллинский парк'!B24,'Твоя Привелегия'!B24,'Исеть Парк'!B24,'Космонавтов 11'!B24,'Утес'!B24) | C24: =SUM('Астон.Движение'!C24,'Астон.Реформа'!C24,'Дом Милый Дом'!C24,'River Park'!C24,'Астрид'!C24,'Живи в Курортном'!C24,'Новое Колпино'!C24,'Таллинский парк'!C24,'Твоя Привелегия'!C24,'Исеть Парк'!C24,'Космонавтов 11'!C24,'Утес'!C24) | D24: =SUM('Астон.Движение'!D24,'Астон.Реформа'!D24,'Дом Милый Дом'!D24,'River Park'!D24,'Астрид'!D24,'Живи в Курортном'!D24,'Новое Колпино'!D24,'Таллинский парк'!D24,'Твоя Привелегия'!D24,'Исеть Парк'!D24,'Космонавтов 11'!D24,'Утес'!D24) | E24: =SUM('Астон.Движение'!E24,'Астон.Реформа'!E24,'Дом Милый Дом'!E24,'River Park'!E24,'Астрид'!E24,'Живи в Курортном'!E24,'Новое Колпино'!E24,'Таллинский парк'!E24,'Твоя Привелегия'!E24,'Исеть Парк'!E24,'Космонавтов 11'!E24,'Утес'!E24) | F24: =SUM('Астон.Движение'!F24,'Астон.Реформа'!F24,'Дом Милый Дом'!F24,'River Park'!F24,'Астрид'!F24,'Живи в Курортном'!F24,'Новое Колпино'!F24,'Таллинский парк'!F24,'Твоя Привелегия'!F24,'Исеть Парк'!F24,'Космонавтов 11'!F24,'Утес'!F24) | G24: =SUM('Астон.Движение'!G24,'Астон.Реформа'!G24,'Дом Милый Дом'!G24,'River Park'!G24,'Астрид'!G24,'Живи в Курортном'!G24,'Новое Колпино'!G24,'Таллинский парк'!G24,'Твоя Привелегия'!G24,'Исеть Парк'!G24,'Космонавтов 11'!G24,'Утес'!G24) | H24: =SUM('Астон.Движение'!H24,'Астон.Реформа'!H24,'Дом Милый Дом'!H24,'River Park'!H24,'Астрид'!H24,'Живи в Курортном'!H24,'Новое Колпино'!H24,'Таллинский парк'!H24,'Твоя Привелегия'!H24,'Исеть Парк'!H24,'Космонавтов 11'!H24,'Утес'!H24) | I24: =SUM('Астон.Движение'!I24,'Астон.Реформа'!I24,'Дом Милый Дом'!I24,'River Park'!I24,'Астрид'!I24,'Живи в Курортном'!I24,'Новое Колпино'!I24,'Таллинский парк'!I24,'Твоя Привелегия'!I24,'Исеть Парк'!I24,'Космонавтов 11'!I24,'Утес'!I24)
A25: Премми (МОП) | B25: =SUM('Астон.Движение'!B25,'Астон.Реформа'!B25,'Дом Милый Дом'!B25,'River Park'!B25,'Астрид'!B25,'Живи в Курортном'!B25,'Новое Колпино'!B25,'Таллинский парк'!B25,'Твоя Привелегия'!B25,'Исеть Парк'!B25,'Космонавтов 11'!B25,'Утес'!B25) | C25: =SUM('Астон.Движение'!C25,'Астон.Реформа'!C25,'Дом Милый Дом'!C25,'River Park'!C25,'Астрид'!C25,'Живи в Курортном'!C25,'Новое Колпино'!C25,'Таллинский парк'!C25,'Твоя Привелегия'!C25,'Исеть Парк'!C25,'Космонавтов 11'!C25,'Утес'!C25) | D25: =SUM('Астон.Движение'!D25,'Астон.Реформа'!D25,'Дом Милый Дом'!D25,'River Park'!D25,'Астрид'!D25,'Живи в Курортном'!D25,'Новое Колпино'!D25,'Таллинский парк'!D25,'Твоя Привелегия'!D25,'Исеть Парк'!D25,'Космонавтов 11'!D25,'Утес'!D25) | E25: =SUM('Астон.Движение'!E25,'Астон.Реформа'!E25,'Дом Милый Дом'!E25,'River Park'!E25,'Астрид'!E25,'Живи в Курортном'!E25,'Новое Колпино'!E25,'Таллинский парк'!E25,'Твоя Привелегия'!E25,'Исеть Парк'!E25,'Космонавтов 11'!E25,'Утес'!E25) | F25: =SUM('Астон.Движение'!F25,'Астон.Реформа'!F25,'Дом Милый Дом'!F25,'River Park'!F25,'Астрид'!F25,'Живи в Курортном'!F25,'Новое Колпино'!F25,'Таллинский парк'!F25,'Твоя Привелегия'!F25,'Исеть Парк'!F25,'Космонавтов 11'!F25,'Утес'!F25) | G25: =SUM('Астон.Движение'!G25,'Астон.Реформа'!G25,'Дом Милый Дом'!G25,'River Park'!G25,'Астрид'!G25,'Живи в Курортном'!G25,'Новое Колпино'!G25,'Таллинский парк'!G25,'Твоя Привелегия'!G25,'Исеть Парк'!G25,'Космонавтов 11'!G25,'Утес'!G25) | H25: =SUM('Астон.Движение'!H25,'Астон.Реформа'!H25,'Дом Милый Дом'!H25,'River Park'!H25,'Астрид'!H25,'Живи в Курортном'!H25,'Новое Колпино'!H25,'Таллинский парк'!H25,'Твоя Привелегия'!H25,'Исеть Парк'!H25,'Космонавтов 11'!H25,'Утес'!H25) | I25: =SUM('Астон.Движение'!I25,'Астон.Реформа'!I25,'Дом Милый Дом'!I25,'River Park'!I25,'Астрид'!I25,'Живи в Курортном'!I25,'Новое Колпино'!I25,'Таллинский парк'!I25,'Твоя Привелегия'!I25,'Исеть Парк'!I25,'Космонавтов 11'!I25,'Утес'!I25)
... A33: Расходы к удержанию | B33: =SUM('Астон.Движение'!B33,'Астон.Реформа'!B33,'Дом Милый Дом'!B33,'River Park'!B33,'Астрид'!B33,'Живи в Курортном'!B33,'Новое Колпино'!B33,'Таллинский парк'!B33,'Твоя Привелегия'!B33,'Исеть Парк'!B33,'Космонавтов 11'!B33,'Утес'!B33) | C33: =SUM('Астон.Движение'!C33,'Астон.Реформа'!C33,'Дом Милый Дом'!C33,'River Park'!C33,'Астрид'!C33,'Живи в Курортном'!C33,'Новое Колпино'!C33,'Таллинский парк'!C33,'Твоя Привелегия'!C33,'Исеть Парк'!C33,'Космонавтов 11'!C33,'Утес'!C33) | D33: =SUM('Астон.Движение'!D33,'Астон.Реформа'!D33,'Дом Милый Дом'!D33,'River Park'!D33,'Астрид'!D33,'Живи в Курортном'!D33,'Новое Колпино'!D33,'Таллинский парк'!D33,'Твоя Привелегия'!D33,'Исеть Парк'!D33,'Космонавтов 11'!D33,'Утес'!D33) | E33: =SUM('Астон.Движение'!E33,'Астон.Реформа'!E33,'Дом Милый Дом'!E33,'River Park'!E33,'Астрид'!E33,'Живи в Курортном'!E33,'Новое Колпино'!E33,'Таллинский парк'!E33,'Твоя Привелегия'!E33,'Исеть Парк'!E33,'Космонавтов 11'!E33,'Утес'!E33) | F33: =SUM('Астон.Движение'!F33,'Астон.Реформа'!F33,'Дом Милый Дом'!F33,'River Park'!F33,'Астрид'!F33,'Живи в Курортном'!F33,'Новое Колпино'!F33,'Таллинский парк'!F33,'Твоя Привелегия'!F33,'Исеть Парк'!F33,'Космонавтов 11'!F33,'Утес'!F33) | G33: =SUM('Астон.Движение'!G33,'Астон.Реформа'!G33,'Дом Милый Дом'!G33,'River Park'!G33,'Астрид'!G33,'Живи в Курортном'!G33,'Новое Колпино'!G33,'Таллинский парк'!G33,'Твоя Привелегия'!G33,'Исеть Парк'!G33,'Космонавтов 11'!G33,'Утес'!G33) | H33: =SUM('Астон.Движение'!H33,'Астон.Реформа'!H33,'Дом Милый Дом'!H33,'River Park'!H33,'Астрид'!H33,'Живи в Курортном'!H33,'Новое Колпино'!H33,'Таллинский парк'!H33,'Твоя Привелегия'!H33,'Исеть Парк'!H33,'Космонавтов 11'!H33,'Утес'!H33) | I33: =SUM('Астон.Движение'!I33,'Астон.Реформа'!I33,'Дом Милый Дом'!I33,'River Park'!I33,'Астрид'!I33,'Живи в Курортном'!I33,'Новое Колпино'!I33,'Таллинский парк'!I33,'Твоя Привелегия'!I33,'Исеть Парк'!I33,'Космонавтов 11'!I33,'Утес'!I33)
A34: Общехозяйственные | B34: =SUM(B35,B36,B37,B38,B39,B40,B41,B42) | C34: =SUM(C35,C36,C37,C38,C39,C40,C41,C42) | D34: =SUM(D35,D36,D37,D38,D39,D40,D41,D42) | E34: =SUM(E35,E36,E37,E38,E39,E40,E41,E42) | F34: =SUM(F35,F36,F37,F38,F39,F40,F41,F42) | G34: =SUM(G35,G36,G37,G38,G39,G40,G41,G42) | H34: =SUM(H35,H36,H37,H38,H39,H40,H41,H42) | I34: =SUM(I35,I36,I37,I38,I39,I40,I41,I42)
A35: Аутсорс (направления) | B35: =SUM('Астон.Движение'!B35,'Астон.Реформа'!B35,'Дом Милый Дом'!B35,'River Park'!B35,'Астрид'!B35,'Живи в Курортном'!B35,'Новое Колпино'!B35,'Таллинский парк'!B35,'Твоя Привелегия'!B35,'Исеть Парк'!B35,'Космонавтов 11'!B35,'Утес'!B35) | C35: =SUM('Астон.Движение'!C35,'Астон.Реформа'!C35,'Дом Милый Дом'!C35,'River Park'!C35,'Астрид'!C35,'Живи в Курортном'!C35,'Новое Колпино'!C35,'Таллинский парк'!C35,'Твоя Привелегия'!C35,'Исеть Парк'!C35,'Космонавтов 11'!C35,'Утес'!C35) | D35: =SUM('Астон.Движение'!D35,'Астон.Реформа'!D35,'Дом Милый Дом'!D35,'River Park'!D35,'Астрид'!D35,'Живи в Курортном'!D35,'Новое Колпино'!D35,'Таллинский парк'!D35,'Твоя Привелегия'!D35,'Исеть Парк'!D35,'Космонавтов 11'!D35,'Утес'!D35) | E35: =SUM('Астон.Движение'!E35,'Астон.Реформа'!E35,'Дом Милый Дом'!E35,'River Park'!E35,'Астрид'!E35,'Живи в Курортном'!E35,'Новое Колпино'!E35,'Таллинский парк'!E35,'Твоя Привелегия'!E35,'Исеть Парк'!E35,'Космонавтов 11'!E35,'Утес'!E35) | F35: =SUM('Астон.Движение'!F35,'Астон.Реформа'!F35,'Дом Милый Дом'!F35,'River Park'!F35,'Астрид'!F35,'Живи в Курортном'!F35,'Новое Колпино'!F35,'Таллинский парк'!F35,'Твоя Привелегия'!F35,'Исеть Парк'!F35,'Космонавтов 11'!F35,'Утес'!F35) | G35: =SUM('Астон.Движение'!G35,'Астон.Реформа'!G35,'Дом Милый Дом'!G35,'River Park'!G35,'Астрид'!G35,'Живи в Курортном'!G35,'Новое Колпино'!G35,'Таллинский парк'!G35,'Твоя Привелегия'!G35,'Исеть Парк'!G35,'Космонавтов 11'!G35,'Утес'!G35) | H35: =SUM('Астон.Движение'!H35,'Астон.Реформа'!H35,'Дом Милый Дом'!H35,'River Park'!H35,'Астрид'!H35,'Живи в Курортном'!H35,'Новое Колпино'!H35,'Таллинский парк'!H35,'Твоя Привелегия'!H35,'Исеть Парк'!H35,'Космонавтов 11'!H35,'Утес'!H35) | I35: =SUM('Астон.Движение'!I35,'Астон.Реформа'!I35,'Дом Милый Дом'!I35,'River Park'!I35,'Астрид'!I35,'Живи в Курортном'!I35,'Новое Колпино'!I35,'Таллинский парк'!I35,'Твоя Привелегия'!I35,'Исеть Парк'!I35,'Космонавтов 11'!I35,'Утес'!I35)
A36: Заработная плата МО АУП | B36: =SUM('Астон.Движение'!B36,'Астон.Реформа'!B36,'Дом Милый Дом'!B36,'River Park'!B36,'Астрид'!B36,'Живи в Курортном'!B36,'Новое Колпино'!B36,'Таллинский парк'!B36,'Твоя Привелегия'!B36,'Исеть Парк'!B36,'Космонавтов 11'!B36,'Утес'!B36) | C36: =SUM('Астон.Движение'!C36,'Астон.Реформа'!C36,'Дом Милый Дом'!C36,'River Park'!C36,'Астрид'!C36,'Живи в Курортном'!C36,'Новое Колпино'!C36,'Таллинский парк'!C36,'Твоя Привелегия'!C36,'Исеть Парк'!C36,'Космонавтов 11'!C36,'Утес'!C36) | D36: =SUM('Астон.Движение'!D36,'Астон.Реформа'!D36,'Дом Милый Дом'!D36,'River Park'!D36,'Астрид'!D36,'Живи в Курортном'!D36,'Новое Колпино'!D36,'Таллинский парк'!D36,'Твоя Привелегия'!D36,'Исеть Парк'!D36,'Космонавтов 11'!D36,'Утес'!D36) | E36: =SUM('Астон.Движение'!E36,'Астон.Реформа'!E36,'Дом Милый Дом'!E36,'River Park'!E36,'Астрид'!E36,'Живи в Курортном'!E36,'Новое Колпино'!E36,'Таллинский парк'!E36,'Твоя Привелегия'!E36,'Исеть Парк'!E36,'Космонавтов 11'!E36,'Утес'!E36) | F36: =SUM('Астон.Движение'!F36,'Астон.Реформа'!F36,'Дом Милый Дом'!F36,'River Park'!F36,'Астрид'!F36,'Живи в Курортном'!F36,'Новое Колпино'!F36,'Таллинский парк'!F36,'Твоя Привелегия'!F36,'Исеть Парк'!F36,'Космонавтов 11'!F36,'Утес'!F36) | G36: =SUM('Астон.Движение'!G36,'Астон.Реформа'!G36,'Дом Милый Дом'!G36,'River Park'!G36,'Астрид'!G36,'Живи в Курортном'!G36,'Новое Колпино'!G36,'Таллинский парк'!G36,'Твоя Привелегия'!G36,'Исеть Парк'!G36,'Космонавтов 11'!G36,'Утес'!G36) | H36: =SUM('Астон.Движение'!H36,'Астон.Реформа'!H36,'Дом Милый Дом'!H36,'River Park'!H36,'Астрид'!H36,'Живи в Курортном'!H36,'Новое Колпино'!H36,'Таллинский парк'!H36,'Твоя Привелегия'!H36,'Исеть Парк'!H36,'Космонавтов 11'!H36,'Утес'!H36) | I36: =SUM('Астон.Движение'!I36,'Астон.Реформа'!I36,'Дом Милый Дом'!I36,'River Park'!I36,'Астрид'!I36,'Живи в Курортном'!I36,'Новое Колпино'!I36,'Таллинский парк'!I36,'Твоя Привелегия'!I36,'Исеть Парк'!I36,'Космонавтов 11'!I36,'Утес'!I36)
A37: Инструменты: ГСМ | B37: =SUM('Астон.Движение'!B37,'Астон.Реформа'!B37,'Дом Милый Дом'!B37,'River Park'!B37,'Астрид'!B37,'Живи в Курортном'!B37,'Новое Колпино'!B37,'Таллинский парк'!B37,'Твоя Привелегия'!B37,'Исеть Парк'!B37,'Космонавтов 11'!B37,'Утес'!B37) | C37: =SUM('Астон.Движение'!C37,'Астон.Реформа'!C37,'Дом Милый Дом'!C37,'River Park'!C37,'Астрид'!C37,'Живи в Курортном'!C37,'Новое Колпино'!C37,'Таллинский парк'!C37,'Твоя Привелегия'!C37,'Исеть Парк'!C37,'Космонавтов 11'!C37,'Утес'!C37) | D37: =SUM('Астон.Движение'!D37,'Астон.Реформа'!D37,'Дом Милый Дом'!D37,'River Park'!D37,'Астрид'!D37,'Живи в Курортном'!D37,'Новое Колпино'!D37,'Таллинский парк'!D37,'Твоя Привелегия'!D37,'Исеть Парк'!D37,'Космонавтов 11'!D37,'Утес'!D37) | E37: =SUM('Астон.Движение'!E37,'Астон.Реформа'!E37,'Дом Милый Дом'!E37,'River Park'!E37,'Астрид'!E37,'Живи в Курортном'!E37,'Новое Колпино'!E37,'Таллинский парк'!E37,'Твоя Привелегия'!E37,'Исеть Парк'!E37,'Космонавтов 11'!E37,'Утес'!E37) | F37: =SUM('Астон.Движение'!F37,'Астон.Реформа'!F37,'Дом Милый Дом'!F37,'River Park'!F37,'Астрид'!F37,'Живи в Курортном'!F37,'Новое Колпино'!F37,'Таллинский парк'!F37,'Твоя Привелегия'!F37,'Исеть Парк'!F37,'Космонавтов 11'!F37,'Утес'!F37) | G37: =SUM('Астон.Движение'!G37,'Астон.Реформа'!G37,'Дом Милый Дом'!G37,'River Park'!G37,'Астрид'!G37,'Живи в Курортном'!G37,'Новое Колпино'!G37,'Таллинский парк'!G37,'Твоя Привелегия'!G37,'Исеть Парк'!G37,'Космонавтов 11'!G37,'Утес'!G37) | H37: =SUM('Астон.Движение'!H37,'Астон.Реформа'!H37,'Дом Милый Дом'!H37,'River Park'!H37,'Астрид'!H37,'Живи в Курортном'!H37,'Новое Колпино'!H37,'Таллинский парк'!H37,'Твоя Привелегия'!H37,'Исеть Парк'!H37,'Космонавтов 11'!H37,'Утес'!H37) | I37: =SUM('Астон.Движение'!I37,'Астон.Реформа'!I37,'Дом Милый Дом'!I37,'River Park'!I37,'Астрид'!I37,'Живи в Курортном'!I37,'Новое Колпино'!I37,'Таллинский парк'!I37,'Твоя Привелегия'!I37,'Исеть Парк'!I37,'Космонавтов 11'!I37,'Утес'!I37)
A38: Медосмотры | B38: =SUM('Астон.Движение'!B38,'Астон.Реформа'!B38,'Дом Милый Дом'!B38,'River Park'!B38,'Астрид'!B38,'Живи в Курортном'!B38,'Новое Колпино'!B38,'Таллинский парк'!B38,'Твоя Привелегия'!B38,'Исеть Парк'!B38,'Космонавтов 11'!B38,'Утес'!B38) | C38: =SUM('Астон.Движение'!C38,'Астон.Реформа'!C38,'Дом Милый Дом'!C38,'River Park'!C38,'Астрид'!C38,'Живи в Курортном'!C38,'Новое Колпино'!C38,'Таллинский парк'!C38,'Твоя Привелегия'!C38,'Исеть Парк'!C38,'Космонавтов 11'!C38,'Утес'!C38) | D38: =SUM('Астон.Движение'!D38,'Астон.Реформа'!D38,'Дом Милый Дом'!D38,'River Park'!D38,'Астрид'!D38,'Живи в Курортном'!D38,'Новое Колпино'!D38,'Таллинский парк'!D38,'Твоя Привелегия'!D38,'Исеть Парк'!D38,'Космонавтов 11'!D38,'Утес'!D38) | E38: =SUM('Астон.Движение'!E38,'Астон.Реформа'!E38,'Дом Милый Дом'!E38,'River Park'!E38,'Астрид'!E38,'Живи в Курортном'!E38,'Новое Колпино'!E38,'Таллинский парк'!E38,'Твоя Привелегия'!E38,'Исеть Парк'!E38,'Космонавтов 11'!E38,'Утес'!E38) | F38: =SUM('Астон.Движение'!F38,'Астон.Реформа'!F38,'Дом Милый Дом'!F38,'River Park'!F38,'Астрид'!F38,'Живи в Курортном'!F38,'Новое Колпино'!F38,'Таллинский парк'!F38,'Твоя Привелегия'!F38,'Исеть Парк'!F38,'Космонавтов 11'!F38,'Утес'!F38) | G38: =SUM('Астон.Движение'!G38,'Астон.Реформа'!G38,'Дом Милый Дом'!G38,'River Park'!G38,'Астрид'!G38,'Живи в Курортном'!G38,'Новое Колпино'!G38,'Таллинский парк'!G38,'Твоя Привелегия'!G38,'Исеть Парк'!G38,'Космонавтов 11'!G38,'Утес'!G38) | H38: =SUM('Астон.Движение'!H38,'Астон.Реформа'!H38,'Дом Милый Дом'!H38,'River Park'!H38,'Астрид'!H38,'Живи в Курортном'!H38,'Новое Колпино'!H38,'Таллинский парк'!H38,'Твоя Привелегия'!H38,'Исеть Парк'!H38,'Космонавтов 11'!H38,'Утес'!H38) | I38: =SUM('Астон.Движение'!I38,'Астон.Реформа'!I38,'Дом Милый Дом'!I38,'River Park'!I38,'Астрид'!I38,'Живи в Курортном'!I38,'Новое Колпино'!I38,'Таллинский парк'!I38,'Твоя Привелегия'!I38,'Исеть Парк'!I38,'Космонавтов 11'!I38,'Утес'!I38)
A39: Налоги с ФОТ (ИП) | B39: =SUM('Астон.Движение'!B39,'Астон.Реформа'!B39,'Дом Милый Дом'!B39,'River Park'!B39,'Астрид'!B39,'Живи в Курортном'!B39,'Новое Колпино'!B39,'Таллинский парк'!B39,'Твоя Привелегия'!B39,'Исеть Парк'!B39,'Космонавтов 11'!B39,'Утес'!B39) | C39: =SUM('Астон.Движение'!C39,'Астон.Реформа'!C39,'Дом Милый Дом'!C39,'River Park'!C39,'Астрид'!C39,'Живи в Курортном'!C39,'Новое Колпино'!C39,'Таллинский парк'!C39,'Твоя Привелегия'!C39,'Исеть Парк'!C39,'Космонавтов 11'!C39,'Утес'!C39) | D39: =SUM('Астон.Движение'!D39,'Астон.Реформа'!D39,'Дом Милый Дом'!D39,'River Park'!D39,'Астрид'!D39,'Живи в Курортном'!D39,'Новое Колпино'!D39,'Таллинский парк'!D39,'Твоя Привелегия'!D39,'Исеть Парк'!D39,'Космонавтов 11'!D39,'Утес'!D39) | E39: =SUM('Астон.Движение'!E39,'Астон.Реформа'!E39,'Дом Милый Дом'!E39,'River Park'!E39,'Астрид'!E39,'Живи в Курортном'!E39,'Новое Колпино'!E39,'Таллинский парк'!E39,'Твоя Привелегия'!E39,'Исеть Парк'!E39,'Космонавтов 11'!E39,'Утес'!E39) | F39: =SUM('Астон.Движение'!F39,'Астон.Реформа'!F39,'Дом Милый Дом'!F39,'River Park'!F39,'Астрид'!F39,'Живи в Курортном'!F39,'Новое Колпино'!F39,'Таллинский парк'!F39,'Твоя Привелегия'!F39,'Исеть Парк'!F39,'Космонавтов 11'!F39,'Утес'!F39) | G39: =SUM('Астон.Движение'!G39,'Астон.Реформа'!G39,'Дом Милый Дом'!G39,'River Park'!G39,'Астрид'!G39,'Живи в Курортном'!G39,'Новое Колпино'!G39,'Таллинский парк'!G39,'Твоя Привелегия'!G39,'Исеть Парк'!G39,'Космонавтов 11'!G39,'Утес'!G39) | H39: =SUM('Астон.Движение'!H39,'Астон.Реформа'!H39,'Дом Милый Дом'!H39,'River Park'!H39,'Астрид'!H39,'Живи в Курортном'!H39,'Новое Колпино'!H39,'Таллинский парк'!H39,'Твоя Привелегия'!H39,'Исеть Парк'!H39,'Космонавтов 11'!H39,'Утес'!H39) | I39: =SUM('Астон.Движение'!I39,'Астон.Реформа'!I39,'Дом Милый Дом'!I39,'River Park'!I39,'Астрид'!I39,'Живи в Курортном'!I39,'Новое Колпино'!I39,'Таллинский парк'!I39,'Твоя Привелегия'!I39,'Исеть Парк'!I39,'Космонавтов 11'!I39,'Утес'!I39)
A40: Приобритение мебели, бытовой техники | B40: =SUM('Астон.Движение'!B40,'Астон.Реформа'!B40,'Дом Милый Дом'!B40,'River Park'!B40,'Астрид'!B40,'Живи в Курортном'!B40,'Новое Колпино'!B40,'Таллинский парк'!B40,'Твоя Привелегия'!B40,'Исеть Парк'!B40,'Космонавтов 11'!B40,'Утес'!B40) | C40: =SUM('Астон.Движение'!C40,'Астон.Реформа'!C40,'Дом Милый Дом'!C40,'River Park'!C40,'Астрид'!C40,'Живи в Курортном'!C40,'Новое Колпино'!C40,'Таллинский парк'!C40,'Твоя Привелегия'!C40,'Исеть Парк'!C40,'Космонавтов 11'!C40,'Утес'!C40) | D40: =SUM('Астон.Движение'!D40,'Астон.Реформа'!D40,'Дом Милый Дом'!D40,'River Park'!D40,'Астрид'!D40,'Живи в Курортном'!D40,'Новое Колпино'!D40,'Таллинский парк'!D40,'Твоя Привелегия'!D40,'Исеть Парк'!D40,'Космонавтов 11'!D40,'Утес'!D40) | E40: =SUM('Астон.Движение'!E40,'Астон.Реформа'!E40,'Дом Милый Дом'!E40,'River Park'!E40,'Астрид'!E40,'Живи в Курортном'!E40,'Новое Колпино'!E40,'Таллинский парк'!E40,'Твоя Привелегия'!E40,'Исеть Парк'!E40,'Космонавтов 11'!E40,'Утес'!E40) | F40: =SUM('Астон.Движение'!F40,'Астон.Реформа'!F40,'Дом Милый Дом'!F40,'River Park'!F40,'Астрид'!F40,'Живи в Курортном'!F40,'Новое Колпино'!F40,'Таллинский парк'!F40,'Твоя Привелегия'!F40,'Исеть Парк'!F40,'Космонавтов 11'!F40,'Утес'!F40) | G40: =SUM('Астон.Движение'!G40,'Астон.Реформа'!G40,'Дом Милый Дом'!G40,'River Park'!G40,'Астрид'!G40,'Живи в Курортном'!G40,'Новое Колпино'!G40,'Таллинский парк'!G40,'Твоя Привелегия'!G40,'Исеть Парк'!G40,'Космонавтов 11'!G40,'Утес'!G40) | H40: =SUM('Астон.Движение'!H40,'Астон.Реформа'!H40,'Дом Милый Дом'!H40,'River Park'!H40,'Астрид'!H40,'Живи в Курортном'!H40,'Новое Колпино'!H40,'Таллинский парк'!H40,'Твоя Привелегия'!H40,'Исеть Парк'!H40,'Космонавтов 11'!H40,'Утес'!H40) | I40: =SUM('Астон.Движение'!I40,'Астон.Реформа'!I40,'Дом Милый Дом'!I40,'River Park'!I40,'Астрид'!I40,'Живи в Курортном'!I40,'Новое Колпино'!I40,'Таллинский парк'!I40,'Твоя Привелегия'!I40,'Исеть Парк'!I40,'Космонавтов 11'!I40,'Утес'!I40)
A41: Комиссия за перевод ЗП | B41: =SUM('Астон.Движение'!B41,'Астон.Реформа'!B41,'Дом Милый Дом'!B41,'River Park'!B41,'Астрид'!B41,'Живи в Курортном'!B41,'Новое Колпино'!B41,'Таллинский парк'!B41,'Твоя Привелегия'!B41,'Исеть Парк'!B41,'Космонавтов 11'!B41,'Утес'!B41) | C41: =SUM('Астон.Движение'!C41,'Астон.Реформа'!C41,'Дом Милый Дом'!C41,'River Park'!C41,'Астрид'!C41,'Живи в Курортном'!C41,'Новое Колпино'!C41,'Таллинский парк'!C41,'Твоя Привелегия'!C41,'Исеть Парк'!C41,'Космонавтов 11'!C41,'Утес'!C41) | D41: =SUM('Астон.Движение'!D41,'Астон.Реформа'!D41,'Дом Милый Дом'!D41,'River Park'!D41,'Астрид'!D41,'Живи в Курортном'!D41,'Новое Колпино'!D41,'Таллинский парк'!D41,'Твоя Привелегия'!D41,'Исеть Парк'!D41,'Космонавтов 11'!D41,'Утес'!D41) | E41: =SUM('Астон.Движение'!E41,'Астон.Реформа'!E41,'Дом Милый Дом'!E41,'River Park'!E41,'Астрид'!E41,'Живи в Курортном'!E41,'Новое Колпино'!E41,'Таллинский парк'!E41,'Твоя Привелегия'!E41,'Исеть Парк'!E41,'Космонавтов 11'!E41,'Утес'!E41) | F41: =SUM('Астон.Движение'!F41,'Астон.Реформа'!F41,'Дом Милый Дом'!F41,'River Park'!F41,'Астрид'!F41,'Живи в Курортном'!F41,'Новое Колпино'!F41,'Таллинский парк'!F41,'Твоя Привелегия'!F41,'Исеть Парк'!F41,'Космонавтов 11'!F41,'Утес'!F41) | G41: =SUM('Астон.Движение'!G41,'Астон.Реформа'!G41,'Дом Милый Дом'!G41,'River Park'!G41,'Астрид'!G41,'Живи в Курортном'!G41,'Новое Колпино'!G41,'Таллинский парк'!G41,'Твоя Привелегия'!G41,'Исеть Парк'!G41,'Космонавтов 11'!G41,'Утес'!G41) | H41: =SUM('Астон.Движение'!H41,'Астон.Реформа'!H41,'Дом Милый Дом'!H41,'River Park'!H41,'Астрид'!H41,'Живи в Курортном'!H41,'Новое Колпино'!H41,'Таллинский парк'!H41,'Твоя Привелегия'!H41,'Исеть Парк'!H41,'Космонавтов 11'!H41,'Утес'!H41) | I41: =SUM('Астон.Движение'!I41,'Астон.Реформа'!I41,'Дом Милый Дом'!I41,'River Park'!I41,'Астрид'!I41,'Живи в Курортном'!I41,'Новое Колпино'!I41,'Таллинский парк'!I41,'Твоя Привелегия'!I41,'Исеть Парк'!I41,'Космонавтов 11'!I41,'Утес'!I41)
A42: Аренда квартиры (включая коммуналку) | B42: =SUM('Астон.Движение'!B42,'Астон.Реформа'!B42,'Дом Милый Дом'!B42,'River Park'!B42,'Астрид'!B42,'Живи в Курортном'!B42,'Новое Колпино'!B42,'Таллинский парк'!B42,'Твоя Привелегия'!B42,'Исеть Парк'!B42,'Космонавтов 11'!B42,'Утес'!B42) | C42: =SUM('Астон.Движение'!C42,'Астон.Реформа'!C42,'Дом Милый Дом'!C42,'River Park'!C42,'Астрид'!C42,'Живи в Курортном'!C42,'Новое Колпино'!C42,'Таллинский парк'!C42,'Твоя Привелегия'!C42,'Исеть Парк'!C42,'Космонавтов 11'!C42,'Утес'!C42) | D42: =SUM('Астон.Движение'!D42,'Астон.Реформа'!D42,'Дом Милый Дом'!D42,'River Park'!D42,'Астрид'!D42,'Живи в Курортном'!D42,'Новое Колпино'!D42,'Таллинский парк'!D42,'Твоя Привелегия'!D42,'Исеть Парк'!D42,'Космонавтов 11'!D42,'Утес'!D42) | E42: =SUM('Астон.Движение'!E42,'Астон.Реформа'!E42,'Дом Милый Дом'!E42,'River Park'!E42,'Астрид'!E42,'Живи в Курортном'!E42,'Новое Колпино'!E42,'Таллинский парк'!E42,'Твоя Привелегия'!E42,'Исеть Парк'!E42,'Космонавтов 11'!E42,'Утес'!E42) | F42: =SUM('Астон.Движение'!F42,'Астон.Реформа'!F42,'Дом Милый Дом'!F42,'River Park'!F42,'Астрид'!F42,'Живи в Курортном'!F42,'Новое Колпино'!F42,'Таллинский парк'!F42,'Твоя Привелегия'!F42,'Исеть Парк'!F42,'Космонавтов 11'!F42,'Утес'!F42) | G42: =SUM('Астон.Движение'!G42,'Астон.Реформа'!G42,'Дом Милый Дом'!G42,'River Park'!G42,'Астрид'!G42,'Живи в Курортном'!G42,'Новое Колпино'!G42,'Таллинский парк'!G42,'Твоя Привелегия'!G42,'Исеть Парк'!G42,'Космонавтов 11'!G42,'Утес'!G42) | H42: =SUM('Астон.Движение'!H42,'Астон.Реформа'!H42,'Дом Милый Дом'!H42,'River Park'!H42,'Астрид'!H42,'Живи в Курортном'!H42,'Новое Колпино'!H42,'Таллинский парк'!H42,'Твоя Привелегия'!H42,'Исеть Парк'!H42,'Космонавтов 11'!H42,'Утес'!H42) | I42: =SUM('Астон.Движение'!I42,'Астон.Реформа'!I42,'Дом Милый Дом'!I42,'River Park'!I42,'Астрид'!I42,'Живи в Курортном'!I42,'Новое Колпино'!I42,'Таллинский парк'!I42,'Твоя Привелегия'!I42,'Исеть Парк'!I42,'Космонавтов 11'!I42,'Утес'!I42)
A43: Валовая прибыль | B43: =B4-B10 | C43: =C4-C10 | D43: =D4-D10 | E43: =E4-E10 | F43: =F4-F10 | G43: =G4-G10 | H43: =H4-H10 | I43: =I4-I10
A44: Валовая рентабельность | B44: =IFERROR(IF(B4=0,"-",B43/B4),"-") | C44: =IFERROR(IF(C4=0,"-",C43/C4),"-") | D44: =IFERROR(IF(D4=0,"-",D43/D4),"-") | E44: =IFERROR(IF(E4=0,"-",E43/E4),"-") | F44: =IFERROR(IF(F4=0,"-",F43/F4),"-") | G44: =IFERROR(IF(G4=0,"-",G43/G4),"-") | H44: =IFERROR(IF(H4=0,"-",H43/H4),"-") | I44: =IFERROR(IF(I4=0,"-",I43/I4),"-")
A45: Косвенные расходы | B45: =SUM(B46,B47,B48,B52,B56,B57,B58,B59,B60,B63,B64,B65,B66,B67,B68,B69,B70,B71,B72,B73,B74,B75,B76,B77,B78,B79) | C45: =SUM(C46,C47,C48,C52,C56,C57,C58,C59,C60,C63,C64,C65,C66,C67,C68,C69,C70,C71,C72,C73,C74,C75,C76,C77,C78,C79) | D45: =SUM(D46,D47,D48,D52,D56,D57,D58,D59,D60,D63,D64,D65,D66,D67,D68,D69,D70,D71,D72,D73,D74,D75,D76,D77,D78,D79) | E45: =SUM(E46,E47,E48,E52,E56,E57,E58,E59,E60,E63,E64,E65,E66,E67,E68,E69,E70,E71,E72,E73,E74,E75,E76,E77,E78,E79) | F45: =SUM(F46,F47,F48,F52,F56,F57,F58,F59,F60,F63,F64,F65,F66,F67,F68,F69,F70,F71,F72,F73,F74,F75,F76,F77,F78,F79) | G45: =SUM(G46,G47,G48,G52,G56,G57,G58,G59,G60,G63,G64,G65,G66,G67,G68,G69,G70,G71,G72,G73,G74,G75,G76,G77,G78,G79) | H45: =SUM(H46,H47,H48,H52,H56,H57,H58,H59,H60,H63,H64,H65,H66,H67,H68,H69,H70,H71,H72,H73,H74,H75,H76,H77,H78,H79) | I45: =SUM(I46,I47,I48,I52,I56,I57,I58,I59,I60,I63,I64,I65,I66,I67,I68,I69,I70,I71,I72,I73,I74,I75,I76,I77,I78,I79)
A46: Расход БЭК-ОФИС | B46: =SUM('Астон.Движение'!B46,'Астон.Реформа'!B46,'Дом Милый Дом'!B46,'River Park'!B46,'Астрид'!B46,'Живи в Курортном'!B46,'Новое Колпино'!B46,'Таллинский парк'!B46,'Твоя Привелегия'!B46,'Исеть Парк'!B46,'Космонавтов 11'!B46,'Утес'!B46) | C46: =SUM('Астон.Движение'!C46,'Астон.Реформа'!C46,'Дом Милый Дом'!C46,'River Park'!C46,'Астрид'!C46,'Живи в Курортном'!C46,'Новое Колпино'!C46,'Таллинский парк'!C46,'Твоя Привелегия'!C46,'Исеть Парк'!C46,'Космонавтов 11'!C46,'Утес'!C46) | D46: =SUM('Астон.Движение'!D46,'Астон.Реформа'!D46,'Дом Милый Дом'!D46,'River Park'!D46,'Астрид'!D46,'Живи в Курортном'!D46,'Новое Колпино'!D46,'Таллинский парк'!D46,'Твоя Привелегия'!D46,'Исеть Парк'!D46,'Космонавтов 11'!D46,'Утес'!D46) | E46: =SUM('Астон.Движение'!E46,'Астон.Реформа'!E46,'Дом Милый Дом'!E46,'River Park'!E46,'Астрид'!E46,'Живи в Курортном'!E46,'Новое Колпино'!E46,'Таллинский парк'!E46,'Твоя Привелегия'!E46,'Исеть Парк'!E46,'Космонавтов 11'!E46,'Утес'!E46) | F46: =SUM('Астон.Движение'!F46,'Астон.Реформа'!F46,'Дом Милый Дом'!F46,'River Park'!F46,'Астрид'!F46,'Живи в Курортном'!F46,'Новое Колпино'!F46,'Таллинский парк'!F46,'Твоя Привелегия'!F46,'Исеть Парк'!F46,'Космонавтов 11'!F46,'Утес'!F46) | G46: =SUM('Астон.Движение'!G46,'Астон.Реформа'!G46,'Дом Милый Дом'!G46,'River Park'!G46,'Астрид'!G46,'Живи в Курортном'!G46,'Новое Колпино'!G46,'Таллинский парк'!G46,'Твоя Привелегия'!G46,'Исеть Парк'!G46,'Космонавтов 11'!G46,'Утес'!G46) | H46: =SUM('Астон.Движение'!H46,'Астон.Реформа'!H46,'Дом Милый Дом'!H46,'River Park'!H46,'Астрид'!H46,'Живи в Курортном'!H46,'Новое Колпино'!H46,'Таллинский парк'!H46,'Твоя Привелегия'!H46,'Исеть Парк'!H46,'Космонавтов 11'!H46,'Утес'!H46) | I46: =SUM('Астон.Движение'!I46,'Астон.Реформа'!I46,'Дом Милый Дом'!I46,'River Park'!I46,'Астрид'!I46,'Живи в Курортном'!I46,'Новое Колпино'!I46,'Таллинский парк'!I46,'Твоя Привелегия'!I46,'Исеть Парк'!I46,'Космонавтов 11'!I46,'Утес'!I46)
A47: Расходы на бэк-офис | B47: =SUM('Астон.Движение'!B47,'Астон.Реформа'!B47,'Дом Милый Дом'!B47,'River Park'!B47,'Астрид'!B47,'Живи в Курортном'!B47,'Новое Колпино'!B47,'Таллинский парк'!B47,'Твоя Привелегия'!B47,'Исеть Парк'!B47,'Космонавтов 11'!B47,'Утес'!B47) | C47: =SUM('Астон.Движение'!C47,'Астон.Реформа'!C47,'Дом Милый Дом'!C47,'River Park'!C47,'Астрид'!C47,'Живи в Курортном'!C47,'Новое Колпино'!C47,'Таллинский парк'!C47,'Твоя Привелегия'!C47,'Исеть Парк'!C47,'Космонавтов 11'!C47,'Утес'!C47) | D47: =SUM('Астон.Движение'!D47,'Астон.Реформа'!D47,'Дом Милый Дом'!D47,'River Park'!D47,'Астрид'!D47,'Живи в Курортном'!D47,'Новое Колпино'!D47,'Таллинский парк'!D47,'Твоя Привелегия'!D47,'Исеть Парк'!D47,'Космонавтов 11'!D47,'Утес'!D47) | E47: =SUM('Астон.Движение'!E47,'Астон.Реформа'!E47,'Дом Милый Дом'!E47,'River Park'!E47,'Астрид'!E47,'Живи в Курортном'!E47,'Новое Колпино'!E47,'Таллинский парк'!E47,'Твоя Привелегия'!E47,'Исеть Парк'!E47,'Космонавтов 11'!E47,'Утес'!E47) | F47: =SUM('Астон.Движение'!F47,'Астон.Реформа'!F47,'Дом Милый Дом'!F47,'River Park'!F47,'Астрид'!F47,'Живи в Курортном'!F47,'Новое Колпино'!F47,'Таллинский парк'!F47,'Твоя Привелегия'!F47,'Исеть Парк'!F47,'Космонавтов 11'!F47,'Утес'!F47) | G47: =SUM('Астон.Движение'!G47,'Астон.Реформа'!G47,'Дом Милый Дом'!G47,'River Park'!G47,'Астрид'!G47,'Живи в Курортном'!G47,'Новое Колпино'!G47,'Таллинский парк'!G47,'Твоя Привелегия'!G47,'Исеть Парк'!G47,'Космонавтов 11'!G47,'Утес'!G47) | H47: =SUM('Астон.Движение'!H47,'Астон.Реформа'!H47,'Дом Милый Дом'!H47,'River Park'!H47,'Астрид'!H47,'Живи в Курортном'!H47,'Новое Колпино'!H47,'Таллинский парк'!H47,'Твоя Привелегия'!H47,'Исеть Парк'!H47,'Космонавтов 11'!H47,'Утес'!H47) | I47: =SUM('Астон.Движение'!I47,'Астон.Реформа'!I47,'Дом Милый Дом'!I47,'River Park'!I47,'Астрид'!I47,'Живи в Курортном'!I47,'Новое Колпино'!I47,'Таллинский парк'!I47,'Твоя Привелегия'!I47,'Исеть Парк'!I47,'Космонавтов 11'!I47,'Утес'!I47)
A48: Автомобиль | B48: =SUM(B49,B50,B51) | C48: =SUM(C49,C50,C51) | D48: =SUM(D49,D50,D51) | E48: =SUM(E49,E50,E51) | F48: =SUM(F49,F50,F51) | G48: =SUM(G49,G50,G51) | H48: =SUM(H49,H50,H51) | I48: =SUM(I49,I50,I51)
A49: Автомобиль: ГСМ | B49: =SUM('Астон.Движение'!B49,'Астон.Реформа'!B49,'Дом Милый Дом'!B49,'River Park'!B49,'Астрид'!B49,'Живи в Курортном'!B49,'Новое Колпино'!B49,'Таллинский парк'!B49,'Твоя Привелегия'!B49,'Исеть Парк'!B49,'Космонавтов 11'!B49,'Утес'!B49) | C49: =SUM('Астон.Движение'!C49,'Астон.Реформа'!C49,'Дом Милый Дом'!C49,'River Park'!C49,'Астрид'!C49,'Живи в Курортном'!C49,'Новое Колпино'!C49,'Таллинский парк'!C49,'Твоя Привелегия'!C49,'Исеть Парк'!C49,'Космонавтов 11'!C49,'Утес'!C49) | D49: =SUM('Астон.Движение'!D49,'Астон.Реформа'!D49,'Дом Милый Дом'!D49,'River Park'!D49,'Астрид'!D49,'Живи в Курортном'!D49,'Новое Колпино'!D49,'Таллинский парк'!D49,'Твоя Привелегия'!D49,'Исеть Парк'!D49,'Космонавтов 11'!D49,'Утес'!D49) | E49: =SUM('Астон.Движение'!E49,'Астон.Реформа'!E49,'Дом Милый Дом'!E49,'River Park'!E49,'Астрид'!E49,'Живи в Курортном'!E49,'Новое Колпино'!E49,'Таллинский парк'!E49,'Твоя Привелегия'!E49,'Исеть Парк'!E49,'Космонавтов 11'!E49,'Утес'!E49) | F49: =SUM('Астон.Движение'!F49,'Астон.Реформа'!F49,'Дом Милый Дом'!F49,'River Park'!F49,'Астрид'!F49,'Живи в Курортном'!F49,'Новое Колпино'!F49,'Таллинский парк'!F49,'Твоя Привелегия'!F49,'Исеть Парк'!F49,'Космонавтов 11'!F49,'Утес'!F49) | G49: =SUM('Астон.Движение'!G49,'Астон.Реформа'!G49,'Дом Милый Дом'!G49,'River Park'!G49,'Астрид'!G49,'Живи в Курортном'!G49,'Новое Колпино'!G49,'Таллинский парк'!G49,'Твоя Привелегия'!G49,'Исеть Парк'!G49,'Космонавтов 11'!G49,'Утес'!G49) | H49: =SUM('Астон.Движение'!H49,'Астон.Реформа'!H49,'Дом Милый Дом'!H49,'River Park'!H49,'Астрид'!H49,'Живи в Курортном'!H49,'Новое Колпино'!H49,'Таллинский парк'!H49,'Твоя Привелегия'!H49,'Исеть Парк'!H49,'Космонавтов 11'!H49,'Утес'!H49) | I49: =SUM('Астон.Движение'!I49,'Астон.Реформа'!I49,'Дом Милый Дом'!I49,'River Park'!I49,'Астрид'!I49,'Живи в Курортном'!I49,'Новое Колпино'!I49,'Таллинский парк'!I49,'Твоя Привелегия'!I49,'Исеть Парк'!I49,'Космонавтов 11'!I49,'Утес'!I49)
A50: Автомобиль: страхование | B50: =SUM('Астон.Движение'!B50,'Астон.Реформа'!B50,'Дом Милый Дом'!B50,'River Park'!B50,'Астрид'!B50,'Живи в Курортном'!B50,'Новое Колпино'!B50,'Таллинский парк'!B50,'Твоя Привелегия'!B50,'Исеть Парк'!B50,'Космонавтов 11'!B50,'Утес'!B50) | C50: =SUM('Астон.Движение'!C50,'Астон.Реформа'!C50,'Дом Милый Дом'!C50,'River Park'!C50,'Астрид'!C50,'Живи в Курортном'!C50,'Новое Колпино'!C50,'Таллинский парк'!C50,'Твоя Привелегия'!C50,'Исеть Парк'!C50,'Космонавтов 11'!C50,'Утес'!C50) | D50: =SUM('Астон.Движение'!D50,'Астон.Реформа'!D50,'Дом Милый Дом'!D50,'River Park'!D50,'Астрид'!D50,'Живи в Курортном'!D50,'Новое Колпино'!D50,'Таллинский парк'!D50,'Твоя Привелегия'!D50,'Исеть Парк'!D50,'Космонавтов 11'!D50,'Утес'!D50) | E50: =SUM('Астон.Движение'!E50,'Астон.Реформа'!E50,'Дом Милый Дом'!E50,'River Park'!E50,'Астрид'!E50,'Живи в Курортном'!E50,'Новое Колпино'!E50,'Таллинский парк'!E50,'Твоя Привелегия'!E50,'Исеть Парк'!E50,'Космонавтов 11'!E50,'Утес'!E50) | F50: =SUM('Астон.Движение'!F50,'Астон.Реформа'!F50,'Дом Милый Дом'!F50,'River Park'!F50,'Астрид'!F50,'Живи в Курортном'!F50,'Новое Колпино'!F50,'Таллинский парк'!F50,'Твоя Привелегия'!F50,'Исеть Парк'!F50,'Космонавтов 11'!F50,'Утес'!F50) | G50: =SUM('Астон.Движение'!G50,'Астон.Реформа'!G50,'Дом Милый Дом'!G50,'River Park'!G50,'Астрид'!G50,'Живи в Курортном'!G50,'Новое Колпино'!G50,'Таллинский парк'!G50,'Твоя Привелегия'!G50,'Исеть Парк'!G50,'Космонавтов 11'!G50,'Утес'!G50) | H50: =SUM('Астон.Движение'!H50,'Астон.Реформа'!H50,'Дом Милый Дом'!H50,'River Park'!H50,'Астрид'!H50,'Живи в Курортном'!H50,'Новое Колпино'!H50,'Таллинский парк'!H50,'Твоя Привелегия'!H50,'Исеть Парк'!H50,'Космонавтов 11'!H50,'Утес'!H50) | I50: =SUM('Астон.Движение'!I50,'Астон.Реформа'!I50,'Дом Милый Дом'!I50,'River Park'!I50,'Астрид'!I50,'Живи в Курортном'!I50,'Новое Колпино'!I50,'Таллинский парк'!I50,'Твоя Привелегия'!I50,'Исеть Парк'!I50,'Космонавтов 11'!I50,'Утес'!I50)
A51: Автомобиль: ТО | B51: =SUM('Астон.Движение'!B51,'Астон.Реформа'!B51,'Дом Милый Дом'!B51,'River Park'!B51,'Астрид'!B51,'Живи в Курортном'!B51,'Новое Колпино'!B51,'Таллинский парк'!B51,'Твоя Привелегия'!B51,'Исеть Парк'!B51,'Космонавтов 11'!B51,'Утес'!B51) | C51: =SUM('Астон.Движение'!C51,'Астон.Реформа'!C51,'Дом Милый Дом'!C51,'River Park'!C51,'Астрид'!C51,'Живи в Курортном'!C51,'Новое Колпино'!C51,'Таллинский парк'!C51,'Твоя Привелегия'!C51,'Исеть Парк'!C51,'Космонавтов 11'!C51,'Утес'!C51) | D51: =SUM('Астон.Движение'!D51,'Астон.Реформа'!D51,'Дом Милый Дом'!D51,'River Park'!D51,'Астрид'!D51,'Живи в Курортном'!D51,'Новое Колпино'!D51,'Таллинский парк'!D51,'Твоя Привелегия'!D51,'Исеть Парк'!D51,'Космонавтов 11'!D51,'Утес'!D51) | E51: =SUM('Астон.Движение'!E51,'Астон.Реформа'!E51,'Дом Милый Дом'!E51,'River Park'!E51,'Астрид'!E51,'Живи в Курортном'!E51,'Новое Колпино'!E51,'Таллинский парк'!E51,'Твоя Привелегия'!E51,'Исеть Парк'!E51,'Космонавтов 11'!E51,'Утес'!E51) | F51: =SUM('Астон.Движение'!F51,'Астон.Реформа'!F51,'Дом Милый Дом'!F51,'River Park'!F51,'Астрид'!F51,'Живи в Курортном'!F51,'Новое Колпино'!F51,'Таллинский парк'!F51,'Твоя Привелегия'!F51,'Исеть Парк'!F51,'Космонавтов 11'!F51,'Утес'!F51) | G51: =SUM('Астон.Движение'!G51,'Астон.Реформа'!G51,'Дом Милый Дом'!G51,'River Park'!G51,'Астрид'!G51,'Живи в Курортном'!G51,'Новое Колпино'!G51,'Таллинский парк'!G51,'Твоя Привелегия'!G51,'Исеть Парк'!G51,'Космонавтов 11'!G51,'Утес'!G51) | H51: =SUM('Астон.Движение'!H51,'Астон.Реформа'!H51,'Дом Милый Дом'!H51,'River Park'!H51,'Астрид'!H51,'Живи в Курортном'!H51,'Новое Колпино'!H51,'Таллинский парк'!H51,'Твоя Привелегия'!H51,'Исеть Парк'!H51,'Космонавтов 11'!H51,'Утес'!H51) | I51: =SUM('Астон.Движение'!I51,'Астон.Реформа'!I51,'Дом Милый Дом'!I51,'River Park'!I51,'Астрид'!I51,'Живи в Курортном'!I51,'Новое Колпино'!I51,'Таллинский парк'!I51,'Твоя Привелегия'!I51,'Исеть Парк'!I51,'Космонавтов 11'!I51,'Утес'!I51)
A52: Офисные расходы | B52: =SUM(B53,B54,B55) | C52: =SUM(C53,C54,C55) | D52: =SUM(D53,D54,D55) | E52: =SUM(E53,E54,E55) | F52: =SUM(F53,F54,F55) | G52: =SUM(G53,G54,G55) | H52: =SUM(H53,H54,H55) | I52: =SUM(I53,I54,I55)
A53: Аренда офиса | B53: =SUM('Астон.Движение'!B53,'Астон.Реформа'!B53,'Дом Милый Дом'!B53,'River Park'!B53,'Астрид'!B53,'Живи в Курортном'!B53,'Новое Колпино'!B53,'Таллинский парк'!B53,'Твоя Привелегия'!B53,'Исеть Парк'!B53,'Космонавтов 11'!B53,'Утес'!B53) | C53: =SUM('Астон.Движение'!C53,'Астон.Реформа'!C53,'Дом Милый Дом'!C53,'River Park'!C53,'Астрид'!C53,'Живи в Курортном'!C53,'Новое Колпино'!C53,'Таллинский парк'!C53,'Твоя Привелегия'!C53,'Исеть Парк'!C53,'Космонавтов 11'!C53,'Утес'!C53) | D53: =SUM('Астон.Движение'!D53,'Астон.Реформа'!D53,'Дом Милый Дом'!D53,'River Park'!D53,'Астрид'!D53,'Живи в Курортном'!D53,'Новое Колпино'!D53,'Таллинский парк'!D53,'Твоя Привелегия'!D53,'Исеть Парк'!D53,'Космонавтов 11'!D53,'Утес'!D53) | E53: =SUM('Астон.Движение'!E53,'Астон.Реформа'!E53,'Дом Милый Дом'!E53,'River Park'!E53,'Астрид'!E53,'Живи в Курортном'!E53,'Новое Колпино'!E53,'Таллинский парк'!E53,'Твоя Привелегия'!E53,'Исеть Парк'!E53,'Космонавтов 11'!E53,'Утес'!E53) | F53: =SUM('Астон.Движение'!F53,'Астон.Реформа'!F53,'Дом Милый Дом'!F53,'River Park'!F53,'Астрид'!F53,'Живи в Курортном'!F53,'Новое Колпино'!F53,'Таллинский парк'!F53,'Твоя Привелегия'!F53,'Исеть Парк'!F53,'Космонавтов 11'!F53,'Утес'!F53) | G53: =SUM('Астон.Движение'!G53,'Астон.Реформа'!G53,'Дом Милый Дом'!G53,'River Park'!G53,'Астрид'!G53,'Живи в Курортном'!G53,'Новое Колпино'!G53,'Таллинский парк'!G53,'Твоя Привелегия'!G53,'Исеть Парк'!G53,'Космонавтов 11'!G53,'Утес'!G53) | H53: =SUM('Астон.Движение'!H53,'Астон.Реформа'!H53,'Дом Милый Дом'!H53,'River Park'!H53,'Астрид'!H53,'Живи в Курортном'!H53,'Новое Колпино'!H53,'Таллинский парк'!H53,'Твоя Привелегия'!H53,'Исеть Парк'!H53,'Космонавтов 11'!H53,'Утес'!H53) | I53: =SUM('Астон.Движение'!I53,'Астон.Реформа'!I53,'Дом Милый Дом'!I53,'River Park'!I53,'Астрид'!I53,'Живи в Курортном'!I53,'Новое Колпино'!I53,'Таллинский парк'!I53,'Твоя Привелегия'!I53,'Исеть Парк'!I53,'Космонавтов 11'!I53,'Утес'!I53)
A54: Канцелярия и обслуживание | B54: =SUM('Астон.Движение'!B54,'Астон.Реформа'!B54,'Дом Милый Дом'!B54,'River Park'!B54,'Астрид'!B54,'Живи в Курортном'!B54,'Новое Колпино'!B54,'Таллинский парк'!B54,'Твоя Привелегия'!B54,'Исеть Парк'!B54,'Космонавтов 11'!B54,'Утес'!B54) | C54: =SUM('Астон.Движение'!C54,'Астон.Реформа'!C54,'Дом Милый Дом'!C54,'River Park'!C54,'Астрид'!C54,'Живи в Курортном'!C54,'Новое Колпино'!C54,'Таллинский парк'!C54,'Твоя Привелегия'!C54,'Исеть Парк'!C54,'Космонавтов 11'!C54,'Утес'!C54) | D54: =SUM('Астон.Движение'!D54,'Астон.Реформа'!D54,'Дом Милый Дом'!D54,'River Park'!D54,'Астрид'!D54,'Живи в Курортном'!D54,'Новое Колпино'!D54,'Таллинский парк'!D54,'Твоя Привелегия'!D54,'Исеть Парк'!D54,'Космонавтов 11'!D54,'Утес'!D54) | E54: =SUM('Астон.Движение'!E54,'Астон.Реформа'!E54,'Дом Милый Дом'!E54,'River Park'!E54,'Астрид'!E54,'Живи в Курортном'!E54,'Новое Колпино'!E54,'Таллинский парк'!E54,'Твоя Привелегия'!E54,'Исеть Парк'!E54,'Космонавтов 11'!E54,'Утес'!E54) | F54: =SUM('Астон.Движение'!F54,'Астон.Реформа'!F54,'Дом Милый Дом'!F54,'River Park'!F54,'Астрид'!F54,'Живи в Курортном'!F54,'Новое Колпино'!F54,'Таллинский парк'!F54,'Твоя Привелегия'!F54,'Исеть Парк'!F54,'Космонавтов 11'!F54,'Утес'!F54) | G54: =SUM('Астон.Движение'!G54,'Астон.Реформа'!G54,'Дом Милый Дом'!G54,'River Park'!G54,'Астрид'!G54,'Живи в Курортном'!G54,'Новое Колпино'!G54,'Таллинский парк'!G54,'Твоя Привелегия'!G54,'Исеть Парк'!G54,'Космонавтов 11'!G54,'Утес'!G54) | H54: =SUM('Астон.Движение'!H54,'Астон.Реформа'!H54,'Дом Милый Дом'!H54,'River Park'!H54,'Астрид'!H54,'Живи в Курортном'!H54,'Новое Колпино'!H54,'Таллинский парк'!H54,'Твоя Привелегия'!H54,'Исеть Парк'!H54,'Космонавтов 11'!H54,'Утес'!H54) | I54: =SUM('Астон.Движение'!I54,'Астон.Реформа'!I54,'Дом Милый Дом'!I54,'River Park'!I54,'Астрид'!I54,'Живи в Курортном'!I54,'Новое Колпино'!I54,'Таллинский парк'!I54,'Твоя Привелегия'!I54,'Исеть Парк'!I54,'Космонавтов 11'!I54,'Утес'!I54)
A55: Интернет и связь | B55: =SUM('Астон.Движение'!B55,'Астон.Реформа'!B55,'Дом Милый Дом'!B55,'River Park'!B55,'Астрид'!B55,'Живи в Курортном'!B55,'Новое Колпино'!B55,'Таллинский парк'!B55,'Твоя Привелегия'!B55,'Исеть Парк'!B55,'Космонавтов 11'!B55,'Утес'!B55) | C55: =SUM('Астон.Движение'!C55,'Астон.Реформа'!C55,'Дом Милый Дом'!C55,'River Park'!C55,'Астрид'!C55,'Живи в Курортном'!C55,'Новое Колпино'!C55,'Таллинский парк'!C55,'Твоя Привелегия'!C55,'Исеть Парк'!C55,'Космонавтов 11'!C55,'Утес'!C55) | D55: =SUM('Астон.Движение'!D55,'Астон.Реформа'!D55,'Дом Милый Дом'!D55,'River Park'!D55,'Астрид'!D55,'Живи в Курортном'!D55,'Новое Колпино'!D55,'Таллинский парк'!D55,'Твоя Привелегия'!D55,'Исеть Парк'!D55,'Космонавтов 11'!D55,'Утес'!D55) | E55: =SUM('Астон.Движение'!E55,'Астон.Реформа'!E55,'Дом Милый Дом'!E55,'River Park'!E55,'Астрид'!E55,'Живи в Курортном'!E55,'Новое Колпино'!E55,'Таллинский парк'!E55,'Твоя Привелегия'!E55,'Исеть Парк'!E55,'Космонавтов 11'!E55,'Утес'!E55) | F55: =SUM('Астон.Движение'!F55,'Астон.Реформа'!F55,'Дом Милый Дом'!F55,'River Park'!F55,'Астрид'!F55,'Живи в Курортном'!F55,'Новое Колпино'!F55,'Таллинский парк'!F55,'Твоя Привелегия'!F55,'Исеть Парк'!F55,'Космонавтов 11'!F55,'Утес'!F55) | G55: =SUM('Астон.Движение'!G55,'Астон.Реформа'!G55,'Дом Милый Дом'!G55,'River Park'!G55,'Астрид'!G55,'Живи в Курортном'!G55,'Новое Колпино'!G55,'Таллинский парк'!G55,'Твоя Привелегия'!G55,'Исеть Парк'!G55,'Космонавтов 11'!G55,'Утес'!G55) | H55: =SUM('Астон.Движение'!H55,'Астон.Реформа'!H55,'Дом Милый Дом'!H55,'River Park'!H55,'Астрид'!H55,'Живи в Курортном'!H55,'Новое Колпино'!H55,'Таллинский парк'!H55,'Твоя Привелегия'!H55,'Исеть Парк'!H55,'Космонавтов 11'!H55,'Утес'!H55) | I55: =SUM('Астон.Движение'!I55,'Астон.Реформа'!I55,'Дом Милый Дом'!I55,'River Park'!I55,'Астрид'!I55,'Живи в Курортном'!I55,'Новое Колпино'!I55,'Таллинский парк'!I55,'Твоя Привелегия'!I55,'Исеть Парк'!I55,'Космонавтов 11'!I55,'Утес'!I55)
A56: Банковские услуги | B56: =SUM('Астон.Движение'!B56,'Астон.Реформа'!B56,'Дом Милый Дом'!B56,'River Park'!B56,'Астрид'!B56,'Живи в Курортном'!B56,'Новое Колпино'!B56,'Таллинский парк'!B56,'Твоя Привелегия'!B56,'Исеть Парк'!B56,'Космонавтов 11'!B56,'Утес'!B56) | C56: =SUM('Астон.Движение'!C56,'Астон.Реформа'!C56,'Дом Милый Дом'!C56,'River Park'!C56,'Астрид'!C56,'Живи в Курортном'!C56,'Новое Колпино'!C56,'Таллинский парк'!C56,'Твоя Привелегия'!C56,'Исеть Парк'!C56,'Космонавтов 11'!C56,'Утес'!C56) | D56: =SUM('Астон.Движение'!D56,'Астон.Реформа'!D56,'Дом Милый Дом'!D56,'River Park'!D56,'Астрид'!D56,'Живи в Курортном'!D56,'Новое Колпино'!D56,'Таллинский парк'!D56,'Твоя Привелегия'!D56,'Исеть Парк'!D56,'Космонавтов 11'!D56,'Утес'!D56) | E56: =SUM('Астон.Движение'!E56,'Астон.Реформа'!E56,'Дом Милый Дом'!E56,'River Park'!E56,'Астрид'!E56,'Живи в Курортном'!E56,'Новое Колпино'!E56,'Таллинский парк'!E56,'Твоя Привелегия'!E56,'Исеть Парк'!E56,'Космонавтов 11'!E56,'Утес'!E56) | F56: =SUM('Астон.Движение'!F56,'Астон.Реформа'!F56,'Дом Милый Дом'!F56,'River Park'!F56,'Астрид'!F56,'Живи в Курортном'!F56,'Новое Колпино'!F56,'Таллинский парк'!F56,'Твоя Привелегия'!F56,'Исеть Парк'!F56,'Космонавтов 11'!F56,'Утес'!F56) | G56: =SUM('Астон.Движение'!G56,'Астон.Реформа'!G56,'Дом Милый Дом'!G56,'River Park'!G56,'Астрид'!G56,'Живи в Курортном'!G56,'Новое Колпино'!G56,'Таллинский парк'!G56,'Твоя Привелегия'!G56,'Исеть Парк'!G56,'Космонавтов 11'!G56,'Утес'!G56) | H56: =SUM('Астон.Движение'!H56,'Астон.Реформа'!H56,'Дом Милый Дом'!H56,'River Park'!H56,'Астрид'!H56,'Живи в Курортном'!H56,'Новое Колпино'!H56,'Таллинский парк'!H56,'Твоя Привелегия'!H56,'Исеть Парк'!H56,'Космонавтов 11'!H56,'Утес'!H56) | I56: =SUM('Астон.Движение'!I56,'Астон.Реформа'!I56,'Дом Милый Дом'!I56,'River Park'!I56,'Астрид'!I56,'Живи в Курортном'!I56,'Новое Колпино'!I56,'Таллинский парк'!I56,'Твоя Привелегия'!I56,'Исеть Парк'!I56,'Космонавтов 11'!I56,'Утес'!I56)
A57: Заработная плата АУП (БО) | B57: =SUM('Астон.Движение'!B57,'Астон.Реформа'!B57,'Дом Милый Дом'!B57,'River Park'!B57,'Астрид'!B57,'Живи в Курортном'!B57,'Новое Колпино'!B57,'Таллинский парк'!B57,'Твоя Привелегия'!B57,'Исеть Парк'!B57,'Космонавтов 11'!B57,'Утес'!B57) | C57: =SUM('Астон.Движение'!C57,'Астон.Реформа'!C57,'Дом Милый Дом'!C57,'River Park'!C57,'Астрид'!C57,'Живи в Курортном'!C57,'Новое Колпино'!C57,'Таллинский парк'!C57,'Твоя Привелегия'!C57,'Исеть Парк'!C57,'Космонавтов 11'!C57,'Утес'!C57) | D57: =SUM('Астон.Движение'!D57,'Астон.Реформа'!D57,'Дом Милый Дом'!D57,'River Park'!D57,'Астрид'!D57,'Живи в Курортном'!D57,'Новое Колпино'!D57,'Таллинский парк'!D57,'Твоя Привелегия'!D57,'Исеть Парк'!D57,'Космонавтов 11'!D57,'Утес'!D57) | E57: =SUM('Астон.Движение'!E57,'Астон.Реформа'!E57,'Дом Милый Дом'!E57,'River Park'!E57,'Астрид'!E57,'Живи в Курортном'!E57,'Новое Колпино'!E57,'Таллинский парк'!E57,'Твоя Привелегия'!E57,'Исеть Парк'!E57,'Космонавтов 11'!E57,'Утес'!E57) | F57: =SUM('Астон.Движение'!F57,'Астон.Реформа'!F57,'Дом Милый Дом'!F57,'River Park'!F57,'Астрид'!F57,'Живи в Курортном'!F57,'Новое Колпино'!F57,'Таллинский парк'!F57,'Твоя Привелегия'!F57,'Исеть Парк'!F57,'Космонавтов 11'!F57,'Утес'!F57) | G57: =SUM('Астон.Движение'!G57,'Астон.Реформа'!G57,'Дом Милый Дом'!G57,'River Park'!G57,'Астрид'!G57,'Живи в Курортном'!G57,'Новое Колпино'!G57,'Таллинский парк'!G57,'Твоя Привелегия'!G57,'Исеть Парк'!G57,'Космонавтов 11'!G57,'Утес'!G57) | H57: =SUM('Астон.Движение'!H57,'Астон.Реформа'!H57,'Дом Милый Дом'!H57,'River Park'!H57,'Астрид'!H57,'Живи в Курортном'!H57,'Новое Колпино'!H57,'Таллинский парк'!H57,'Твоя Привелегия'!H57,'Исеть Парк'!H57,'Космонавтов 11'!H57,'Утес'!H57) | I57: =SUM('Астон.Движение'!I57,'Астон.Реформа'!I57,'Дом Милый Дом'!I57,'River Park'!I57,'Астрид'!I57,'Живи в Курортном'!I57,'Новое Колпино'!I57,'Таллинский парк'!I57,'Твоя Привелегия'!I57,'Исеть Парк'!I57,'Космонавтов 11'!I57,'Утес'!I57)
A58: Заработная плата бухгалтерии (БО) | B58: =SUM('Астон.Движение'!B58,'Астон.Реформа'!B58,'Дом Милый Дом'!B58,'River Park'!B58,'Астрид'!B58,'Живи в Курортном'!B58,'Новое Колпино'!B58,'Таллинский парк'!B58,'Твоя Привелегия'!B58,'Исеть Парк'!B58,'Космонавтов 11'!B58,'Утес'!B58) | C58: =SUM('Астон.Движение'!C58,'Астон.Реформа'!C58,'Дом Милый Дом'!C58,'River Park'!C58,'Астрид'!C58,'Живи в Курортном'!C58,'Новое Колпино'!C58,'Таллинский парк'!C58,'Твоя Привелегия'!C58,'Исеть Парк'!C58,'Космонавтов 11'!C58,'Утес'!C58) | D58: =SUM('Астон.Движение'!D58,'Астон.Реформа'!D58,'Дом Милый Дом'!D58,'River Park'!D58,'Астрид'!D58,'Живи в Курортном'!D58,'Новое Колпино'!D58,'Таллинский парк'!D58,'Твоя Привелегия'!D58,'Исеть Парк'!D58,'Космонавтов 11'!D58,'Утес'!D58) | E58: =SUM('Астон.Движение'!E58,'Астон.Реформа'!E58,'Дом Милый Дом'!E58,'River Park'!E58,'Астрид'!E58,'Живи в Курортном'!E58,'Новое Колпино'!E58,'Таллинский парк'!E58,'Твоя Привелегия'!E58,'Исеть Парк'!E58,'Космонавтов 11'!E58,'Утес'!E58) | F58: =SUM('Астон.Движение'!F58,'Астон.Реформа'!F58,'Дом Милый Дом'!F58,'River Park'!F58,'Астрид'!F58,'Живи в Курортном'!F58,'Новое Колпино'!F58,'Таллинский парк'!F58,'Твоя Привелегия'!F58,'Исеть Парк'!F58,'Космонавтов 11'!F58,'Утес'!F58) | G58: =SUM('Астон.Движение'!G58,'Астон.Реформа'!G58,'Дом Милый Дом'!G58,'River Park'!G58,'Астрид'!G58,'Живи в Курортном'!G58,'Новое Колпино'!G58,'Таллинский парк'!G58,'Твоя Привелегия'!G58,'Исеть Парк'!G58,'Космонавтов 11'!G58,'Утес'!G58) | H58: =SUM('Астон.Движение'!H58,'Астон.Реформа'!H58,'Дом Милый Дом'!H58,'River Park'!H58,'Астрид'!H58,'Живи в Курортном'!H58,'Новое Колпино'!H58,'Таллинский парк'!H58,'Твоя Привелегия'!H58,'Исеть Парк'!H58,'Космонавтов 11'!H58,'Утес'!H58) | I58: =SUM('Астон.Движение'!I58,'Астон.Реформа'!I58,'Дом Милый Дом'!I58,'River Park'!I58,'Астрид'!I58,'Живи в Курортном'!I58,'Новое Колпино'!I58,'Таллинский парк'!I58,'Твоя Привелегия'!I58,'Исеть Парк'!I58,'Космонавтов 11'!I58,'Утес'!I58)
A59: Заработная плата СБ (БО) | B59: =SUM('Астон.Движение'!B59,'Астон.Реформа'!B59,'Дом Милый Дом'!B59,'River Park'!B59,'Астрид'!B59,'Живи в Курортном'!B59,'Новое Колпино'!B59,'Таллинский парк'!B59,'Твоя Привелегия'!B59,'Исеть Парк'!B59,'Космонавтов 11'!B59,'Утес'!B59) | C59: =SUM('Астон.Движение'!C59,'Астон.Реформа'!C59,'Дом Милый Дом'!C59,'River Park'!C59,'Астрид'!C59,'Живи в Курортном'!C59,'Новое Колпино'!C59,'Таллинский парк'!C59,'Твоя Привелегия'!C59,'Исеть Парк'!C59,'Космонавтов 11'!C59,'Утес'!C59) | D59: =SUM('Астон.Движение'!D59,'Астон.Реформа'!D59,'Дом Милый Дом'!D59,'River Park'!D59,'Астрид'!D59,'Живи в Курортном'!D59,'Новое Колпино'!D59,'Таллинский парк'!D59,'Твоя Привелегия'!D59,'Исеть Парк'!D59,'Космонавтов 11'!D59,'Утес'!D59) | E59: =SUM('Астон.Движение'!E59,'Астон.Реформа'!E59,'Дом Милый Дом'!E59,'River Park'!E59,'Астрид'!E59,'Живи в Курортном'!E59,'Новое Колпино'!E59,'Таллинский парк'!E59,'Твоя Привелегия'!E59,'Исеть Парк'!E59,'Космонавтов 11'!E59,'Утес'!E59) | F59: =SUM('Астон.Движение'!F59,'Астон.Реформа'!F59,'Дом Милый Дом'!F59,'River Park'!F59,'Астрид'!F59,'Живи в Курортном'!F59,'Новое Колпино'!F59,'Таллинский парк'!F59,'Твоя Привелегия'!F59,'Исеть Парк'!F59,'Космонавтов 11'!F59,'Утес'!F59) | G59: =SUM('Астон.Движение'!G59,'Астон.Реформа'!G59,'Дом Милый Дом'!G59,'River Park'!G59,'Астрид'!G59,'Живи в Курортном'!G59,'Новое Колпино'!G59,'Таллинский парк'!G59,'Твоя Привелегия'!G59,'Исеть Парк'!G59,'Космонавтов 11'!G59,'Утес'!G59) | H59: =SUM('Астон.Движение'!H59,'Астон.Реформа'!H59,'Дом Милый Дом'!H59,'River Park'!H59,'Астрид'!H59,'Живи в Курортном'!H59,'Новое Колпино'!H59,'Таллинский парк'!H59,'Твоя Привелегия'!H59,'Исеть Парк'!H59,'Космонавтов 11'!H59,'Утес'!H59) | I59: =SUM('Астон.Движение'!I59,'Астон.Реформа'!I59,'Дом Милый Дом'!I59,'River Park'!I59,'Астрид'!I59,'Живи в Курортном'!I59,'Новое Колпино'!I59,'Таллинский парк'!I59,'Твоя Привелегия'!I59,'Исеть Парк'!I59,'Космонавтов 11'!I59,'Утес'!I59)
A60: Командировочные расходы | B60: =SUM(B61,B62) | C60: =SUM(C61,C62) | D60: =SUM(D61,D62) | E60: =SUM(E61,E62) | F60: =SUM(F61,F62) | G60: =SUM(G61,G62) | H60: =SUM(H61,H62) | I60: =SUM(I61,I62)
A61: Командировнчеы расходы: билеты (БО) | B61: =SUM('Астон.Движение'!B61,'Астон.Реформа'!B61,'Дом Милый Дом'!B61,'River Park'!B61,'Астрид'!B61,'Живи в Курортном'!B61,'Новое Колпино'!B61,'Таллинский парк'!B61,'Твоя Привелегия'!B61,'Исеть Парк'!B61,'Космонавтов 11'!B61,'Утес'!B61) | C61: =SUM('Астон.Движение'!C61,'Астон.Реформа'!C61,'Дом Милый Дом'!C61,'River Park'!C61,'Астрид'!C61,'Живи в Курортном'!C61,'Новое Колпино'!C61,'Таллинский парк'!C61,'Твоя Привелегия'!C61,'Исеть Парк'!C61,'Космонавтов 11'!C61,'Утес'!C61) | D61: =SUM('Астон.Движение'!D61,'Астон.Реформа'!D61,'Дом Милый Дом'!D61,'River Park'!D61,'Астрид'!D61,'Живи в Курортном'!D61,'Новое Колпино'!D61,'Таллинский парк'!D61,'Твоя Привелегия'!D61,'Исеть Парк'!D61,'Космонавтов 11'!D61,'Утес'!D61) | E61: =SUM('Астон.Движение'!E61,'Астон.Реформа'!E61,'Дом Милый Дом'!E61,'River Park'!E61,'Астрид'!E61,'Живи в Курортном'!E61,'Новое Колпино'!E61,'Таллинский парк'!E61,'Твоя Привелегия'!E61,'Исеть Парк'!E61,'Космонавтов 11'!E61,'Утес'!E61) | F61: =SUM('Астон.Движение'!F61,'Астон.Реформа'!F61,'Дом Милый Дом'!F61,'River Park'!F61,'Астрид'!F61,'Живи в Курортном'!F61,'Новое Колпино'!F61,'Таллинский парк'!F61,'Твоя Привелегия'!F61,'Исеть Парк'!F61,'Космонавтов 11'!F61,'Утес'!F61) | G61: =SUM('Астон.Движение'!G61,'Астон.Реформа'!G61,'Дом Милый Дом'!G61,'River Park'!G61,'Астрид'!G61,'Живи в Курортном'!G61,'Новое Колпино'!G61,'Таллинский парк'!G61,'Твоя Привелегия'!G61,'Исеть Парк'!G61,'Космонавтов 11'!G61,'Утес'!G61) | H61: =SUM('Астон.Движение'!H61,'Астон.Реформа'!H61,'Дом Милый Дом'!H61,'River Park'!H61,'Астрид'!H61,'Живи в Курортном'!H61,'Новое Колпино'!H61,'Таллинский парк'!H61,'Твоя Привелегия'!H61,'Исеть Парк'!H61,'Космонавтов 11'!H61,'Утес'!H61) | I61: =SUM('Астон.Движение'!I61,'Астон.Реформа'!I61,'Дом Милый Дом'!I61,'River Park'!I61,'Астрид'!I61,'Живи в Курортном'!I61,'Новое Колпино'!I61,'Таллинский парк'!I61,'Твоя Привелегия'!I61,'Исеть Парк'!I61,'Космонавтов 11'!I61,'Утес'!I61)
A62: Командировнчеы расходы: проживание (БО) | B62: =SUM('Астон.Движение'!B62,'Астон.Реформа'!B62,'Дом Милый Дом'!B62,'River Park'!B62,'Астрид'!B62,'Живи в Курортном'!B62,'Новое Колпино'!B62,'Таллинский парк'!B62,'Твоя Привелегия'!B62,'Исеть Парк'!B62,'Космонавтов 11'!B62,'Утес'!B62) | C62: =SUM('Астон.Движение'!C62,'Астон.Реформа'!C62,'Дом Милый Дом'!C62,'River Park'!C62,'Астрид'!C62,'Живи в Курортном'!C62,'Новое Колпино'!C62,'Таллинский парк'!C62,'Твоя Привелегия'!C62,'Исеть Парк'!C62,'Космонавтов 11'!C62,'Утес'!C62) | D62: =SUM('Астон.Движение'!D62,'Астон.Реформа'!D62,'Дом Милый Дом'!D62,'River Park'!D62,'Астрид'!D62,'Живи в Курортном'!D62,'Новое Колпино'!D62,'Таллинский парк'!D62,'Твоя Привелегия'!D62,'Исеть Парк'!D62,'Космонавтов 11'!D62,'Утес'!D62) | E62: =SUM('Астон.Движение'!E62,'Астон.Реформа'!E62,'Дом Милый Дом'!E62,'River Park'!E62,'Астрид'!E62,'Живи в Курортном'!E62,'Новое Колпино'!E62,'Таллинский парк'!E62,'Твоя Привелегия'!E62,'Исеть Парк'!E62,'Космонавтов 11'!E62,'Утес'!E62) | F62: =SUM('Астон.Движение'!F62,'Астон.Реформа'!F62,'Дом Милый Дом'!F62,'River Park'!F62,'Астрид'!F62,'Живи в Курортном'!F62,'Новое Колпино'!F62,'Таллинский парк'!F62,'Твоя Привелегия'!F62,'Исеть Парк'!F62,'Космонавтов 11'!F62,'Утес'!F62) | G62: =SUM('Астон.Движение'!G62,'Астон.Реформа'!G62,'Дом Милый Дом'!G62,'River Park'!G62,'Астрид'!G62,'Живи в Курортном'!G62,'Новое Колпино'!G62,'Таллинский парк'!G62,'Твоя Привелегия'!G62,'Исеть Парк'!G62,'Космонавтов 11'!G62,'Утес'!G62) | H62: =SUM('Астон.Движение'!H62,'Астон.Реформа'!H62,'Дом Милый Дом'!H62,'River Park'!H62,'Астрид'!H62,'Живи в Курортном'!H62,'Новое Колпино'!H62,'Таллинский парк'!H62,'Твоя Привелегия'!H62,'Исеть Парк'!H62,'Космонавтов 11'!H62,'Утес'!H62) | I62: =SUM('Астон.Движение'!I62,'Астон.Реформа'!I62,'Дом Милый Дом'!I62,'River Park'!I62,'Астрид'!I62,'Живи в Курортном'!I62,'Новое Колпино'!I62,'Таллинский парк'!I62,'Твоя Привелегия'!I62,'Исеть Парк'!I62,'Космонавтов 11'!I62,'Утес'!I62)
A63: Комиссия УК ДОМ | B63: =SUM('Астон.Движение'!B63,'Астон.Реформа'!B63,'Дом Милый Дом'!B63,'River Park'!B63,'Астрид'!B63,'Живи в Курортном'!B63,'Новое Колпино'!B63,'Таллинский парк'!B63,'Твоя Привелегия'!B63,'Исеть Парк'!B63,'Космонавтов 11'!B63,'Утес'!B63) | C63: =SUM('Астон.Движение'!C63,'Астон.Реформа'!C63,'Дом Милый Дом'!C63,'River Park'!C63,'Астрид'!C63,'Живи в Курортном'!C63,'Новое Колпино'!C63,'Таллинский парк'!C63,'Твоя Привелегия'!C63,'Исеть Парк'!C63,'Космонавтов 11'!C63,'Утес'!C63) | D63: =SUM('Астон.Движение'!D63,'Астон.Реформа'!D63,'Дом Милый Дом'!D63,'River Park'!D63,'Астрид'!D63,'Живи в Курортном'!D63,'Новое Колпино'!D63,'Таллинский парк'!D63,'Твоя Привелегия'!D63,'Исеть Парк'!D63,'Космонавтов 11'!D63,'Утес'!D63) | E63: =SUM('Астон.Движение'!E63,'Астон.Реформа'!E63,'Дом Милый Дом'!E63,'River Park'!E63,'Астрид'!E63,'Живи в Курортном'!E63,'Новое Колпино'!E63,'Таллинский парк'!E63,'Твоя Привелегия'!E63,'Исеть Парк'!E63,'Космонавтов 11'!E63,'Утес'!E63) | F63: =SUM('Астон.Движение'!F63,'Астон.Реформа'!F63,'Дом Милый Дом'!F63,'River Park'!F63,'Астрид'!F63,'Живи в Курортном'!F63,'Новое Колпино'!F63,'Таллинский парк'!F63,'Твоя Привелегия'!F63,'Исеть Парк'!F63,'Космонавтов 11'!F63,'Утес'!F63) | G63: =SUM('Астон.Движение'!G63,'Астон.Реформа'!G63,'Дом Милый Дом'!G63,'River Park'!G63,'Астрид'!G63,'Живи в Курортном'!G63,'Новое Колпино'!G63,'Таллинский парк'!G63,'Твоя Привелегия'!G63,'Исеть Парк'!G63,'Космонавтов 11'!G63,'Утес'!G63) | H63: =SUM('Астон.Движение'!H63,'Астон.Реформа'!H63,'Дом Милый Дом'!H63,'River Park'!H63,'Астрид'!H63,'Живи в Курортном'!H63,'Новое Колпино'!H63,'Таллинский парк'!H63,'Твоя Привелегия'!H63,'Исеть Парк'!H63,'Космонавтов 11'!H63,'Утес'!H63) | I63: =SUM('Астон.Движение'!I63,'Астон.Реформа'!I63,'Дом Милый Дом'!I63,'River Park'!I63,'Астрид'!I63,'Живи в Курортном'!I63,'Новое Колпино'!I63,'Таллинский парк'!I63,'Твоя Привелегия'!I63,'Исеть Парк'!I63,'Космонавтов 11'!I63,'Утес'!I63)
A64: Налоги с ФОТ (ИП)_БО | B64: =SUM('Астон.Движение'!B64,'Астон.Реформа'!B64,'Дом Милый Дом'!B64,'River Park'!B64,'Астрид'!B64,'Живи в Курортном'!B64,'Новое Колпино'!B64,'Таллинский парк'!B64,'Твоя Привелегия'!B64,'Исеть Парк'!B64,'Космонавтов 11'!B64,'Утес'!B64) | C64: =SUM('Астон.Движение'!C64,'Астон.Реформа'!C64,'Дом Милый Дом'!C64,'River Park'!C64,'Астрид'!C64,'Живи в Курортном'!C64,'Новое Колпино'!C64,'Таллинский парк'!C64,'Твоя Привелегия'!C64,'Исеть Парк'!C64,'Космонавтов 11'!C64,'Утес'!C64) | D64: =SUM('Астон.Движение'!D64,'Астон.Реформа'!D64,'Дом Милый Дом'!D64,'River Park'!D64,'Астрид'!D64,'Живи в Курортном'!D64,'Новое Колпино'!D64,'Таллинский парк'!D64,'Твоя Привелегия'!D64,'Исеть Парк'!D64,'Космонавтов 11'!D64,'Утес'!D64) | E64: =SUM('Астон.Движение'!E64,'Астон.Реформа'!E64,'Дом Милый Дом'!E64,'River Park'!E64,'Астрид'!E64,'Живи в Курортном'!E64,'Новое Колпино'!E64,'Таллинский парк'!E64,'Твоя Привелегия'!E64,'Исеть Парк'!E64,'Космонавтов 11'!E64,'Утес'!E64) | F64: =SUM('Астон.Движение'!F64,'Астон.Реформа'!F64,'Дом Милый Дом'!F64,'River Park'!F64,'Астрид'!F64,'Живи в Курортном'!F64,'Новое Колпино'!F64,'Таллинский парк'!F64,'Твоя Привелегия'!F64,'Исеть Парк'!F64,'Космонавтов 11'!F64,'Утес'!F64) | G64: =SUM('Астон.Движение'!G64,'Астон.Реформа'!G64,'Дом Милый Дом'!G64,'River Park'!G64,'Астрид'!G64,'Живи в Курортном'!G64,'Новое Колпино'!G64,'Таллинский парк'!G64,'Твоя Привелегия'!G64,'Исеть Парк'!G64,'Космонавтов 11'!G64,'Утес'!G64) | H64: =SUM('Астон.Движение'!H64,'Астон.Реформа'!H64,'Дом Милый Дом'!H64,'River Park'!H64,'Астрид'!H64,'Живи в Курортном'!H64,'Новое Колпино'!H64,'Таллинский парк'!H64,'Твоя Привелегия'!H64,'Исеть Парк'!H64,'Космонавтов 11'!H64,'Утес'!H64) | I64: =SUM('Астон.Движение'!I64,'Астон.Реформа'!I64,'Дом Милый Дом'!I64,'River Park'!I64,'Астрид'!I64,'Живи в Курортном'!I64,'Новое Колпино'!I64,'Таллинский парк'!I64,'Твоя Привелегия'!I64,'Исеть Парк'!I64,'Космонавтов 11'!I64,'Утес'!I64)
A65: Налоги с ФОТ (НДФЛ) БО | B65: =SUM('Астон.Движение'!B65,'Астон.Реформа'!B65,'Дом Милый Дом'!B65,'River Park'!B65,'Астрид'!B65,'Живи в Курортном'!B65,'Новое Колпино'!B65,'Таллинский парк'!B65,'Твоя Привелегия'!B65,'Исеть Парк'!B65,'Космонавтов 11'!B65,'Утес'!B65) | C65: =SUM('Астон.Движение'!C65,'Астон.Реформа'!C65,'Дом Милый Дом'!C65,'River Park'!C65,'Астрид'!C65,'Живи в Курортном'!C65,'Новое Колпино'!C65,'Таллинский парк'!C65,'Твоя Привелегия'!C65,'Исеть Парк'!C65,'Космонавтов 11'!C65,'Утес'!C65) | D65: =SUM('Астон.Движение'!D65,'Астон.Реформа'!D65,'Дом Милый Дом'!D65,'River Park'!D65,'Астрид'!D65,'Живи в Курортном'!D65,'Новое Колпино'!D65,'Таллинский парк'!D65,'Твоя Привелегия'!D65,'Исеть Парк'!D65,'Космонавтов 11'!D65,'Утес'!D65) | E65: =SUM('Астон.Движение'!E65,'Астон.Реформа'!E65,'Дом Милый Дом'!E65,'River Park'!E65,'Астрид'!E65,'Живи в Курортном'!E65,'Новое Колпино'!E65,'Таллинский парк'!E65,'Твоя Привелегия'!E65,'Исеть Парк'!E65,'Космонавтов 11'!E65,'Утес'!E65) | F65: =SUM('Астон.Движение'!F65,'Астон.Реформа'!F65,'Дом Милый Дом'!F65,'River Park'!F65,'Астрид'!F65,'Живи в Курортном'!F65,'Новое Колпино'!F65,'Таллинский парк'!F65,'Твоя Привелегия'!F65,'Исеть Парк'!F65,'Космонавтов 11'!F65,'Утес'!F65) | G65: =SUM('Астон.Движение'!G65,'Астон.Реформа'!G65,'Дом Милый Дом'!G65,'River Park'!G65,'Астрид'!G65,'Живи в Курортном'!G65,'Новое Колпино'!G65,'Таллинский парк'!G65,'Твоя Привелегия'!G65,'Исеть Парк'!G65,'Космонавтов 11'!G65,'Утес'!G65) | H65: =SUM('Астон.Движение'!H65,'Астон.Реформа'!H65,'Дом Милый Дом'!H65,'River Park'!H65,'Астрид'!H65,'Живи в Курортном'!H65,'Новое Колпино'!H65,'Таллинский парк'!H65,'Твоя Привелегия'!H65,'Исеть Парк'!H65,'Космонавтов 11'!H65,'Утес'!H65) | I65: =SUM('Астон.Движение'!I65,'Астон.Реформа'!I65,'Дом Милый Дом'!I65,'River Park'!I65,'Астрид'!I65,'Живи в Курортном'!I65,'Новое Колпино'!I65,'Таллинский парк'!I65,'Твоя Привелегия'!I65,'Исеть Парк'!I65,'Космонавтов 11'!I65,'Утес'!I65)
A66: Налоги с ФОТ (страховые взносы) БО | B66: =SUM('Астон.Движение'!B66,'Астон.Реформа'!B66,'Дом Милый Дом'!B66,'River Park'!B66,'Астрид'!B66,'Живи в Курортном'!B66,'Новое Колпино'!B66,'Таллинский парк'!B66,'Твоя Привелегия'!B66,'Исеть Парк'!B66,'Космонавтов 11'!B66,'Утес'!B66) | C66: =SUM('Астон.Движение'!C66,'Астон.Реформа'!C66,'Дом Милый Дом'!C66,'River Park'!C66,'Астрид'!C66,'Живи в Курортном'!C66,'Новое Колпино'!C66,'Таллинский парк'!C66,'Твоя Привелегия'!C66,'Исеть Парк'!C66,'Космонавтов 11'!C66,'Утес'!C66) | D66: =SUM('Астон.Движение'!D66,'Астон.Реформа'!D66,'Дом Милый Дом'!D66,'River Park'!D66,'Астрид'!D66,'Живи в Курортном'!D66,'Новое Колпино'!D66,'Таллинский парк'!D66,'Твоя Привелегия'!D66,'Исеть Парк'!D66,'Космонавтов 11'!D66,'Утес'!D66) | E66: =SUM('Астон.Движение'!E66,'Астон.Реформа'!E66,'Дом Милый Дом'!E66,'River Park'!E66,'Астрид'!E66,'Живи в Курортном'!E66,'Новое Колпино'!E66,'Таллинский парк'!E66,'Твоя Привелегия'!E66,'Исеть Парк'!E66,'Космонавтов 11'!E66,'Утес'!E66) | F66: =SUM('Астон.Движение'!F66,'Астон.Реформа'!F66,'Дом Милый Дом'!F66,'River Park'!F66,'Астрид'!F66,'Живи в Курортном'!F66,'Новое Колпино'!F66,'Таллинский парк'!F66,'Твоя Привелегия'!F66,'Исеть Парк'!F66,'Космонавтов 11'!F66,'Утес'!F66) | G66: =SUM('Астон.Движение'!G66,'Астон.Реформа'!G66,'Дом Милый Дом'!G66,'River Park'!G66,'Астрид'!G66,'Живи в Курортном'!G66,'Новое Колпино'!G66,'Таллинский парк'!G66,'Твоя Привелегия'!G66,'Исеть Парк'!G66,'Космонавтов 11'!G66,'Утес'!G66) | H66: =SUM('Астон.Движение'!H66,'Астон.Реформа'!H66,'Дом Милый Дом'!H66,'River Park'!H66,'Астрид'!H66,'Живи в Курортном'!H66,'Новое Колпино'!H66,'Таллинский парк'!H66,'Твоя Привелегия'!H66,'Исеть Парк'!H66,'Космонавтов 11'!H66,'Утес'!H66) | I66: =SUM('Астон.Движение'!I66,'Астон.Реформа'!I66,'Дом Милый Дом'!I66,'River Park'!I66,'Астрид'!I66,'Живи в Курортном'!I66,'Новое Колпино'!I66,'Таллинский парк'!I66,'Твоя Привелегия'!I66,'Исеть Парк'!I66,'Космонавтов 11'!I66,'Утес'!I66)
A67: Нотариальные услуги | B67: =SUM('Астон.Движение'!B67,'Астон.Реформа'!B67,'Дом Милый Дом'!B67,'River Park'!B67,'Астрид'!B67,'Живи в Курортном'!B67,'Новое Колпино'!B67,'Таллинский парк'!B67,'Твоя Привелегия'!B67,'Исеть Парк'!B67,'Космонавтов 11'!B67,'Утес'!B67) | C67: =SUM('Астон.Движение'!C67,'Астон.Реформа'!C67,'Дом Милый Дом'!C67,'River Park'!C67,'Астрид'!C67,'Живи в Курортном'!C67,'Новое Колпино'!C67,'Таллинский парк'!C67,'Твоя Привелегия'!C67,'Исеть Парк'!C67,'Космонавтов 11'!C67,'Утес'!C67) | D67: =SUM('Астон.Движение'!D67,'Астон.Реформа'!D67,'Дом Милый Дом'!D67,'River Park'!D67,'Астрид'!D67,'Живи в Курортном'!D67,'Новое Колпино'!D67,'Таллинский парк'!D67,'Твоя Привелегия'!D67,'Исеть Парк'!D67,'Космонавтов 11'!D67,'Утес'!D67) | E67: =SUM('Астон.Движение'!E67,'Астон.Реформа'!E67,'Дом Милый Дом'!E67,'River Park'!E67,'Астрид'!E67,'Живи в Курортном'!E67,'Новое Колпино'!E67,'Таллинский парк'!E67,'Твоя Привелегия'!E67,'Исеть Парк'!E67,'Космонавтов 11'!E67,'Утес'!E67) | F67: =SUM('Астон.Движение'!F67,'Астон.Реформа'!F67,'Дом Милый Дом'!F67,'River Park'!F67,'Астрид'!F67,'Живи в Курортном'!F67,'Новое Колпино'!F67,'Таллинский парк'!F67,'Твоя Привелегия'!F67,'Исеть Парк'!F67,'Космонавтов 11'!F67,'Утес'!F67) | G67: =SUM('Астон.Движение'!G67,'Астон.Реформа'!G67,'Дом Милый Дом'!G67,'River Park'!G67,'Астрид'!G67,'Живи в Курортном'!G67,'Новое Колпино'!G67,'Таллинский парк'!G67,'Твоя Привелегия'!G67,'Исеть Парк'!G67,'Космонавтов 11'!G67,'Утес'!G67) | H67: =SUM('Астон.Движение'!H67,'Астон.Реформа'!H67,'Дом Милый Дом'!H67,'River Park'!H67,'Астрид'!H67,'Живи в Курортном'!H67,'Новое Колпино'!H67,'Таллинский парк'!H67,'Твоя Привелегия'!H67,'Исеть Парк'!H67,'Космонавтов 11'!H67,'Утес'!H67) | I67: =SUM('Астон.Движение'!I67,'Астон.Реформа'!I67,'Дом Милый Дом'!I67,'River Park'!I67,'Астрид'!I67,'Живи в Курортном'!I67,'Новое Колпино'!I67,'Таллинский парк'!I67,'Твоя Привелегия'!I67,'Исеть Парк'!I67,'Космонавтов 11'!I67,'Утес'!I67)
A68: Обслуживание техники (БО) | B68: =SUM('Астон.Движение'!B68,'Астон.Реформа'!B68,'Дом Милый Дом'!B68,'River Park'!B68,'Астрид'!B68,'Живи в Курортном'!B68,'Новое Колпино'!B68,'Таллинский парк'!B68,'Твоя Привелегия'!B68,'Исеть Парк'!B68,'Космонавтов 11'!B68,'Утес'!B68) | C68: =SUM('Астон.Движение'!C68,'Астон.Реформа'!C68,'Дом Милый Дом'!C68,'River Park'!C68,'Астрид'!C68,'Живи в Курортном'!C68,'Новое Колпино'!C68,'Таллинский парк'!C68,'Твоя Привелегия'!C68,'Исеть Парк'!C68,'Космонавтов 11'!C68,'Утес'!C68) | D68: =SUM('Астон.Движение'!D68,'Астон.Реформа'!D68,'Дом Милый Дом'!D68,'River Park'!D68,'Астрид'!D68,'Живи в Курортном'!D68,'Новое Колпино'!D68,'Таллинский парк'!D68,'Твоя Привелегия'!D68,'Исеть Парк'!D68,'Космонавтов 11'!D68,'Утес'!D68) | E68: =SUM('Астон.Движение'!E68,'Астон.Реформа'!E68,'Дом Милый Дом'!E68,'River Park'!E68,'Астрид'!E68,'Живи в Курортном'!E68,'Новое Колпино'!E68,'Таллинский парк'!E68,'Твоя Привелегия'!E68,'Исеть Парк'!E68,'Космонавтов 11'!E68,'Утес'!E68) | F68: =SUM('Астон.Движение'!F68,'Астон.Реформа'!F68,'Дом Милый Дом'!F68,'River Park'!F68,'Астрид'!F68,'Живи в Курортном'!F68,'Новое Колпино'!F68,'Таллинский парк'!F68,'Твоя Привелегия'!F68,'Исеть Парк'!F68,'Космонавтов 11'!F68,'Утес'!F68) | G68: =SUM('Астон.Движение'!G68,'Астон.Реформа'!G68,'Дом Милый Дом'!G68,'River Park'!G68,'Астрид'!G68,'Живи в Курортном'!G68,'Новое Колпино'!G68,'Таллинский парк'!G68,'Твоя Привелегия'!G68,'Исеть Парк'!G68,'Космонавтов 11'!G68,'Утес'!G68) | H68: =SUM('Астон.Движение'!H68,'Астон.Реформа'!H68,'Дом Милый Дом'!H68,'River Park'!H68,'Астрид'!H68,'Живи в Курортном'!H68,'Новое Колпино'!H68,'Таллинский парк'!H68,'Твоя Привелегия'!H68,'Исеть Парк'!H68,'Космонавтов 11'!H68,'Утес'!H68) | I68: =SUM('Астон.Движение'!I68,'Астон.Реформа'!I68,'Дом Милый Дом'!I68,'River Park'!I68,'Астрид'!I68,'Живи в Курортном'!I68,'Новое Колпино'!I68,'Таллинский парк'!I68,'Твоя Привелегия'!I68,'Исеть Парк'!I68,'Космонавтов 11'!I68,'Утес'!I68)
A69: Программное обеспечение (БО) | B69: =SUM('Астон.Движение'!B69,'Астон.Реформа'!B69,'Дом Милый Дом'!B69,'River Park'!B69,'Астрид'!B69,'Живи в Курортном'!B69,'Новое Колпино'!B69,'Таллинский парк'!B69,'Твоя Привелегия'!B69,'Исеть Парк'!B69,'Космонавтов 11'!B69,'Утес'!B69) | C69: =SUM('Астон.Движение'!C69,'Астон.Реформа'!C69,'Дом Милый Дом'!C69,'River Park'!C69,'Астрид'!C69,'Живи в Курортном'!C69,'Новое Колпино'!C69,'Таллинский парк'!C69,'Твоя Привелегия'!C69,'Исеть Парк'!C69,'Космонавтов 11'!C69,'Утес'!C69) | D69: =SUM('Астон.Движение'!D69,'Астон.Реформа'!D69,'Дом Милый Дом'!D69,'River Park'!D69,'Астрид'!D69,'Живи в Курортном'!D69,'Новое Колпино'!D69,'Таллинский парк'!D69,'Твоя Привелегия'!D69,'Исеть Парк'!D69,'Космонавтов 11'!D69,'Утес'!D69) | E69: =SUM('Астон.Движение'!E69,'Астон.Реформа'!E69,'Дом Милый Дом'!E69,'River Park'!E69,'Астрид'!E69,'Живи в Курортном'!E69,'Новое Колпино'!E69,'Таллинский парк'!E69,'Твоя Привелегия'!E69,'Исеть Парк'!E69,'Космонавтов 11'!E69,'Утес'!E69) | F69: =SUM('Астон.Движение'!F69,'Астон.Реформа'!F69,'Дом Милый Дом'!F69,'River Park'!F69,'Астрид'!F69,'Живи в Курортном'!F69,'Новое Колпино'!F69,'Таллинский парк'!F69,'Твоя Привелегия'!F69,'Исеть Парк'!F69,'Космонавтов 11'!F69,'Утес'!F69) | G69: =SUM('Астон.Движение'!G69,'Астон.Реформа'!G69,'Дом Милый Дом'!G69,'River Park'!G69,'Астрид'!G69,'Живи в Курортном'!G69,'Новое Колпино'!G69,'Таллинский парк'!G69,'Твоя Привелегия'!G69,'Исеть Парк'!G69,'Космонавтов 11'!G69,'Утес'!G69) | H69: =SUM('Астон.Движение'!H69,'Астон.Реформа'!H69,'Дом Милый Дом'!H69,'River Park'!H69,'Астрид'!H69,'Живи в Курортном'!H69,'Новое Колпино'!H69,'Таллинский парк'!H69,'Твоя Привелегия'!H69,'Исеть Парк'!H69,'Космонавтов 11'!H69,'Утес'!H69) | I69: =SUM('Астон.Движение'!I69,'Астон.Реформа'!I69,'Дом Милый Дом'!I69,'River Park'!I69,'Астрид'!I69,'Живи в Курортном'!I69,'Новое Колпино'!I69,'Таллинский парк'!I69,'Твоя Привелегия'!I69,'Исеть Парк'!I69,'Космонавтов 11'!I69,'Утес'!I69)
A70: ПланФакт | B70: =SUM('Астон.Движение'!B70,'Астон.Реформа'!B70,'Дом Милый Дом'!B70,'River Park'!B70,'Астрид'!B70,'Живи в Курортном'!B70,'Новое Колпино'!B70,'Таллинский парк'!B70,'Твоя Привелегия'!B70,'Исеть Парк'!B70,'Космонавтов 11'!B70,'Утес'!B70) | C70: =SUM('Астон.Движение'!C70,'Астон.Реформа'!C70,'Дом Милый Дом'!C70,'River Park'!C70,'Астрид'!C70,'Живи в Курортном'!C70,'Новое Колпино'!C70,'Таллинский парк'!C70,'Твоя Привелегия'!C70,'Исеть Парк'!C70,'Космонавтов 11'!C70,'Утес'!C70) | D70: =SUM('Астон.Движение'!D70,'Астон.Реформа'!D70,'Дом Милый Дом'!D70,'River Park'!D70,'Астрид'!D70,'Живи в Курортном'!D70,'Новое Колпино'!D70,'Таллинский парк'!D70,'Твоя Привелегия'!D70,'Исеть Парк'!D70,'Космонавтов 11'!D70,'Утес'!D70) | E70: =SUM('Астон.Движение'!E70,'Астон.Реформа'!E70,'Дом Милый Дом'!E70,'River Park'!E70,'Астрид'!E70,'Живи в Курортном'!E70,'Новое Колпино'!E70,'Таллинский парк'!E70,'Твоя Привелегия'!E70,'Исеть Парк'!E70,'Космонавтов 11'!E70,'Утес'!E70) | F70: =SUM('Астон.Движение'!F70,'Астон.Реформа'!F70,'Дом Милый Дом'!F70,'River Park'!F70,'Астрид'!F70,'Живи в Курортном'!F70,'Новое Колпино'!F70,'Таллинский парк'!F70,'Твоя Привелегия'!F70,'Исеть Парк'!F70,'Космонавтов 11'!F70,'Утес'!F70) | G70: =SUM('Астон.Движение'!G70,'Астон.Реформа'!G70,'Дом Милый Дом'!G70,'River Park'!G70,'Астрид'!G70,'Живи в Курортном'!G70,'Новое Колпино'!G70,'Таллинский парк'!G70,'Твоя Привелегия'!G70,'Исеть Парк'!G70,'Космонавтов 11'!G70,'Утес'!G70) | H70: =SUM('Астон.Движение'!H70,'Астон.Реформа'!H70,'Дом Милый Дом'!H70,'River Park'!H70,'Астрид'!H70,'Живи в Курортном'!H70,'Новое Колпино'!H70,'Таллинский парк'!H70,'Твоя Привелегия'!H70,'Исеть Парк'!H70,'Космонавтов 11'!H70,'Утес'!H70) | I70: =SUM('Астон.Движение'!I70,'Астон.Реформа'!I70,'Дом Милый Дом'!I70,'River Park'!I70,'Астрид'!I70,'Живи в Курортном'!I70,'Новое Колпино'!I70,'Таллинский парк'!I70,'Твоя Привелегия'!I70,'Исеть Парк'!I70,'Космонавтов 11'!I70,'Утес'!I70)
A71: ТБ | B71: =SUM('Астон.Движение'!B71,'Астон.Реформа'!B71,'Дом Милый Дом'!B71,'River Park'!B71,'Астрид'!B71,'Живи в Курортном'!B71,'Новое Колпино'!B71,'Таллинский парк'!B71,'Твоя Привелегия'!B71,'Исеть Парк'!B71,'Космонавтов 11'!B71,'Утес'!B71) | C71: =SUM('Астон.Движение'!C71,'Астон.Реформа'!C71,'Дом Милый Дом'!C71,'River Park'!C71,'Астрид'!C71,'Живи в Курортном'!C71,'Новое Колпино'!C71,'Таллинский парк'!C71,'Твоя Привелегия'!C71,'Исеть Парк'!C71,'Космонавтов 11'!C71,'Утес'!C71) | D71: =SUM('Астон.Движение'!D71,'Астон.Реформа'!D71,'Дом Милый Дом'!D71,'River Park'!D71,'Астрид'!D71,'Живи в Курортном'!D71,'Новое Колпино'!D71,'Таллинский парк'!D71,'Твоя Привелегия'!D71,'Исеть Парк'!D71,'Космонавтов 11'!D71,'Утес'!D71) | E71: =SUM('Астон.Движение'!E71,'Астон.Реформа'!E71,'Дом Милый Дом'!E71,'River Park'!E71,'Астрид'!E71,'Живи в Курортном'!E71,'Новое Колпино'!E71,'Таллинский парк'!E71,'Твоя Привелегия'!E71,'Исеть Парк'!E71,'Космонавтов 11'!E71,'Утес'!E71) | F71: =SUM('Астон.Движение'!F71,'Астон.Реформа'!F71,'Дом Милый Дом'!F71,'River Park'!F71,'Астрид'!F71,'Живи в Курортном'!F71,'Новое Колпино'!F71,'Таллинский парк'!F71,'Твоя Привелегия'!F71,'Исеть Парк'!F71,'Космонавтов 11'!F71,'Утес'!F71) | G71: =SUM('Астон.Движение'!G71,'Астон.Реформа'!G71,'Дом Милый Дом'!G71,'River Park'!G71,'Астрид'!G71,'Живи в Курортном'!G71,'Новое Колпино'!G71,'Таллинский парк'!G71,'Твоя Привелегия'!G71,'Исеть Парк'!G71,'Космонавтов 11'!G71,'Утес'!G71) | H71: =SUM('Астон.Движение'!H71,'Астон.Реформа'!H71,'Дом Милый Дом'!H71,'River Park'!H71,'Астрид'!H71,'Живи в Курортном'!H71,'Новое Колпино'!H71,'Таллинский парк'!H71,'Твоя Привелегия'!H71,'Исеть Парк'!H71,'Космонавтов 11'!H71,'Утес'!H71) | I71: =SUM('Астон.Движение'!I71,'Астон.Реформа'!I71,'Дом Милый Дом'!I71,'River Park'!I71,'Астрид'!I71,'Живи в Курортном'!I71,'Новое Колпино'!I71,'Таллинский парк'!I71,'Твоя Привелегия'!I71,'Исеть Парк'!I71,'Космонавтов 11'!I71,'Утес'!I71)
A72: Контур | B72: =SUM('Астон.Движение'!B72,'Астон.Реформа'!B72,'Дом Милый Дом'!B72,'River Park'!B72,'Астрид'!B72,'Живи в Курортном'!B72,'Новое Колпино'!B72,'Таллинский парк'!B72,'Твоя Привелегия'!B72,'Исеть Парк'!B72,'Космонавтов 11'!B72,'Утес'!B72) | C72: =SUM('Астон.Движение'!C72,'Астон.Реформа'!C72,'Дом Милый Дом'!C72,'River Park'!C72,'Астрид'!C72,'Живи в Курортном'!C72,'Новое Колпино'!C72,'Таллинский парк'!C72,'Твоя Привелегия'!C72,'Исеть Парк'!C72,'Космонавтов 11'!C72,'Утес'!C72) | D72: =SUM('Астон.Движение'!D72,'Астон.Реформа'!D72,'Дом Милый Дом'!D72,'River Park'!D72,'Астрид'!D72,'Живи в Курортном'!D72,'Новое Колпино'!D72,'Таллинский парк'!D72,'Твоя Привелегия'!D72,'Исеть Парк'!D72,'Космонавтов 11'!D72,'Утес'!D72) | E72: =SUM('Астон.Движение'!E72,'Астон.Реформа'!E72,'Дом Милый Дом'!E72,'River Park'!E72,'Астрид'!E72,'Живи в Курортном'!E72,'Новое Колпино'!E72,'Таллинский парк'!E72,'Твоя Привелегия'!E72,'Исеть Парк'!E72,'Космонавтов 11'!E72,'Утес'!E72) | F72: =SUM('Астон.Движение'!F72,'Астон.Реформа'!F72,'Дом Милый Дом'!F72,'River Park'!F72,'Астрид'!F72,'Живи в Курортном'!F72,'Новое Колпино'!F72,'Таллинский парк'!F72,'Твоя Привелегия'!F72,'Исеть Парк'!F72,'Космонавтов 11'!F72,'Утес'!F72) | G72: =SUM('Астон.Движение'!G72,'Астон.Реформа'!G72,'Дом Милый Дом'!G72,'River Park'!G72,'Астрид'!G72,'Живи в Курортном'!G72,'Новое Колпино'!G72,'Таллинский парк'!G72,'Твоя Привелегия'!G72,'Исеть Парк'!G72,'Космонавтов 11'!G72,'Утес'!G72) | H72: =SUM('Астон.Движение'!H72,'Астон.Реформа'!H72,'Дом Милый Дом'!H72,'River Park'!H72,'Астрид'!H72,'Живи в Курортном'!H72,'Новое Колпино'!H72,'Таллинский парк'!H72,'Твоя Привелегия'!H72,'Исеть Парк'!H72,'Космонавтов 11'!H72,'Утес'!H72) | I72: =SUM('Астон.Движение'!I72,'Астон.Реформа'!I72,'Дом Милый Дом'!I72,'River Park'!I72,'Астрид'!I72,'Живи в Курортном'!I72,'Новое Колпино'!I72,'Таллинский парк'!I72,'Твоя Привелегия'!I72,'Исеть Парк'!I72,'Космонавтов 11'!I72,'Утес'!I72)
... A79: HR (аутсорс) | B79: =SUM('Астон.Движение'!B79,'Астон.Реформа'!B79,'Дом Милый Дом'!B79,'River Park'!B79,'Астрид'!B79,'Живи в Курортном'!B79,'Новое Колпино'!B79,'Таллинский парк'!B79,'Твоя Привелегия'!B79,'Исеть Парк'!B79,'Космонавтов 11'!B79,'Утес'!B79) | C79: =SUM('Астон.Движение'!C79,'Астон.Реформа'!C79,'Дом Милый Дом'!C79,'River Park'!C79,'Астрид'!C79,'Живи в Курортном'!C79,'Новое Колпино'!C79,'Таллинский парк'!C79,'Твоя Привелегия'!C79,'Исеть Парк'!C79,'Космонавтов 11'!C79,'Утес'!C79) | D79: =SUM('Астон.Движение'!D79,'Астон.Реформа'!D79,'Дом Милый Дом'!D79,'River Park'!D79,'Астрид'!D79,'Живи в Курортном'!D79,'Новое Колпино'!D79,'Таллинский парк'!D79,'Твоя Привелегия'!D79,'Исеть Парк'!D79,'Космонавтов 11'!D79,'Утес'!D79) | E79: =SUM('Астон.Движение'!E79,'Астон.Реформа'!E79,'Дом Милый Дом'!E79,'River Park'!E79,'Астрид'!E79,'Живи в Курортном'!E79,'Новое Колпино'!E79,'Таллинский парк'!E79,'Твоя Привелегия'!E79,'Исеть Парк'!E79,'Космонавтов 11'!E79,'Утес'!E79) | F79: =SUM('Астон.Движение'!F79,'Астон.Реформа'!F79,'Дом Милый Дом'!F79,'River Park'!F79,'Астрид'!F79,'Живи в Курортном'!F79,'Новое Колпино'!F79,'Таллинский парк'!F79,'Твоя Привелегия'!F79,'Исеть Парк'!F79,'Космонавтов 11'!F79,'Утес'!F79) | G79: =SUM('Астон.Движение'!G79,'Астон.Реформа'!G79,'Дом Милый Дом'!G79,'River Park'!G79,'Астрид'!G79,'Живи в Курортном'!G79,'Новое Колпино'!G79,'Таллинский парк'!G79,'Твоя Привелегия'!G79,'Исеть Парк'!G79,'Космонавтов 11'!G79,'Утес'!G79) | H79: =SUM('Астон.Движение'!H79,'Астон.Реформа'!H79,'Дом Милый Дом'!H79,'River Park'!H79,'Астрид'!H79,'Живи в Курортном'!H79,'Новое Колпино'!H79,'Таллинский парк'!H79,'Твоя Привелегия'!H79,'Исеть Парк'!H79,'Космонавтов 11'!H79,'Утес'!H79) | I79: =SUM('Астон.Движение'!I79,'Астон.Реформа'!I79,'Дом Милый Дом'!I79,'River Park'!I79,'Астрид'!I79,'Живи в Курортном'!I79,'Новое Колпино'!I79,'Таллинский парк'!I79,'Твоя Привелегия'!I79,'Исеть Парк'!I79,'Космонавтов 11'!I79,'Утес'!I79)
A80: Операционная прибыль | B80: =B43-B45 | C80: =C43-C45 | D80: =D43-D45 | E80: =E43-E45 | F80: =F43-F45 | G80: =G43-G45 | H80: =H43-H45 | I80: =I43-I45
A81: Операционная рентабельность | B81: =IFERROR(IF(B4=0,"-",B80/B4),"-") | C81: =IFERROR(IF(C4=0,"-",C80/C4),"-") | D81: =IFERROR(IF(D4=0,"-",D80/D4),"-") | E81: =IFERROR(IF(E4=0,"-",E80/E4),"-") | F81: =IFERROR(IF(F4=0,"-",F80/F4),"-") | G81: =IFERROR(IF(G4=0,"-",G80/G4),"-") | H81: =IFERROR(IF(H4=0,"-",H80/H4),"-") | I81: =IFERROR(IF(I4=0,"-",I80/I4),"-")
A82: Прочие доходы | B82: =SUM(B83,B84,B85,B86) | C82: =SUM(C83,C84,C85,C86) | D82: =SUM(D83,D84,D85,D86) | E82: =SUM(E83,E84,E85,E86) | F82: =SUM(F83,F84,F85,F86) | G82: =SUM(G83,G84,G85,G86) | H82: =SUM(H83,H84,H85,H86) | I82: =SUM(I83,I84,I85,I86)
A83: Доход БЭК-ОФИС | B83: =SUM('Астон.Движение'!B83,'Астон.Реформа'!B83,'Дом Милый Дом'!B83,'River Park'!B83,'Астрид'!B83,'Живи в Курортном'!B83,'Новое Колпино'!B83,'Таллинский парк'!B83,'Твоя Привелегия'!B83,'Исеть Парк'!B83,'Космонавтов 11'!B83,'Утес'!B83) | C83: =SUM('Астон.Движение'!C83,'Астон.Реформа'!C83,'Дом Милый Дом'!C83,'River Park'!C83,'Астрид'!C83,'Живи в Курортном'!C83,'Новое Колпино'!C83,'Таллинский парк'!C83,'Твоя Привелегия'!C83,'Исеть Парк'!C83,'Космонавтов 11'!C83,'Утес'!C83) | D83: =SUM('Астон.Движение'!D83,'Астон.Реформа'!D83,'Дом Милый Дом'!D83,'River Park'!D83,'Астрид'!D83,'Живи в Курортном'!D83,'Новое Колпино'!D83,'Таллинский парк'!D83,'Твоя Привелегия'!D83,'Исеть Парк'!D83,'Космонавтов 11'!D83,'Утес'!D83) | E83: =SUM('Астон.Движение'!E83,'Астон.Реформа'!E83,'Дом Милый Дом'!E83,'River Park'!E83,'Астрид'!E83,'Живи в Курортном'!E83,'Новое Колпино'!E83,'Таллинский парк'!E83,'Твоя Привелегия'!E83,'Исеть Парк'!E83,'Космонавтов 11'!E83,'Утес'!E83) | F83: =SUM('Астон.Движение'!F83,'Астон.Реформа'!F83,'Дом Милый Дом'!F83,'River Park'!F83,'Астрид'!F83,'Живи в Курортном'!F83,'Новое Колпино'!F83,'Таллинский парк'!F83,'Твоя Привелегия'!F83,'Исеть Парк'!F83,'Космонавтов 11'!F83,'Утес'!F83) | G83: =SUM('Астон.Движение'!G83,'Астон.Реформа'!G83,'Дом Милый Дом'!G83,'River Park'!G83,'Астрид'!G83,'Живи в Курортном'!G83,'Новое Колпино'!G83,'Таллинский парк'!G83,'Твоя Привелегия'!G83,'Исеть Парк'!G83,'Космонавтов 11'!G83,'Утес'!G83) | H83: =SUM('Астон.Движение'!H83,'Астон.Реформа'!H83,'Дом Милый Дом'!H83,'River Park'!H83,'Астрид'!H83,'Живи в Курортном'!H83,'Новое Колпино'!H83,'Таллинский парк'!H83,'Твоя Привелегия'!H83,'Исеть Парк'!H83,'Космонавтов 11'!H83,'Утес'!H83) | I83: =SUM('Астон.Движение'!I83,'Астон.Реформа'!I83,'Дом Милый Дом'!I83,'River Park'!I83,'Астрид'!I83,'Живи в Курортном'!I83,'Новое Колпино'!I83,'Таллинский парк'!I83,'Твоя Привелегия'!I83,'Исеть Парк'!I83,'Космонавтов 11'!I83,'Утес'!I83)
A84: Пополненин бэк-офис | B84: =SUM('Астон.Движение'!B84,'Астон.Реформа'!B84,'Дом Милый Дом'!B84,'River Park'!B84,'Астрид'!B84,'Живи в Курортном'!B84,'Новое Колпино'!B84,'Таллинский парк'!B84,'Твоя Привелегия'!B84,'Исеть Парк'!B84,'Космонавтов 11'!B84,'Утес'!B84) | C84: =SUM('Астон.Движение'!C84,'Астон.Реформа'!C84,'Дом Милый Дом'!C84,'River Park'!C84,'Астрид'!C84,'Живи в Курортном'!C84,'Новое Колпино'!C84,'Таллинский парк'!C84,'Твоя Привелегия'!C84,'Исеть Парк'!C84,'Космонавтов 11'!C84,'Утес'!C84) | D84: =SUM('Астон.Движение'!D84,'Астон.Реформа'!D84,'Дом Милый Дом'!D84,'River Park'!D84,'Астрид'!D84,'Живи в Курортном'!D84,'Новое Колпино'!D84,'Таллинский парк'!D84,'Твоя Привелегия'!D84,'Исеть Парк'!D84,'Космонавтов 11'!D84,'Утес'!D84) | E84: =SUM('Астон.Движение'!E84,'Астон.Реформа'!E84,'Дом Милый Дом'!E84,'River Park'!E84,'Астрид'!E84,'Живи в Курортном'!E84,'Новое Колпино'!E84,'Таллинский парк'!E84,'Твоя Привелегия'!E84,'Исеть Парк'!E84,'Космонавтов 11'!E84,'Утес'!E84) | F84: =SUM('Астон.Движение'!F84,'Астон.Реформа'!F84,'Дом Милый Дом'!F84,'River Park'!F84,'Астрид'!F84,'Живи в Курортном'!F84,'Новое Колпино'!F84,'Таллинский парк'!F84,'Твоя Привелегия'!F84,'Исеть Парк'!F84,'Космонавтов 11'!F84,'Утес'!F84) | G84: =SUM('Астон.Движение'!G84,'Астон.Реформа'!G84,'Дом Милый Дом'!G84,'River Park'!G84,'Астрид'!G84,'Живи в Курортном'!G84,'Новое Колпино'!G84,'Таллинский парк'!G84,'Твоя Привелегия'!G84,'Исеть Парк'!G84,'Космонавтов 11'!G84,'Утес'!G84) | H84: =SUM('Астон.Движение'!H84,'Астон.Реформа'!H84,'Дом Милый Дом'!H84,'River Park'!H84,'Астрид'!H84,'Живи в Курортном'!H84,'Новое Колпино'!H84,'Таллинский парк'!H84,'Твоя Привелегия'!H84,'Исеть Парк'!H84,'Космонавтов 11'!H84,'Утес'!H84) | I84: =SUM('Астон.Движение'!I84,'Астон.Реформа'!I84,'Дом Милый Дом'!I84,'River Park'!I84,'Астрид'!I84,'Живи в Курортном'!I84,'Новое Колпино'!I84,'Таллинский парк'!I84,'Твоя Привелегия'!I84,'Исеть Парк'!I84,'Космонавтов 11'!I84,'Утес'!I84)
A85: Проценты по вкладам | B85: =SUM('Астон.Движение'!B85,'Астон.Реформа'!B85,'Дом Милый Дом'!B85,'River Park'!B85,'Астрид'!B85,'Живи в Курортном'!B85,'Новое Колпино'!B85,'Таллинский парк'!B85,'Твоя Привелегия'!B85,'Исеть Парк'!B85,'Космонавтов 11'!B85,'Утес'!B85) | C85: =SUM('Астон.Движение'!C85,'Астон.Реформа'!C85,'Дом Милый Дом'!C85,'River Park'!C85,'Астрид'!C85,'Живи в Курортном'!C85,'Новое Колпино'!C85,'Таллинский парк'!C85,'Твоя Привелегия'!C85,'Исеть Парк'!C85,'Космонавтов 11'!C85,'Утес'!C85) | D85: =SUM('Астон.Движение'!D85,'Астон.Реформа'!D85,'Дом Милый Дом'!D85,'River Park'!D85,'Астрид'!D85,'Живи в Курортном'!D85,'Новое Колпино'!D85,'Таллинский парк'!D85,'Твоя Привелегия'!D85,'Исеть Парк'!D85,'Космонавтов 11'!D85,'Утес'!D85) | E85: =SUM('Астон.Движение'!E85,'Астон.Реформа'!E85,'Дом Милый Дом'!E85,'River Park'!E85,'Астрид'!E85,'Живи в Курортном'!E85,'Новое Колпино'!E85,'Таллинский парк'!E85,'Твоя Привелегия'!E85,'Исеть Парк'!E85,'Космонавтов 11'!E85,'Утес'!E85) | F85: =SUM('Астон.Движение'!F85,'Астон.Реформа'!F85,'Дом Милый Дом'!F85,'River Park'!F85,'Астрид'!F85,'Живи в Курортном'!F85,'Новое Колпино'!F85,'Таллинский парк'!F85,'Твоя Привелегия'!F85,'Исеть Парк'!F85,'Космонавтов 11'!F85,'Утес'!F85) | G85: =SUM('Астон.Движение'!G85,'Астон.Реформа'!G85,'Дом Милый Дом'!G85,'River Park'!G85,'Астрид'!G85,'Живи в Курортном'!G85,'Новое Колпино'!G85,'Таллинский парк'!G85,'Твоя Привелегия'!G85,'Исеть Парк'!G85,'Космонавтов 11'!G85,'Утес'!G85) | H85: =SUM('Астон.Движение'!H85,'Астон.Реформа'!H85,'Дом Милый Дом'!H85,'River Park'!H85,'Астрид'!H85,'Живи в Курортном'!H85,'Новое Колпино'!H85,'Таллинский парк'!H85,'Твоя Привелегия'!H85,'Исеть Парк'!H85,'Космонавтов 11'!H85,'Утес'!H85) | I85: =SUM('Астон.Движение'!I85,'Астон.Реформа'!I85,'Дом Милый Дом'!I85,'River Park'!I85,'Астрид'!I85,'Живи в Курортном'!I85,'Новое Колпино'!I85,'Таллинский парк'!I85,'Твоя Привелегия'!I85,'Исеть Парк'!I85,'Космонавтов 11'!I85,'Утес'!I85)
A86: Курсовая разница (+) | B86: =SUM('Астон.Движение'!B86,'Астон.Реформа'!B86,'Дом Милый Дом'!B86,'River Park'!B86,'Астрид'!B86,'Живи в Курортном'!B86,'Новое Колпино'!B86,'Таллинский парк'!B86,'Твоя Привелегия'!B86,'Исеть Парк'!B86,'Космонавтов 11'!B86,'Утес'!B86) | C86: =SUM('Астон.Движение'!C86,'Астон.Реформа'!C86,'Дом Милый Дом'!C86,'River Park'!C86,'Астрид'!C86,'Живи в Курортном'!C86,'Новое Колпино'!C86,'Таллинский парк'!C86,'Твоя Привелегия'!C86,'Исеть Парк'!C86,'Космонавтов 11'!C86,'Утес'!C86) | D86: =SUM('Астон.Движение'!D86,'Астон.Реформа'!D86,'Дом Милый Дом'!D86,'River Park'!D86,'Астрид'!D86,'Живи в Курортном'!D86,'Новое Колпино'!D86,'Таллинский парк'!D86,'Твоя Привелегия'!D86,'Исеть Парк'!D86,'Космонавтов 11'!D86,'Утес'!D86) | E86: =SUM('Астон.Движение'!E86,'Астон.Реформа'!E86,'Дом Милый Дом'!E86,'River Park'!E86,'Астрид'!E86,'Живи в Курортном'!E86,'Новое Колпино'!E86,'Таллинский парк'!E86,'Твоя Привелегия'!E86,'Исеть Парк'!E86,'Космонавтов 11'!E86,'Утес'!E86) | F86: =SUM('Астон.Движение'!F86,'Астон.Реформа'!F86,'Дом Милый Дом'!F86,'River Park'!F86,'Астрид'!F86,'Живи в Курортном'!F86,'Новое Колпино'!F86,'Таллинский парк'!F86,'Твоя Привелегия'!F86,'Исеть Парк'!F86,'Космонавтов 11'!F86,'Утес'!F86) | G86: =SUM('Астон.Движение'!G86,'Астон.Реформа'!G86,'Дом Милый Дом'!G86,'River Park'!G86,'Астрид'!G86,'Живи в Курортном'!G86,'Новое Колпино'!G86,'Таллинский парк'!G86,'Твоя Привелегия'!G86,'Исеть Парк'!G86,'Космонавтов 11'!G86,'Утес'!G86) | H86: =SUM('Астон.Движение'!H86,'Астон.Реформа'!H86,'Дом Милый Дом'!H86,'River Park'!H86,'Астрид'!H86,'Живи в Курортном'!H86,'Новое Колпино'!H86,'Таллинский парк'!H86,'Твоя Привелегия'!H86,'Исеть Парк'!H86,'Космонавтов 11'!H86,'Утес'!H86) | I86: =SUM('Астон.Движение'!I86,'Астон.Реформа'!I86,'Дом Милый Дом'!I86,'River Park'!I86,'Астрид'!I86,'Живи в Курортном'!I86,'Новое Колпино'!I86,'Таллинский парк'!I86,'Твоя Привелегия'!I86,'Исеть Парк'!I86,'Космонавтов 11'!I86,'Утес'!I86)
A87: Прочие расходы | B87: =SUM(B88) | C87: =SUM(C88) | D87: =SUM(D88) | E87: =SUM(E88) | F87: =SUM(F88) | G87: =SUM(G88) | H87: =SUM(H88) | I87: =SUM(I88)
A88: Курсовая разница (-) | B88: =SUM('Астон.Движение'!B88,'Астон.Реформа'!B88,'Дом Милый Дом'!B88,'River Park'!B88,'Астрид'!B88,'Живи в Курортном'!B88,'Новое Колпино'!B88,'Таллинский парк'!B88,'Твоя Привелегия'!B88,'Исеть Парк'!B88,'Космонавтов 11'!B88,'Утес'!B88) | C88: =SUM('Астон.Движение'!C88,'Астон.Реформа'!C88,'Дом Милый Дом'!C88,'River Park'!C88,'Астрид'!C88,'Живи в Курортном'!C88,'Новое Колпино'!C88,'Таллинский парк'!C88,'Твоя Привелегия'!C88,'Исеть Парк'!C88,'Космонавтов 11'!C88,'Утес'!C88) | D88: =SUM('Астон.Движение'!D88,'Астон.Реформа'!D88,'Дом Милый Дом'!D88,'River Park'!D88,'Астрид'!D88,'Живи в Курортном'!D88,'Новое Колпино'!D88,'Таллинский парк'!D88,'Твоя Привелегия'!D88,'Исеть Парк'!D88,'Космонавтов 11'!D88,'Утес'!D88) | E88: =SUM('Астон.Движение'!E88,'Астон.Реформа'!E88,'Дом Милый Дом'!E88,'River Park'!E88,'Астрид'!E88,'Живи в Курортном'!E88,'Новое Колпино'!E88,'Таллинский парк'!E88,'Твоя Привелегия'!E88,'Исеть Парк'!E88,'Космонавтов 11'!E88,'Утес'!E88) | F88: =SUM('Астон.Движение'!F88,'Астон.Реформа'!F88,'Дом Милый Дом'!F88,'River Park'!F88,'Астрид'!F88,'Живи в Курортном'!F88,'Новое Колпино'!F88,'Таллинский парк'!F88,'Твоя Привелегия'!F88,'Исеть Парк'!F88,'Космонавтов 11'!F88,'Утес'!F88) | G88: =SUM('Астон.Движение'!G88,'Астон.Реформа'!G88,'Дом Милый Дом'!G88,'River Park'!G88,'Астрид'!G88,'Живи в Курортном'!G88,'Новое Колпино'!G88,'Таллинский парк'!G88,'Твоя Привелегия'!G88,'Исеть Парк'!G88,'Космонавтов 11'!G88,'Утес'!G88) | H88: =SUM('Астон.Движение'!H88,'Астон.Реформа'!H88,'Дом Милый Дом'!H88,'River Park'!H88,'Астрид'!H88,'Живи в Курортном'!H88,'Новое Колпино'!H88,'Таллинский парк'!H88,'Твоя Привелегия'!H88,'Исеть Парк'!H88,'Космонавтов 11'!H88,'Утес'!H88) | I88: =SUM('Астон.Движение'!I88,'Астон.Реформа'!I88,'Дом Милый Дом'!I88,'River Park'!I88,'Астрид'!I88,'Живи в Курортном'!I88,'Новое Колпино'!I88,'Таллинский парк'!I88,'Твоя Привелегия'!I88,'Исеть Парк'!I88,'Космонавтов 11'!I88,'Утес'!I88)
A89: EBITDA | B89: =B80+IFERROR(B82*1,0)-IFERROR(B87*1,0) | C89: =C80+IFERROR(C82*1,0)-IFERROR(C87*1,0) | D89: =D80+IFERROR(D82*1,0)-IFERROR(D87*1,0) | E89: =E80+IFERROR(E82*1,0)-IFERROR(E87*1,0) | F89: =F80+IFERROR(F82*1,0)-IFERROR(F87*1,0) | G89: =G80+IFERROR(G82*1,0)-IFERROR(G87*1,0) | H89: =H80+IFERROR(H82*1,0)-IFERROR(H87*1,0) | I89: =I80+IFERROR(I82*1,0)-IFERROR(I87*1,0)
A90: Рентабельность по EBITDA | B90: =IFERROR(IF(B4=0,"-",B89/B4),"-") | C90: =IFERROR(IF(C4=0,"-",C89/C4),"-") | D90: =IFERROR(IF(D4=0,"-",D89/D4),"-") | E90: =IFERROR(IF(E4=0,"-",E89/E4),"-") | F90: =IFERROR(IF(F4=0,"-",F89/F4),"-") | G90: =IFERROR(IF(G4=0,"-",G89/G4),"-") | H90: =IFERROR(IF(H4=0,"-",H89/H4),"-") | I90: =IFERROR(IF(I4=0,"-",I89/I4),"-")
A91: Амортизация | B91: =SUM(B92,B93) | C91: =SUM(C92,C93) | D91: =SUM(D92,D93) | E91: =SUM(E92,E93) | F91: =SUM(F92,F93) | G91: =SUM(G92,G93) | H91: =SUM(H92,H93) | I91: =SUM(I92,I93)
A92: Амортизация ОС (ПТ) | B92: =SUM('Астон.Движение'!B92,'Астон.Реформа'!B92,'Дом Милый Дом'!B92,'River Park'!B92,'Астрид'!B92,'Живи в Курортном'!B92,'Новое Колпино'!B92,'Таллинский парк'!B92,'Твоя Привелегия'!B92,'Исеть Парк'!B92,'Космонавтов 11'!B92,'Утес'!B92) | C92: =SUM('Астон.Движение'!C92,'Астон.Реформа'!C92,'Дом Милый Дом'!C92,'River Park'!C92,'Астрид'!C92,'Живи в Курортном'!C92,'Новое Колпино'!C92,'Таллинский парк'!C92,'Твоя Привелегия'!C92,'Исеть Парк'!C92,'Космонавтов 11'!C92,'Утес'!C92) | D92: =SUM('Астон.Движение'!D92,'Астон.Реформа'!D92,'Дом Милый Дом'!D92,'River Park'!D92,'Астрид'!D92,'Живи в Курортном'!D92,'Новое Колпино'!D92,'Таллинский парк'!D92,'Твоя Привелегия'!D92,'Исеть Парк'!D92,'Космонавтов 11'!D92,'Утес'!D92) | E92: =SUM('Астон.Движение'!E92,'Астон.Реформа'!E92,'Дом Милый Дом'!E92,'River Park'!E92,'Астрид'!E92,'Живи в Курортном'!E92,'Новое Колпино'!E92,'Таллинский парк'!E92,'Твоя Привелегия'!E92,'Исеть Парк'!E92,'Космонавтов 11'!E92,'Утес'!E92) | F92: =SUM('Астон.Движение'!F92,'Астон.Реформа'!F92,'Дом Милый Дом'!F92,'River Park'!F92,'Астрид'!F92,'Живи в Курортном'!F92,'Новое Колпино'!F92,'Таллинский парк'!F92,'Твоя Привелегия'!F92,'Исеть Парк'!F92,'Космонавтов 11'!F92,'Утес'!F92) | G92: =SUM('Астон.Движение'!G92,'Астон.Реформа'!G92,'Дом Милый Дом'!G92,'River Park'!G92,'Астрид'!G92,'Живи в Курортном'!G92,'Новое Колпино'!G92,'Таллинский парк'!G92,'Твоя Привелегия'!G92,'Исеть Парк'!G92,'Космонавтов 11'!G92,'Утес'!G92) | H92: =SUM('Астон.Движение'!H92,'Астон.Реформа'!H92,'Дом Милый Дом'!H92,'River Park'!H92,'Астрид'!H92,'Живи в Курортном'!H92,'Новое Колпино'!H92,'Таллинский парк'!H92,'Твоя Привелегия'!H92,'Исеть Парк'!H92,'Космонавтов 11'!H92,'Утес'!H92) | I92: =SUM('Астон.Движение'!I92,'Астон.Реформа'!I92,'Дом Милый Дом'!I92,'River Park'!I92,'Астрид'!I92,'Живи в Курортном'!I92,'Новое Колпино'!I92,'Таллинский парк'!I92,'Твоя Привелегия'!I92,'Исеть Парк'!I92,'Космонавтов 11'!I92,'Утес'!I92)
A93: Амортизация ОС (МОП) | B93: =SUM('Астон.Движение'!B93,'Астон.Реформа'!B93,'Дом Милый Дом'!B93,'River Park'!B93,'Астрид'!B93,'Живи в Курортном'!B93,'Новое Колпино'!B93,'Таллинский парк'!B93,'Твоя Привелегия'!B93,'Исеть Парк'!B93,'Космонавтов 11'!B93,'Утес'!B93) | C93: =SUM('Астон.Движение'!C93,'Астон.Реформа'!C93,'Дом Милый Дом'!C93,'River Park'!C93,'Астрид'!C93,'Живи в Курортном'!C93,'Новое Колпино'!C93,'Таллинский парк'!C93,'Твоя Привелегия'!C93,'Исеть Парк'!C93,'Космонавтов 11'!C93,'Утес'!C93) | D93: =SUM('Астон.Движение'!D93,'Астон.Реформа'!D93,'Дом Милый Дом'!D93,'River Park'!D93,'Астрид'!D93,'Живи в Курортном'!D93,'Новое Колпино'!D93,'Таллинский парк'!D93,'Твоя Привелегия'!D93,'Исеть Парк'!D93,'Космонавтов 11'!D93,'Утес'!D93) | E93: =SUM('Астон.Движение'!E93,'Астон.Реформа'!E93,'Дом Милый Дом'!E93,'River Park'!E93,'Астрид'!E93,'Живи в Курортном'!E93,'Новое Колпино'!E93,'Таллинский парк'!E93,'Твоя Привелегия'!E93,'Исеть Парк'!E93,'Космонавтов 11'!E93,'Утес'!E93) | F93: =SUM('Астон.Движение'!F93,'Астон.Реформа'!F93,'Дом Милый Дом'!F93,'River Park'!F93,'Астрид'!F93,'Живи в Курортном'!F93,'Новое Колпино'!F93,'Таллинский парк'!F93,'Твоя Привелегия'!F93,'Исеть Парк'!F93,'Космонавтов 11'!F93,'Утес'!F93) | G93: =SUM('Астон.Движение'!G93,'Астон.Реформа'!G93,'Дом Милый Дом'!G93,'River Park'!G93,'Астрид'!G93,'Живи в Курортном'!G93,'Новое Колпино'!G93,'Таллинский парк'!G93,'Твоя Привелегия'!G93,'Исеть Парк'!G93,'Космонавтов 11'!G93,'Утес'!G93) | H93: =SUM('Астон.Движение'!H93,'Астон.Реформа'!H93,'Дом Милый Дом'!H93,'River Park'!H93,'Астрид'!H93,'Живи в Курортном'!H93,'Новое Колпино'!H93,'Таллинский парк'!H93,'Твоя Привелегия'!H93,'Исеть Парк'!H93,'Космонавтов 11'!H93,'Утес'!H93) | I93: =SUM('Астон.Движение'!I93,'Астон.Реформа'!I93,'Дом Милый Дом'!I93,'River Park'!I93,'Астрид'!I93,'Живи в Курортном'!I93,'Новое Колпино'!I93,'Таллинский парк'!I93,'Твоя Привелегия'!I93,'Исеть Парк'!I93,'Космонавтов 11'!I93,'Утес'!I93)
A94: Проценты по кредитам и займам | B94: =SUM('Астон.Движение'!B94,'Астон.Реформа'!B94,'Дом Милый Дом'!B94,'River Park'!B94,'Астрид'!B94,'Живи в Курортном'!B94,'Новое Колпино'!B94,'Таллинский парк'!B94,'Твоя Привелегия'!B94,'Исеть Парк'!B94,'Космонавтов 11'!B94,'Утес'!B94) | C94: =SUM('Астон.Движение'!C94,'Астон.Реформа'!C94,'Дом Милый Дом'!C94,'River Park'!C94,'Астрид'!C94,'Живи в Курортном'!C94,'Новое Колпино'!C94,'Таллинский парк'!C94,'Твоя Привелегия'!C94,'Исеть Парк'!C94,'Космонавтов 11'!C94,'Утес'!C94) | D94: =SUM('Астон.Движение'!D94,'Астон.Реформа'!D94,'Дом Милый Дом'!D94,'River Park'!D94,'Астрид'!D94,'Живи в Курортном'!D94,'Новое Колпино'!D94,'Таллинский парк'!D94,'Твоя Привелегия'!D94,'Исеть Парк'!D94,'Космонавтов 11'!D94,'Утес'!D94) | E94: =SUM('Астон.Движение'!E94,'Астон.Реформа'!E94,'Дом Милый Дом'!E94,'River Park'!E94,'Астрид'!E94,'Живи в Курортном'!E94,'Новое Колпино'!E94,'Таллинский парк'!E94,'Твоя Привелегия'!E94,'Исеть Парк'!E94,'Космонавтов 11'!E94,'Утес'!E94) | F94: =SUM('Астон.Движение'!F94,'Астон.Реформа'!F94,'Дом Милый Дом'!F94,'River Park'!F94,'Астрид'!F94,'Живи в Курортном'!F94,'Новое Колпино'!F94,'Таллинский парк'!F94,'Твоя Привелегия'!F94,'Исеть Парк'!F94,'Космонавтов 11'!F94,'Утес'!F94) | G94: =SUM('Астон.Движение'!G94,'Астон.Реформа'!G94,'Дом Милый Дом'!G94,'River Park'!G94,'Астрид'!G94,'Живи в Курортном'!G94,'Новое Колпино'!G94,'Таллинский парк'!G94,'Твоя Привелегия'!G94,'Исеть Парк'!G94,'Космонавтов 11'!G94,'Утес'!G94) | H94: =SUM('Астон.Движение'!H94,'Астон.Реформа'!H94,'Дом Милый Дом'!H94,'River Park'!H94,'Астрид'!H94,'Живи в Курортном'!H94,'Новое Колпино'!H94,'Таллинский парк'!H94,'Твоя Привелегия'!H94,'Исеть Парк'!H94,'Космонавтов 11'!H94,'Утес'!H94) | I94: =SUM('Астон.Движение'!I94,'Астон.Реформа'!I94,'Дом Милый Дом'!I94,'River Park'!I94,'Астрид'!I94,'Живи в Курортном'!I94,'Новое Колпино'!I94,'Таллинский парк'!I94,'Твоя Привелегия'!I94,'Исеть Парк'!I94,'Космонавтов 11'!I94,'Утес'!I94)
A95: Налог на прибыль | B95: =SUM(B96,B97) | C95: =SUM(C96,C97) | D95: =SUM(D96,D97) | E95: =SUM(E96,E97) | F95: =SUM(F96,F97) | G95: =SUM(G96,G97) | H95: =SUM(H96,H97) | I95: =SUM(I96,I97)
A96: Налоги УСН | B96: =SUM('Астон.Движение'!B96,'Астон.Реформа'!B96,'Дом Милый Дом'!B96,'River Park'!B96,'Астрид'!B96,'Живи в Курортном'!B96,'Новое Колпино'!B96,'Таллинский парк'!B96,'Твоя Привелегия'!B96,'Исеть Парк'!B96,'Космонавтов 11'!B96,'Утес'!B96) | C96: =SUM('Астон.Движение'!C96,'Астон.Реформа'!C96,'Дом Милый Дом'!C96,'River Park'!C96,'Астрид'!C96,'Живи в Курортном'!C96,'Новое Колпино'!C96,'Таллинский парк'!C96,'Твоя Привелегия'!C96,'Исеть Парк'!C96,'Космонавтов 11'!C96,'Утес'!C96) | D96: =SUM('Астон.Движение'!D96,'Астон.Реформа'!D96,'Дом Милый Дом'!D96,'River Park'!D96,'Астрид'!D96,'Живи в Курортном'!D96,'Новое Колпино'!D96,'Таллинский парк'!D96,'Твоя Привелегия'!D96,'Исеть Парк'!D96,'Космонавтов 11'!D96,'Утес'!D96) | E96: =SUM('Астон.Движение'!E96,'Астон.Реформа'!E96,'Дом Милый Дом'!E96,'River Park'!E96,'Астрид'!E96,'Живи в Курортном'!E96,'Новое Колпино'!E96,'Таллинский парк'!E96,'Твоя Привелегия'!E96,'Исеть Парк'!E96,'Космонавтов 11'!E96,'Утес'!E96) | F96: =SUM('Астон.Движение'!F96,'Астон.Реформа'!F96,'Дом Милый Дом'!F96,'River Park'!F96,'Астрид'!F96,'Живи в Курортном'!F96,'Новое Колпино'!F96,'Таллинский парк'!F96,'Твоя Привелегия'!F96,'Исеть Парк'!F96,'Космонавтов 11'!F96,'Утес'!F96) | G96: =SUM('Астон.Движение'!G96,'Астон.Реформа'!G96,'Дом Милый Дом'!G96,'River Park'!G96,'Астрид'!G96,'Живи в Курортном'!G96,'Новое Колпино'!G96,'Таллинский парк'!G96,'Твоя Привелегия'!G96,'Исеть Парк'!G96,'Космонавтов 11'!G96,'Утес'!G96) | H96: =SUM('Астон.Движение'!H96,'Астон.Реформа'!H96,'Дом Милый Дом'!H96,'River Park'!H96,'Астрид'!H96,'Живи в Курортном'!H96,'Новое Колпино'!H96,'Таллинский парк'!H96,'Твоя Привелегия'!H96,'Исеть Парк'!H96,'Космонавтов 11'!H96,'Утес'!H96) | I96: =SUM('Астон.Движение'!I96,'Астон.Реформа'!I96,'Дом Милый Дом'!I96,'River Park'!I96,'Астрид'!I96,'Живи в Курортном'!I96,'Новое Колпино'!I96,'Таллинский парк'!I96,'Твоя Привелегия'!I96,'Исеть Парк'!I96,'Космонавтов 11'!I96,'Утес'!I96)
A97: Налоги НДС 5% | B97: =SUM('Астон.Движение'!B97,'Астон.Реформа'!B97,'Дом Милый Дом'!B97,'River Park'!B97,'Астрид'!B97,'Живи в Курортном'!B97,'Новое Колпино'!B97,'Таллинский парк'!B97,'Твоя Привелегия'!B97,'Исеть Парк'!B97,'Космонавтов 11'!B97,'Утес'!B97) | C97: =SUM('Астон.Движение'!C97,'Астон.Реформа'!C97,'Дом Милый Дом'!C97,'River Park'!C97,'Астрид'!C97,'Живи в Курортном'!C97,'Новое Колпино'!C97,'Таллинский парк'!C97,'Твоя Привелегия'!C97,'Исеть Парк'!C97,'Космонавтов 11'!C97,'Утес'!C97) | D97: =SUM('Астон.Движение'!D97,'Астон.Реформа'!D97,'Дом Милый Дом'!D97,'River Park'!D97,'Астрид'!D97,'Живи в Курортном'!D97,'Новое Колпино'!D97,'Таллинский парк'!D97,'Твоя Привелегия'!D97,'Исеть Парк'!D97,'Космонавтов 11'!D97,'Утес'!D97) | E97: =SUM('Астон.Движение'!E97,'Астон.Реформа'!E97,'Дом Милый Дом'!E97,'River Park'!E97,'Астрид'!E97,'Живи в Курортном'!E97,'Новое Колпино'!E97,'Таллинский парк'!E97,'Твоя Привелегия'!E97,'Исеть Парк'!E97,'Космонавтов 11'!E97,'Утес'!E97) | F97: =SUM('Астон.Движение'!F97,'Астон.Реформа'!F97,'Дом Милый Дом'!F97,'River Park'!F97,'Астрид'!F97,'Живи в Курортном'!F97,'Новое Колпино'!F97,'Таллинский парк'!F97,'Твоя Привелегия'!F97,'Исеть Парк'!F97,'Космонавтов 11'!F97,'Утес'!F97) | G97: =SUM('Астон.Движение'!G97,'Астон.Реформа'!G97,'Дом Милый Дом'!G97,'River Park'!G97,'Астрид'!G97,'Живи в Курортном'!G97,'Новое Колпино'!G97,'Таллинский парк'!G97,'Твоя Привелегия'!G97,'Исеть Парк'!G97,'Космонавтов 11'!G97,'Утес'!G97) | H97: =SUM('Астон.Движение'!H97,'Астон.Реформа'!H97,'Дом Милый Дом'!H97,'River Park'!H97,'Астрид'!H97,'Живи в Курортном'!H97,'Новое Колпино'!H97,'Таллинский парк'!H97,'Твоя Привелегия'!H97,'Исеть Парк'!H97,'Космонавтов 11'!H97,'Утес'!H97) | I97: =SUM('Астон.Движение'!I97,'Астон.Реформа'!I97,'Дом Милый Дом'!I97,'River Park'!I97,'Астрид'!I97,'Живи в Курортном'!I97,'Новое Колпино'!I97,'Таллинский парк'!I97,'Твоя Привелегия'!I97,'Исеть Парк'!I97,'Космонавтов 11'!I97,'Утес'!I97)
A98: Чистая прибыль (убыток) | B98: =IFERROR(B89*1,0)-IFERROR(B91*1,0)-IFERROR(B94*1,0)-IFERROR(B95*1,0) | C98: =IFERROR(C89*1,0)-IFERROR(C91*1,0)-IFERROR(C94*1,0)-IFERROR(C95*1,0) | D98: =IFERROR(D89*1,0)-IFERROR(D91*1,0)-IFERROR(D94*1,0)-IFERROR(D95*1,0) | E98: =IFERROR(E89*1,0)-IFERROR(E91*1,0)-IFERROR(E94*1,0)-IFERROR(E95*1,0) | F98: =IFERROR(F89*1,0)-IFERROR(F91*1,0)-IFERROR(F94*1,0)-IFERROR(F95*1,0) | G98: =IFERROR(G89*1,0)-IFERROR(G91*1,0)-IFERROR(G94*1,0)-IFERROR(G95*1,0) | H98: =IFERROR(H89*1,0)-IFERROR(H91*1,0)-IFERROR(H94*1,0)-IFERROR(H95*1,0) | I98: =IFERROR(I89*1,0)-IFERROR(I91*1,0)-IFERROR(I94*1,0)-IFERROR(I95*1,0)
A99: Рентабельность чистой прибыли | B99: =IFERROR(IF(B4=0,"-",B98/B4),"-") | C99: =IFERROR(IF(C4=0,"-",C98/C4),"-") | D99: =IFERROR(IF(D4=0,"-",D98/D4),"-") | E99: =IFERROR(IF(E4=0,"-",E98/E4),"-") | F99: =IFERROR(IF(F4=0,"-",F98/F4),"-") | G99: =IFERROR(IF(G4=0,"-",G98/G4),"-") | H99: =IFERROR(IF(H4=0,"-",H98/H4),"-") | I99: =IFERROR(IF(I4=0,"-",I98/I4),"-")

Sheet Астон.Движение
A1: ПланФакт | B1: Создано с помощью сервиса ПланФакт | I1: =HYPERLINK("https://app.planfact.io/?from=Pf_BDR", "Перейти в сервис")
B2: Итого | C2: июнь` 26 | D2: июль` 26 | E2: август` 26 | F2: сентябрь` 26 | G2: октябрь` 26 | H2: ноябрь` 26 | I2: декабрь` 26
A3: Астон.Движение | B3: план | C3: план | D3: план | E3: план | F3: план | G3: план | H3: план | I3: план
A4: Выручка | B4: =SUM(B5,B6) | C4: =SUM(C5,C6) | D4: =SUM(D5,D6) | E4: =SUM(E5,E6) | F4: =SUM(F5,F6) | G4: =SUM(G5,G6) | H4: =SUM(H5,H6) | I4: =SUM(I5,I6)
A5: Нераспределенный доход | B5: - | C5: - | D5: - | E5: - | F5: - | G5: - | H5: - | I5: -
A6: Выручка | B6: =SUM(B7,B8,B9) | C6: =SUM(C7,C8,C9) | D6: =SUM(D7,D8,D9) | E6: =SUM(E7,E8,E9) | F6: =SUM(F7,F8,F9) | G6: =SUM(G7,G8,G9) | H6: =SUM(H7,H8,H9) | I6: =SUM(I7,I8,I9)
A7: Реализация услуг Клининг (ОД) | B7: 656000 | C7: 164000 | D7: 164000 | E7: 164000 | F7: 164000 | G7: - | H7: - | I7: -
A8: Реализация услуг Клининг (Доп.услуги) | B8: - | C8: - | D8: - | E8: - | F8: - | G8: - | H8: - | I8: -
A9: Реализация услуг Клининг (снег) | B9: - | C9: - | D9: - | E9: - | F9: - | G9: - | H9: - | I9: -
A10: Прямые расходы | B10: =SUM(B11,B12,B13,B21,B22,B23,B24,B25,B26,B27,B28,B29,B30,B31,B32,B33,B34) | C10: =SUM(C11,C12,C13,C21,C22,C23,C24,C25,C26,C27,C28,C29,C30,C31,C32,C33,C34) | D10: =SUM(D11,D12,D13,D21,D22,D23,D24,D25,D26,D27,D28,D29,D30,D31,D32,D33,D34) | E10: =SUM(E11,E12,E13,E21,E22,E23,E24,E25,E26,E27,E28,E29,E30,E31,E32,E33,E34) | F10: =SUM(F11,F12,F13,F21,F22,F23,F24,F25,F26,F27,F28,F29,F30,F31,F32,F33,F34) | G10: =SUM(G11,G12,G13,G21,G22,G23,G24,G25,G26,G27,G28,G29,G30,G31,G32,G33,G34) | H10: =SUM(H11,H12,H13,H21,H22,H23,H24,H25,H26,H27,H28,H29,H30,H31,H32,H33,H34) | I10: =SUM(I11,I12,I13,I21,I22,I23,I24,I25,I26,I27,I28,I29,I30,I31,I32,I33,I34)
A11: Нераспределенный расход | B11: - | C11: - | D11: - | E11: - | F11: - | G11: - | H11: - | I11: -
A12: Транспортные расходы | B12: 1486 | C12: 1486 | D12: - | E12: - | F12: - | G12: - | H12: - | I12: -
A13: Переменные | B13: =SUM(B14,B15,B16,B17,B18,B19,B20) | C13: =SUM(C14,C15,C16,C17,C18,C19,C20) | D13: =SUM(D14,D15,D16,D17,D18,D19,D20) | E13: =SUM(E14,E15,E16,E17,E18,E19,E20) | F13: =SUM(F14,F15,F16,F17,F18,F19,F20) | G13: =SUM(G14,G15,G16,G17,G18,G19,G20) | H13: =SUM(H14,H15,H16,H17,H18,H19,H20) | I13: =SUM(I14,I15,I16,I17,I18,I19,I20)
A14: Услуги техниги для уборки снега (ПТ) | B14: - | C14: - | D14: - | E14: - | F14: - | G14: - | H14: - | I14: -
A15: Услуги садовника (ПТ) | B15: - | C15: - | D15: - | E15: - | F15: - | G15: - | H15: - | I15: -
A16: Сыпучие материалы (ПТ) | B16: - | C16: - | D16: - | E16: - | F16: - | G16: - | H16: - | I16: -
A17: Расходные материалы и инстументы (МОП) | B17: 8000 | C17: 2000 | D17: 2000 | E17: 2000 | F17: 2000 | G17: - | H17: - | I17: -
A18: Расходные материалы и инстументы (ПТ) | B18: 7262 | C18: 1262 | D18: 2000 | E18: 2000 | F18: 2000 | G18: - | H18: - | I18: -
A19: Арена оборудования (ПТ) | B19: - | C19: - | D19: - | E19: - | F19: - | G19: - | H19: - | I19: -
A20: Арена оборудования (МОП) | B20: - | C20: - | D20: - | E20: - | F20: - | G20: - | H20: - | I20: -
A21: Заработная плата (МОП) | B21: 200000 | C21: 50000 | D21: 50000 | E21: 50000 | F21: 50000 | G21: - | H21: - | I21: -
A22: Заработная плата (ПТ) | B22: 280000 | C22: 70000 | D22: 70000 | E22: 70000 | F22: 70000 | G22: - | H22: - | I22: -
A23: Налоги с ФОТ (МОП) | B23: - | C23: - | D23: - | E23: - | F23: - | G23: - | H23: - | I23: -
A24: Налоги с ФОТ (ПТ) | B24: - | C24: - | D24: - | E24: - | F24: - | G24: - | H24: - | I24: -
A25: Премми (МОП) | B25: - | C25: - | D25: - | E25: - | F25: - | G25: - | H25: - | I25: -
A26: Премми (ПТ) | B26: - | C26: - | D26: - | E26: - | F26: - | G26: - | H26: - | I26: -
A27: Униформа (МОП) | B27: - | C27: - | D27: - | E27: - | F27: - | G27: - | H27: - | I27: -
A28: Униформа (ПТ) | B28: - | C28: - | D28: - | E28: - | F28: - | G28: - | H28: - | I28: -
A29: Ремонт оборудования (МОП) | B29: - | C29: - | D29: - | E29: - | F29: - | G29: - | H29: - | I29: -
A30: Ремонт оборудования (ПТ) | B30: - | C30: - | D30: - | E30: - | F30: - | G30: - | H30: - | I30: -
A31: Вывоз мусора | B31: - | C31: - | D31: - | E31: - | F31: - | G31: - | H31: - | I31: -
A32: Штрафы, пени, неустойки | B32: - | C32: - | D32: - | E32: - | F32: - | G32: - | H32: - | I32: -
A33: Расходы к удержанию | B33: - | C33: - | D33: - | E33: - | F33: - | G33: - | H33: - | I33: -
A34: Общехозяйственные | B34: =SUM(B35,B36,B37,B38,B39,B40,B41,B42) | C34: =SUM(C35,C36,C37,C38,C39,C40,C41,C42) | D34: =SUM(D35,D36,D37,D38,D39,D40,D41,D42) | E34: =SUM(E35,E36,E37,E38,E39,E40,E41,E42) | F34: =SUM(F35,F36,F37,F38,F39,F40,F41,F42) | G34: =SUM(G35,G36,G37,G38,G39,G40,G41,G42) | H34: =SUM(H35,H36,H37,H38,H39,H40,H41,H42) | I34: =SUM(I35,I36,I37,I38,I39,I40,I41,I42)
A35: Аутсорс (направления) | B35: - | C35: - | D35: - | E35: - | F35: - | G35: - | H35: - | I35: -
A36: Заработная плата МО АУП | B36: - | C36: - | D36: - | E36: - | F36: - | G36: - | H36: - | I36: -
A37: Инструменты: ГСМ | B37: 332.45 | C37: 332.45 | D37: - | E37: - | F37: - | G37: - | H37: - | I37: -
A38: Медосмотры | B38: - | C38: - | D38: - | E38: - | F38: - | G38: - | H38: - | I38: -
A39: Налоги с ФОТ (ИП) | B39: 33600 | C39: 8400 | D39: 8400 | E39: 8400 | F39: 8400 | G39: - | H39: - | I39: -
A40: Приобритение мебели, бытовой техники | B40: - | C40: - | D40: - | E40: - | F40: - | G40: - | H40: - | I40: -
A41: Комиссия за перевод ЗП | B41: - | C41: - | D41: - | E41: - | F41: - | G41: - | H41: - | I41: -
A42: Аренда квартиры (включая коммуналку) | B42: - | C42: - | D42: - | E42: - | F42: - | G42: - | H42: - | I42: -
A43: Валовая прибыль | B43: =B4-B10 | C43: =C4-C10 | D43: =D4-D10 | E43: =E4-E10 | F43: =F4-F10 | G43: =G4-G10 | H43: =H4-H10 | I43: =I4-I10
A44: Валовая рентабельность | B44: =IFERROR(IF(B4=0,"-",B43/B4),"-") | C44: =IFERROR(IF(C4=0,"-",C43/C4),"-") | D44: =IFERROR(IF(D4=0,"-",D43/D4),"-") | E44: =IFERROR(IF(E4=0,"-",E43/E4),"-") | F44: =IFERROR(IF(F4=0,"-",F43/F4),"-") | G44: =IFERROR(IF(G4=0,"-",G43/G4),"-") | H44: =IFERROR(IF(H4=0,"-",H43/H4),"-") | I44: =IFERROR(IF(I4=0,"-",I43/I4),"-")
A45: Косвенные расходы | B45: =SUM(B46,B47,B48,B52,B56,B57,B58,B59,B60,B63,B64,B65,B66,B67,B68,B69,B70,B71,B72,B73,B74,B75,B76,B77,B78,B79) | C45: =SUM(C46,C47,C48,C52,C56,C57,C58,C59,C60,C63,C64,C65,C66,C67,C68,C69,C70,C71,C72,C73,C74,C75,C76,C77,C78,C79) | D45: =SUM(D46,D47,D48,D52,D56,D57,D58,D59,D60,D63,D64,D65,D66,D67,D68,D69,D70,D71,D72,D73,D74,D75,D76,D77,D78,D79) | E45: =SUM(E46,E47,E48,E52,E56,E57,E58,E59,E60,E63,E64,E65,E66,E67,E68,E69,E70,E71,E72,E73,E74,E75,E76,E77,E78,E79) | F45: =SUM(F46,F47,F48,F52,F56,F57,F58,F59,F60,F63,F64,F65,F66,F67,F68,F69,F70,F71,F72,F73,F74,F75,F76,F77,F78,F79) | G45: =SUM(G46,G47,G48,G52,G56,G57,G58,G59,G60,G63,G64,G65,G66,G67,G68,G69,G70,G71,G72,G73,G74,G75,G76,G77,G78,G79) | H45: =SUM(H46,H47,H48,H52,H56,H57,H58,H59,H60,H63,H64,H65,H66,H67,H68,H69,H70,H71,H72,H73,H74,H75,H76,H77,H78,H79) | I45: =SUM(I46,I47,I48,I52,I56,I57,I58,I59,I60,I63,I64,I65,I66,I67,I68,I69,I70,I71,I72,I73,I74,I75,I76,I77,I78,I79)
A46: Расход БЭК-ОФИС | B46: - | C46: - | D46: - | E46: - | F46: - | G46: - | H46: - | I46: -
A47: Расходы на бэк-офис | B47: - | C47: - | D47: - | E47: - | F47: - | G47: - | H47: - | I47: -
A48: Автомобиль | B48: =SUM(B49,B50,B51) | C48: =SUM(C49,C50,C51) | D48: =SUM(D49,D50,D51) | E48: =SUM(E49,E50,E51) | F48: =SUM(F49,F50,F51) | G48: =SUM(G49,G50,G51) | H48: =SUM(H49,H50,H51) | I48: =SUM(I49,I50,I51)
A49: Автомобиль: ГСМ | B49: - | C49: - | D49: - | E49: - | F49: - | G49: - | H49: - | I49: -
A50: Автомобиль: страхование | B50: - | C50: - | D50: - | E50: - | F50: - | G50: - | H50: - | I50: -
A51: Автомобиль: ТО | B51: - | C51: - | D51: - | E51: - | F51: - | G51: - | H51: - | I51: -
A52: Офисные расходы | B52: =SUM(B53,B54,B55) | C52: =SUM(C53,C54,C55) | D52: =SUM(D53,D54,D55) | E52: =SUM(E53,E54,E55) | F52: =SUM(F53,F54,F55) | G52: =SUM(G53,G54,G55) | H52: =SUM(H53,H54,H55) | I52: =SUM(I53,I54,I55)
A53: Аренда офиса | B53: - | C53: - | D53: - | E53: - | F53: - | G53: - | H53: - | I53: -
A54: Канцелярия и обслуживание | B54: - | C54: - | D54: - | E54: - | F54: - | G54: - | H54: - | I54: -
A55: Интернет и связь | B55: - | C55: - | D55: - | E55: - | F55: - | G55: - | H55: - | I55: -
A56: Банковские услуги | B56: - | C56: - | D56: - | E56: - | F56: - | G56: - | H56: - | I56: -
A57: Заработная плата АУП (БО) | B57: - | C57: - | D57: - | E57: - | F57: - | G57: - | H57: - | I57: -
A58: Заработная плата бухгалтерии (БО) | B58: - | C58: - | D58: - | E58: - | F58: - | G58: - | H58: - | I58: -
A59: Заработная плата СБ (БО) | B59: - | C59: - | D59: - | E59: - | F59: - | G59: - | H59: - | I59: -
A60: Командировочные расходы | B60: =SUM(B61,B62) | C60: =SUM(C61,C62) | D60: =SUM(D61,D62) | E60: =SUM(E61,E62) | F60: =SUM(F61,F62) | G60: =SUM(G61,G62) | H60: =SUM(H61,H62) | I60: =SUM(I61,I62)
A61: Командировнчеы расходы: билеты (БО) | B61: - | C61: - | D61: - | E61: - | F61: - | G61: - | H61: - | I61: -
A62: Командировнчеы расходы: проживание (БО) | B62: - | C62: - | D62: - | E62: - | F62: - | G62: - | H62: - | I62: -
A63: Комиссия УК ДОМ | B63: - | C63: - | D63: - | E63: - | F63: - | G63: - | H63: - | I63: -
A64: Налоги с ФОТ (ИП)_БО | B64: - | C64: - | D64: - | E64: - | F64: - | G64: - | H64: - | I64: -
A65: Налоги с ФОТ (НДФЛ) БО | B65: - | C65: - | D65: - | E65: - | F65: - | G65: - | H65: - | I65: -
A66: Налоги с ФОТ (страховые взносы) БО | B66: - | C66: - | D66: - | E66: - | F66: - | G66: - | H66: - | I66: -
A67: Нотариальные услуги | B67: - | C67: - | D67: - | E67: - | F67: - | G67: - | H67: - | I67: -
A68: Обслуживание техники (БО) | B68: - | C68: - | D68: - | E68: - | F68: - | G68: - | H68: - | I68: -
A69: Программное обеспечение (БО) | B69: - | C69: - | D69: - | E69: - | F69: - | G69: - | H69: - | I69: -
A70: ПланФакт | B70: - | C70: - | D70: - | E70: - | F70: - | G70: - | H70: - | I70: -
A71: ТБ | B71: - | C71: - | D71: - | E71: - | F71: - | G71: - | H71: - | I71: -
A72: Контур | B72: - | C72: - | D72: - | E72: - | F72: - | G72: - | H72: - | I72: -
... A79: HR (аутсорс) | B79: - | C79: - | D79: - | E79: - | F79: - | G79: - | H79: - | I79: -
A80: Операционная прибыль | B80: =B43-B45 | C80: =C43-C45 | D80: =D43-D45 | E80: =E43-E45 | F80: =F43-F45 | G80: =G43-G45 | H80: =H43-H45 | I80: =I43-I45
A81: Операционная рентабельность | B81: =IFERROR(IF(B4=0,"-",B80/B4),"-") | C81: =IFERROR(IF(C4=0,"-",C80/C4),"-") | D81: =IFERROR(IF(D4=0,"-",D80/D4),"-") | E81: =IFERROR(IF(E4=0,"-",E80/E4),"-") | F81: =IFERROR(IF(F4=0,"-",F80/F4),"-") | G81: =IFERROR(IF(G4=0,"-",G80/G4),"-") | H81: =IFERROR(IF(H4=0,"-",H80/H4),"-") | I81: =IFERROR(IF(I4=0,"-",I80/I4),"-")
A82: Прочие доходы | B82: =SUM(B83,B84,B85,B86) | C82: =SUM(C83,C84,C85,C86) | D82: =SUM(D83,D84,D85,D86) | E82: =SUM(E83,E84,E85,E86) | F82: =SUM(F83,F84,F85,F86) | G82: =SUM(G83,G84,G85,G86) | H82: =SUM(H83,H84,H85,H86) | I82: =SUM(I83,I84,I85,I86)
A83: Доход БЭК-ОФИС | B83: - | C83: - | D83: - | E83: - | F83: - | G83: - | H83: - | I83: -
A84: Пополненин бэк-офис | B84: - | C84: - | D84: - | E84: - | F84: - | G84: - | H84: - | I84: -
A85: Проценты по вкладам | B85: - | C85: - | D85: - | E85: - | F85: - | G85: - | H85: - | I85: -
A86: Курсовая разница (+) | B86: - | C86: - | D86: - | E86: - | F86: - | G86: - | H86: - | I86: -
A87: Прочие расходы | B87: =SUM(B88) | C87: =SUM(C88) | D87: =SUM(D88) | E87: =SUM(E88) | F87: =SUM(F88) | G87: =SUM(G88) | H87: =SUM(H88) | I87: =SUM(I88)
A88: Курсовая разница (-) | B88: - | C88: - | D88: - | E88: - | F88: - | G88: - | H88: - | I88: -
A89: EBITDA | B89: =B80+IFERROR(B82*1,0)-IFERROR(B87*1,0) | C89: =C80+IFERROR(C82*1,0)-IFERROR(C87*1,0) | D89: =D80+IFERROR(D82*1,0)-IFERROR(D87*1,0) | E89: =E80+IFERROR(E82*1,0)-IFERROR(E87*1,0) | F89: =F80+IFERROR(F82*1,0)-IFERROR(F87*1,0) | G89: =G80+IFERROR(G82*1,0)-IFERROR(G87*1,0) | H89: =H80+IFERROR(H82*1,0)-IFERROR(H87*1,0) | I89: =I80+IFERROR(I82*1,0)-IFERROR(I87*1,0)
A90: Рентабельность по EBITDA | B90: =IFERROR(IF(B4=0,"-",B89/B4),"-") | C90: =IFERROR(IF(C4=0,"-",C89/C4),"-") | D90: =IFERROR(IF(D4=0,"-",D89/D4),"-") | E90: =IFERROR(IF(E4=0,"-",E89/E4),"-") | F90: =IFERROR(IF(F4=0,"-",F89/F4),"-") | G90: =IFERROR(IF(G4=0,"-",G89/G4),"-") | H90: =IFERROR(IF(H4=0,"-",H89/H4),"-") | I90: =IFERROR(IF(I4=0,"-",I89/I4),"-")
A91: Амортизация | B91: =SUM(B92,B93) | C91: =SUM(C92,C93) | D91: =SUM(D92,D93) | E91: =SUM(E92,E93) | F91: =SUM(F92,F93) | G91: =SUM(G92,G93) | H91: =SUM(H92,H93) | I91: =SUM(I92,I93)
A92: Амортизация ОС (ПТ) | B92: - | C92: - | D92: - | E92: - | F92: - | G92: - | H92: - | I92: -
A93: Амортизация ОС (МОП) | B93: - | C93: - | D93: - | E93: - | F93: - | G93: - | H93: - | I93: -
A94: Проценты по кредитам и займам | B94: - | C94: - | D94: - | E94: - | F94: - | G94: - | H94: - | I94: -
A95: Налог на прибыль | B95: =SUM(B96,B97) | C95: =SUM(C96,C97) | D95: =SUM(D96,D97) | E95: =SUM(E96,E97) | F95: =SUM(F96,F97) | G95: =SUM(G96,G97) | H95: =SUM(H96,H97) | I95: =SUM(I96,I97)
A96: Налоги УСН | B96: 46000 | C96: 11500 | D96: 11500 | E96: 11500 | F96: 11500 | G96: - | H96: - | I96: -
A97: Налоги НДС 5% | B97: - | C97: - | D97: - | E97: - | F97: - | G97: - | H97: - | I97: -
A98: Чистая прибыль (убыток) | B98: =IFERROR(B89*1,0)-IFERROR(B91*1,0)-IFERROR(B94*1,0)-IFERROR(B95*1,0) | C98: =IFERROR(C89*1,0)-IFERROR(C91*1,0)-IFERROR(C94*1,0)-IFERROR(C95*1,0) | D98: =IFERROR(D89*1,0)-IFERROR(D91*1,0)-IFERROR(D94*1,0)-IFERROR(D95*1,0) | E98: =IFERROR(E89*1,0)-IFERROR(E91*1,0)-IFERROR(E94*1,0)-IFERROR(E95*1,0) | F98: =IFERROR(F89*1,0)-IFERROR(F91*1,0)-IFERROR(F94*1,0)-IFERROR(F95*1,0) | G98: =IFERROR(G89*1,0)-IFERROR(G91*1,0)-IFERROR(G94*1,0)-IFERROR(G95*1,0) | H98: =IFERROR(H89*1,0)-IFERROR(H91*1,0)-IFERROR(H94*1,0)-IFERROR(H95*1,0) | I98: =IFERROR(I89*1,0)-IFERROR(I91*1,0)-IFERROR(I94*1,0)-IFERROR(I95*1,0)
A99: Рентабельность чистой прибыли | B99: =IFERROR(IF(B4=0,"-",B98/B4),"-") | C99: =IFERROR(IF(C4=0,"-",C98/C4),"-") | D99: =IFERROR(IF(D4=0,"-",D98/D4),"-") | E99: =IFERROR(IF(E4=0,"-",E98/E4),"-") | F99: =IFERROR(IF(F4=0,"-",F98/F4),"-") | G99: =IFERROR(IF(G4=0,"-",G98/G4),"-") | H99: =IFERROR(IF(H4=0,"-",H98/H4),"-") | I99: =IFERROR(IF(I4=0,"-",I98/I4),"-")

Sheet Астон.Реформа
A1: ПланФакт | B1: Создано с помощью сервиса ПланФакт | I1: =HYPERLINK("https://app.planfact.io/?from=Pf_BDR", "Перейти в сервис")
B2: Итого | C2: июнь` 26 | D2: июль` 26 | E2: август` 26 | F2: сентябрь` 26 | G2: октябрь` 26 | H2: ноябрь` 26 | I2: декабрь` 26
A3: Астон.Реформа | B3: план | C3: план | D3: план | E3: план | F3: план | G3: план | H3: план | I3: план
A4: Выручка | B4: =SUM(B5,B6) | C4: =SUM(C5,C6) | D4: =SUM(D5,D6) | E4: =SUM(E5,E6) | F4: =SUM(F5,F6) | G4: =SUM(G5,G6) | H4: =SUM(H5,H6) | I4: =SUM(I5,I6)
A5: Нераспределенный доход | B5: - | C5: - | D5: - | E5: - | F5: - | G5: - | H5: - | I5: -
A6: Выручка | B6: =SUM(B7,B8,B9) | C6: =SUM(C7,C8,C9) | D6: =SUM(D7,D8,D9) | E6: =SUM(E7,E8,E9) | F6: =SUM(F7,F8,F9) | G6: =SUM(G7,G8,G9) | H6: =SUM(H7,H8,H9) | I6: =SUM(I7,I8,I9)
A7: Реализация услуг Клининг (ОД) | B7: 384000 | C7: 96000 | D7: 96000 | E7: 96000 | F7: 96000 | G7: - | H7: - | I7: -
A8: Реализация услуг Клининг (Доп.услуги) | B8: - | C8: - | D8: - | E8: - | F8: - | G8: - | H8: - | I8: -
A9: Реализация услуг Клининг (снег) | B9: - | C9: - | D9: - | E9: - | F9: - | G9: - | H9: - | I9: -
A10: Прямые расходы | B10: =SUM(B11,B12,B13,B21,B22,B23,B24,B25,B26,B27,B28,B29,B30,B31,B32,B33,B34) | C10: =SUM(C11,C12,C13,C21,C22,C23,C24,C25,C26,C27,C28,C29,C30,C31,C32,C33,C34) | D10: =SUM(D11,D12,D13,D21,D22,D23,D24,D25,D26,D27,D28,D29,D30,D31,D32,D33,D34) | E10: =SUM(E11,E12,E13,E21,E22,E23,E24,E25,E26,E27,E28,E29,E30,E31,E32,E33,E34) | F10: =SUM(F11,F12,F13,F21,F22,F23,F24,F25,F26,F27,F28,F29,F30,F31,F32,F33,F34) | G10: =SUM(G11,G12,G13,G21,G22,G23,G24,G25,G26,G27,G28,G29,G30,G31,G32,G33,G34) | H10: =SUM(H11,H12,H13,H21,H22,H23,H24,H25,H26,H27,H28,H29,H30,H31,H32,H33,H34) | I10: =SUM(I11,I12,I13,I21,I22,I23,I24,I25,I26,I27,I28,I29,I30,I31,I32,I33,I34)
A11: Нераспределенный расход | B11: - | C11: - | D11: - | E11: - | F11: - | G11: - | H11: - | I11: -
A12: Транспортные расходы | B12: - | C12: - | D12: - | E12: - | F12: - | G12: - | H12: - | I12: -
A13: Переменные | B13: =SUM(B14,B15,B16,B17,B18,B19,B20) | C13: =SUM(C14,C15,C16,C17,C18,C19,C20) | D13: =SUM(D14,D15,D16,D17,D18,D19,D20) | E13: =SUM(E14,E15,E16,E17,E18,E19,E20) | F13: =SUM(F14,F15,F16,F17,F18,F19,F20) | G13: =SUM(G14,G15,G16,G17,G18,G19,G20) | H13: =SUM(H14,H15,H16,H17,H18,H19,H20) | I13: =SUM(I14,I15,I16,I17,I18,I19,I20)
A14: Услуги техниги для уборки снега (ПТ) | B14: - | C14: - | D14: - | E14: - | F14: - | G14: - | H14: - | I14: -
A15: Услуги садовника (ПТ) | B15: - | C15: - | D15: - | E15: - | F15: - | G15: - | H15: - | I15: -
A16: Сыпучие материалы (ПТ) | B16: - | C16: - | D16: - | E16: - | F16: - | G16: - | H16: - | I16: -
A17: Расходные материалы и инстументы (МОП) | B17: 8000 | C17: 2000 | D17: 2000 | E17: 2000 | F17: 2000 | G17: - | H17: - | I17: -
A18: Расходные материалы и инстументы (ПТ) | B18: 8000 | C18: 2000 | D18: 2000 | E18: 2000 | F18: 2000 | G18: - | H18: - | I18: -
A19: Арена оборудования (ПТ) | B19: - | C19: - | D19: - | E19: - | F19: - | G19: - | H19: - | I19: -
A20: Арена оборудования (МОП) | B20: - | C20: - | D20: - | E20: - | F20: - | G20: - | H20: - | I20: -
A21: Заработная плата (МОП) | B21: 140000 | C21: 35000 | D21: 35000 | E21: 35000 | F21: 35000 | G21: - | H21: - | I21: -
A22: Заработная плата (ПТ) | B22: 140000 | C22: 35000 | D22: 35000 | E22: 35000 | F22: 35000 | G22: - | H22: - | I22: -
A23: Налоги с ФОТ (МОП) | B23: 42000 | C23: - | D23: 14000 | E23: 14000 | F23: 14000 | G23: - | H23: - | I23: -
A24: Налоги с ФОТ (ПТ) | B24: - | C24: - | D24: - | E24: - | F24: - | G24: - | H24: - | I24: -
A25: Премми (МОП) | B25: - | C25: - | D25: - | E25: - | F25: - | G25: - | H25: - | I25: -
A26: Премми (ПТ) | B26: - | C26: - | D26: - | E26: - | F26: - | G26: - | H26: - | I26: -
A27: Униформа (МОП) | B27: - | C27: - | D27: - | E27: - | F27: - | G27: - | H27: - | I27: -
A28: Униформа (ПТ) | B28: - | C28: - | D28: - | E28: - | F28: - | G28: - | H28: - | I28: -
A29: Ремонт оборудования (МОП) | B29: - | C29: - | D29: - | E29: - | F29: - | G29: - | H29: - | I29: -
A30: Ремонт оборудования (ПТ) | B30: - | C30: - | D30: - | E30: - | F30: - | G30: - | H30: - | I30: -
A31: Вывоз мусора | B31: - | C31: - | D31: - | E31: - | F31: - | G31: - | H31: - | I31: -
A32: Штрафы, пени, неустойки | B32: - | C32: - | D32: - | E32: - | F32: - | G32: - | H32: - | I32: -
A33: Расходы к удержанию | B33: - | C33: - | D33: - | E33: - | F33: - | G33: - | H33: - | I33: -
A34: Общехозяйственные | B34: =SUM(B35,B36,B37,B38,B39,B40,B41,B42) | C34: =SUM(C35,C36,C37,C38,C39,C40,C41,C42) | D34: =SUM(D35,D36,D37,D38,D39,D40,D41,D42) | E34: =SUM(E35,E36,E37,E38,E39,E40,E41,E42) | F34: =SUM(F35,F36,F37,F38,F39,F40,F41,F42) | G34: =SUM(G35,G36,G37,G38,G39,G40,G41,G42) | H34: =SUM(H35,H36,H37,H38,H39,H40,H41,H42) | I34: =SUM(I35,I36,I37,I38,I39,I40,I41,I42)
A35: Аутсорс (направления) | B35: - | C35: - | D35: - | E35: - | F35: - | G35: - | H35: - | I35: -
A36: Заработная плата МО АУП | B36: - | C36: - | D36: - | E36: - | F36: - | G36: - | H36: - | I36: -
A37: Инструменты: ГСМ | B37: - | C37: - | D37: - | E37: - | F37: - | G37: - | H37: - | I37: -
A38: Медосмотры | B38: - | C38: - | D38: - | E38: - | F38: - | G38: - | H38: - | I38: -
A39: Налоги с ФОТ (ИП) | B39: 12000 | C39: 3000 | D39: 3000 | E39: 3000 | F39: 3000 | G39: - | H39: - | I39: -
A40: Приобритение мебели, бытовой техники | B40: - | C40: - | D40: - | E40: - | F40: - | G40: - | H40: - | I40: -
A41: Комиссия за перевод ЗП | B41: - | C41: - | D41: - | E41: - | F41: - | G41: - | H41: - | I41: -
A42: Аренда квартиры (включая коммуналку) | B42: - | C42: - | D42: - | E42: - | F42: - | G42: - | H42: - | I42: -
A43: Валовая прибыль | B43: =B4-B10 | C43: =C4-C10 | D43: =D4-D10 | E43: =E4-E10 | F43: =F4-F10 | G43: =G4-G10 | H43: =H4-H10 | I43: =I4-I10
A44: Валовая рентабельность | B44: =IFERROR(IF(B4=0,"-",B43/B4),"-") | C44: =IFERROR(IF(C4=0,"-",C43/C4),"-") | D44: =IFERROR(IF(D4=0,"-",D43/D4),"-") | E44: =IFERROR(IF(E4=0,"-",E43/E4),"-") | F44: =IFERROR(IF(F4=0,"-",F43/F4),"-") | G44: =IFERROR(IF(G4=0,"-",G43/G4),"-") | H44: =IFERROR(IF(H4=0,"-",H43/H4),"-") | I44: =IFERROR(IF(I4=0,"-",I43/I4),"-")
A45: Косвенные расходы | B45: =SUM(B46,B47,B48,B52,B56,B57,B58,B59,B60,B63,B64,B65,B66,B67,B68,B69,B70,B71,B72,B73,B74,B75,B76,B77,B78,B79) | C45: =SUM(C46,C47,C48,C52,C56,C57,C58,C59,C60,C63,C64,C65,C66,C67,C68,C69,C70,C71,C72,C73,C74,C75,C76,C77,C78,C79) | D45: =SUM(D46,D47,D48,D52,D56,D57,D58,D59,D60,D63,D64,D65,D66,D67,D68,D69,D70,D71,D72,D73,D74,D75,D76,D77,D78,D79) | E45: =SUM(E46,E47,E48,E52,E56,E57,E58,E59,E60,E63,E64,E65,E66,E67,E68,E69,E70,E71,E72,E73,E74,E75,E76,E77,E78,E79) | F45: =SUM(F46,F47,F48,F52,F56,F57,F58,F59,F60,F63,F64,F65,F66,F67,F68,F69,F70,F71,F72,F73,F74,F75,F76,F77,F78,F79) | G45: =SUM(G46,G47,G48,G52,G56,G57,G58,G59,G60,G63,G64,G65,G66,G67,G68,G69,G70,G71,G72,G73,G74,G75,G76,G77,G78,G79) | H45: =SUM(H46,H47,H48,H52,H56,H57,H58,H59,H60,H63,H64,H65,H66,H67,H68,H69,H70,H71,H72,H73,H74,H75,H76,H77,H78,H79) | I45: =SUM(I46,I47,I48,I52,I56,I57,I58,I59,I60,I63,I64,I65,I66,I67,I68,I69,I70,I71,I72,I73,I74,I75,I76,I77,I78,I79)
A46: Расход БЭК-ОФИС | B46: - | C46: - | D46: - | E46: - | F46: - | G46: - | H46: - | I46: -
A47: Расходы на бэк-офис | B47: - | C47: - | D47: - | E47: - | F47: - | G47: - | H47: - | I47: -
A48: Автомобиль | B48: =SUM(B49,B50,B51) | C48: =SUM(C49,C50,C51) | D48: =SUM(D49,D50,D51) | E48: =SUM(E49,E50,E51) | F48: =SUM(F49,F50,F51) | G48: =SUM(G49,G50,G51) | H48: =SUM(H49,H50,H51) | I48: =SUM(I49,I50,I51)
A49: Автомобиль: ГСМ | B49: - | C49: - | D49: - | E49: - | F49: - | G49: - | H49: - | I49: -
A50: Автомобиль: страхование | B50: - | C50: - | D50: - | E50: - | F50: - | G50: - | H50: - | I50: -
A51: Автомобиль: ТО | B51: - | C51: - | D51: - | E51: - | F51: - | G51: - | H51: - | I51: -
A52: Офисные расходы | B52: =SUM(B53,B54,B55) | C52: =SUM(C53,C54,C55) | D52: =SUM(D53,D54,D55) | E52: =SUM(E53,E54,E55) | F52: =SUM(F53,F54,F55) | G52: =SUM(G53,G54,G55) | H52: =SUM(H53,H54,H55) | I52: =SUM(I53,I54,I55)
A53: Аренда офиса | B53: - | C53: - | D53: - | E53: - | F53: - | G53: - | H53: - | I53: -
A54: Канцелярия и обслуживание | B54: - | C54: - | D54: - | E54: - | F54: - | G54: - | H54: - | I54: -
A55: Интернет и связь | B55: - | C55: - | D55: - | E55: - | F55: - | G55: - | H55: - | I55: -
A56: Банковские услуги | B56: - | C56: - | D56: - | E56: - | F56: - | G56: - | H56: - | I56: -
A57: Заработная плата АУП (БО) | B57: - | C57: - | D57: - | E57: - | F57: - | G57: - | H57: - | I57: -
A58: Заработная плата бухгалтерии (БО) | B58: - | C58: - | D58: - | E58: - | F58: - | G58: - | H58: - | I58: -
A59: Заработная плата СБ (БО) | B59: - | C59: - | D59: - | E59: - | F59: - | G59: - | H59: - | I59: -
A60: Командировочные расходы | B60: =SUM(B61,B62) | C60: =SUM(C61,C62) | D60: =SUM(D61,D62) | E60: =SUM(E61,E62) | F60: =SUM(F61,F62) | G60: =SUM(G61,G62) | H60: =SUM(H61,H62) | I60: =SUM(I61,I62)
A61: Командировнчеы расходы: билеты (БО) | B61: - | C61: - | D61: - | E61: - | F61: - | G61: - | H61: - | I61: -
A62: Командировнчеы расходы: проживание (БО) | B62: - | C62: - | D62: - | E62: - | F62: - | G62: - | H62: - | I62: -
A63: Комиссия УК ДОМ | B63: - | C63: - | D63: - | E63: - | F63: - | G63: - | H63: - | I63: -
A64: Налоги с ФОТ (ИП)_БО | B64: - | C64: - | D64: - | E64: - | F64: - | G64: - | H64: - | I64: -
A65: Налоги с ФОТ (НДФЛ) БО | B65: - | C65: - | D65: - | E65: - | F65: - | G65: - | H65: - | I65: -
A66: Налоги с ФОТ (страховые взносы) БО | B66: - | C66: - | D66: - | E66: - | F66: - | G66: - | H66: - | I66: -
A67: Нотариальные услуги | B67: - | C67: - | D67: - | E67: - | F67: - | G67: - | H67: - | I67: -
A68: Обслуживание техники (БО) | B68: - | C68: - | D68: - | E68: - | F68: - | G68: - | H68: - | I68: -
A69: Программное обеспечение (БО) | B69: - | C69: - | D69: - | E69: - | F69: - | G69: - | H69: - | I69: -
A70: ПланФакт | B70: - | C70: - | D70: - | E70: - | F70: - | G70: - | H70: - | I70: -
A71: ТБ | B71: - | C71: - | D71: - | E71: - | F71: - | G71: - | H71: - | I71: -
A72: Контур | B72: - | C72: - | D72: - | E72: - | F72: - | G72: - | H72: - | I72: -
... A79: HR (аутсорс) | B79: - | C79: - | D79: - | E79: - | F79: - | G79: - | H79: - | I79: -
A80: Операционная прибыль | B80: =B43-B45 | C80: =C43-C45 | D80: =D43-D45 | E80: =E43-E45 | F80: =F43-F45 | G80: =G43-G45 | H80: =H43-H45 | I80: =I43-I45
A81: Операционная рентабельность | B81: =IFERROR(IF(B4=0,"-",B80/B4),"-") | C81: =IFERROR(IF(C4=0,"-",C80/C4),"-") | D81: =IFERROR(IF(D4=0,"-",D80/D4),"-") | E81: =IFERROR(IF(E4=0,"-",E80/E4),"-") | F81: =IFERROR(IF(F4=0,"-",F80/F4),"-") | G81: =IFERROR(IF(G4=0,"-",G80/G4),"-") | H81: =IFERROR(IF(H4=0,"-",H80/H4),"-") | I81: =IFERROR(IF(I4=0,"-",I80/I4),"-")
A82: Прочие доходы | B82: =SUM(B83,B84,B85,B86) | C82: =SUM(C83,C84,C85,C86) | D82: =SUM(D83,D84,D85,D86) | E82: =SUM(E83,E84,E85,E86) | F82: =SUM(F83,F84,F85,F86) | G82: =SUM(G83,G84,G85,G86) | H82: =SUM(H83,H84,H85,H86) | I82: =SUM(I83,I84,I85,I86)
A83: Доход БЭК-ОФИС | B83: - | C83: - | D83: - | E83: - | F83: - | G83: - | H83: - | I83: -
A84: Пополненин бэк-офис | B84: - | C84: - | D84: - | E84: - | F84: - | G84: - | H84: - | I84: -
A85: Проценты по вкладам | B85: - | C85: - | D85: - | E85: - | F85: - | G85: - | H85: - | I85: -
A86: Курсовая разница (+) | B86: - | C86: - | D86: - | E86: - | F86: - | G86: - | H86: - | I86: -
A87: Прочие расходы | B87: =SUM(B88) | C87: =SUM(C88) | D87: =SUM(D88) | E87: =SUM(E88) | F87: =SUM(F88) | G87: =SUM(G88) | H87: =SUM(H88) | I87: =SUM(I88)
A88: Курсовая разница (-) | B88: - | C88: - | D88: - | E88: - | F88: - | G88: - | H88: - | I88: -
A89: EBITDA | B89: =B80+IFERROR(B82*1,0)-IFERROR(B87*1,0) | C89: =C80+IFERROR(C82*1,0)-IFERROR(C87*1,0) | D89: =D80+IFERROR(D82*1,0)-IFERROR(D87*1,0) | E89: =E80+IFERROR(E82*1,0)-IFERROR(E87*1,0) | F89: =F80+IFERROR(F82*1,0)-IFERROR(F87*1,0) | G89: =G80+IFERROR(G82*1,0)-IFERROR(G87*1,0) | H89: =H80+IFERROR(H82*1,0)-IFERROR(H87*1,0) | I89: =I80+IFERROR(I82*1,0)-IFERROR(I87*1,0)
A90: Рентабельность по EBITDA | B90: =IFERROR(IF(B4=0,"-",B89/B4),"-") | C90: =IFERROR(IF(C4=0,"-",C89/C4),"-") | D90: =IFERROR(IF(D4=0,"-",D89/D4),"-") | E90: =IFERROR(IF(E4=0,"-",E89/E4),"-") | F90: =IFERROR(IF(F4=0,"-",F89/F4),"-") | G90: =IFERROR(IF(G4=0,"-",G89/G4),"-") | H90: =IFERROR(IF(H4=0,"-",H89/H4),"-") | I90: =IFERROR(IF(I4=0,"-",I89/I4),"-")
A91: Амортизация | B91: =SUM(B92,B93) | C91: =SUM(C92,C93) | D91: =SUM(D92,D93) | E91: =SUM(E92,E93) | F91: =SUM(F92,F93) | G91: =SUM(G92,G93) | H91: =SUM(H92,H93) | I91: =SUM(I92,I93)
A92: Амортизация ОС (ПТ) | B92: - | C92: - | D92: - | E92: - | F92: - | G92: - | H92: - | I92: -
A93: Амортизация ОС (МОП) | B93: - | C93: - | D93: - | E93: - | F93: - | G93: - | H93: - | I93: -
A94: Проценты по кредитам и займам | B94: - | C94: - | D94: - | E94: - | F94: - | G94: - | H94: - | I94: -
A95: Налог на прибыль | B95: =SUM(B96,B97) | C95: =SUM(C96,C97) | D95: =SUM(D96,D97) | E95: =SUM(E96,E97) | F95: =SUM(F96,F97) | G95: =SUM(G96,G97) | H95: =SUM(H96,H97) | I95: =SUM(I96,I97)
A96: Налоги УСН | B96: 26800 | C96: 6700 | D96: 6700 | E96: 6700 | F96: 6700 | G96: - | H96: - | I96: -
A97: Налоги НДС 5% | B97: - | C97: - | D97: - | E97: - | F97: - | G97: - | H97: - | I97: -
A98: Чистая прибыль (убыток) | B98: =IFERROR(B89*1,0)-IFERROR(B91*1,0)-IFERROR(B94*1,0)-IFERROR(B95*1,0) | C98: =IFERROR(C89*1,0)-IFERROR(C91*1,0)-IFERROR(C94*1,0)-IFERROR(C95*1,0) | D98: =IFERROR(D89*1,0)-IFERROR(D91*1,0)-IFERROR(D94*1,0)-IFERROR(D95*1,0) | E98: =IFERROR(E89*1,0)-IFERROR(E91*1,0)-IFERROR(E94*1,0)-IFERROR(E95*1,0) | F98: =IFERROR(F89*1,0)-IFERROR(F91*1,0)-IFERROR(F94*1,0)-IFERROR(F95*1,0) | G98: =IFERROR(G89*1,0)-IFERROR(G91*1,0)-IFERROR(G94*1,0)-IFERROR(G95*1,0) | H98: =IFERROR(H89*1,0)-IFERROR(H91*1,0)-IFERROR(H94*1,0)-IFERROR(H95*1,0) | I98: =IFERROR(I89*1,0)-IFERROR(I91*1,0)-IFERROR(I94*1,0)-IFERROR(I95*1,0)
A99: Рентабельность чистой прибыли | B99: =IFERROR(IF(B4=0,"-",B98/B4),"-") | C99: =IFERROR(IF(C4=0,"-",C98/C4),"-") | D99: =IFERROR(IF(D4=0,"-",D98/D4),"-") | E99: =IFERROR(IF(E4=0,"-",E98/E4),"-") | F99: =IFERROR(IF(F4=0,"-",F98/F4),"-") | G99: =IFERROR(IF(G4=0,"-",G98/G4),"-") | H99: =IFERROR(IF(H4=0,"-",H98/H4),"-") | I99: =IFERROR(IF(I4=0,"-",I98/I4),"-")

Sheet Дом Милый Дом
A1: ПланФакт | B1: Создано с помощью сервиса ПланФакт | I1: =HYPERLINK("https://app.planfact.io/?from=Pf_BDR", "Перейти в сервис")
B2: Итого | C2: июнь` 26 | D2: июль` 26 | E2: август` 26 | F2: сентябрь` 26 | G2: октябрь` 26 | H2: ноябрь` 26 | I2: декабрь` 26
A3: Дом Милый Дом | B3: план | C3: план | D3: план | E3: план | F3: план | G3: план | H3: план | I3: план
A4: Выручка | B4: =SUM(B5,B6) | C4: =SUM(C5,C6) | D4: =SUM(D5,D6) | E4: =SUM(E5,E6) | F4: =SUM(F5,F6) | G4: =SUM(G5,G6) | H4: =SUM(H5,H6) | I4: =SUM(I5,I6)
A5: Нераспределенный доход | B5: - | C5: - | D5: - | E5: - | F5: - | G5: - | H5: - | I5: -
A6: Выручка | B6: =SUM(B7,B8,B9) | C6: =SUM(C7,C8,C9) | D6: =SUM(D7,D8,D9) | E6: =SUM(E7,E8,E9) | F6: =SUM(F7,F8,F9) | G6: =SUM(G7,G8,G9) | H6: =SUM(H7,H8,H9) | I6: =SUM(I7,I8,I9)
A7: Реализация услуг Клининг (ОД) | B7: 2451750.6 | C7: 373920.6 | D7: 692610 | E7: 692610 | F7: 692610 | G7: - | H7: - | I7: -
A8: Реализация услуг Клининг (Доп.услуги) | B8: - | C8: - | D8: - | E8: - | F8: - | G8: - | H8: - | I8: -
A9: Реализация услуг Клининг (снег) | B9: - | C9: - | D9: - | E9: - | F9: - | G9: - | H9: - | I9: -
A10: Прямые расходы | B10: =SUM(B11,B12,B13,B21,B22,B23,B24,B25,B26,B27,B28,B29,B30,B31,B32,B33,B34) | C10: =SUM(C11,C12,C13,C21,C22,C23,C24,C25,C26,C27,C28,C29,C30,C31,C32,C33,C34) | D10: =SUM(D11,D12,D13,D21,D22,D23,D24,D25,D26,D27,D28,D29,D30,D31,D32,D33,D34) | E10: =SUM(E11,E12,E13,E21,E22,E23,E24,E25,E26,E27,E28,E29,E30,E31,E32,E33,E34) | F10: =SUM(F11,F12,F13,F21,F22,F23,F24,F25,F26,F27,F28,F29,F30,F31,F32,F33,F34) | G10: =SUM(G11,G12,G13,G21,G22,G23,G24,G25,G26,G27,G28,G29,G30,G31,G32,G33,G34) | H10: =SUM(H11,H12,H13,H21,H22,H23,H24,H25,H26,H27,H28,H29,H30,H31,H32,H33,H34) | I10: =SUM(I11,I12,I13,I21,I22,I23,I24,I25,I26,I27,I28,I29,I30,I31,I32,I33,I34)
A11: Нераспределенный расход | B11: - | C11: - | D11: - | E11: - | F11: - | G11: - | H11: - | I11: -
A12: Транспортные расходы | B12: - | C12: - | D12: - | E12: - | F12: - | G12: - | H12: - | I12: -
A13: Переменные | B13: =SUM(B14,B15,B16,B17,B18,B19,B20) | C13: =SUM(C14,C15,C16,C17,C18,C19,C20) | D13: =SUM(D14,D15,D16,D17,D18,D19,D20) | E13: =SUM(E14,E15,E16,E17,E18,E19,E20) | F13: =SUM(F14,F15,F16,F17,F18,F19,F20) | G13: =SUM(G14,G15,G16,G17,G18,G19,G20) | H13: =SUM(H14,H15,H16,H17,H18,H19,H20) | I13: =SUM(I14,I15,I16,I17,I18,I19,I20)
A14: Услуги техниги для уборки снега (ПТ) | B14: - | C14: - | D14: - | E14: - | F14: - | G14: - | H14: - | I14: -
A15: Услуги садовника (ПТ) | B15: - | C15: - | D15: - | E15: - | F15: - | G15: - | H15: - | I15: -
A16: Сыпучие материалы (ПТ) | B16: - | C16: - | D16: - | E16: - | F16: - | G16: - | H16: - | I16: -
A17: Расходные материалы и инстументы (МОП) | B17: 120000 | C17: - | D17: 40000 | E17: 40000 | F17: 40000 | G17: - | H17: - | I17: -
A18: Расходные материалы и инстументы (ПТ) | B18: 20000 | C18: 5000 | D18: 5000 | E18: 5000 | F18: 5000 | G18: - | H18: - | I18: -
A19: Арена оборудования (ПТ) | B19: - | C19: - | D19: - | E19: - | F19: - | G19: - | H19: - | I19: -
A20: Арена оборудования (МОП) | B20: 30000 | C20: 30000 | D20: - | E20: - | F20: - | G20: - | H20: - | I20: -
A21: Заработная плата (МОП) | B21: 200000 | C21: 50000 | D21: 50000 | E21: 50000 | F21: 50000 | G21: - | H21: - | I21: -
A22: Заработная плата (ПТ) | B22: 452500 | C22: 62500 | D22: 130000 | E22: 130000 | F22: 130000 | G22: - | H22: - | I22: -
A23: Налоги с ФОТ (МОП) | B23: 45037.68 | C23: 3037.68 | D23: 14000 | E23: 14000 | F23: 14000 | G23: - | H23: - | I23: -
A24: Налоги с ФОТ (ПТ) | B24: - | C24: - | D24: - | E24: - | F24: - | G24: - | H24: - | I24: -
A25: Премми (МОП) | B25: - | C25: - | D25: - | E25: - | F25: - | G25: - | H25: - | I25: -
A26: Премми (ПТ) | B26: - | C26: - | D26: - | E26: - | F26: - | G26: - | H26: - | I26: -
A27: Униформа (МОП) | B27: - | C27: - | D27: - | E27: - | F27: - | G27: - | H27: - | I27: -
A28: Униформа (ПТ) | B28: - | C28: - | D28: - | E28: - | F28: - | G28: - | H28: - | I28: -
A29: Ремонт оборудования (МОП) | B29: - | C29: - | D29: - | E29: - | F29: - | G29: - | H29: - | I29: -
A30: Ремонт оборудования (ПТ) | B30: - | C30: - | D30: - | E30: - | F30: - | G30: - | H30: - | I30: -
A31: Вывоз мусора | B31: - | C31: - | D31: - | E31: - | F31: - | G31: - | H31: - | I31: -
A32: Штрафы, пени, неустойки | B32: - | C32: - | D32: - | E32: - | F32: - | G32: - | H32: - | I32: -
A33: Расходы к удержанию | B33: - | C33: - | D33: - | E33: - | F33: - | G33: - | H33: - | I33: -
A34: Общехозяйственные | B34: =SUM(B35,B36,B37,B38,B39,B40,B41,B42) | C34: =SUM(C35,C36,C37,C38,C39,C40,C41,C42) | D34: =SUM(D35,D36,D37,D38,D39,D40,D41,D42) | E34: =SUM(E35,E36,E37,E38,E39,E40,E41,E42) | F34: =SUM(F35,F36,F37,F38,F39,F40,F41,F42) | G34: =SUM(G35,G36,G37,G38,G39,G40,G41,G42) | H34: =SUM(H35,H36,H37,H38,H39,H40,H41,H42) | I34: =SUM(I35,I36,I37,I38,I39,I40,I41,I42)
A35: Аутсорс (направления) | B35: - | C35: - | D35: - | E35: - | F35: - | G35: - | H35: - | I35: -
A36: Заработная плата МО АУП | B36: 120000 | C36: 30000 | D36: 30000 | E36: 30000 | F36: 30000 | G36: - | H36: - | I36: -
A37: Инструменты: ГСМ | B37: - | C37: - | D37: - | E37: - | F37: - | G37: - | H37: - | I37: -
A38: Медосмотры | B38: - | C38: - | D38: - | E38: - | F38: - | G38: - | H38: - | I38: -
A39: Налоги с ФОТ (ИП) | B39: 39500 | C39: 3500 | D39: 12000 | E39: 12000 | F39: 12000 | G39: - | H39: - | I39: -
A40: Приобритение мебели, бытовой техники | B40: - | C40: - | D40: - | E40: - | F40: - | G40: - | H40: - | I40: -
A41: Комиссия за перевод ЗП | B41: 1500 | C41: - | D41: 500 | E41: 500 | F41: 500 | G41: - | H41: - | I41: -
A42: Аренда квартиры (включая коммуналку) | B42: - | C42: - | D42: - | E42: - | F42: - | G42: - | H42: - | I42: -
A43: Валовая прибыль | B43: =B4-B10 | C43: =C4-C10 | D43: =D4-D10 | E43: =E4-E10 | F43: =F4-F10 | G43: =G4-G10 | H43: =H4-H10 | I43: =I4-I10
A44: Валовая рентабельность | B44: =IFERROR(IF(B4=0,"-",B43/B4),"-") | C44: =IFERROR(IF(C4=0,"-",C43/C4),"-") | D44: =IFERROR(IF(D4=0,"-",D43/D4),"-") | E44: =IFERROR(IF(E4=0,"-",E43/E4),"-") | F44: =IFERROR(IF(F4=0,"-",F43/F4),"-") | G44: =IFERROR(IF(G4=0,"-",G43/G4),"-") | H44: =IFERROR(IF(H4=0,"-",H43/H4),"-") | I44: =IFERROR(IF(I4=0,"-",I43/I4),"-")
A45: Косвенные расходы | B45: =SUM(B46,B47,B48,B52,B56,B57,B58,B59,B60,B63,B64,B65,B66,B67,B68,B69,B70,B71,B72,B73,B74,B75,B76,B77,B78,B79) | C45: =SUM(C46,C47,C48,C52,C56,C57,C58,C59,C60,C63,C64,C65,C66,C67,C68,C69,C70,C71,C72,C73,C74,C75,C76,C77,C78,C79) | D45: =SUM(D46,D47,D48,D52,D56,D57,D58,D59,D60,D63,D64,D65,D66,D67,D68,D69,D70,D71,D72,D73,D74,D75,D76,D77,D78,D79) | E45: =SUM(E46,E47,E48,E52,E56,E57,E58,E59,E60,E63,E64,E65,E66,E67,E68,E69,E70,E71,E72,E73,E74,E75,E76,E77,E78,E79) | F45: =SUM(F46,F47,F48,F52,F56,F57,F58,F59,F60,F63,F64,F65,F66,F67,F68,F69,F70,F71,F72,F73,F74,F75,F76,F77,F78,F79) | G45: =SUM(G46,G47,G48,G52,G56,G57,G58,G59,G60,G63,G64,G65,G66,G67,G68,G69,G70,G71,G72,G73,G74,G75,G76,G77,G78,G79) | H45: =SUM(H46,H47,H48,H52,H56,H57,H58,H59,H60,H63,H64,H65,H66,H67,H68,H69,H70,H71,H72,H73,H74,H75,H76,H77,H78,H79) | I45: =SUM(I46,I47,I48,I52,I56,I57,I58,I59,I60,I63,I64,I65,I66,I67,I68,I69,I70,I71,I72,I73,I74,I75,I76,I77,I78,I79)
A46: Расход БЭК-ОФИС | B46: - | C46: - | D46: - | E46: - | F46: - | G46: - | H46: - | I46: -
A47: Расходы на бэк-офис | B47: - | C47: - | D47: - | E47: - | F47: - | G47: - | H47: - | I47: -
A48: Автомобиль | B48: =SUM(B49,B50,B51) | C48: =SUM(C49,C50,C51) | D48: =SUM(D49,D50,D51) | E48: =SUM(E49,E50,E51) | F48: =SUM(F49,F50,F51) | G48: =SUM(G49,G50,G51) | H48: =SUM(H49,H50,H51) | I48: =SUM(I49,I50,I51)
A49: Автомобиль: ГСМ | B49: - | C49: - | D49: - | E49: - | F49: - | G49: - | H49: - | I49: -
A50: Автомобиль: страхование | B50: - | C50: - | D50: - | E50: - | F50: - | G50: - | H50: - | I50: -
A51: Автомобиль: ТО | B51: - | C51: - | D51: - | E51: - | F51: - | G51: - | H51: - | I51: -
A52: Офисные расходы | B52: =SUM(B53,B54,B55) | C52: =SUM(C53,C54,C55) | D52: =SUM(D53,D54,D55) | E52: =SUM(E53,E54,E55) | F52: =SUM(F53,F54,F55) | G52: =SUM(G53,G54,G55) | H52: =SUM(H53,H54,H55) | I52: =SUM(I53,I54,I55)
A53: Аренда офиса | B53: - | C53: - | D53: - | E53: - | F53: - | G53: - | H53: - | I53: -
A54: Канцелярия и обслуживание | B54: - | C54: - | D54: - | E54: - | F54: - | G54: - | H54: - | I54: -
A55: Интернет и связь | B55: - | C55: - | D55: - | E55: - | F55: - | G55: - | H55: - | I55: -
A56: Банковские услуги | B56: - | C56: - | D56: - | E56: - | F56: - | G56: - | H56: - | I56: -
A57: Заработная плата АУП (БО) | B57: - | C57: - | D57: - | E57: - | F57: - | G57: - | H57: - | I57: -
A58: Заработная плата бухгалтерии (БО) | B58: - | C58: - | D58: - | E58: - | F58: - | G58: - | H58: - | I58: -
A59: Заработная плата СБ (БО) | B59: - | C59: - | D59: - | E59: - | F59: - | G59: - | H59: - | I59: -
A60: Командировочные расходы | B60: =SUM(B61,B62) | C60: =SUM(C61,C62) | D60: =SUM(D61,D62) | E60: =SUM(E61,E62) | F60: =SUM(F61,F62) | G60: =SUM(G61,G62) | H60: =SUM(H61,H62) | I60: =SUM(I61,I62)
A61: Командировнчеы расходы: билеты (БО) | B61: - | C61: - | D61: - | E61: - | F61: - | G61: - | H61: - | I61: -
A62: Командировнчеы расходы: проживание (БО) | B62: - | C62: - | D62: - | E62: - | F62: - | G62: - | H62: - | I62: -
A63: Комиссия УК ДОМ | B63: - | C63: - | D63: - | E63: - | F63: - | G63: - | H63: - | I63: -
A64: Налоги с ФОТ (ИП)_БО | B64: - | C64: - | D64: - | E64: - | F64: - | G64: - | H64: - | I64: -
A65: Налоги с ФОТ (НДФЛ) БО | B65: - | C65: - | D65: - | E65: - | F65: - | G65: - | H65: - | I65: -
A66: Налоги с ФОТ (страховые взносы) БО | B66: - | C66: - | D66: - | E66: - | F66: - | G66: - | H66: - | I66: -
A67: Нотариальные услуги | B67: - | C67: - | D67: - | E67: - | F67: - | G67: - | H67: - | I67: -
A68: Обслуживание техники (БО) | B68: - | C68: - | D68: - | E68: - | F68: - | G68: - | H68: - | I68: -
A69: Программное обеспечение (БО) | B69: - | C69: - | D69: - | E69: - | F69: - | G69: - | H69: - | I69: -
A70: ПланФакт | B70: - | C70: - | D70: - | E70: - | F70: - | G70: - | H70: - | I70: -
A71: ТБ | B71: - | C71: - | D71: - | E71: - | F71: - | G71: - | H71: - | I71: -
A72: Контур | B72: - | C72: - | D72: - | E72: - | F72: - | G72: - | H72: - | I72: -
... A79: HR (аутсорс) | B79: - | C79: - | D79: - | E79: - | F79: - | G79: - | H79: - | I79: -
A80: Операционная прибыль | B80: =B43-B45 | C80: =C43-C45 | D80: =D43-D45 | E80: =E43-E45 | F80: =F43-F45 | G80: =G43-G45 | H80: =H43-H45 | I80: =I43-I45
A81: Операционная рентабельность | B81: =IFERROR(IF(B4=0,"-",B80/B4),"-") | C81: =IFERROR(IF(C4=0,"-",C80/C4),"-") | D81: =IFERROR(IF(D4=0,"-",D80/D4),"-") | E81: =IFERROR(IF(E4=0,"-",E80/E4),"-") | F81: =IFERROR(IF(F4=0,"-",F80/F4),"-") | G81: =IFERROR(IF(G4=0,"-",G80/G4),"-") | H81: =IFERROR(IF(H4=0,"-",H80/H4),"-") | I81: =IFERROR(IF(I4=0,"-",I80/I4),"-")
A82: Прочие доходы | B82: =SUM(B83,B84,B85,B86) | C82: =SUM(C83,C84,C85,C86) | D82: =SUM(D83,D84,D85,D86) | E82: =SUM(E83,E84,E85,E86) | F82: =SUM(F83,F84,F85,F86) | G82: =SUM(G83,G84,G85,G86) | H82: =SUM(H83,H84,H85,H86) | I82: =SUM(I83,I84,I85,I86)
A83: Доход БЭК-ОФИС | B83: - | C83: - | D83: - | E83: - | F83: - | G83: - | H83: - | I83: -
A84: Пополненин бэк-офис | B84: - | C84: - | D84: - | E84: - | F84: - | G84: - | H84: - | I84: -
A85: Проценты по вкладам | B85: - | C85: - | D85: - | E85: - | F85: - | G85: - | H85: - | I85: -
A86: Курсовая разница (+) | B86: - | C86: - | D86: - | E86: - | F86: - | G86: - | H86: - | I86: -
A87: Прочие расходы | B87: =SUM(B88) | C87: =SUM(C88) | D87: =SUM(D88) | E87: =SUM(E88) | F87: =SUM(F88) | G87: =SUM(G88) | H87: =SUM(H88) | I87: =SUM(I88)
A88: Курсовая разница (-) | B88: - | C88: - | D88: - | E88: - | F88: - | G88: - | H88: - | I88: -
A89: EBITDA | B89: =B80+IFERROR(B82*1,0)-IFERROR(B87*1,0) | C89: =C80+IFERROR(C82*1,0)-IFERROR(C87*1,0) | D89: =D80+IFERROR(D82*1,0)-IFERROR(D87*1,0) | E89: =E80+IFERROR(E82*1,0)-IFERROR(E87*1,0) | F89: =F80+IFERROR(F82*1,0)-IFERROR(F87*1,0) | G89: =G80+IFERROR(G82*1,0)-IFERROR(G87*1,0) | H89: =H80+IFERROR(H82*1,0)-IFERROR(H87*1,0) | I89: =I80+IFERROR(I82*1,0)-IFERROR(I87*1,0)
A90: Рентабельность по EBITDA | B90: =IFERROR(IF(B4=0,"-",B89/B4),"-") | C90: =IFERROR(IF(C4=0,"-",C89/C4),"-") | D90: =IFERROR(IF(D4=0,"-",D89/D4),"-") | E90: =IFERROR(IF(E4=0,"-",E89/E4),"-") | F90: =IFERROR(IF(F4=0,"-",F89/F4),"-") | G90: =IFERROR(IF(G4=0,"-",G89/G4),"-") | H90: =IFERROR(IF(H4=0,"-",H89/H4),"-") | I90: =IFERROR(IF(I4=0,"-",I89/I4),"-")
A91: Амортизация | B91: =SUM(B92,B93) | C91: =SUM(C92,C93) | D91: =SUM(D92,D93) | E91: =SUM(E92,E93) | F91: =SUM(F92,F93) | G91: =SUM(G92,G93) | H91: =SUM(H92,H93) | I91: =SUM(I92,I93)
A92: Амортизация ОС (ПТ) | B92: - | C92: - | D92: - | E92: - | F92: - | G92: - | H92: - | I92: -
A93: Амортизация ОС (МОП) | B93: 225000 | C93: - | D93: 225000 | E93: - | F93: - | G93: - | H93: - | I93: -
A94: Проценты по кредитам и займам | B94: - | C94: - | D94: - | E94: - | F94: - | G94: - | H94: - | I94: -
A95: Налог на прибыль | B95: =SUM(B96,B97) | C95: =SUM(C96,C97) | D95: =SUM(D96,D97) | E95: =SUM(E96,E97) | F95: =SUM(F96,F97) | G95: =SUM(G96,G97) | H95: =SUM(H96,H97) | I95: =SUM(I96,I97)
A96: Налоги УСН | B96: 36900 | C96: 5700 | D96: 10400 | E96: 10400 | F96: 10400 | G96: - | H96: - | I96: -
A97: Налоги НДС 5% | B97: 121695.74 | C97: 17805.74 | D97: 34630 | E97: 34630 | F97: 34630 | G97: - | H97: - | I97: -
A98: Чистая прибыль (убыток) | B98: =IFERROR(B89*1,0)-IFERROR(B91*1,0)-IFERROR(B94*1,0)-IFERROR(B95*1,0) | C98: =IFERROR(C89*1,0)-IFERROR(C91*1,0)-IFERROR(C94*1,0)-IFERROR(C95*1,0) | D98: =IFERROR(D89*1,0)-IFERROR(D91*1,0)-IFERROR(D94*1,0)-IFERROR(D95*1,0) | E98: =IFERROR(E89*1,0)-IFERROR(E91*1,0)-IFERROR(E94*1,0)-IFERROR(E95*1,0) | F98: =IFERROR(F89*1,0)-IFERROR(F91*1,0)-IFERROR(F94*1,0)-IFERROR(F95*1,0) | G98: =IFERROR(G89*1,0)-IFERROR(G91*1,0)-IFERROR(G94*1,0)-IFERROR(G95*1,0) | H98: =IFERROR(H89*1,0)-IFERROR(H91*1,0)-IFERROR(H94*1,0)-IFERROR(H95*1,0) | I98: =IFERROR(I89*1,0)-IFERROR(I91*1,0)-IFERROR(I94*1,0)-IFERROR(I95*1,0)
A99: Рентабельность чистой прибыли | B99: =IFERROR(IF(B4=0,"-",B98/B4),"-") | C99: =IFERROR(IF(C4=0,"-",C98/C4),"-") | D99: =IFERROR(IF(D4=0,"-",D98/D4),"-") | E99: =IFERROR(IF(E4=0,"-",E98/E4),"-") | F99: =IFERROR(IF(F4=0,"-",F98/F4),"-") | G99: =IFERROR(IF(G4=0,"-",G98/G4),"-") | H99: =IFERROR(IF(H4=0,"-",H98/H4),"-") | I99: =IFERROR(IF(I4=0,"-",I98/I4),"-")

Sheet River Park
A1: ПланФакт | B1: Создано с помощью сервиса ПланФакт | I1: =HYPERLINK("https://app.planfact.io/?from=Pf_BDR", "Перейти в сервис")
B2: Итого | C2: июнь` 26 | D2: июль` 26 | E2: август` 26 | F2: сентябрь` 26 | G2: октябрь` 26 | H2: ноябрь` 26 | I2: декабрь` 26
A3: River Park | B3: план | C3: план | D3: план | E3: план | F3: план | G3: план | H3: план | I3: план
A4: Выручка | B4: =SUM(B5,B6) | C4: =SUM(C5,C6) | D4: =SUM(D5,D6) | E4: =SUM(E5,E6) | F4: =SUM(F5,F6) | G4: =SUM(G5,G6) | H4: =SUM(H5,H6) | I4: =SUM(I5,I6)
A5: Нераспределенный доход | B5: - | C5: - | D5: - | E5: - | F5: - | G5: - | H5: - | I5: -
A6: Выручка | B6: =SUM(B7,B8,B9) | C6: =SUM(C7,C8,C9) | D6: =SUM(D7,D8,D9) | E6: =SUM(E7,E8,E9) | F6: =SUM(F7,F8,F9) | G6: =SUM(G7,G8,G9) | H6: =SUM(H7,H8,H9) | I6: =SUM(I7,I8,I9)
A7: Реализация услуг Клининг (ОД) | B7: 2539080 | C7: 846360 | D7: 846360 | E7: 846360 | F7: - | G7: - | H7: - | I7: -
A8: Реализация услуг Клининг (Доп.услуги) | B8: - | C8: - | D8: - | E8: - | F8: - | G8: - | H8: - | I8: -
A9: Реализация услуг Клининг (снег) | B9: - | C9: - | D9: - | E9: - | F9: - | G9: - | H9: - | I9: -
A10: Прямые расходы | B10: =SUM(B11,B12,B13,B21,B22,B23,B24,B25,B26,B27,B28,B29,B30,B31,B32,B33,B34) | C10: =SUM(C11,C12,C13,C21,C22,C23,C24,C25,C26,C27,C28,C29,C30,C31,C32,C33,C34) | D10: =SUM(D11,D12,D13,D21,D22,D23,D24,D25,D26,D27,D28,D29,D30,D31,D32,D33,D34) | E10: =SUM(E11,E12,E13,E21,E22,E23,E24,E25,E26,E27,E28,E29,E30,E31,E32,E33,E34) | F10: =SUM(F11,F12,F13,F21,F22,F23,F24,F25,F26,F27,F28,F29,F30,F31,F32,F33,F34) | G10: =SUM(G11,G12,G13,G21,G22,G23,G24,G25,G26,G27,G28,G29,G30,G31,G32,G33,G34) | H10: =SUM(H11,H12,H13,H21,H22,H23,H24,H25,H26,H27,H28,H29,H30,H31,H32,H33,H34) | I10: =SUM(I11,I12,I13,I21,I22,I23,I24,I25,I26,I27,I28,I29,I30,I31,I32,I33,I34)
A11: Нераспределенный расход | B11: - | C11: - | D11: - | E11: - | F11: - | G11: - | H11: - | I11: -
A12: Транспортные расходы | B12: 10352 | C12: 10352 | D12: - | E12: - | F12: - | G12: - | H12: - | I12: -
A13: Переменные | B13: =SUM(B14,B15,B16,B17,B18,B19,B20) | C13: =SUM(C14,C15,C16,C17,C18,C19,C20) | D13: =SUM(D14,D15,D16,D17,D18,D19,D20) | E13: =SUM(E14,E15,E16,E17,E18,E19,E20) | F13: =SUM(F14,F15,F16,F17,F18,F19,F20) | G13: =SUM(G14,G15,G16,G17,G18,G19,G20) | H13: =SUM(H14,H15,H16,H17,H18,H19,H20) | I13: =SUM(I14,I15,I16,I17,I18,I19,I20)
A14: Услуги техниги для уборки снега (ПТ) | B14: - | C14: - | D14: - | E14: - | F14: - | G14: - | H14: - | I14: -
A15: Услуги садовника (ПТ) | B15: - | C15: - | D15: - | E15: - | F15: - | G15: - | H15: - | I15: -
A16: Сыпучие материалы (ПТ) | B16: - | C16: - | D16: - | E16: - | F16: - | G16: - | H16: - | I16: -
A17: Расходные материалы и инстументы (МОП) | B17: 32073.9 | C17: 22073.9 | D17: 5000 | E17: 5000 | F17: - | G17: - | H17: - | I17: -
A18: Расходные материалы и инстументы (ПТ) | B18: 18643.49 | C18: 8643.49 | D18: 5000 | E18: 5000 | F18: - | G18: - | H18: - | I18: -
A19: Арена оборудования (ПТ) | B19: - | C19: - | D19: - | E19: - | F19: - | G19: - | H19: - | I19: -
A20: Арена оборудования (МОП) | B20: - | C20: - | D20: - | E20: - | F20: - | G20: - | H20: - | I20: -
A21: Заработная плата (МОП) | B21: 820000 | C21: 260000 | D21: 280000 | E21: 280000 | F21: - | G21: - | H21: - | I21: -
A22: Заработная плата (ПТ) | B22: 810000 | C22: 270000 | D22: 270000 | E22: 270000 | F22: - | G22: - | H22: - | I22: -
A23: Налоги с ФОТ (МОП) | B23: - | C23: - | D23: - | E23: - | F23: - | G23: - | H23: - | I23: -
A24: Налоги с ФОТ (ПТ) | B24: - | C24: - | D24: - | E24: - | F24: - | G24: - | H24: - | I24: -
A25: Премми (МОП) | B25: - | C25: - | D25: - | E25: - | F25: - | G25: - | H25: - | I25: -
A26: Премми (ПТ) | B26: - | C26: - | D26: - | E26: - | F26: - | G26: - | H26: - | I26: -
A27: Униформа (МОП) | B27: - | C27: - | D27: - | E27: - | F27: - | G27: - | H27: - | I27: -
A28: Униформа (ПТ) | B28: - | C28: - | D28: - | E28: - | F28: - | G28: - | H28: - | I28: -
A29: Ремонт оборудования (МОП) | B29: - | C29: - | D29: - | E29: - | F29: - | G29: - | H29: - | I29: -
A30: Ремонт оборудования (ПТ) | B30: 8000 | C30: 2000 | D30: 3000 | E30: 3000 | F30: - | G30: - | H30: - | I30: -
A31: Вывоз мусора | B31: 7920 | C31: 7920 | D31: - | E31: - | F31: - | G31: - | H31: - | I31: -
A32: Штрафы, пени, неустойки | B32: - | C32: - | D32: - | E32: - | F32: - | G32: - | H32: - | I32: -
A33: Расходы к удержанию | B33: - | C33: - | D33: - | E33: - | F33: - | G33: - | H33: - | I33: -
A34: Общехозяйственные | B34: =SUM(B35,B36,B37,B38,B39,B40,B41,B42) | C34: =SUM(C35,C36,C37,C38,C39,C40,C41,C42) | D34: =SUM(D35,D36,D37,D38,D39,D40,D41,D42) | E34: =SUM(E35,E36,E37,E38,E39,E40,E41,E42) | F34: =SUM(F35,F36,F37,F38,F39,F40,F41,F42) | G34: =SUM(G35,G36,G37,G38,G39,G40,G41,G42) | H34: =SUM(H35,H36,H37,H38,H39,H40,H41,H42) | I34: =SUM(I35,I36,I37,I38,I39,I40,I41,I42)
A35: Аутсорс (направления) | B35: 12500 | C35: 7500 | D35: 2500 | E35: 2500 | F35: - | G35: - | H35: - | I35: -
A36: Заработная плата МО АУП | B36: 195000 | C36: 65000 | D36: 65000 | E36: 65000 | F36: - | G36: - | H36: - | I36: -
A37: Инструменты: ГСМ | B37: 8620 | C37: 2620 | D37: 3000 | E37: 3000 | F37: - | G37: - | H37: - | I37: -
A38: Медосмотры | B38: - | C38: - | D38: - | E38: - | F38: - | G38: - | H38: - | I38: -
A39: Налоги с ФОТ (ИП) | B39: 159000 | C39: 53000 | D39: 53000 | E39: 53000 | F39: - | G39: - | H39: - | I39: -
A40: Приобритение мебели, бытовой техники | B40: - | C40: - | D40: - | E40: - | F40: - | G40: - | H40: - | I40: -
A41: Комиссия за перевод ЗП | B41: 6000 | C41: 2000 | D41: 2000 | E41: 2000 | F41: - | G41: - | H41: - | I41: -
A42: Аренда квартиры (включая коммуналку) | B42: - | C42: - | D42: - | E42: - | F42: - | G42: - | H42: - | I42: -
A43: Валовая прибыль | B43: =B4-B10 | C43: =C4-C10 | D43: =D4-D10 | E43: =E4-E10 | F43: =F4-F10 | G43: =G4-G10 | H43: =H4-H10 | I43: =I4-I10
A44: Валовая рентабельность | B44: =IFERROR(IF(B4=0,"-",B43/B4),"-") | C44: =IFERROR(IF(C4=0,"-",C43/C4),"-") | D44: =IFERROR(IF(D4=0,"-",D43/D4),"-") | E44: =IFERROR(IF(E4=0,"-",E43/E4),"-") | F44: =IFERROR(IF(F4=0,"-",F43/F4),"-") | G44: =IFERROR(IF(G4=0,"-",G43/G4),"-") | H44: =IFERROR(IF(H4=0,"-",H43/H4),"-") | I44: =IFERROR(IF(I4=0,"-",I43/I4),"-")
A45: Косвенные расходы | B45: =SUM(B46,B47,B48,B52,B56,B57,B58,B59,B60,B63,B64,B65,B66,B67,B68,B69,B70,B71,B72,B73,B74,B75,B76,B77,B78,B79) | C45: =SUM(C46,C47,C48,C52,C56,C57,C58,C59,C60,C63,C64,C65,C66,C67,C68,C69,C70,C71,C72,C73,C74,C75,C76,C77,C78,C79) | D45: =SUM(D46,D47,D48,D52,D56,D57,D58,D59,D60,D63,D64,D65,D66,D67,D68,D69,D70,D71,D72,D73,D74,D75,D76,D77,D78,D79) | E45: =SUM(E46,E47,E48,E52,E56,E57,E58,E59,E60,E63,E64,E65,E66,E67,E68,E69,E70,E71,E72,E73,E74,E75,E76,E77,E78,E79) | F45: =SUM(F46,F47,F48,F52,F56,F57,F58,F59,F60,F63,F64,F65,F66,F67,F68,F69,F70,F71,F72,F73,F74,F75,F76,F77,F78,F79) | G45: =SUM(G46,G47,G48,G52,G56,G57,G58,G59,G60,G63,G64,G65,G66,G67,G68,G69,G70,G71,G72,G73,G74,G75,G76,G77,G78,G79) | H45: =SUM(H46,H47,H48,H52,H56,H57,H58,H59,H60,H63,H64,H65,H66,H67,H68,H69,H70,H71,H72,H73,H74,H75,H76,H77,H78,H79) | I45: =SUM(I46,I47,I48,I52,I56,I57,I58,I59,I60,I63,I64,I65,I66,I67,I68,I69,I70,I71,I72,I73,I74,I75,I76,I77,I78,I79)
A46: Расход БЭК-ОФИС | B46: - | C46: - | D46: - | E46: - | F46: - | G46: - | H46: - | I46: -
A47: Расходы на бэк-офис | B47: - | C47: - | D47: - | E47: - | F47: - | G47: - | H47: - | I47: -
A48: Автомобиль | B48: =SUM(B49,B50,B51) | C48: =SUM(C49,C50,C51) | D48: =SUM(D49,D50,D51) | E48: =SUM(E49,E50,E51) | F48: =SUM(F49,F50,F51) | G48: =SUM(G49,G50,G51) | H48: =SUM(H49,H50,H51) | I48: =SUM(I49,I50,I51)
A49: Автомобиль: ГСМ | B49: - | C49: - | D49: - | E49: - | F49: - | G49: - | H49: - | I49: -
A50: Автомобиль: страхование | B50: - | C50: - | D50: - | E50: - | F50: - | G50: - | H50: - | I50: -
A51: Автомобиль: ТО | B51: - | C51: - | D51: - | E51: - | F51: - | G51: - | H51: - | I51: -
A52: Офисные расходы | B52: =SUM(B53,B54,B55) | C52: =SUM(C53,C54,C55) | D52: =SUM(D53,D54,D55) | E52: =SUM(E53,E54,E55) | F52: =SUM(F53,F54,F55) | G52: =SUM(G53,G54,G55) | H52: =SUM(H53,H54,H55) | I52: =SUM(I53,I54,I55)
A53: Аренда офиса | B53: - | C53: - | D53: - | E53: - | F53: - | G53: - | H53: - | I53: -
A54: Канцелярия и обслуживание | B54: - | C54: - | D54: - | E54: - | F54: - | G54: - | H54: - | I54: -
A55: Интернет и связь | B55: - | C55: - | D55: - | E55: - | F55: - | G55: - | H55: - | I55: -
A56: Банковские услуги | B56: - | C56: - | D56: - | E56: - | F56: - | G56: - | H56: - | I56: -
A57: Заработная плата АУП (БО) | B57: - | C57: - | D57: - | E57: - | F57: - | G57: - | H57: - | I57: -
A58: Заработная плата бухгалтерии (БО) | B58: - | C58: - | D58: - | E58: - | F58: - | G58: - | H58: - | I58: -
A59: Заработная плата СБ (БО) | B59: - | C59: - | D59: - | E59: - | F59: - | G59: - | H59: - | I59: -
A60: Командировочные расходы | B60: =SUM(B61,B62) | C60: =SUM(C61,C62) | D60: =SUM(D61,D62) | E60: =SUM(E61,E62) | F60: =SUM(F61,F62) | G60: =SUM(G61,G62) | H60: =SUM(H61,H62) | I60: =SUM(I61,I62)
A61: Командировнчеы расходы: билеты (БО) | B61: - | C61: - | D61: - | E61: - | F61: - | G61: - | H61: - | I61: -
A62: Командировнчеы расходы: проживание (БО) | B62: - | C62: - | D62: - | E62: - | F62: - | G62: - | H62: - | I62: -
A63: Комиссия УК ДОМ | B63: - | C63: - | D63: - | E63: - | F63: - | G63: - | H63: - | I63: -
A64: Налоги с ФОТ (ИП)_БО | B64: - | C64: - | D64: - | E64: - | F64: - | G64: - | H64: - | I64: -
A65: Налоги с ФОТ (НДФЛ) БО | B65: - | C65: - | D65: - | E65: - | F65: - | G65: - | H65: - | I65: -
A66: Налоги с ФОТ (страховые взносы) БО | B66: - | C66: - | D66: - | E66: - | F66: - | G66: - | H66: - | I66: -
A67: Нотариальные услуги | B67: - | C67: - | D67: - | E67: - | F67: - | G67: - | H67: - | I67: -
A68: Обслуживание техники (БО) | B68: - | C68: - | D68: - | E68: - | F68: - | G68: - | H68: - | I68: -
A69: Программное обеспечение (БО) | B69: - | C69: - | D69: - | E69: - | F69: - | G69: - | H69: - | I69: -
A70: ПланФакт | B70: - | C70: - | D70: - | E70: - | F70: - | G70: - | H70: - | I70: -
A71: ТБ | B71: - | C71: - | D71: - | E71: - | F71: - | G71: - | H71: - | I71: -
A72: Контур | B72: - | C72: - | D72: - | E72: - | F72: - | G72: - | H72: - | I72: -
... A79: HR (аутсорс) | B79: - | C79: - | D79: - | E79: - | F79: - | G79: - | H79: - | I79: -
A80: Операционная прибыль | B80: =B43-B45 | C80: =C43-C45 | D80: =D43-D45 | E80: =E43-E45 | F80: =F43-F45 | G80: =G43-G45 | H80: =H43-H45 | I80: =I43-I45
A81: Операционная рентабельность | B81: =IFERROR(IF(B4=0,"-",B80/B4),"-") | C81: =IFERROR(IF(C4=0,"-",C80/C4),"-") | D81: =IFERROR(IF(D4=0,"-",D80/D4),"-") | E81: =IFERROR(IF(E4=0,"-",E80/E4),"-") | F81: =IFERROR(IF(F4=0,"-",F80/F4),"-") | G81: =IFERROR(IF(G4=0,"-",G80/G4),"-") | H81: =IFERROR(IF(H4=0,"-",H80/H4),"-") | I81: =IFERROR(IF(I4=0,"-",I80/I4),"-")
A82: Прочие доходы | B82: =SUM(B83,B84,B85,B86) | C82: =SUM(C83,C84,C85,C86) | D82: =SUM(D83,D84,D85,D86) | E82: =SUM(E83,E84,E85,E86) | F82: =SUM(F83,F84,F85,F86) | G82: =SUM(G83,G84,G85,G86) | H82: =SUM(H83,H84,H85,H86) | I82: =SUM(I83,I84,I85,I86)
A83: Доход БЭК-ОФИС | B83: - | C83: - | D83: - | E83: - | F83: - | G83: - | H83: - | I83: -
A84: Пополненин бэк-офис | B84: - | C84: - | D84: - | E84: - | F84: - | G84: - | H84: - | I84: -
A85: Проценты по вкладам | B85: - | C85: - | D85: - | E85: - | F85: - | G85: - | H85: - | I85: -
A86: Курсовая разница (+) | B86: - | C86: - | D86: - | E86: - | F86: - | G86: - | H86: - | I86: -
A87: Прочие расходы | B87: =SUM(B88) | C87: =SUM(C88) | D87: =SUM(D88) | E87: =SUM(E88) | F87: =SUM(F88) | G87: =SUM(G88) | H87: =SUM(H88) | I87: =SUM(I88)
A88: Курсовая разница (-) | B88: - | C88: - | D88: - | E88: - | F88: - | G88: - | H88: - | I88: -
A89: EBITDA | B89: =B80+IFERROR(B82*1,0)-IFERROR(B87*1,0) | C89: =C80+IFERROR(C82*1,0)-IFERROR(C87*1,0) | D89: =D80+IFERROR(D82*1,0)-IFERROR(D87*1,0) | E89: =E80+IFERROR(E82*1,0)-IFERROR(E87*1,0) | F89: =F80+IFERROR(F82*1,0)-IFERROR(F87*1,0) | G89: =G80+IFERROR(G82*1,0)-IFERROR(G87*1,0) | H89: =H80+IFERROR(H82*1,0)-IFERROR(H87*1,0) | I89: =I80+IFERROR(I82*1,0)-IFERROR(I87*1,0)
A90: Рентабельность по EBITDA | B90: =IFERROR(IF(B4=0,"-",B89/B4),"-") | C90: =IFERROR(IF(C4=0,"-",C89/C4),"-") | D90: =IFERROR(IF(D4=0,"-",D89/D4),"-") | E90: =IFERROR(IF(E4=0,"-",E89/E4),"-") | F90: =IFERROR(IF(F4=0,"-",F89/F4),"-") | G90: =IFERROR(IF(G4=0,"-",G89/G4),"-") | H90: =IFERROR(IF(H4=0,"-",H89/H4),"-") | I90: =IFERROR(IF(I4=0,"-",I89/I4),"-")
A91: Амортизация | B91: =SUM(B92,B93) | C91: =SUM(C92,C93) | D91: =SUM(D92,D93) | E91: =SUM(E92,E93) | F91: =SUM(F92,F93) | G91: =SUM(G92,G93) | H91: =SUM(H92,H93) | I91: =SUM(I92,I93)
A92: Амортизация ОС (ПТ) | B92: - | C92: - | D92: - | E92: - | F92: - | G92: - | H92: - | I92: -
A93: Амортизация ОС (МОП) | B93: - | C93: - | D93: - | E93: - | F93: - | G93: - | H93: - | I93: -
A94: Проценты по кредитам и займам | B94: - | C94: - | D94: - | E94: - | F94: - | G94: - | H94: - | I94: -
A95: Налог на прибыль | B95: =SUM(B96,B97) | C95: =SUM(C96,C97) | D95: =SUM(D96,D97) | E95: =SUM(E96,E97) | F95: =SUM(F96,F97) | G95: =SUM(G96,G97) | H95: =SUM(H96,H97) | I95: =SUM(I96,I97)
A96: Налоги УСН | B96: 36000 | C96: 12000 | D96: 12000 | E96: 12000 | F96: - | G96: - | H96: - | I96: -
A97: Налоги НДС 5% | B97: 156000 | C97: 52000 | D97: 52000 | E97: 52000 | F97: - | G97: - | H97: - | I97: -
A98: Чистая прибыль (убыток) | B98: =IFERROR(B89*1,0)-IFERROR(B91*1,0)-IFERROR(B94*1,0)-IFERROR(B95*1,0) | C98: =IFERROR(C89*1,0)-IFERROR(C91*1,0)-IFERROR(C94*1,0)-IFERROR(C95*1,0) | D98: =IFERROR(D89*1,0)-IFERROR(D91*1,0)-IFERROR(D94*1,0)-IFERROR(D95*1,0) | E98: =IFERROR(E89*1,0)-IFERROR(E91*1,0)-IFERROR(E94*1,0)-IFERROR(E95*1,0) | F98: =IFERROR(F89*1,0)-IFERROR(F91*1,0)-IFERROR(F94*1,0)-IFERROR(F95*1,0) | G98: =IFERROR(G89*1,0)-IFERROR(G91*1,0)-IFERROR(G94*1,0)-IFERROR(G95*1,0) | H98: =IFERROR(H89*1,0)-IFERROR(H91*1,0)-IFERROR(H94*1,0)-IFERROR(H95*1,0) | I98: =IFERROR(I89*1,0)-IFERROR(I91*1,0)-IFERROR(I94*1,0)-IFERROR(I95*1,0)
A99: Рентабельность чистой прибыли | B99: =IFERROR(IF(B4=0,"-",B98/B4),"-") | C99: =IFERROR(IF(C4=0,"-",C98/C4),"-") | D99: =IFERROR(IF(D4=0,"-",D98/D4),"-") | E99: =IFERROR(IF(E4=0,"-",E98/E4),"-") | F99: =IFERROR(IF(F4=0,"-",F98/F4),"-") | G99: =IFERROR(IF(G4=0,"-",G98/G4),"-") | H99: =IFERROR(IF(H4=0,"-",H98/H4),"-") | I99: =IFERROR(IF(I4=0,"-",I98/I4),"-")

Sheet Астрид
A1: ПланФакт | B1: Создано с помощью сервиса ПланФакт | I1: =HYPERLINK("https://app.planfact.io/?from=Pf_BDR", "Перейти в сервис")
B2: Итого | C2: июнь` 26 | D2: июль` 26 | E2: август` 26 | F2: сентябрь` 26 | G2: октябрь` 26 | H2: ноябрь` 26 | I2: декабрь` 26
A3: Астрид | B3: план | C3: план | D3: план | E3: план | F3: план | G3: план | H3: план | I3: план
A4: Выручка | B4: =SUM(B5,B6) | C4: =SUM(C5,C6) | D4: =SUM(D5,D6) | E4: =SUM(E5,E6) | F4: =SUM(F5,F6) | G4: =SUM(G5,G6) | H4: =SUM(H5,H6) | I4: =SUM(I5,I6)
A5: Нераспределенный доход | B5: - | C5: - | D5: - | E5: - | F5: - | G5: - | H5: - | I5: -
A6: Выручка | B6: =SUM(B7,B8,B9) | C6: =SUM(C7,C8,C9) | D6: =SUM(D7,D8,D9) | E6: =SUM(E7,E8,E9) | F6: =SUM(F7,F8,F9) | G6: =SUM(G7,G8,G9) | H6: =SUM(H7,H8,H9) | I6: =SUM(I7,I8,I9)
A7: Реализация услуг Клининг (ОД) | B7: 2615842.3 | C7: 228370.58 | D7: 653960.57 | E7: 228370.58 | F7: 653960.57 | G7: - | H7: 653960.57 | I7: -
A8: Реализация услуг Клининг (Доп.услуги) | B8: 470000 | C8: - | D8: 470000 | E8: - | F8: - | G8: - | H8: - | I8: -
A9: Реализация услуг Клининг (снег) | B9: - | C9: - | D9: - | E9: - | F9: - | G9: - | H9: - | I9: -
A10: Прямые расходы | B10: =SUM(B11,B12,B13,B21,B22,B23,B24,B25,B26,B27,B28,B29,B30,B31,B32,B33,B34) | C10: =SUM(C11,C12,C13,C21,C22,C23,C24,C25,C26,C27,C28,C29,C30,C31,C32,C33,C34) | D10: =SUM(D11,D12,D13,D21,D22,D23,D24,D25,D26,D27,D28,D29,D30,D31,D32,D33,D34) | E10: =SUM(E11,E12,E13,E21,E22,E23,E24,E25,E26,E27,E28,E29,E30,E31,E32,E33,E34) | F10: =SUM(F11,F12,F13,F21,F22,F23,F24,F25,F26,F27,F28,F29,F30,F31,F32,F33,F34) | G10: =SUM(G11,G12,G13,G21,G22,G23,G24,G25,G26,G27,G28,G29,G30,G31,G32,G33,G34) | H10: =SUM(H11,H12,H13,H21,H22,H23,H24,H25,H26,H27,H28,H29,H30,H31,H32,H33,H34) | I10: =SUM(I11,I12,I13,I21,I22,I23,I24,I25,I26,I27,I28,I29,I30,I31,I32,I33,I34)
A11: Нераспределенный расход | B11: - | C11: - | D11: - | E11: - | F11: - | G11: - | H11: - | I11: -
A12: Транспортные расходы | B12: - | C12: - | D12: - | E12: - | F12: - | G12: - | H12: - | I12: -
A13: Переменные | B13: =SUM(B14,B15,B16,B17,B18,B19,B20) | C13: =SUM(C14,C15,C16,C17,C18,C19,C20) | D13: =SUM(D14,D15,D16,D17,D18,D19,D20) | E13: =SUM(E14,E15,E16,E17,E18,E19,E20) | F13: =SUM(F14,F15,F16,F17,F18,F19,F20) | G13: =SUM(G14,G15,G16,G17,G18,G19,G20) | H13: =SUM(H14,H15,H16,H17,H18,H19,H20) | I13: =SUM(I14,I15,I16,I17,I18,I19,I20)
A14: Услуги техниги для уборки снега (ПТ) | B14: - | C14: - | D14: - | E14: - | F14: - | G14: - | H14: - | I14: -
A15: Услуги садовника (ПТ) | B15: - | C15: - | D15: - | E15: - | F15: - | G15: - | H15: - | I15: -
A16: Сыпучие материалы (ПТ) | B16: - | C16: - | D16: - | E16: - | F16: - | G16: - | H16: - | I16: -
A17: Расходные материалы и инстументы (МОП) | B17: 51587.92 | C17: 10587.92 | D17: 21587.92 | E17: 10587.92 | F17: 10000 | G17: - | H17: 10000 | I17: -
A18: Расходные материалы и инстументы (ПТ) | B18: 20000 | C18: - | D18: 5000 | E18: - | F18: 5000 | G18: - | H18: 5000 | I18: -
A19: Арена оборудования (ПТ) | B19: - | C19: - | D19: - | E19: - | F19: - | G19: - | H19: - | I19: -
A20: Арена оборудования (МОП) | B20: - | C20: - | D20: - | E20: - | F20: - | G20: - | H20: - | I20: -
A21: Заработная плата (МОП) | B21: 840120 | C21: 209688.53 | D21: 210030 | E21: 209688.53 | F21: 210030 | G21: - | H21: 210030 | I21: -
A22: Заработная плата (ПТ) | B22: 1032000 | C22: 294494.09 | D22: 258000 | E22: 294494.09 | F22: 258000 | G22: - | H22: 258000 | I22: -
A23: Налоги с ФОТ (МОП) | B23: 190800 | C23: 19188.5 | D23: 64800 | E23: 19188.5 | F23: 42000 | G23: - | H23: 42000 | I23: -
A24: Налоги с ФОТ (ПТ) | B24: 5012.59 | C24: 13380.59 | D24: 5012.59 | E24: 13380.59 | F24: - | G24: - | H24: - | I24: -
A25: Премми (МОП) | B25: - | C25: - | D25: - | E25: - | F25: - | G25: - | H25: - | I25: -
A26: Премми (ПТ) | B26: - | C26: - | D26: - | E26: - | F26: - | G26: - | H26: - | I26: -
A27: Униформа (МОП) | B27: - | C27: - | D27: - | E27: - | F27: - | G27: - | H27: - | I27: -
A28: Униформа (ПТ) | B28: - | C28: - | D28: - | E28: - | F28: - | G28: - | H28: - | I28: -
A29: Ремонт оборудования (МОП) | B29: - | C29: - | D29: - | E29: - | F29: - | G29: - | H29: - | I29: -
A30: Ремонт оборудования (ПТ) | B30: - | C30: 1019 | D30: - | E30: 1019 | F30: - | G30: - | H30: - | I30: -
A31: Вывоз мусора | B31: - | C31: - | D31: - | E31: - | F31: - | G31: - | H31: - | I31: -
A32: Штрафы, пени, неустойки | B32: - | C32: - | D32: - | E32: - | F32: - | G32: - | H32: - | I32: -
A33: Расходы к удержанию | B33: - | C33: - | D33: - | E33: - | F33: - | G33: - | H33: - | I33: -
A34: Общехозяйственные | B34: =SUM(B35,B36,B37,B38,B39,B40,B41,B42) | C34: =SUM(C35,C36,C37,C38,C39,C40,C41,C42) | D34: =SUM(D35,D36,D37,D38,D39,D40,D41,D42) | E34: =SUM(E35,E36,E37,E38,E39,E40,E41,E42) | F34: =SUM(F35,F36,F37,F38,F39,F40,F41,F42) | G34: =SUM(G35,G36,G37,G38,G39,G40,G41,G42) | H34: =SUM(H35,H36,H37,H38,H39,H40,H41,H42) | I34: =SUM(I35,I36,I37,I38,I39,I40,I41,I42)
A35: Аутсорс (направления) | B35: 15000 | C35: 10000 | D35: 7500 | E35: 10000 | F35: 2500 | G35: - | H35: 2500 | I35: -
A36: Заработная плата МО АУП | B36: 240000 | C36: 60000 | D36: 60000 | E36: 60000 | F36: 60000 | G36: - | H36: 60000 | I36: -
A37: Инструменты: ГСМ | B37: 4000 | C37: 2000 | D37: 1000 | E37: 2000 | F37: 1000 | G37: - | H37: 1000 | I37: -
A38: Медосмотры | B38: - | C38: - | D38: - | E38: - | F38: - | G38: - | H38: - | I38: -
A39: Налоги с ФОТ (ИП) | B39: 147840 | C39: 26500 | D39: 36960 | E39: 26500 | F39: 36960 | G39: - | H39: 36960 | I39: -
A40: Приобритение мебели, бытовой техники | B40: - | C40: - | D40: - | E40: - | F40: - | G40: - | H40: - | I40: -
A41: Комиссия за перевод ЗП | B41: - | C41: 1000 | D41: - | E41: 1000 | F41: - | G41: - | H41: - | I41: -
A42: Аренда квартиры (включая коммуналку) | B42: - | C42: - | D42: - | E42: - | F42: - | G42: - | H42: - | I42: -
A43: Валовая прибыль | B43: =B4-B10 | C43: =C4-C10 | D43: =D4-D10 | E43: =E4-E10 | F43: =F4-F10 | G43: =G4-G10 | H43: =H4-H10 | I43: =I4-I10
A44: Валовая рентабельность | B44: =IFERROR(IF(B4=0,"-",B43/B4),"-") | C44: =IFERROR(IF(C4=0,"-",C43/C4),"-") | D44: =IFERROR(IF(D4=0,"-",D43/D4),"-") | E44: =IFERROR(IF(E4=0,"-",E43/E4),"-") | F44: =IFERROR(IF(F4=0,"-",F43/F4),"-") | G44: =IFERROR(IF(G4=0,"-",G43/G4),"-") | H44: =IFERROR(IF(H4=0,"-",H43/H4),"-") | I44: =IFERROR(IF(I4=0,"-",I43/I4),"-")
A45: Косвенные расходы | B45: =SUM(B46,B47,B48,B52,B56,B57,B58,B59,B60,B63,B64,B65,B66,B67,B68,B69,B70,B71,B72,B73,B74,B75,B76,B77,B78,B79) | C45: =SUM(C46,C47,C48,C52,C56,C57,C58,C59,C60,C63,C64,C65,C66,C67,C68,C69,C70,C71,C72,C73,C74,C75,C76,C77,C78,C79) | D45: =SUM(D46,D47,D48,D52,D56,D57,D58,D59,D60,D63,D64,D65,D66,D67,D68,D69,D70,D71,D72,D73,D74,D75,D76,D77,D78,D79) | E45: =SUM(E46,E47,E48,E52,E56,E57,E58,E59,E60,E63,E64,E65,E66,E67,E68,E69,E70,E71,E72,E73,E74,E75,E76,E77,E78,E79) | F45: =SUM(F46,F47,F48,F52,F56,F57,F58,F59,F60,F63,F64,F65,F66,F67,F68,F69,F70,F71,F72,F73,F74,F75,F76,F77,F78,F79) | G45: =SUM(G46,G47,G48,G52,G56,G57,G58,G59,G60,G63,G64,G65,G66,G67,G68,G69,G70,G71,G72,G73,G74,G75,G76,G77,G78,G79) | H45: =SUM(H46,H47,H48,H52,H56,H57,H58,H59,H60,H63,H64,H65,H66,H67,H68,H69,H70,H71,H72,H73,H74,H75,H76,H77,H78,H79) | I45: =SUM(I46,I47,I48,I52,I56,I57,I58,I59,I60,I63,I64,I65,I66,I67,I68,I69,I70,I71,I72,I73,I74,I75,I76,I77,I78,I79)
A46: Расход БЭК-ОФИС | B46: 339676.8 | C46: 55821.21 | D46: 84919.2 | E46: 55821.21 | F46: 84919.2 | G46: - | H46: 84919.2 | I46: -
A47: Расходы на бэк-офис | B47: - | C47: - | D47: - | E47: - | F47: - | G47: - | H47: - | I47: -
A48: Автомобиль | B48: =SUM(B49,B50,B51) | C48: =SUM(C49,C50,C51) | D48: =SUM(D49,D50,D51) | E48: =SUM(E49,E50,E51) | F48: =SUM(F49,F50,F51) | G48: =SUM(G49,G50,G51) | H48: =SUM(H49,H50,H51) | I48: =SUM(I49,I50,I51)
A49: Автомобиль: ГСМ | B49: - | C49: - | D49: - | E49: - | F49: - | G49: - | H49: - | I49: -
A50: Автомобиль: страхование | B50: - | C50: - | D50: - | E50: - | F50: - | G50: - | H50: - | I50: -
A51: Автомобиль: ТО | B51: - | C51: - | D51: - | E51: - | F51: - | G51: - | H51: - | I51: -
A52: Офисные расходы | B52: =SUM(B53,B54,B55) | C52: =SUM(C53,C54,C55) | D52: =SUM(D53,D54,D55) | E52: =SUM(E53,E54,E55) | F52: =SUM(F53,F54,F55) | G52: =SUM(G53,G54,G55) | H52: =SUM(H53,H54,H55) | I52: =SUM(I53,I54,I55)
A53: Аренда офиса | B53: - | C53: - | D53: - | E53: - | F53: - | G53: - | H53: - | I53: -
A54: Канцелярия и обслуживание | B54: - | C54: - | D54: - | E54: - | F54: - | G54: - | H54: - | I54: -
A55: Интернет и связь | B55: - | C55: - | D55: - | E55: - | F55: - | G55: - | H55: - | I55: -
A56: Банковские услуги | B56: - | C56: - | D56: - | E56: - | F56: - | G56: - | H56: - | I56: -
A57: Заработная плата АУП (БО) | B57: - | C57: - | D57: - | E57: - | F57: - | G57: - | H57: - | I57: -
A58: Заработная плата бухгалтерии (БО) | B58: - | C58: - | D58: - | E58: - | F58: - | G58: - | H58: - | I58: -
A59: Заработная плата СБ (БО) | B59: - | C59: - | D59: - | E59: - | F59: - | G59: - | H59: - | I59: -
A60: Командировочные расходы | B60: =SUM(B61,B62) | C60: =SUM(C61,C62) | D60: =SUM(D61,D62) | E60: =SUM(E61,E62) | F60: =SUM(F61,F62) | G60: =SUM(G61,G62) | H60: =SUM(H61,H62) | I60: =SUM(I61,I62)
A61: Командировнчеы расходы: билеты (БО) | B61: - | C61: - | D61: - | E61: - | F61: - | G61: - | H61: - | I61: -
A62: Командировнчеы расходы: проживание (БО) | B62: - | C62: - | D62: - | E62: - | F62: - | G62: - | H62: - | I62: -
A63: Комиссия УК ДОМ | B63: - | C63: - | D63: - | E63: - | F63: - | G63: - | H63: - | I63: -
A64: Налоги с ФОТ (ИП)_БО | B64: - | C64: - | D64: - | E64: - | F64: - | G64: - | H64: - | I64: -
A65: Налоги с ФОТ (НДФЛ) БО | B65: - | C65: - | D65: - | E65: - | F65: - | G65: - | H65: - | I65: -
A66: Налоги с ФОТ (страховые взносы) БО | B66: - | C66: - | D66: - | E66: - | F66: - | G66: - | H66: - | I66: -
A67: Нотариальные услуги | B67: - | C67: - | D67: - | E67: - | F67: - | G67: - | H67: - | I67: -
A68: Обслуживание техники (БО) | B68: - | C68: - | D68: - | E68: - | F68: - | G68: - | H68: - | I68: -
A69: Программное обеспечение (БО) | B69: - | C69: - | D69: - | E69: - | F69: - | G69: - | H69: - | I69: -
A70: ПланФакт | B70: - | C70: - | D70: - | E70: - | F70: - | G70: - | H70: - | I70: -
A71: ТБ | B71: - | C71: - | D71: - | E71: - | F71: - | G71: - | H71: - | I71: -
A72: Контур | B72: - | C72: - | D72: - | E72: - | F72: - | G72: - | H72: - | I72: -
... A79: HR (аутсорс) | B79: - | C79: - | D79: - | E79: - | F79: - | G79: - | H79: - | I79: -
A80: Операционная прибыль | B80: =B43-B45 | C80: =C43-C45 | D80: =D43-D45 | E80: =E43-E45 | F80: =F43-F45 | G80: =G43-G45 | H80: =H43-H45 | I80: =I43-I45
A81: Операционная рентабельность | B81: =IFERROR(IF(B4=0,"-",B80/B4),"-") | C81: =IFERROR(IF(C4=0,"-",C80/C4),"-") | D81: =IFERROR(IF(D4=0,"-",D80/D4),"-") | E81: =IFERROR(IF(E4=0,"-",E80/E4),"-") | F81: =IFERROR(IF(F4=0,"-",F80/F4),"-") | G81: =IFERROR(IF(G4=0,"-",G80/G4),"-") | H81: =IFERROR(IF(H4=0,"-",H80/H4),"-") | I81: =IFERROR(IF(I4=0,"-",I80/I4),"-")
A82: Прочие доходы | B82: =SUM(B83,B84,B85,B86) | C82: =SUM(C83,C84,C85,C86) | D82: =SUM(D83,D84,D85,D86) | E82: =SUM(E83,E84,E85,E86) | F82: =SUM(F83,F84,F85,F86) | G82: =SUM(G83,G84,G85,G86) | H82: =SUM(H83,H84,H85,H86) | I82: =SUM(I83,I84,I85,I86)
A83: Доход БЭК-ОФИС | B83: - | C83: - | D83: - | E83: - | F83: - | G83: - | H83: - | I83: -
A84: Пополненин бэк-офис | B84: - | C84: - | D84: - | E84: - | F84: - | G84: - | H84: - | I84: -
A85: Проценты по вкладам | B85: - | C85: - | D85: - | E85: - | F85: - | G85: - | H85: - | I85: -
A86: Курсовая разница (+) | B86: - | C86: - | D86: - | E86: - | F86: - | G86: - | H86: - | I86: -
A87: Прочие расходы | B87: =SUM(B88) | C87: =SUM(C88) | D87: =SUM(D88) | E87: =SUM(E88) | F87: =SUM(F88) | G87: =SUM(G88) | H87: =SUM(H88) | I87: =SUM(I88)
A88: Курсовая разница (-) | B88: - | C88: - | D88: - | E88: - | F88: - | G88: - | H88: - | I88: -
A89: EBITDA | B89: =B80+IFERROR(B82*1,0)-IFERROR(B87*1,0) | C89: =C80+IFERROR(C82*1,0)-IFERROR(C87*1,0) | D89: =D80+IFERROR(D82*1,0)-IFERROR(D87*1,0) | E89: =E80+IFERROR(E82*1,0)-IFERROR(E87*1,0) | F89: =F80+IFERROR(F82*1,0)-IFERROR(F87*1,0) | G89: =G80+IFERROR(G82*1,0)-IFERROR(G87*1,0) | H89: =H80+IFERROR(H82*1,0)-IFERROR(H87*1,0) | I89: =I80+IFERROR(I82*1,0)-IFERROR(I87*1,0)
A90: Рентабельность по EBITDA | B90: =IFERROR(IF(B4=0,"-",B89/B4),"-") | C90: =IFERROR(IF(C4=0,"-",C89/C4),"-") | D90: =IFERROR(IF(D4=0,"-",D89/D4),"-") | E90: =IFERROR(IF(E4=0,"-",E89/E4),"-") | F90: =IFERROR(IF(F4=0,"-",F89/F4),"-") | G90: =IFERROR(IF(G4=0,"-",G89/G4),"-") | H90: =IFERROR(IF(H4=0,"-",H89/H4),"-") | I90: =IFERROR(IF(I4=0,"-",I89/I4),"-")
A91: Амортизация | B91: =SUM(B92,B93) | C91: =SUM(C92,C93) | D91: =SUM(D92,D93) | E91: =SUM(E92,E93) | F91: =SUM(F92,F93) | G91: =SUM(G92,G93) | H91: =SUM(H92,H93) | I91: =SUM(I92,I93)
A92: Амортизация ОС (ПТ) | B92: - | C92: - | D92: - | E92: - | F92: - | G92: - | H92: - | I92: -
A93: Амортизация ОС (МОП) | B93: - | C93: - | D93: - | E93: - | F93: - | G93: - | H93: - | I93: -
A94: Проценты по кредитам и займам | B94: - | C94: - | D94: - | E94: - | F94: - | G94: - | H94: - | I94: -
A95: Налог на прибыль | B95: =SUM(B96,B97) | C95: =SUM(C96,C97) | D95: =SUM(D96,D97) | E95: =SUM(E96,E97) | F95: =SUM(F96,F97) | G95: =SUM(G96,G97) | H95: =SUM(H96,H97) | I95: =SUM(I96,I97)
A96: Налоги УСН | B96: 40000 | C96: - | D96: 10000 | E96: - | F96: 10000 | G96: - | H96: 10000 | I96: -
A97: Налоги НДС 5% | B97: 124563.96 | C97: 38678.65 | D97: 31140.99 | E97: 38678.65 | F97: 31140.99 | G97: - | H97: 31140.99 | I97: -
A98: Чистая прибыль (убыток) | B98: =IFERROR(B89*1,0)-IFERROR(B91*1,0)-IFERROR(B94*1,0)-IFERROR(B95*1,0) | C98: =IFERROR(C89*1,0)-IFERROR(C91*1,0)-IFERROR(C94*1,0)-IFERROR(C95*1,0) | D98: =IFERROR(D89*1,0)-IFERROR(D91*1,0)-IFERROR(D94*1,0)-IFERROR(D95*1,0) | E98: =IFERROR(E89*1,0)-IFERROR(E91*1,0)-IFERROR(E94*1,0)-IFERROR(E95*1,0) | F98: =IFERROR(F89*1,0)-IFERROR(F91*1,0)-IFERROR(F94*1,0)-IFERROR(F95*1,0) | G98: =IFERROR(G89*1,0)-IFERROR(G91*1,0)-IFERROR(G94*1,0)-IFERROR(G95*1,0) | H98: =IFERROR(H89*1,0)-IFERROR(H91*1,0)-IFERROR(H94*1,0)-IFERROR(H95*1,0) | I98: =IFERROR(I89*1,0)-IFERROR(I91*1,0)-IFERROR(I94*1,0)-IFERROR(I95*1,0)
A99: Рентабельность чистой прибыли | B99: =IFERROR(IF(B4=0,"-",B98/B4),"-") | C99: =IFERROR(IF(C4=0,"-",C98/C4),"-") | D99: =IFERROR(IF(D4=0,"-",D98/D4),"-") | E99: =IFERROR(IF(E4=0,"-",E98/E4),"-") | F99: =IFERROR(IF(F4=0,"-",F98/F4),"-") | G99: =IFERROR(IF(G4=0,"-",G98/G4),"-") | H99: =IFERROR(IF(H4=0,"-",H98/H4),"-") | I99: =IFERROR(IF(I4=0,"-",I98/I4),"-")

Sheet Живи в Курортном
A1: ПланФакт | B1: Создано с помощью сервиса ПланФакт | I1: =HYPERLINK("https://app.planfact.io/?from=Pf_BDR", "Перейти в сервис")
B2: Итого | C2: июнь` 26 | D2: июль` 26 | E2: август` 26 | F2: сентябрь` 26 | G2: октябрь` 26 | H2: ноябрь` 26 | I2: декабрь` 26
A3: Живи в Курортном | B3: план | C3: план | D3: план | E3: план | F3: план | G3: план | H3: план | I3: план
A4: Выручка | B4: =SUM(B5,B6) | C4: =SUM(C5,C6) | D4: =SUM(D5,D6) | E4: =SUM(E5,E6) | F4: =SUM(F5,F6) | G4: =SUM(G5,G6) | H4: =SUM(H5,H6) | I4: =SUM(I5,I6)
A5: Нераспределенный доход | B5: - | C5: - | D5: - | E5: - | F5: - | G5: - | H5: - | I5: -
A6: Выручка | B6: =SUM(B7,B8,B9) | C6: =SUM(C7,C8,C9) | D6: =SUM(D7,D8,D9) | E6: =SUM(E7,E8,E9) | F6: =SUM(F7,F8,F9) | G6: =SUM(G7,G8,G9) | H6: =SUM(H7,H8,H9) | I6: =SUM(I7,I8,I9)
