Workbook

Sheet Группа 1
A1: ПланФакт | B1: Создано с помощью сервиса ПланФакт | I1: =HYPERLINK("https://app.planfact.io/?from=Pf_BDR", "Перейти в сервис")
B2: Итого | C2: июнь` 26 | D2: июль` 26 | E2: август` 26 | F2: сентябрь` 26 | G2: октябрь` 26 | H2: ноябрь` 26 | I2: декабрь` 26
A3: Сводный бюджет — Астон.Движение, Астон.Реформа, Милый дом, River Park | B3: план | C3: план | D3: план | E3: план | F3: план | G3: план | H3: план | I3: план
A4: Выручка | B4: =SUM(B5,B6) | C4: =SUM(C5,C6) | D4: =SUM(D5,D6) | E4: =SUM(E5,E6) | F4: =SUM(F5,F6) | G4: =SUM(G5,G6) | H4: - | I4: =SUM(I5,I6)
A5: Нераспределенный доход | B5: =SUM('Астон.Движение'!B5,'Астон.Реформа'!B5,'Милый дом'!B5,'River Park'!B5) | C5: =SUM('Астон.Движение'!C5,'Астон.Реформа'!C5,'Милый дом'!C5,'River Park'!C5) | D5: =SUM('Астон.Движение'!D5,'Астон.Реформа'!D5,'Милый дом'!D5,'River Park'!D5) | E5: =SUM('Астон.Движение'!E5,'Астон.Реформа'!E5,'Милый дом'!E5,'River Park'!E5) | F5: =SUM('Астон.Движение'!F5,'Астон.Реформа'!F5,'Милый дом'!F5,'River Park'!F5) | G5: =SUM('Астон.Движение'!G5,'Астон.Реформа'!G5,'Милый дом'!G5,'River Park'!G5) | H5: - | I5: =SUM('Астон.Движение'!I5,'Астон.Реформа'!I5,'Милый дом'!I5,'River Park'!I5)
A6: Выручка | B6: =SUM(B7,B8,B9) | C6: =SUM(C7,C8,C9) | D6: =SUM(D7,D8,D9) | E6: =SUM(E7,E8,E9) | F6: =SUM(F7,F8,F9) | G6: =SUM(G7,G8,G9) | H6: - | I6: =SUM(I7,I8,I9)
A7: Реализация услуг Клининг (ОД) | B7: =SUM('Астон.Движение'!B7,'Астон.Реформа'!B7,'Милый дом'!B7,'River Park'!B7) | C7: =SUM('Астон.Движение'!C7,'Астон.Реформа'!C7,'Милый дом'!C7,'River Park'!C7) | D7: =SUM('Астон.Движение'!D7,'Астон.Реформа'!D7,'Милый дом'!D7,'River Park'!D7) | E7: =SUM('Астон.Движение'!E7,'Астон.Реформа'!E7,'Милый дом'!E7,'River Park'!E7) | F7: =SUM('Астон.Движение'!F7,'Астон.Реформа'!F7,'Милый дом'!F7,'River Park'!F7) | G7: =SUM('Астон.Движение'!G7,'Астон.Реформа'!G7,'Милый дом'!G7,'River Park'!G7) | H7: - | I7: =SUM('Астон.Движение'!I7,'Астон.Реформа'!I7,'Милый дом'!I7,'River Park'!I7)
A8: Реализация услуг Клининг (Доп.услуги) | B8: =SUM('Астон.Движение'!B8,'Астон.Реформа'!B8,'Милый дом'!B8,'River Park'!B8) | C8: =SUM('Астон.Движение'!C8,'Астон.Реформа'!C8,'Милый дом'!C8,'River Park'!C8) | D8: =SUM('Астон.Движение'!D8,'Астон.Реформа'!D8,'Милый дом'!D8,'River Park'!D8) | E8: =SUM('Астон.Движение'!E8,'Астон.Реформа'!E8,'Милый дом'!E8,'River Park'!E8) | F8: =SUM('Астон.Движение'!F8,'Астон.Реформа'!F8,'Милый дом'!F8,'River Park'!F8) | G8: =SUM('Астон.Движение'!G8,'Астон.Реформа'!G8,'Милый дом'!G8,'River Park'!G8) | H8: - | I8: =SUM('Астон.Движение'!I8,'Астон.Реформа'!I8,'Милый дом'!I8,'River Park'!I8)
A9: Реализация услуг Клининг (снег) | B9: =SUM('Астон.Движение'!B9,'Астон.Реформа'!B9,'Милый дом'!B9,'River Park'!B9) | C9: =SUM('Астон.Движение'!C9,'Астон.Реформа'!C9,'Милый дом'!C9,'River Park'!C9) | D9: =SUM('Астон.Движение'!D9,'Астон.Реформа'!D9,'Милый дом'!D9,'River Park'!D9) | E9: =SUM('Астон.Движение'!E9,'Астон.Реформа'!E9,'Милый дом'!E9,'River Park'!E9) | F9: =SUM('Астон.Движение'!F9,'Астон.Реформа'!F9,'Милый дом'!F9,'River Park'!F9) | G9: =SUM('Астон.Движение'!G9,'Астон.Реформа'!G9,'Милый дом'!G9,'River Park'!G9) | H9: - | I9: =SUM('Астон.Движение'!I9,'Астон.Реформа'!I9,'Милый дом'!I9,'River Park'!I9)
A10: Прямые расходы | B10: =SUM(B11,B12,B13,B21,B22,B23,B24,B25,B26,B27,B28,B29,B30,B31,B32,B33,B34) | C10: =SUM(C11,C12,C13,C21,C22,C23,C24,C25,C26,C27,C28,C29,C30,C31,C32,C33,C34) | D10: =SUM(D11,D12,D13,D21,D22,D23,D24,D25,D26,D27,D28,D29,D30,D31,D32,D33,D34) | E10: =SUM(E11,E12,E13,E21,E22,E23,E24,E25,E26,E27,E28,E29,E30,E31,E32,E33,E34) | F10: =SUM(F11,F12,F13,F21,F22,F23,F24,F25,F26,F27,F28,F29,F30,F31,F32,F33,F34) | G10: =SUM(G11,G12,G13,G21,G22,G23,G24,G25,G26,G27,G28,G29,G30,G31,G32,G33,G34) | H10: - | I10: =SUM(I11,I12,I13,I21,I22,I23,I24,I25,I26,I27,I28,I29,I30,I31,I32,I33,I34)
A11: Нераспределенный расход | B11: =SUM('Астон.Движение'!B11,'Астон.Реформа'!B11,'Милый дом'!B11,'River Park'!B11) | C11: =SUM('Астон.Движение'!C11,'Астон.Реформа'!C11,'Милый дом'!C11,'River Park'!C11) | D11: =SUM('Астон.Движение'!D11,'Астон.Реформа'!D11,'Милый дом'!D11,'River Park'!D11) | E11: =SUM('Астон.Движение'!E11,'Астон.Реформа'!E11,'Милый дом'!E11,'River Park'!E11) | F11: =SUM('Астон.Движение'!F11,'Астон.Реформа'!F11,'Милый дом'!F11,'River Park'!F11) | G11: =SUM('Астон.Движение'!G11,'Астон.Реформа'!G11,'Милый дом'!G11,'River Park'!G11) | H11: - | I11: =SUM('Астон.Движение'!I11,'Астон.Реформа'!I11,'Милый дом'!I11,'River Park'!I11)
A12: Транспортные расходы | B12: =SUM('Астон.Движение'!B12,'Астон.Реформа'!B12,'Милый дом'!B12,'River Park'!B12) | C12: =SUM('Астон.Движение'!C12,'Астон.Реформа'!C12,'Милый дом'!C12,'River Park'!C12) | D12: =SUM('Астон.Движение'!D12,'Астон.Реформа'!D12,'Милый дом'!D12,'River Park'!D12) | E12: =SUM('Астон.Движение'!E12,'Астон.Реформа'!E12,'Милый дом'!E12,'River Park'!E12) | F12: =SUM('Астон.Движение'!F12,'Астон.Реформа'!F12,'Милый дом'!F12,'River Park'!F12) | G12: =SUM('Астон.Движение'!G12,'Астон.Реформа'!G12,'Милый дом'!G12,'River Park'!G12) | H12: - | I12: =SUM('Астон.Движение'!I12,'Астон.Реформа'!I12,'Милый дом'!I12,'River Park'!I12)
A13: Переменные | B13: =SUM(B14,B15,B16,B17,B18,B19,B20) | C13: =SUM(C14,C15,C16,C17,C18,C19,C20) | D13: =SUM(D14,D15,D16,D17,D18,D19,D20) | E13: =SUM(E14,E15,E16,E17,E18,E19,E20) | F13: =SUM(F14,F15,F16,F17,F18,F19,F20) | G13: =SUM(G14,G15,G16,G17,G18,G19,G20) | H13: - | I13: =SUM(I14,I15,I16,I17,I18,I19,I20)
A14: Услуги техниги для уборки снега (ПТ) | B14: =SUM('Астон.Движение'!B14,'Астон.Реформа'!B14,'Милый дом'!B14,'River Park'!B14) | C14: =SUM('Астон.Движение'!C14,'Астон.Реформа'!C14,'Милый дом'!C14,'River Park'!C14) | D14: =SUM('Астон.Движение'!D14,'Астон.Реформа'!D14,'Милый дом'!D14,'River Park'!D14) | E14: =SUM('Астон.Движение'!E14,'Астон.Реформа'!E14,'Милый дом'!E14,'River Park'!E14) | F14: =SUM('Астон.Движение'!F14,'Астон.Реформа'!F14,'Милый дом'!F14,'River Park'!F14) | G14: =SUM('Астон.Движение'!G14,'Астон.Реформа'!G14,'Милый дом'!G14,'River Park'!G14) | H14: - | I14: =SUM('Астон.Движение'!I14,'Астон.Реформа'!I14,'Милый дом'!I14,'River Park'!I14)
A15: Услуги садовника (ПТ) | B15: =SUM('Астон.Движение'!B15,'Астон.Реформа'!B15,'Милый дом'!B15,'River Park'!B15) | C15: =SUM('Астон.Движение'!C15,'Астон.Реформа'!C15,'Милый дом'!C15,'River Park'!C15) | D15: =SUM('Астон.Движение'!D15,'Астон.Реформа'!D15,'Милый дом'!D15,'River Park'!D15) | E15: =SUM('Астон.Движение'!E15,'Астон.Реформа'!E15,'Милый дом'!E15,'River Park'!E15) | F15: =SUM('Астон.Движение'!F15,'Астон.Реформа'!F15,'Милый дом'!F15,'River Park'!F15) | G15: =SUM('Астон.Движение'!G15,'Астон.Реформа'!G15,'Милый дом'!G15,'River Park'!G15) | H15: - | I15: =SUM('Астон.Движение'!I15,'Астон.Реформа'!I15,'Милый дом'!I15,'River Park'!I15)
A16: Сыпучие материалы (ПТ) | B16: =SUM('Астон.Движение'!B16,'Астон.Реформа'!B16,'Милый дом'!B16,'River Park'!B16) | C16: =SUM('Астон.Движение'!C16,'Астон.Реформа'!C16,'Милый дом'!C16,'River Park'!C16) | D16: =SUM('Астон.Движение'!D16,'Астон.Реформа'!D16,'Милый дом'!D16,'River Park'!D16) | E16: =SUM('Астон.Движение'!E16,'Астон.Реформа'!E16,'Милый дом'!E16,'River Park'!E16) | F16: =SUM('Астон.Движение'!F16,'Астон.Реформа'!F16,'Милый дом'!F16,'River Park'!F16) | G16: =SUM('Астон.Движение'!G16,'Астон.Реформа'!G16,'Милый дом'!G16,'River Park'!G16) | H16: - | I16: =SUM('Астон.Движение'!I16,'Астон.Реформа'!I16,'Милый дом'!I16,'River Park'!I16)
A17: Расходные материалы и инстументы (МОП) | B17: =SUM('Астон.Движение'!B17,'Астон.Реформа'!B17,'Милый дом'!B17,'River Park'!B17) | C17: =SUM('Астон.Движение'!C17,'Астон.Реформа'!C17,'Милый дом'!C17,'River Park'!C17) | D17: =SUM('Астон.Движение'!D17,'Астон.Реформа'!D17,'Милый дом'!D17,'River Park'!D17) | E17: =SUM('Астон.Движение'!E17,'Астон.Реформа'!E17,'Милый дом'!E17,'River Park'!E17) | F17: =SUM('Астон.Движение'!F17,'Астон.Реформа'!F17,'Милый дом'!F17,'River Park'!F17) | G17: =SUM('Астон.Движение'!G17,'Астон.Реформа'!G17,'Милый дом'!G17,'River Park'!G17) | H17: - | I17: =SUM('Астон.Движение'!I17,'Астон.Реформа'!I17,'Милый дом'!I17,'River Park'!I17)
A18: Расходные материалы и инстументы (ПТ) | B18: =SUM('Астон.Движение'!B18,'Астон.Реформа'!B18,'Милый дом'!B18,'River Park'!B18) | C18: =SUM('Астон.Движение'!C18,'Астон.Реформа'!C18,'Милый дом'!C18,'River Park'!C18) | D18: =SUM('Астон.Движение'!D18,'Астон.Реформа'!D18,'Милый дом'!D18,'River Park'!D18) | E18: =SUM('Астон.Движение'!E18,'Астон.Реформа'!E18,'Милый дом'!E18,'River Park'!E18) | F18: =SUM('Астон.Движение'!F18,'Астон.Реформа'!F18,'Милый дом'!F18,'River Park'!F18) | G18: =SUM('Астон.Движение'!G18,'Астон.Реформа'!G18,'Милый дом'!G18,'River Park'!G18) | H18: - | I18: =SUM('Астон.Движение'!I18,'Астон.Реформа'!I18,'Милый дом'!I18,'River Park'!I18)
A19: Арена оборудования (ПТ) | B19: =SUM('Астон.Движение'!B19,'Астон.Реформа'!B19,'Милый дом'!B19,'River Park'!B19) | C19: =SUM('Астон.Движение'!C19,'Астон.Реформа'!C19,'Милый дом'!C19,'River Park'!C19) | D19: =SUM('Астон.Движение'!D19,'Астон.Реформа'!D19,'Милый дом'!D19,'River Park'!D19) | E19: =SUM('Астон.Движение'!E19,'Астон.Реформа'!E19,'Милый дом'!E19,'River Park'!E19) | F19: =SUM('Астон.Движение'!F19,'Астон.Реформа'!F19,'Милый дом'!F19,'River Park'!F19) | G19: =SUM('Астон.Движение'!G19,'Астон.Реформа'!G19,'Милый дом'!G19,'River Park'!G19) | H19: - | I19: =SUM('Астон.Движение'!I19,'Астон.Реформа'!I19,'Милый дом'!I19,'River Park'!I19)
A20: Арена оборудования (МОП) | B20: =SUM('Астон.Движение'!B20,'Астон.Реформа'!B20,'Милый дом'!B20,'River Park'!B20) | C20: =SUM('Астон.Движение'!C20,'Астон.Реформа'!C20,'Милый дом'!C20,'River Park'!C20) | D20: =SUM('Астон.Движение'!D20,'Астон.Реформа'!D20,'Милый дом'!D20,'River Park'!D20) | E20: =SUM('Астон.Движение'!E20,'Астон.Реформа'!E20,'Милый дом'!E20,'River Park'!E20) | F20: =SUM('Астон.Движение'!F20,'Астон.Реформа'!F20,'Милый дом'!F20,'River Park'!F20) | G20: =SUM('Астон.Движение'!G20,'Астон.Реформа'!G20,'Милый дом'!G20,'River Park'!G20) | H20: - | I20: =SUM('Астон.Движение'!I20,'Астон.Реформа'!I20,'Милый дом'!I20,'River Park'!I20)
A21: Заработная плата (МОП) | B21: =SUM('Астон.Движение'!B21,'Астон.Реформа'!B21,'Милый дом'!B21,'River Park'!B21) | C21: =SUM('Астон.Движение'!C21,'Астон.Реформа'!C21,'Милый дом'!C21,'River Park'!C21) | D21: =SUM('Астон.Движение'!D21,'Астон.Реформа'!D21,'Милый дом'!D21,'River Park'!D21) | E21: =SUM('Астон.Движение'!E21,'Астон.Реформа'!E21,'Милый дом'!E21,'River Park'!E21) | F21: =SUM('Астон.Движение'!F21,'Астон.Реформа'!F21,'Милый дом'!F21,'River Park'!F21) | G21: =SUM('Астон.Движение'!G21,'Астон.Реформа'!G21,'Милый дом'!G21,'River Park'!G21) | H21: - | I21: =SUM('Астон.Движение'!I21,'Астон.Реформа'!I21,'Милый дом'!I21,'River Park'!I21)
A22: Заработная плата (ПТ) | B22: =SUM('Астон.Движение'!B22,'Астон.Реформа'!B22,'Милый дом'!B22,'River Park'!B22) | C22: =SUM('Астон.Движение'!C22,'Астон.Реформа'!C22,'Милый дом'!C22,'River Park'!C22) | D22: =SUM('Астон.Движение'!D22,'Астон.Реформа'!D22,'Милый дом'!D22,'River Park'!D22) | E22: =SUM('Астон.Движение'!E22,'Астон.Реформа'!E22,'Милый дом'!E22,'River Park'!E22) | F22: =SUM('Астон.Движение'!F22,'Астон.Реформа'!F22,'Милый дом'!F22,'River Park'!F22) | G22: =SUM('Астон.Движение'!G22,'Астон.Реформа'!G22,'Милый дом'!G22,'River Park'!G22) | H22: - | I22: =SUM('Астон.Движение'!I22,'Астон.Реформа'!I22,'Милый дом'!I22,'River Park'!I22)
A23: Налоги с ФОТ (МОП) | B23: =SUM('Астон.Движение'!B23,'Астон.Реформа'!B23,'Милый дом'!B23,'River Park'!B23) | C23: =SUM('Астон.Движение'!C23,'Астон.Реформа'!C23,'Милый дом'!C23,'River Park'!C23) | D23: =SUM('Астон.Движение'!D23,'Астон.Реформа'!D23,'Милый дом'!D23,'River Park'!D23) | E23: =SUM('Астон.Движение'!E23,'Астон.Реформа'!E23,'Милый дом'!E23,'River Park'!E23) | F23: =SUM('Астон.Движение'!F23,'Астон.Реформа'!F23,'Милый дом'!F23,'River Park'!F23) | G23: =SUM('Астон.Движение'!G23,'Астон.Реформа'!G23,'Милый дом'!G23,'River Park'!G23) | H23: - | I23: =SUM('Астон.Движение'!I23,'Астон.Реформа'!I23,'Милый дом'!I23,'River Park'!I23)
A24: Налоги с ФОТ (ПТ) | B24: =SUM('Астон.Движение'!B24,'Астон.Реформа'!B24,'Милый дом'!B24,'River Park'!B24) | C24: =SUM('Астон.Движение'!C24,'Астон.Реформа'!C24,'Милый дом'!C24,'River Park'!C24) | D24: =SUM('Астон.Движение'!D24,'Астон.Реформа'!D24,'Милый дом'!D24,'River Park'!D24) | E24: =SUM('Астон.Движение'!E24,'Астон.Реформа'!E24,'Милый дом'!E24,'River Park'!E24) | F24: =SUM('Астон.Движение'!F24,'Астон.Реформа'!F24,'Милый дом'!F24,'River Park'!F24) | G24: =SUM('Астон.Движение'!G24,'Астон.Реформа'!G24,'Милый дом'!G24,'River Park'!G24) | H24: - | I24: =SUM('Астон.Движение'!I24,'Астон.Реформа'!I24,'Милый дом'!I24,'River Park'!I24)
A25: Премми (МОП) | B25: =SUM('Астон.Движение'!B25,'Астон.Реформа'!B25,'Милый дом'!B25,'River Park'!B25) | C25: =SUM('Астон.Движение'!C25,'Астон.Реформа'!C25,'Милый дом'!C25,'River Park'!C25) | D25: =SUM('Астон.Движение'!D25,'Астон.Реформа'!D25,'Милый дом'!D25,'River Park'!D25) | E25: =SUM('Астон.Движение'!E25,'Астон.Реформа'!E25,'Милый дом'!E25,'River Park'!E25) | F25: =SUM('Астон.Движение'!F25,'Астон.Реформа'!F25,'Милый дом'!F25,'River Park'!F25) | G25: =SUM('Астон.Движение'!G25,'Астон.Реформа'!G25,'Милый дом'!G25,'River Park'!G25) | H25: - | I25: =SUM('Астон.Движение'!I25,'Астон.Реформа'!I25,'Милый дом'!I25,'River Park'!I25)
... A33: Расходы к удержанию | B33: =SUM('Астон.Движение'!B33,'Астон.Реформа'!B33,'Милый дом'!B33,'River Park'!B33) | C33: =SUM('Астон.Движение'!C33,'Астон.Реформа'!C33,'Милый дом'!C33,'River Park'!C33) | D33: =SUM('Астон.Движение'!D33,'Астон.Реформа'!D33,'Милый дом'!D33,'River Park'!D33) | E33: =SUM('Астон.Движение'!E33,'Астон.Реформа'!E33,'Милый дом'!E33,'River Park'!E33) | F33: =SUM('Астон.Движение'!F33,'Астон.Реформа'!F33,'Милый дом'!F33,'River Park'!F33) | G33: =SUM('Астон.Движение'!G33,'Астон.Реформа'!G33,'Милый дом'!G33,'River Park'!G33) | H33: - | I33: =SUM('Астон.Движение'!I33,'Астон.Реформа'!I33,'Милый дом'!I33,'River Park'!I33)
A34: Общехозяйственные | B34: =SUM(B35,B36,B37,B38,B39,B40,B41,B42) | C34: =SUM(C35,C36,C37,C38,C39,C40,C41,C42) | D34: =SUM(D35,D36,D37,D38,D39,D40,D41,D42) | E34: =SUM(E35,E36,E37,E38,E39,E40,E41,E42) | F34: =SUM(F35,F36,F37,F38,F39,F40,F41,F42) | G34: =SUM(G35,G36,G37,G38,G39,G40,G41,G42) | H34: - | I34: =SUM(I35,I36,I37,I38,I39,I40,I41,I42)
A35: Аутсорс (направления) | B35: =SUM('Астон.Движение'!B35,'Астон.Реформа'!B35,'Милый дом'!B35,'River Park'!B35) | C35: =SUM('Астон.Движение'!C35,'Астон.Реформа'!C35,'Милый дом'!C35,'River Park'!C35) | D35: =SUM('Астон.Движение'!D35,'Астон.Реформа'!D35,'Милый дом'!D35,'River Park'!D35) | E35: =SUM('Астон.Движение'!E35,'Астон.Реформа'!E35,'Милый дом'!E35,'River Park'!E35) | F35: =SUM('Астон.Движение'!F35,'Астон.Реформа'!F35,'Милый дом'!F35,'River Park'!F35) | G35: =SUM('Астон.Движение'!G35,'Астон.Реформа'!G35,'Милый дом'!G35,'River Park'!G35) | H35: - | I35: =SUM('Астон.Движение'!I35,'Астон.Реформа'!I35,'Милый дом'!I35,'River Park'!I35)
A36: Заработная плата МО АУП | B36: =SUM('Астон.Движение'!B36,'Астон.Реформа'!B36,'Милый дом'!B36,'River Park'!B36) | C36: =SUM('Астон.Движение'!C36,'Астон.Реформа'!C36,'Милый дом'!C36,'River Park'!C36) | D36: =SUM('Астон.Движение'!D36,'Астон.Реформа'!D36,'Милый дом'!D36,'River Park'!D36) | E36: =SUM('Астон.Движение'!E36,'Астон.Реформа'!E36,'Милый дом'!E36,'River Park'!E36) | F36: =SUM('Астон.Движение'!F36,'Астон.Реформа'!F36,'Милый дом'!F36,'River Park'!F36) | G36: =SUM('Астон.Движение'!G36,'Астон.Реформа'!G36,'Милый дом'!G36,'River Park'!G36) | H36: - | I36: =SUM('Астон.Движение'!I36,'Астон.Реформа'!I36,'Милый дом'!I36,'River Park'!I36)
A37: Инструменты: ГСМ | B37: =SUM('Астон.Движение'!B37,'Астон.Реформа'!B37,'Милый дом'!B37,'River Park'!B37) | C37: =SUM('Астон.Движение'!C37,'Астон.Реформа'!C37,'Милый дом'!C37,'River Park'!C37) | D37: =SUM('Астон.Движение'!D37,'Астон.Реформа'!D37,'Милый дом'!D37,'River Park'!D37) | E37: =SUM('Астон.Движение'!E37,'Астон.Реформа'!E37,'Милый дом'!E37,'River Park'!E37) | F37: =SUM('Астон.Движение'!F37,'Астон.Реформа'!F37,'Милый дом'!F37,'River Park'!F37) | G37: =SUM('Астон.Движение'!G37,'Астон.Реформа'!G37,'Милый дом'!G37,'River Park'!G37) | H37: - | I37: =SUM('Астон.Движение'!I37,'Астон.Реформа'!I37,'Милый дом'!I37,'River Park'!I37)
A38: Медосмотры | B38: =SUM('Астон.Движение'!B38,'Астон.Реформа'!B38,'Милый дом'!B38,'River Park'!B38) | C38: =SUM('Астон.Движение'!C38,'Астон.Реформа'!C38,'Милый дом'!C38,'River Park'!C38) | D38: =SUM('Астон.Движение'!D38,'Астон.Реформа'!D38,'Милый дом'!D38,'River Park'!D38) | E38: =SUM('Астон.Движение'!E38,'Астон.Реформа'!E38,'Милый дом'!E38,'River Park'!E38) | F38: =SUM('Астон.Движение'!F38,'Астон.Реформа'!F38,'Милый дом'!F38,'River Park'!F38) | G38: =SUM('Астон.Движение'!G38,'Астон.Реформа'!G38,'Милый дом'!G38,'River Park'!G38) | H38: - | I38: =SUM('Астон.Движение'!I38,'Астон.Реформа'!I38,'Милый дом'!I38,'River Park'!I38)
A39: Налоги с ФОТ (ИП) | B39: =SUM('Астон.Движение'!B39,'Астон.Реформа'!B39,'Милый дом'!B39,'River Park'!B39) | C39: =SUM('Астон.Движение'!C39,'Астон.Реформа'!C39,'Милый дом'!C39,'River Park'!C39) | D39: =SUM('Астон.Движение'!D39,'Астон.Реформа'!D39,'Милый дом'!D39,'River Park'!D39) | E39: =SUM('Астон.Движение'!E39,'Астон.Реформа'!E39,'Милый дом'!E39,'River Park'!E39) | F39: =SUM('Астон.Движение'!F39,'Астон.Реформа'!F39,'Милый дом'!F39,'River Park'!F39) | G39: =SUM('Астон.Движение'!G39,'Астон.Реформа'!G39,'Милый дом'!G39,'River Park'!G39) | H39: - | I39: =SUM('Астон.Движение'!I39,'Астон.Реформа'!I39,'Милый дом'!I39,'River Park'!I39)
A40: Приобритение мебели, бытовой техники | B40: =SUM('Астон.Движение'!B40,'Астон.Реформа'!B40,'Милый дом'!B40,'River Park'!B40) | C40: =SUM('Астон.Движение'!C40,'Астон.Реформа'!C40,'Милый дом'!C40,'River Park'!C40) | D40: =SUM('Астон.Движение'!D40,'Астон.Реформа'!D40,'Милый дом'!D40,'River Park'!D40) | E40: =SUM('Астон.Движение'!E40,'Астон.Реформа'!E40,'Милый дом'!E40,'River Park'!E40) | F40: =SUM('Астон.Движение'!F40,'Астон.Реформа'!F40,'Милый дом'!F40,'River Park'!F40) | G40: =SUM('Астон.Движение'!G40,'Астон.Реформа'!G40,'Милый дом'!G40,'River Park'!G40) | H40: - | I40: =SUM('Астон.Движение'!I40,'Астон.Реформа'!I40,'Милый дом'!I40,'River Park'!I40)
A41: Комиссия за перевод ЗП | B41: =SUM('Астон.Движение'!B41,'Астон.Реформа'!B41,'Милый дом'!B41,'River Park'!B41) | C41: =SUM('Астон.Движение'!C41,'Астон.Реформа'!C41,'Милый дом'!C41,'River Park'!C41) | D41: =SUM('Астон.Движение'!D41,'Астон.Реформа'!D41,'Милый дом'!D41,'River Park'!D41) | E41: =SUM('Астон.Движение'!E41,'Астон.Реформа'!E41,'Милый дом'!E41,'River Park'!E41) | F41: =SUM('Астон.Движение'!F41,'Астон.Реформа'!F41,'Милый дом'!F41,'River Park'!F41) | G41: =SUM('Астон.Движение'!G41,'Астон.Реформа'!G41,'Милый дом'!G41,'River Park'!G41) | H41: - | I41: =SUM('Астон.Движение'!I41,'Астон.Реформа'!I41,'Милый дом'!I41,'River Park'!I41)
A42: Аренда квартиры (включая коммуналку) | B42: =SUM('Астон.Движение'!B42,'Астон.Реформа'!B42,'Милый дом'!B42,'River Park'!B42) | C42: =SUM('Астон.Движение'!C42,'Астон.Реформа'!C42,'Милый дом'!C42,'River Park'!C42) | D42: =SUM('Астон.Движение'!D42,'Астон.Реформа'!D42,'Милый дом'!D42,'River Park'!D42) | E42: =SUM('Астон.Движение'!E42,'Астон.Реформа'!E42,'Милый дом'!E42,'River Park'!E42) | F42: =SUM('Астон.Движение'!F42,'Астон.Реформа'!F42,'Милый дом'!F42,'River Park'!F42) | G42: =SUM('Астон.Движение'!G42,'Астон.Реформа'!G42,'Милый дом'!G42,'River Park'!G42) | H42: - | I42: =SUM('Астон.Движение'!I42,'Астон.Реформа'!I42,'Милый дом'!I42,'River Park'!I42)
A43: Валовая прибыль | B43: =B4-B10 | C43: =C4-C10 | D43: =D4-D10 | E43: =E4-E10 | F43: =F4-F10 | G43: =G4-G10 | H43: - | I43: =I4-I10
A44: Валовая рентабельность | B44: =IFERROR(IF(B4=0,"-",B43/B4),"-") | C44: =IFERROR(IF(C4=0,"-",C43/C4),"-") | D44: =IFERROR(IF(D4=0,"-",D43/D4),"-") | E44: =IFERROR(IF(E4=0,"-",E43/E4),"-") | F44: =IFERROR(IF(F4=0,"-",F43/F4),"-") | G44: =IFERROR(IF(G4=0,"-",G43/G4),"-") | H44: - | I44: =IFERROR(IF(I4=0,"-",I43/I4),"-")
A45: Косвенные расходы | B45: =SUM(B46,B47,B48,B52,B56,B57,B58,B59,B60,B63,B64,B65,B66,B67,B68,B69,B70,B71,B72,B73,B74,B75,B76,B77,B78,B79) | C45: =SUM(C46,C47,C48,C52,C56,C57,C58,C59,C60,C63,C64,C65,C66,C67,C68,C69,C70,C71,C72,C73,C74,C75,C76,C77,C78,C79) | D45: =SUM(D46,D47,D48,D52,D56,D57,D58,D59,D60,D63,D64,D65,D66,D67,D68,D69,D70,D71,D72,D73,D74,D75,D76,D77,D78,D79) | E45: =SUM(E46,E47,E48,E52,E56,E57,E58,E59,E60,E63,E64,E65,E66,E67,E68,E69,E70,E71,E72,E73,E74,E75,E76,E77,E78,E79) | F45: =SUM(F46,F47,F48,F52,F56,F57,F58,F59,F60,F63,F64,F65,F66,F67,F68,F69,F70,F71,F72,F73,F74,F75,F76,F77,F78,F79) | G45: =SUM(G46,G47,G48,G52,G56,G57,G58,G59,G60,G63,G64,G65,G66,G67,G68,G69,G70,G71,G72,G73,G74,G75,G76,G77,G78,G79) | H45: - | I45: =SUM(I46,I47,I48,I52,I56,I57,I58,I59,I60,I63,I64,I65,I66,I67,I68,I69,I70,I71,I72,I73,I74,I75,I76,I77,I78,I79)
A46: Расход БЭК-ОФИС | B46: =SUM('Астон.Движение'!B46,'Астон.Реформа'!B46,'Милый дом'!B46,'River Park'!B46) | C46: =SUM('Астон.Движение'!C46,'Астон.Реформа'!C46,'Милый дом'!C46,'River Park'!C46) | D46: =SUM('Астон.Движение'!D46,'Астон.Реформа'!D46,'Милый дом'!D46,'River Park'!D46) | E46: =SUM('Астон.Движение'!E46,'Астон.Реформа'!E46,'Милый дом'!E46,'River Park'!E46) | F46: =SUM('Астон.Движение'!F46,'Астон.Реформа'!F46,'Милый дом'!F46,'River Park'!F46) | G46: =SUM('Астон.Движение'!G46,'Астон.Реформа'!G46,'Милый дом'!G46,'River Park'!G46) | H46: - | I46: =SUM('Астон.Движение'!I46,'Астон.Реформа'!I46,'Милый дом'!I46,'River Park'!I46)
A47: Расходы на бэк-офис | B47: =SUM('Астон.Движение'!B47,'Астон.Реформа'!B47,'Милый дом'!B47,'River Park'!B47) | C47: =SUM('Астон.Движение'!C47,'Астон.Реформа'!C47,'Милый дом'!C47,'River Park'!C47) | D47: =SUM('Астон.Движение'!D47,'Астон.Реформа'!D47,'Милый дом'!D47,'River Park'!D47) | E47: =SUM('Астон.Движение'!E47,'Астон.Реформа'!E47,'Милый дом'!E47,'River Park'!E47) | F47: =SUM('Астон.Движение'!F47,'Астон.Реформа'!F47,'Милый дом'!F47,'River Park'!F47) | G47: =SUM('Астон.Движение'!G47,'Астон.Реформа'!G47,'Милый дом'!G47,'River Park'!G47) | H47: - | I47: =SUM('Астон.Движение'!I47,'Астон.Реформа'!I47,'Милый дом'!I47,'River Park'!I47)
A48: Автомобиль | B48: =SUM(B49,B50,B51) | C48: =SUM(C49,C50,C51) | D48: =SUM(D49,D50,D51) | E48: =SUM(E49,E50,E51) | F48: =SUM(F49,F50,F51) | G48: =SUM(G49,G50,G51) | H48: - | I48: =SUM(I49,I50,I51)
A49: Автомобиль: ГСМ | B49: =SUM('Астон.Движение'!B49,'Астон.Реформа'!B49,'Милый дом'!B49,'River Park'!B49) | C49: =SUM('Астон.Движение'!C49,'Астон.Реформа'!C49,'Милый дом'!C49,'River Park'!C49) | D49: =SUM('Астон.Движение'!D49,'Астон.Реформа'!D49,'Милый дом'!D49,'River Park'!D49) | E49: =SUM('Астон.Движение'!E49,'Астон.Реформа'!E49,'Милый дом'!E49,'River Park'!E49) | F49: =SUM('Астон.Движение'!F49,'Астон.Реформа'!F49,'Милый дом'!F49,'River Park'!F49) | G49: =SUM('Астон.Движение'!G49,'Астон.Реформа'!G49,'Милый дом'!G49,'River Park'!G49) | H49: - | I49: =SUM('Астон.Движение'!I49,'Астон.Реформа'!I49,'Милый дом'!I49,'River Park'!I49)
A50: Автомобиль: страхование | B50: =SUM('Астон.Движение'!B50,'Астон.Реформа'!B50,'Милый дом'!B50,'River Park'!B50) | C50: =SUM('Астон.Движение'!C50,'Астон.Реформа'!C50,'Милый дом'!C50,'River Park'!C50) | D50: =SUM('Астон.Движение'!D50,'Астон.Реформа'!D50,'Милый дом'!D50,'River Park'!D50) | E50: =SUM('Астон.Движение'!E50,'Астон.Реформа'!E50,'Милый дом'!E50,'River Park'!E50) | F50: =SUM('Астон.Движение'!F50,'Астон.Реформа'!F50,'Милый дом'!F50,'River Park'!F50) | G50: =SUM('Астон.Движение'!G50,'Астон.Реформа'!G50,'Милый дом'!G50,'River Park'!G50) | H50: - | I50: =SUM('Астон.Движение'!I50,'Астон.Реформа'!I50,'Милый дом'!I50,'River Park'!I50)
A51: Автомобиль: ТО | B51: =SUM('Астон.Движение'!B51,'Астон.Реформа'!B51,'Милый дом'!B51,'River Park'!B51) | C51: =SUM('Астон.Движение'!C51,'Астон.Реформа'!C51,'Милый дом'!C51,'River Park'!C51) | D51: =SUM('Астон.Движение'!D51,'Астон.Реформа'!D51,'Милый дом'!D51,'River Park'!D51) | E51: =SUM('Астон.Движение'!E51,'Астон.Реформа'!E51,'Милый дом'!E51,'River Park'!E51) | F51: =SUM('Астон.Движение'!F51,'Астон.Реформа'!F51,'Милый дом'!F51,'River Park'!F51) | G51: =SUM('Астон.Движение'!G51,'Астон.Реформа'!G51,'Милый дом'!G51,'River Park'!G51) | H51: - | I51: =SUM('Астон.Движение'!I51,'Астон.Реформа'!I51,'Милый дом'!I51,'River Park'!I51)
A52: Офисные расходы | B52: =SUM(B53,B54,B55) | C52: =SUM(C53,C54,C55) | D52: =SUM(D53,D54,D55) | E52: =SUM(E53,E54,E55) | F52: =SUM(F53,F54,F55) | G52: =SUM(G53,G54,G55) | H52: - | I52: =SUM(I53,I54,I55)
A53: Аренда офиса | B53: =SUM('Астон.Движение'!B53,'Астон.Реформа'!B53,'Милый дом'!B53,'River Park'!B53) | C53: =SUM('Астон.Движение'!C53,'Астон.Реформа'!C53,'Милый дом'!C53,'River Park'!C53) | D53: =SUM('Астон.Движение'!D53,'Астон.Реформа'!D53,'Милый дом'!D53,'River Park'!D53) | E53: =SUM('Астон.Движение'!E53,'Астон.Реформа'!E53,'Милый дом'!E53,'River Park'!E53) | F53: =SUM('Астон.Движение'!F53,'Астон.Реформа'!F53,'Милый дом'!F53,'River Park'!F53) | G53: =SUM('Астон.Движение'!G53,'Астон.Реформа'!G53,'Милый дом'!G53,'River Park'!G53) | H53: - | I53: =SUM('Астон.Движение'!I53,'Астон.Реформа'!I53,'Милый дом'!I53,'River Park'!I53)
A54: Канцелярия и обслуживание | B54: =SUM('Астон.Движение'!B54,'Астон.Реформа'!B54,'Милый дом'!B54,'River Park'!B54) | C54: =SUM('Астон.Движение'!C54,'Астон.Реформа'!C54,'Милый дом'!C54,'River Park'!C54) | D54: =SUM('Астон.Движение'!D54,'Астон.Реформа'!D54,'Милый дом'!D54,'River Park'!D54) | E54: =SUM('Астон.Движение'!E54,'Астон.Реформа'!E54,'Милый дом'!E54,'River Park'!E54) | F54: =SUM('Астон.Движение'!F54,'Астон.Реформа'!F54,'Милый дом'!F54,'River Park'!F54) | G54: =SUM('Астон.Движение'!G54,'Астон.Реформа'!G54,'Милый дом'!G54,'River Park'!G54) | H54: - | I54: =SUM('Астон.Движение'!I54,'Астон.Реформа'!I54,'Милый дом'!I54,'River Park'!I54)
A55: Интернет и связь | B55: =SUM('Астон.Движение'!B55,'Астон.Реформа'!B55,'Милый дом'!B55,'River Park'!B55) | C55: =SUM('Астон.Движение'!C55,'Астон.Реформа'!C55,'Милый дом'!C55,'River Park'!C55) | D55: =SUM('Астон.Движение'!D55,'Астон.Реформа'!D55,'Милый дом'!D55,'River Park'!D55) | E55: =SUM('Астон.Движение'!E55,'Астон.Реформа'!E55,'Милый дом'!E55,'River Park'!E55) | F55: =SUM('Астон.Движение'!F55,'Астон.Реформа'!F55,'Милый дом'!F55,'River Park'!F55) | G55: =SUM('Астон.Движение'!G55,'Астон.Реформа'!G55,'Милый дом'!G55,'River Park'!G55) | H55: - | I55: =SUM('Астон.Движение'!I55,'Астон.Реформа'!I55,'Милый дом'!I55,'River Park'!I55)
A56: Банковские услуги | B56: =SUM('Астон.Движение'!B56,'Астон.Реформа'!B56,'Милый дом'!B56,'River Park'!B56) | C56: =SUM('Астон.Движение'!C56,'Астон.Реформа'!C56,'Милый дом'!C56,'River Park'!C56) | D56: =SUM('Астон.Движение'!D56,'Астон.Реформа'!D56,'Милый дом'!D56,'River Park'!D56) | E56: =SUM('Астон.Движение'!E56,'Астон.Реформа'!E56,'Милый дом'!E56,'River Park'!E56) | F56: =SUM('Астон.Движение'!F56,'Астон.Реформа'!F56,'Милый дом'!F56,'River Park'!F56) | G56: =SUM('Астон.Движение'!G56,'Астон.Реформа'!G56,'Милый дом'!G56,'River Park'!G56) | H56: - | I56: =SUM('Астон.Движение'!I56,'Астон.Реформа'!I56,'Милый дом'!I56,'River Park'!I56)
A57: Заработная плата АУП (БО) | B57: =SUM('Астон.Движение'!B57,'Астон.Реформа'!B57,'Милый дом'!B57,'River Park'!B57) | C57: =SUM('Астон.Движение'!C57,'Астон.Реформа'!C57,'Милый дом'!C57,'River Park'!C57) | D57: =SUM('Астон.Движение'!D57,'Астон.Реформа'!D57,'Милый дом'!D57,'River Park'!D57) | E57: =SUM('Астон.Движение'!E57,'Астон.Реформа'!E57,'Милый дом'!E57,'River Park'!E57) | F57: =SUM('Астон.Движение'!F57,'Астон.Реформа'!F57,'Милый дом'!F57,'River Park'!F57) | G57: =SUM('Астон.Движение'!G57,'Астон.Реформа'!G57,'Милый дом'!G57,'River Park'!G57) | H57: - | I57: =SUM('Астон.Движение'!I57,'Астон.Реформа'!I57,'Милый дом'!I57,'River Park'!I57)
A58: Заработная плата бухгалтерии (БО) | B58: =SUM('Астон.Движение'!B58,'Астон.Реформа'!B58,'Милый дом'!B58,'River Park'!B58) | C58: =SUM('Астон.Движение'!C58,'Астон.Реформа'!C58,'Милый дом'!C58,'River Park'!C58) | D58: =SUM('Астон.Движение'!D58,'Астон.Реформа'!D58,'Милый дом'!D58,'River Park'!D58) | E58: =SUM('Астон.Движение'!E58,'Астон.Реформа'!E58,'Милый дом'!E58,'River Park'!E58) | F58: =SUM('Астон.Движение'!F58,'Астон.Реформа'!F58,'Милый дом'!F58,'River Park'!F58) | G58: =SUM('Астон.Движение'!G58,'Астон.Реформа'!G58,'Милый дом'!G58,'River Park'!G58) | H58: - | I58: =SUM('Астон.Движение'!I58,'Астон.Реформа'!I58,'Милый дом'!I58,'River Park'!I58)
A59: Заработная плата СБ (БО) | B59: =SUM('Астон.Движение'!B59,'Астон.Реформа'!B59,'Милый дом'!B59,'River Park'!B59) | C59: =SUM('Астон.Движение'!C59,'Астон.Реформа'!C59,'Милый дом'!C59,'River Park'!C59) | D59: =SUM('Астон.Движение'!D59,'Астон.Реформа'!D59,'Милый дом'!D59,'River Park'!D59) | E59: =SUM('Астон.Движение'!E59,'Астон.Реформа'!E59,'Милый дом'!E59,'River Park'!E59) | F59: =SUM('Астон.Движение'!F59,'Астон.Реформа'!F59,'Милый дом'!F59,'River Park'!F59) | G59: =SUM('Астон.Движение'!G59,'Астон.Реформа'!G59,'Милый дом'!G59,'River Park'!G59) | H59: - | I59: =SUM('Астон.Движение'!I59,'Астон.Реформа'!I59,'Милый дом'!I59,'River Park'!I59)
A60: Командировочные расходы | B60: =SUM(B61,B62) | C60: =SUM(C61,C62) | D60: =SUM(D61,D62) | E60: =SUM(E61,E62) | F60: =SUM(F61,F62) | G60: =SUM(G61,G62) | H60: - | I60: =SUM(I61,I62)
A61: Командировнчеы расходы: билеты (БО) | B61: =SUM('Астон.Движение'!B61,'Астон.Реформа'!B61,'Милый дом'!B61,'River Park'!B61) | C61: =SUM('Астон.Движение'!C61,'Астон.Реформа'!C61,'Милый дом'!C61,'River Park'!C61) | D61: =SUM('Астон.Движение'!D61,'Астон.Реформа'!D61,'Милый дом'!D61,'River Park'!D61) | E61: =SUM('Астон.Движение'!E61,'Астон.Реформа'!E61,'Милый дом'!E61,'River Park'!E61) | F61: =SUM('Астон.Движение'!F61,'Астон.Реформа'!F61,'Милый дом'!F61,'River Park'!F61) | G61: =SUM('Астон.Движение'!G61,'Астон.Реформа'!G61,'Милый дом'!G61,'River Park'!G61) | H61: - | I61: =SUM('Астон.Движение'!I61,'Астон.Реформа'!I61,'Милый дом'!I61,'River Park'!I61)
A62: Командировнчеы расходы: проживание (БО) | B62: =SUM('Астон.Движение'!B62,'Астон.Реформа'!B62,'Милый дом'!B62,'River Park'!B62) | C62: =SUM('Астон.Движение'!C62,'Астон.Реформа'!C62,'Милый дом'!C62,'River Park'!C62) | D62: =SUM('Астон.Движение'!D62,'Астон.Реформа'!D62,'Милый дом'!D62,'River Park'!D62) | E62: =SUM('Астон.Движение'!E62,'Астон.Реформа'!E62,'Милый дом'!E62,'River Park'!E62) | F62: =SUM('Астон.Движение'!F62,'Астон.Реформа'!F62,'Милый дом'!F62,'River Park'!F62) | G62: =SUM('Астон.Движение'!G62,'Астон.Реформа'!G62,'Милый дом'!G62,'River Park'!G62) | H62: - | I62: =SUM('Астон.Движение'!I62,'Астон.Реформа'!I62,'Милый дом'!I62,'River Park'!I62)
A63: Комиссия УК ДОМ | B63: =SUM('Астон.Движение'!B63,'Астон.Реформа'!B63,'Милый дом'!B63,'River Park'!B63) | C63: =SUM('Астон.Движение'!C63,'Астон.Реформа'!C63,'Милый дом'!C63,'River Park'!C63) | D63: =SUM('Астон.Движение'!D63,'Астон.Реформа'!D63,'Милый дом'!D63,'River Park'!D63) | E63: =SUM('Астон.Движение'!E63,'Астон.Реформа'!E63,'Милый дом'!E63,'River Park'!E63) | F63: =SUM('Астон.Движение'!F63,'Астон.Реформа'!F63,'Милый дом'!F63,'River Park'!F63) | G63: =SUM('Астон.Движение'!G63,'Астон.Реформа'!G63,'Милый дом'!G63,'River Park'!G63) | H63: - | I63: =SUM('Астон.Движение'!I63,'Астон.Реформа'!I63,'Милый дом'!I63,'River Park'!I63)
A64: Налоги с ФОТ (ИП)_БО | B64: =SUM('Астон.Движение'!B64,'Астон.Реформа'!B64,'Милый дом'!B64,'River Park'!B64) | C64: =SUM('Астон.Движение'!C64,'Астон.Реформа'!C64,'Милый дом'!C64,'River Park'!C64) | D64: =SUM('Астон.Движение'!D64,'Астон.Реформа'!D64,'Милый дом'!D64,'River Park'!D64) | E64: =SUM('Астон.Движение'!E64,'Астон.Реформа'!E64,'Милый дом'!E64,'River Park'!E64) | F64: =SUM('Астон.Движение'!F64,'Астон.Реформа'!F64,'Милый дом'!F64,'River Park'!F64) | G64: =SUM('Астон.Движение'!G64,'Астон.Реформа'!G64,'Милый дом'!G64,'River Park'!G64) | H64: - | I64: =SUM('Астон.Движение'!I64,'Астон.Реформа'!I64,'Милый дом'!I64,'River Park'!I64)
A65: Налоги с ФОТ (НДФЛ) БО | B65: =SUM('Астон.Движение'!B65,'Астон.Реформа'!B65,'Милый дом'!B65,'River Park'!B65) | C65: =SUM('Астон.Движение'!C65,'Астон.Реформа'!C65,'Милый дом'!C65,'River Park'!C65) | D65: =SUM('Астон.Движение'!D65,'Астон.Реформа'!D65,'Милый дом'!D65,'River Park'!D65) | E65: =SUM('Астон.Движение'!E65,'Астон.Реформа'!E65,'Милый дом'!E65,'River Park'!E65) | F65: =SUM('Астон.Движение'!F65,'Астон.Реформа'!F65,'Милый дом'!F65,'River Park'!F65) | G65: =SUM('Астон.Движение'!G65,'Астон.Реформа'!G65,'Милый дом'!G65,'River Park'!G65) | H65: - | I65: =SUM('Астон.Движение'!I65,'Астон.Реформа'!I65,'Милый дом'!I65,'River Park'!I65)
A66: Налоги с ФОТ (страховые взносы) БО | B66: =SUM('Астон.Движение'!B66,'Астон.Реформа'!B66,'Милый дом'!B66,'River Park'!B66) | C66: =SUM('Астон.Движение'!C66,'Астон.Реформа'!C66,'Милый дом'!C66,'River Park'!C66) | D66: =SUM('Астон.Движение'!D66,'Астон.Реформа'!D66,'Милый дом'!D66,'River Park'!D66) | E66: =SUM('Астон.Движение'!E66,'Астон.Реформа'!E66,'Милый дом'!E66,'River Park'!E66) | F66: =SUM('Астон.Движение'!F66,'Астон.Реформа'!F66,'Милый дом'!F66,'River Park'!F66) | G66: =SUM('Астон.Движение'!G66,'Астон.Реформа'!G66,'Милый дом'!G66,'River Park'!G66) | H66: - | I66: =SUM('Астон.Движение'!I66,'Астон.Реформа'!I66,'Милый дом'!I66,'River Park'!I66)
A67: Нотариальные услуги | B67: =SUM('Астон.Движение'!B67,'Астон.Реформа'!B67,'Милый дом'!B67,'River Park'!B67) | C67: =SUM('Астон.Движение'!C67,'Астон.Реформа'!C67,'Милый дом'!C67,'River Park'!C67) | D67: =SUM('Астон.Движение'!D67,'Астон.Реформа'!D67,'Милый дом'!D67,'River Park'!D67) | E67: =SUM('Астон.Движение'!E67,'Астон.Реформа'!E67,'Милый дом'!E67,'River Park'!E67) | F67: =SUM('Астон.Движение'!F67,'Астон.Реформа'!F67,'Милый дом'!F67,'River Park'!F67) | G67: =SUM('Астон.Движение'!G67,'Астон.Реформа'!G67,'Милый дом'!G67,'River Park'!G67) | H67: - | I67: =SUM('Астон.Движение'!I67,'Астон.Реформа'!I67,'Милый дом'!I67,'River Park'!I67)
A68: Обслуживание техники (БО) | B68: =SUM('Астон.Движение'!B68,'Астон.Реформа'!B68,'Милый дом'!B68,'River Park'!B68) | C68: =SUM('Астон.Движение'!C68,'Астон.Реформа'!C68,'Милый дом'!C68,'River Park'!C68) | D68: =SUM('Астон.Движение'!D68,'Астон.Реформа'!D68,'Милый дом'!D68,'River Park'!D68) | E68: =SUM('Астон.Движение'!E68,'Астон.Реформа'!E68,'Милый дом'!E68,'River Park'!E68) | F68: =SUM('Астон.Движение'!F68,'Астон.Реформа'!F68,'Милый дом'!F68,'River Park'!F68) | G68: =SUM('Астон.Движение'!G68,'Астон.Реформа'!G68,'Милый дом'!G68,'River Park'!G68) | H68: - | I68: =SUM('Астон.Движение'!I68,'Астон.Реформа'!I68,'Милый дом'!I68,'River Park'!I68)
A69: Программное обеспечение (БО) | B69: =SUM('Астон.Движение'!B69,'Астон.Реформа'!B69,'Милый дом'!B69,'River Park'!B69) | C69: =SUM('Астон.Движение'!C69,'Астон.Реформа'!C69,'Милый дом'!C69,'River Park'!C69) | D69: =SUM('Астон.Движение'!D69,'Астон.Реформа'!D69,'Милый дом'!D69,'River Park'!D69) | E69: =SUM('Астон.Движение'!E69,'Астон.Реформа'!E69,'Милый дом'!E69,'River Park'!E69) | F69: =SUM('Астон.Движение'!F69,'Астон.Реформа'!F69,'Милый дом'!F69,'River Park'!F69) | G69: =SUM('Астон.Движение'!G69,'Астон.Реформа'!G69,'Милый дом'!G69,'River Park'!G69) | H69: - | I69: =SUM('Астон.Движение'!I69,'Астон.Реформа'!I69,'Милый дом'!I69,'River Park'!I69)
A70: ПланФакт | B70: =SUM('Астон.Движение'!B70,'Астон.Реформа'!B70,'Милый дом'!B70,'River Park'!B70) | C70: =SUM('Астон.Движение'!C70,'Астон.Реформа'!C70,'Милый дом'!C70,'River Park'!C70) | D70: =SUM('Астон.Движение'!D70,'Астон.Реформа'!D70,'Милый дом'!D70,'River Park'!D70) | E70: =SUM('Астон.Движение'!E70,'Астон.Реформа'!E70,'Милый дом'!E70,'River Park'!E70) | F70: =SUM('Астон.Движение'!F70,'Астон.Реформа'!F70,'Милый дом'!F70,'River Park'!F70) | G70: =SUM('Астон.Движение'!G70,'Астон.Реформа'!G70,'Милый дом'!G70,'River Park'!G70) | H70: - | I70: =SUM('Астон.Движение'!I70,'Астон.Реформа'!I70,'Милый дом'!I70,'River Park'!I70)
A71: ТБ | B71: =SUM('Астон.Движение'!B71,'Астон.Реформа'!B71,'Милый дом'!B71,'River Park'!B71) | C71: =SUM('Астон.Движение'!C71,'Астон.Реформа'!C71,'Милый дом'!C71,'River Park'!C71) | D71: =SUM('Астон.Движение'!D71,'Астон.Реформа'!D71,'Милый дом'!D71,'River Park'!D71) | E71: =SUM('Астон.Движение'!E71,'Астон.Реформа'!E71,'Милый дом'!E71,'River Park'!E71) | F71: =SUM('Астон.Движение'!F71,'Астон.Реформа'!F71,'Милый дом'!F71,'River Park'!F71) | G71: =SUM('Астон.Движение'!G71,'Астон.Реформа'!G71,'Милый дом'!G71,'River Park'!G71) | H71: - | I71: =SUM('Астон.Движение'!I71,'Астон.Реформа'!I71,'Милый дом'!I71,'River Park'!I71)
A72: Контур | B72: =SUM('Астон.Движение'!B72,'Астон.Реформа'!B72,'Милый дом'!B72,'River Park'!B72) | C72: =SUM('Астон.Движение'!C72,'Астон.Реформа'!C72,'Милый дом'!C72,'River Park'!C72) | D72: =SUM('Астон.Движение'!D72,'Астон.Реформа'!D72,'Милый дом'!D72,'River Park'!D72) | E72: =SUM('Астон.Движение'!E72,'Астон.Реформа'!E72,'Милый дом'!E72,'River Park'!E72) | F72: =SUM('Астон.Движение'!F72,'Астон.Реформа'!F72,'Милый дом'!F72,'River Park'!F72) | G72: =SUM('Астон.Движение'!G72,'Астон.Реформа'!G72,'Милый дом'!G72,'River Park'!G72) | H72: - | I72: =SUM('Астон.Движение'!I72,'Астон.Реформа'!I72,'Милый дом'!I72,'River Park'!I72)
... A79: HR (аутсорс) | B79: =SUM('Астон.Движение'!B79,'Астон.Реформа'!B79,'Милый дом'!B79,'River Park'!B79) | C79: =SUM('Астон.Движение'!C79,'Астон.Реформа'!C79,'Милый дом'!C79,'River Park'!C79) | D79: =SUM('Астон.Движение'!D79,'Астон.Реформа'!D79,'Милый дом'!D79,'River Park'!D79) | E79: =SUM('Астон.Движение'!E79,'Астон.Реформа'!E79,'Милый дом'!E79,'River Park'!E79) | F79: =SUM('Астон.Движение'!F79,'Астон.Реформа'!F79,'Милый дом'!F79,'River Park'!F79) | G79: =SUM('Астон.Движение'!G79,'Астон.Реформа'!G79,'Милый дом'!G79,'River Park'!G79) | H79: - | I79: =SUM('Астон.Движение'!I79,'Астон.Реформа'!I79,'Милый дом'!I79,'River Park'!I79)
A80: Операционная прибыль | B80: =B43-B45 | C80: =C43-C45 | D80: =D43-D45 | E80: =E43-E45 | F80: =F43-F45 | G80: =G43-G45 | H80: - | I80: =I43-I45
A81: Операционная рентабельность | B81: =IFERROR(IF(B4=0,"-",B80/B4),"-") | C81: =IFERROR(IF(C4=0,"-",C80/C4),"-") | D81: =IFERROR(IF(D4=0,"-",D80/D4),"-") | E81: =IFERROR(IF(E4=0,"-",E80/E4),"-") | F81: =IFERROR(IF(F4=0,"-",F80/F4),"-") | G81: =IFERROR(IF(G4=0,"-",G80/G4),"-") | H81: - | I81: =IFERROR(IF(I4=0,"-",I80/I4),"-")
A82: Прочие доходы | B82: =SUM(B83,B84,B85,B86) | C82: =SUM(C83,C84,C85,C86) | D82: =SUM(D83,D84,D85,D86) | E82: =SUM(E83,E84,E85,E86) | F82: =SUM(F83,F84,F85,F86) | G82: =SUM(G83,G84,G85,G86) | H82: - | I82: =SUM(I83,I84,I85,I86)
A83: Доход БЭК-ОФИС | B83: =SUM('Астон.Движение'!B83,'Астон.Реформа'!B83,'Милый дом'!B83,'River Park'!B83) | C83: =SUM('Астон.Движение'!C83,'Астон.Реформа'!C83,'Милый дом'!C83,'River Park'!C83) | D83: =SUM('Астон.Движение'!D83,'Астон.Реформа'!D83,'Милый дом'!D83,'River Park'!D83) | E83: =SUM('Астон.Движение'!E83,'Астон.Реформа'!E83,'Милый дом'!E83,'River Park'!E83) | F83: =SUM('Астон.Движение'!F83,'Астон.Реформа'!F83,'Милый дом'!F83,'River Park'!F83) | G83: =SUM('Астон.Движение'!G83,'Астон.Реформа'!G83,'Милый дом'!G83,'River Park'!G83) | H83: - | I83: =SUM('Астон.Движение'!I83,'Астон.Реформа'!I83,'Милый дом'!I83,'River Park'!I83)
A84: Пополненин бэк-офис | B84: =SUM('Астон.Движение'!B84,'Астон.Реформа'!B84,'Милый дом'!B84,'River Park'!B84) | C84: =SUM('Астон.Движение'!C84,'Астон.Реформа'!C84,'Милый дом'!C84,'River Park'!C84) | D84: =SUM('Астон.Движение'!D84,'Астон.Реформа'!D84,'Милый дом'!D84,'River Park'!D84) | E84: =SUM('Астон.Движение'!E84,'Астон.Реформа'!E84,'Милый дом'!E84,'River Park'!E84) | F84: =SUM('Астон.Движение'!F84,'Астон.Реформа'!F84,'Милый дом'!F84,'River Park'!F84) | G84: =SUM('Астон.Движение'!G84,'Астон.Реформа'!G84,'Милый дом'!G84,'River Park'!G84) | H84: - | I84: =SUM('Астон.Движение'!I84,'Астон.Реформа'!I84,'Милый дом'!I84,'River Park'!I84)
A85: Проценты по вкладам | B85: =SUM('Астон.Движение'!B85,'Астон.Реформа'!B85,'Милый дом'!B85,'River Park'!B85) | C85: =SUM('Астон.Движение'!C85,'Астон.Реформа'!C85,'Милый дом'!C85,'River Park'!C85) | D85: =SUM('Астон.Движение'!D85,'Астон.Реформа'!D85,'Милый дом'!D85,'River Park'!D85) | E85: =SUM('Астон.Движение'!E85,'Астон.Реформа'!E85,'Милый дом'!E85,'River Park'!E85) | F85: =SUM('Астон.Движение'!F85,'Астон.Реформа'!F85,'Милый дом'!F85,'River Park'!F85) | G85: =SUM('Астон.Движение'!G85,'Астон.Реформа'!G85,'Милый дом'!G85,'River Park'!G85) | H85: - | I85: =SUM('Астон.Движение'!I85,'Астон.Реформа'!I85,'Милый дом'!I85,'River Park'!I85)
A86: Курсовая разница (+) | B86: =SUM('Астон.Движение'!B86,'Астон.Реформа'!B86,'Милый дом'!B86,'River Park'!B86) | C86: =SUM('Астон.Движение'!C86,'Астон.Реформа'!C86,'Милый дом'!C86,'River Park'!C86) | D86: =SUM('Астон.Движение'!D86,'Астон.Реформа'!D86,'Милый дом'!D86,'River Park'!D86) | E86: =SUM('Астон.Движение'!E86,'Астон.Реформа'!E86,'Милый дом'!E86,'River Park'!E86) | F86: =SUM('Астон.Движение'!F86,'Астон.Реформа'!F86,'Милый дом'!F86,'River Park'!F86) | G86: =SUM('Астон.Движение'!G86,'Астон.Реформа'!G86,'Милый дом'!G86,'River Park'!G86) | H86: - | I86: =SUM('Астон.Движение'!I86,'Астон.Реформа'!I86,'Милый дом'!I86,'River Park'!I86)
A87: Прочие расходы | B87: =SUM(B88) | C87: =SUM(C88) | D87: =SUM(D88) | E87: =SUM(E88) | F87: =SUM(F88) | G87: =SUM(G88) | H87: - | I87: =SUM(I88)
A88: Курсовая разница (-) | B88: =SUM('Астон.Движение'!B88,'Астон.Реформа'!B88,'Милый дом'!B88,'River Park'!B88) | C88: =SUM('Астон.Движение'!C88,'Астон.Реформа'!C88,'Милый дом'!C88,'River Park'!C88) | D88: =SUM('Астон.Движение'!D88,'Астон.Реформа'!D88,'Милый дом'!D88,'River Park'!D88) | E88: =SUM('Астон.Движение'!E88,'Астон.Реформа'!E88,'Милый дом'!E88,'River Park'!E88) | F88: =SUM('Астон.Движение'!F88,'Астон.Реформа'!F88,'Милый дом'!F88,'River Park'!F88) | G88: =SUM('Астон.Движение'!G88,'Астон.Реформа'!G88,'Милый дом'!G88,'River Park'!G88) | H88: - | I88: =SUM('Астон.Движение'!I88,'Астон.Реформа'!I88,'Милый дом'!I88,'River Park'!I88)
A89: EBITDA | B89: =B80+IFERROR(B82*1,0)-IFERROR(B87*1,0) | C89: =C80+IFERROR(C82*1,0)-IFERROR(C87*1,0) | D89: =D80+IFERROR(D82*1,0)-IFERROR(D87*1,0) | E89: =E80+IFERROR(E82*1,0)-IFERROR(E87*1,0) | F89: =F80+IFERROR(F82*1,0)-IFERROR(F87*1,0) | G89: =G80+IFERROR(G82*1,0)-IFERROR(G87*1,0) | H89: - | I89: =I80+IFERROR(I82*1,0)-IFERROR(I87*1,0)
A90: Рентабельность по EBITDA | B90: =IFERROR(IF(B4=0,"-",B89/B4),"-") | C90: =IFERROR(IF(C4=0,"-",C89/C4),"-") | D90: =IFERROR(IF(D4=0,"-",D89/D4),"-") | E90: =IFERROR(IF(E4=0,"-",E89/E4),"-") | F90: =IFERROR(IF(F4=0,"-",F89/F4),"-") | G90: =IFERROR(IF(G4=0,"-",G89/G4),"-") | H90: - | I90: =IFERROR(IF(I4=0,"-",I89/I4),"-")
A91: Амортизация | B91: =SUM(B92,B93) | C91: =SUM(C92,C93) | D91: =SUM(D92,D93) | E91: =SUM(E92,E93) | F91: =SUM(F92,F93) | G91: =SUM(G92,G93) | H91: - | I91: =SUM(I92,I93)
A92: Амортизация ОС (ПТ) | B92: =SUM('Астон.Движение'!B92,'Астон.Реформа'!B92,'Милый дом'!B92,'River Park'!B92) | C92: =SUM('Астон.Движение'!C92,'Астон.Реформа'!C92,'Милый дом'!C92,'River Park'!C92) | D92: =SUM('Астон.Движение'!D92,'Астон.Реформа'!D92,'Милый дом'!D92,'River Park'!D92) | E92: =SUM('Астон.Движение'!E92,'Астон.Реформа'!E92,'Милый дом'!E92,'River Park'!E92) | F92: =SUM('Астон.Движение'!F92,'Астон.Реформа'!F92,'Милый дом'!F92,'River Park'!F92) | G92: =SUM('Астон.Движение'!G92,'Астон.Реформа'!G92,'Милый дом'!G92,'River Park'!G92) | H92: - | I92: =SUM('Астон.Движение'!I92,'Астон.Реформа'!I92,'Милый дом'!I92,'River Park'!I92)
A93: Амортизация ОС (МОП) | B93: =SUM('Астон.Движение'!B93,'Астон.Реформа'!B93,'Милый дом'!B93,'River Park'!B93) | C93: =SUM('Астон.Движение'!C93,'Астон.Реформа'!C93,'Милый дом'!C93,'River Park'!C93) | D93: =SUM('Астон.Движение'!D93,'Астон.Реформа'!D93,'Милый дом'!D93,'River Park'!D93) | E93: =SUM('Астон.Движение'!E93,'Астон.Реформа'!E93,'Милый дом'!E93,'River Park'!E93) | F93: =SUM('Астон.Движение'!F93,'Астон.Реформа'!F93,'Милый дом'!F93,'River Park'!F93) | G93: =SUM('Астон.Движение'!G93,'Астон.Реформа'!G93,'Милый дом'!G93,'River Park'!G93) | H93: - | I93: =SUM('Астон.Движение'!I93,'Астон.Реформа'!I93,'Милый дом'!I93,'River Park'!I93)
A94: Проценты по кредитам и займам | B94: =SUM('Астон.Движение'!B94,'Астон.Реформа'!B94,'Милый дом'!B94,'River Park'!B94) | C94: =SUM('Астон.Движение'!C94,'Астон.Реформа'!C94,'Милый дом'!C94,'River Park'!C94) | D94: =SUM('Астон.Движение'!D94,'Астон.Реформа'!D94,'Милый дом'!D94,'River Park'!D94) | E94: =SUM('Астон.Движение'!E94,'Астон.Реформа'!E94,'Милый дом'!E94,'River Park'!E94) | F94: =SUM('Астон.Движение'!F94,'Астон.Реформа'!F94,'Милый дом'!F94,'River Park'!F94) | G94: =SUM('Астон.Движение'!G94,'Астон.Реформа'!G94,'Милый дом'!G94,'River Park'!G94) | H94: - | I94: =SUM('Астон.Движение'!I94,'Астон.Реформа'!I94,'Милый дом'!I94,'River Park'!I94)
A95: Налог на прибыль | B95: =SUM(B96,B97) | C95: =SUM(C96,C97) | D95: =SUM(D96,D97) | E95: =SUM(E96,E97) | F95: =SUM(F96,F97) | G95: =SUM(G96,G97) | H95: - | I95: =SUM(I96,I97)
A96: Налоги УСН | B96: =SUM('Астон.Движение'!B96,'Астон.Реформа'!B96,'Милый дом'!B96,'River Park'!B96) | C96: =SUM('Астон.Движение'!C96,'Астон.Реформа'!C96,'Милый дом'!C96,'River Park'!C96) | D96: =SUM('Астон.Движение'!D96,'Астон.Реформа'!D96,'Милый дом'!D96,'River Park'!D96) | E96: =SUM('Астон.Движение'!E96,'Астон.Реформа'!E96,'Милый дом'!E96,'River Park'!E96) | F96: =SUM('Астон.Движение'!F96,'Астон.Реформа'!F96,'Милый дом'!F96,'River Park'!F96) | G96: =SUM('Астон.Движение'!G96,'Астон.Реформа'!G96,'Милый дом'!G96,'River Park'!G96) | H96: - | I96: =SUM('Астон.Движение'!I96,'Астон.Реформа'!I96,'Милый дом'!I96,'River Park'!I96)
A97: Налоги НДС 5% | B97: =SUM('Астон.Движение'!B97,'Астон.Реформа'!B97,'Милый дом'!B97,'River Park'!B97) | C97: =SUM('Астон.Движение'!C97,'Астон.Реформа'!C97,'Милый дом'!C97,'River Park'!C97) | D97: =SUM('Астон.Движение'!D97,'Астон.Реформа'!D97,'Милый дом'!D97,'River Park'!D97) | E97: =SUM('Астон.Движение'!E97,'Астон.Реформа'!E97,'Милый дом'!E97,'River Park'!E97) | F97: =SUM('Астон.Движение'!F97,'Астон.Реформа'!F97,'Милый дом'!F97,'River Park'!F97) | G97: =SUM('Астон.Движение'!G97,'Астон.Реформа'!G97,'Милый дом'!G97,'River Park'!G97) | H97: - | I97: =SUM('Астон.Движение'!I97,'Астон.Реформа'!I97,'Милый дом'!I97,'River Park'!I97)
A98: Чистая прибыль (убыток) | B98: =IFERROR(B89*1,0)-IFERROR(B91*1,0)-IFERROR(B94*1,0)-IFERROR(B95*1,0) | C98: =IFERROR(C89*1,0)-IFERROR(C91*1,0)-IFERROR(C94*1,0)-IFERROR(C95*1,0) | D98: =IFERROR(D89*1,0)-IFERROR(D91*1,0)-IFERROR(D94*1,0)-IFERROR(D95*1,0) | E98: =IFERROR(E89*1,0)-IFERROR(E91*1,0)-IFERROR(E94*1,0)-IFERROR(E95*1,0) | F98: =IFERROR(F89*1,0)-IFERROR(F91*1,0)-IFERROR(F94*1,0)-IFERROR(F95*1,0) | G98: =IFERROR(G89*1,0)-IFERROR(G91*1,0)-IFERROR(G94*1,0)-IFERROR(G95*1,0) | H98: - | I98: =IFERROR(I89*1,0)-IFERROR(I91*1,0)-IFERROR(I94*1,0)-IFERROR(I95*1,0)
A99: Рентабельность чистой прибыли | B99: =IFERROR(IF(B4=0,"-",B98/B4),"-") | C99: =IFERROR(IF(C4=0,"-",C98/C4),"-") | D99: =IFERROR(IF(D4=0,"-",D98/D4),"-") | E99: =IFERROR(IF(E4=0,"-",E98/E4),"-") | F99: =IFERROR(IF(F4=0,"-",F98/F4),"-") | G99: =IFERROR(IF(G4=0,"-",G98/G4),"-") | H99: - | I99: =IFERROR(IF(I4=0,"-",I98/I4),"-")

Sheet Астон.Движение
A1: ПланФакт | B1: Создано с помощью сервиса ПланФакт | I1: =HYPERLINK("https://app.planfact.io/?from=Pf_BDR", "Перейти в сервис")
B2: Итого | C2: июнь` 26 | D2: июль` 26 | E2: август` 26 | F2: сентябрь` 26 | G2: октябрь` 26 | H2: ноябрь` 26 | I2: декабрь` 26
A3: Астон.Движение | B3: план | C3: план | D3: план | E3: план | F3: план | G3: план | H3: план | I3: план
A4: Выручка | B4: 656000 | C4: =SUM(C5,C6) | D4: =SUM(D5,D6) | E4: =SUM(E5,E6) | F4: =SUM(F5,F6) | G4: =SUM(G5,G6) | H4: - | I4: =SUM(I5,I6)
A5: Нераспределенный доход | B5: - | C5: - | D5: - | E5: - | F5: - | G5: - | H5: - | I5: -
A6: Выручка | B6: 656000 | C6: =SUM(C7,C8,C9) | D6: =SUM(D7,D8,D9) | E6: =SUM(E7,E8,E9) | F6: =SUM(F7,F8,F9) | G6: =SUM(G7,G8,G9) | H6: - | I6: =SUM(I7,I8,I9)
A7: Реализация услуг Клининг (ОД) | B7: 656000 | C7: 164000 | D7: 164000 | E7: 164000 | F7: 164000 | G7: - | H7: - | I7: -
A8: Реализация услуг Клининг (Доп.услуги) | B8: - | C8: - | D8: - | E8: - | F8: - | G8: - | H8: - | I8: -
A9: Реализация услуг Клининг (снег) | B9: - | C9: - | D9: - | E9: - | F9: - | G9: - | H9: - | I9: -
A10: Прямые расходы | B10: 530680.45 | C10: =SUM(C11,C12,C13,C21,C22,C23,C24,C25,C26,C27,C28,C29,C30,C31,C32,C33,C34) | D10: =SUM(D11,D12,D13,D21,D22,D23,D24,D25,D26,D27,D28,D29,D30,D31,D32,D33,D34) | E10: =SUM(E11,E12,E13,E21,E22,E23,E24,E25,E26,E27,E28,E29,E30,E31,E32,E33,E34) | F10: =SUM(F11,F12,F13,F21,F22,F23,F24,F25,F26,F27,F28,F29,F30,F31,F32,F33,F34) | G10: =SUM(G11,G12,G13,G21,G22,G23,G24,G25,G26,G27,G28,G29,G30,G31,G32,G33,G34) | H10: - | I10: =SUM(I11,I12,I13,I21,I22,I23,I24,I25,I26,I27,I28,I29,I30,I31,I32,I33,I34)
A11: Нераспределенный расход | B11: - | C11: - | D11: - | E11: - | F11: - | G11: - | H11: - | I11: -
A12: Транспортные расходы | B12: 1486 | C12: 1486 | D12: - | E12: - | F12: - | G12: - | H12: - | I12: -
A13: Переменные | B13: 15262 | C13: =SUM(C14,C15,C16,C17,C18,C19,C20) | D13: =SUM(D14,D15,D16,D17,D18,D19,D20) | E13: =SUM(E14,E15,E16,E17,E18,E19,E20) | F13: =SUM(F14,F15,F16,F17,F18,F19,F20) | G13: =SUM(G14,G15,G16,G17,G18,G19,G20) | H13: - | I13: =SUM(I14,I15,I16,I17,I18,I19,I20)
A14: Услуги техниги для уборки снега (ПТ) | B14: - | C14: - | D14: - | E14: - | F14: - | G14: - | H14: - | I14: -
A15: Услуги садовника (ПТ) | B15: - | C15: - | D15: - | E15: - | F15: - | G15: - | H15: - | I15: -
A16: Сыпучие материалы (ПТ) | B16: - | C16: - | D16: - | E16: - | F16: - | G16: - | H16: - | I16: -
A17: Расходные материалы и инстументы (МОП) | B17: 8000 | C17: 2000 | D17: 2000 | E17: 2000 | F17: 2000 | G17: - | H17: - | I17: -
A18: Расходные материалы и инстументы (ПТ) | B18: 7262 | C18: 1262 | D18: 2000 | E18: 2000 | F18: 2000 | G18: - | H18: - | I18: -
A19: Арена оборудования (ПТ) | B19: - | C19: - | D19: - | E19: - | F19: - | G19: - | H19: - | I19: -
A20: Арена оборудования (МОП) | B20: - | C20: - | D20: - | E20: - | F20: - | G20: - | H20: - | I20: -
A21: Заработная плата (МОП) | B21: 200000 | C21: 50000 | D21: 50000 | E21: 50000 | F21: 50000 | G21: - | H21: - | I21: -
A22: Заработная плата (ПТ) | B22: 280000 | C22: 70000 | D22: 70000 | E22: 70000 | F22: 70000 | G22: - | H22: - | I22: -
A23: Налоги с ФОТ (МОП) | B23: - | C23: - | D23: - | E23: - | F23: - | G23: - | H23: - | I23: -
A24: Налоги с ФОТ (ПТ) | B24: - | C24: - | D24: - | E24: - | F24: - | G24: - | H24: - | I24: -
A25: Премми (МОП) | B25: - | C25: - | D25: - | E25: - | F25: - | G25: - | H25: - | I25: -
A26: Премми (ПТ) | B26: - | C26: - | D26: - | E26: - | F26: - | G26: - | H26: - | I26: -
A27: Униформа (МОП) | B27: - | C27: - | D27: - | E27: - | F27: - | G27: - | H27: - | I27: -
A28: Униформа (ПТ) | B28: - | C28: - | D28: - | E28: - | F28: - | G28: - | H28: - | I28: -
A29: Ремонт оборудования (МОП) | B29: - | C29: - | D29: - | E29: - | F29: - | G29: - | H29: - | I29: -
A30: Ремонт оборудования (ПТ) | B30: - | C30: - | D30: - | E30: - | F30: - | G30: - | H30: - | I30: -
A31: Вывоз мусора | B31: - | C31: - | D31: - | E31: - | F31: - | G31: - | H31: - | I31: -
A32: Штрафы, пени, неустойки | B32: - | C32: - | D32: - | E32: - | F32: - | G32: - | H32: - | I32: -
A33: Расходы к удержанию | B33: - | C33: - | D33: - | E33: - | F33: - | G33: - | H33: - | I33: -
A34: Общехозяйственные | B34: 33932.45 | C34: =SUM(C35,C36,C37,C38,C39,C40,C41,C42) | D34: =SUM(D35,D36,D37,D38,D39,D40,D41,D42) | E34: =SUM(E35,E36,E37,E38,E39,E40,E41,E42) | F34: =SUM(F35,F36,F37,F38,F39,F40,F41,F42) | G34: =SUM(G35,G36,G37,G38,G39,G40,G41,G42) | H34: - | I34: =SUM(I35,I36,I37,I38,I39,I40,I41,I42)
A35: Аутсорс (направления) | B35: - | C35: - | D35: - | E35: - | F35: - | G35: - | H35: - | I35: -
A36: Заработная плата МО АУП | B36: - | C36: - | D36: - | E36: - | F36: - | G36: - | H36: - | I36: -
A37: Инструменты: ГСМ | B37: 332.45 | C37: 332.45 | D37: - | E37: - | F37: - | G37: - | H37: - | I37: -
A38: Медосмотры | B38: - | C38: - | D38: - | E38: - | F38: - | G38: - | H38: - | I38: -
A39: Налоги с ФОТ (ИП) | B39: 33600 | C39: 8400 | D39: 8400 | E39: 8400 | F39: 8400 | G39: - | H39: - | I39: -
A40: Приобритение мебели, бытовой техники | B40: - | C40: - | D40: - | E40: - | F40: - | G40: - | H40: - | I40: -
A41: Комиссия за перевод ЗП | B41: - | C41: - | D41: - | E41: - | F41: - | G41: - | H41: - | I41: -
A42: Аренда квартиры (включая коммуналку) | B42: - | C42: - | D42: - | E42: - | F42: - | G42: - | H42: - | I42: -
A43: Валовая прибыль | B43: 125319.55 | C43: =C4-C10 | D43: =D4-D10 | E43: =E4-E10 | F43: =F4-F10 | G43: =G4-G10 | H43: - | I43: =I4-I10
A44: Валовая рентабельность | B44: 19.10% | C44: =IFERROR(IF(C4=0,"-",C43/C4),"-") | D44: =IFERROR(IF(D4=0,"-",D43/D4),"-") | E44: =IFERROR(IF(E4=0,"-",E43/E4),"-") | F44: =IFERROR(IF(F4=0,"-",F43/F4),"-") | G44: =IFERROR(IF(G4=0,"-",G43/G4),"-") | H44: - | I44: =IFERROR(IF(I4=0,"-",I43/I4),"-")
A45: Косвенные расходы | B45: - | C45: =SUM(C46,C47,C48,C52,C56,C57,C58,C59,C60,C63,C64,C65,C66,C67,C68,C69,C70,C71,C72,C73,C74,C75,C76,C77,C78,C79) | D45: =SUM(D46,D47,D48,D52,D56,D57,D58,D59,D60,D63,D64,D65,D66,D67,D68,D69,D70,D71,D72,D73,D74,D75,D76,D77,D78,D79) | E45: =SUM(E46,E47,E48,E52,E56,E57,E58,E59,E60,E63,E64,E65,E66,E67,E68,E69,E70,E71,E72,E73,E74,E75,E76,E77,E78,E79) | F45: =SUM(F46,F47,F48,F52,F56,F57,F58,F59,F60,F63,F64,F65,F66,F67,F68,F69,F70,F71,F72,F73,F74,F75,F76,F77,F78,F79) | G45: =SUM(G46,G47,G48,G52,G56,G57,G58,G59,G60,G63,G64,G65,G66,G67,G68,G69,G70,G71,G72,G73,G74,G75,G76,G77,G78,G79) | H45: - | I45: =SUM(I46,I47,I48,I52,I56,I57,I58,I59,I60,I63,I64,I65,I66,I67,I68,I69,I70,I71,I72,I73,I74,I75,I76,I77,I78,I79)
A46: Расход БЭК-ОФИС | B46: - | C46: - | D46: - | E46: - | F46: - | G46: - | H46: - | I46: -
A47: Расходы на бэк-офис | B47: - | C47: - | D47: - | E47: - | F47: - | G47: - | H47: - | I47: -
A48: Автомобиль | B48: - | C48: =SUM(C49,C50,C51) | D48: =SUM(D49,D50,D51) | E48: =SUM(E49,E50,E51) | F48: =SUM(F49,F50,F51) | G48: =SUM(G49,G50,G51) | H48: - | I48: =SUM(I49,I50,I51)
A49: Автомобиль: ГСМ | B49: - | C49: - | D49: - | E49: - | F49: - | G49: - | H49: - | I49: -
A50: Автомобиль: страхование | B50: - | C50: - | D50: - | E50: - | F50: - | G50: - | H50: - | I50: -
A51: Автомобиль: ТО | B51: - | C51: - | D51: - | E51: - | F51: - | G51: - | H51: - | I51: -
A52: Офисные расходы | B52: - | C52: =SUM(C53,C54,C55) | D52: =SUM(D53,D54,D55) | E52: =SUM(E53,E54,E55) | F52: =SUM(F53,F54,F55) | G52: =SUM(G53,G54,G55) | H52: - | I52: =SUM(I53,I54,I55)
A53: Аренда офиса | B53: - | C53: - | D53: - | E53: - | F53: - | G53: - | H53: - | I53: -
A54: Канцелярия и обслуживание | B54: - | C54: - | D54: - | E54: - | F54: - | G54: - | H54: - | I54: -
A55: Интернет и связь | B55: - | C55: - | D55: - | E55: - | F55: - | G55: - | H55: - | I55: -
A56: Банковские услуги | B56: - | C56: - | D56: - | E56: - | F56: - | G56: - | H56: - | I56: -
A57: Заработная плата АУП (БО) | B57: - | C57: - | D57: - | E57: - | F57: - | G57: - | H57: - | I57: -
A58: Заработная плата бухгалтерии (БО) | B58: - | C58: - | D58: - | E58: - | F58: - | G58: - | H58: - | I58: -
A59: Заработная плата СБ (БО) | B59: - | C59: - | D59: - | E59: - | F59: - | G59: - | H59: - | I59: -
A60: Командировочные расходы | B60: - | C60: =SUM(C61,C62) | D60: =SUM(D61,D62) | E60: =SUM(E61,E62) | F60: =SUM(F61,F62) | G60: =SUM(G61,G62) | H60: - | I60: =SUM(I61,I62)
A61: Командировнчеы расходы: билеты (БО) | B61: - | C61: - | D61: - | E61: - | F61: - | G61: - | H61: - | I61: -
A62: Командировнчеы расходы: проживание (БО) | B62: - | C62: - | D62: - | E62: - | F62: - | G62: - | H62: - | I62: -
A63: Комиссия УК ДОМ | B63: - | C63: - | D63: - | E63: - | F63: - | G63: - | H63: - | I63: -
A64: Налоги с ФОТ (ИП)_БО | B64: - | C64: - | D64: - | E64: - | F64: - | G64: - | H64: - | I64: -
A65: Налоги с ФОТ (НДФЛ) БО | B65: - | C65: - | D65: - | E65: - | F65: - | G65: - | H65: - | I65: -
A66: Налоги с ФОТ (страховые взносы) БО | B66: - | C66: - | D66: - | E66: - | F66: - | G66: - | H66: - | I66: -
A67: Нотариальные услуги | B67: - | C67: - | D67: - | E67: - | F67: - | G67: - | H67: - | I67: -
A68: Обслуживание техники (БО) | B68: - | C68: - | D68: - | E68: - | F68: - | G68: - | H68: - | I68: -
A69: Программное обеспечение (БО) | B69: - | C69: - | D69: - | E69: - | F69: - | G69: - | H69: - | I69: -
A70: ПланФакт | B70: - | C70: - | D70: - | E70: - | F70: - | G70: - | H70: - | I70: -
A71: ТБ | B71: - | C71: - | D71: - | E71: - | F71: - | G71: - | H71: - | I71: -
A72: Контур | B72: - | C72: - | D72: - | E72: - | F72: - | G72: - | H72: - | I72: -
... A79: HR (аутсорс) | B79: - | C79: - | D79: - | E79: - | F79: - | G79: - | H79: - | I79: -
A80: Операционная прибыль | B80: 125319.55 | C80: =C43-C45 | D80: =D43-D45 | E80: =E43-E45 | F80: =F43-F45 | G80: =G43-G45 | H80: - | I80: =I43-I45
A81: Операционная рентабельность | B81: 19.10% | C81: =IFERROR(IF(C4=0,"-",C80/C4),"-") | D81: =IFERROR(IF(D4=0,"-",D80/D4),"-") | E81: =IFERROR(IF(E4=0,"-",E80/E4),"-") | F81: =IFERROR(IF(F4=0,"-",F80/F4),"-") | G81: =IFERROR(IF(G4=0,"-",G80/G4),"-") | H81: - | I81: =IFERROR(IF(I4=0,"-",I80/I4),"-")
A82: Прочие доходы | B82: - | C82: =SUM(C83,C84,C85,C86) | D82: =SUM(D83,D84,D85,D86) | E82: =SUM(E83,E84,E85,E86) | F82: =SUM(F83,F84,F85,F86) | G82: =SUM(G83,G84,G85,G86) | H82: - | I82: =SUM(I83,I84,I85,I86)
A83: Доход БЭК-ОФИС | B83: - | C83: - | D83: - | E83: - | F83: - | G83: - | H83: - | I83: -
A84: Пополненин бэк-офис | B84: - | C84: - | D84: - | E84: - | F84: - | G84: - | H84: - | I84: -
A85: Проценты по вкладам | B85: - | C85: - | D85: - | E85: - | F85: - | G85: - | H85: - | I85: -
A86: Курсовая разница (+) | B86: - | C86: - | D86: - | E86: - | F86: - | G86: - | H86: - | I86: -
A87: Прочие расходы | B87: - | C87: =SUM(C88) | D87: =SUM(D88) | E87: =SUM(E88) | F87: =SUM(F88) | G87: =SUM(G88) | H87: - | I87: =SUM(I88)
A88: Курсовая разница (-) | B88: - | C88: - | D88: - | E88: - | F88: - | G88: - | H88: - | I88: -
A89: EBITDA | B89: 125319.55 | C89: =C80+IFERROR(C82*1,0)-IFERROR(C87*1,0) | D89: =D80+IFERROR(D82*1,0)-IFERROR(D87*1,0) | E89: =E80+IFERROR(E82*1,0)-IFERROR(E87*1,0) | F89: =F80+IFERROR(F82*1,0)-IFERROR(F87*1,0) | G89: =G80+IFERROR(G82*1,0)-IFERROR(G87*1,0) | H89: - | I89: =I80+IFERROR(I82*1,0)-IFERROR(I87*1,0)
A90: Рентабельность по EBITDA | B90: 19.10% | C90: =IFERROR(IF(C4=0,"-",C89/C4),"-") | D90: =IFERROR(IF(D4=0,"-",D89/D4),"-") | E90: =IFERROR(IF(E4=0,"-",E89/E4),"-") | F90: =IFERROR(IF(F4=0,"-",F89/F4),"-") | G90: =IFERROR(IF(G4=0,"-",G89/G4),"-") | H90: - | I90: =IFERROR(IF(I4=0,"-",I89/I4),"-")
A91: Амортизация | B91: - | C91: =SUM(C92,C93) | D91: =SUM(D92,D93) | E91: =SUM(E92,E93) | F91: =SUM(F92,F93) | G91: =SUM(G92,G93) | H91: - | I91: =SUM(I92,I93)
A92: Амортизация ОС (ПТ) | B92: - | C92: - | D92: - | E92: - | F92: - | G92: - | H92: - | I92: -
A93: Амортизация ОС (МОП) | B93: - | C93: - | D93: - | E93: - | F93: - | G93: - | H93: - | I93: -
A94: Проценты по кредитам и займам | B94: - | C94: - | D94: - | E94: - | F94: - | G94: - | H94: - | I94: -
A95: Налог на прибыль | B95: 46000 | C95: =SUM(C96,C97) | D95: =SUM(D96,D97) | E95: =SUM(E96,E97) | F95: =SUM(F96,F97) | G95: =SUM(G96,G97) | H95: - | I95: =SUM(I96,I97)
A96: Налоги УСН | B96: 46000 | C96: 11500 | D96: 11500 | E96: 11500 | F96: 11500 | G96: - | H96: - | I96: -
A97: Налоги НДС 5% | B97: - | C97: - | D97: - | E97: - | F97: - | G97: - | H97: - | I97: -
A98: Чистая прибыль (убыток) | B98: 79319.55 | C98: =IFERROR(C89*1,0)-IFERROR(C91*1,0)-IFERROR(C94*1,0)-IFERROR(C95*1,0) | D98: =IFERROR(D89*1,0)-IFERROR(D91*1,0)-IFERROR(D94*1,0)-IFERROR(D95*1,0) | E98: =IFERROR(E89*1,0)-IFERROR(E91*1,0)-IFERROR(E94*1,0)-IFERROR(E95*1,0) | F98: =IFERROR(F89*1,0)-IFERROR(F91*1,0)-IFERROR(F94*1,0)-IFERROR(F95*1,0) | G98: =IFERROR(G89*1,0)-IFERROR(G91*1,0)-IFERROR(G94*1,0)-IFERROR(G95*1,0) | H98: - | I98: =IFERROR(I89*1,0)-IFERROR(I91*1,0)-IFERROR(I94*1,0)-IFERROR(I95*1,0)
A99: Рентабельность чистой прибыли | B99: 12.09% | C99: =IFERROR(IF(C4=0,"-",C98/C4),"-") | D99: =IFERROR(IF(D4=0,"-",D98/D4),"-") | E99: =IFERROR(IF(E4=0,"-",E98/E4),"-") | F99: =IFERROR(IF(F4=0,"-",F98/F4),"-") | G99: =IFERROR(IF(G4=0,"-",G98/G4),"-") | H99: - | I99: =IFERROR(IF(I4=0,"-",I98/I4),"-")

Sheet Астон.Реформа
A1: ПланФакт | B1: Создано с помощью сервиса ПланФакт | I1: =HYPERLINK("https://app.planfact.io/?from=Pf_BDR", "Перейти в сервис")
B2: Итого | C2: июнь` 26 | D2: июль` 26 | E2: август` 26 | F2: сентябрь` 26 | G2: октябрь` 26 | H2: ноябрь` 26 | I2: декабрь` 26
A3: Астон.Реформа | B3: план | C3: план | D3: план | E3: план | F3: план | G3: план | H3: план | I3: план
A4: Выручка | B4: 384000 | C4: =SUM(C5,C6) | D4: =SUM(D5,D6) | E4: =SUM(E5,E6) | F4: =SUM(F5,F6) | G4: =SUM(G5,G6) | H4: - | I4: =SUM(I5,I6)
A5: Нераспределенный доход | B5: - | C5: - | D5: - | E5: - | F5: - | G5: - | H5: - | I5: -
A6: Выручка | B6: 384000 | C6: =SUM(C7,C8,C9) | D6: =SUM(D7,D8,D9) | E6: =SUM(E7,E8,E9) | F6: =SUM(F7,F8,F9) | G6: =SUM(G7,G8,G9) | H6: - | I6: =SUM(I7,I8,I9)
A7: Реализация услуг Клининг (ОД) | B7: 384000 | C7: 96000 | D7: 96000 | E7: 96000 | F7: 96000 | G7: - | H7: - | I7: -
A8: Реализация услуг Клининг (Доп.услуги) | B8: - | C8: - | D8: - | E8: - | F8: - | G8: - | H8: - | I8: -
A9: Реализация услуг Клининг (снег) | B9: - | C9: - | D9: - | E9: - | F9: - | G9: - | H9: - | I9: -
A10: Прямые расходы | B10: 350000 | C10: =SUM(C11,C12,C13,C21,C22,C23,C24,C25,C26,C27,C28,C29,C30,C31,C32,C33,C34) | D10: =SUM(D11,D12,D13,D21,D22,D23,D24,D25,D26,D27,D28,D29,D30,D31,D32,D33,D34) | E10: =SUM(E11,E12,E13,E21,E22,E23,E24,E25,E26,E27,E28,E29,E30,E31,E32,E33,E34) | F10: =SUM(F11,F12,F13,F21,F22,F23,F24,F25,F26,F27,F28,F29,F30,F31,F32,F33,F34) | G10: =SUM(G11,G12,G13,G21,G22,G23,G24,G25,G26,G27,G28,G29,G30,G31,G32,G33,G34) | H10: - | I10: =SUM(I11,I12,I13,I21,I22,I23,I24,I25,I26,I27,I28,I29,I30,I31,I32,I33,I34)
A11: Нераспределенный расход | B11: - | C11: - | D11: - | E11: - | F11: - | G11: - | H11: - | I11: -
A12: Транспортные расходы | B12: - | C12: - | D12: - | E12: - | F12: - | G12: - | H12: - | I12: -
A13: Переменные | B13: 16000 | C13: =SUM(C14,C15,C16,C17,C18,C19,C20) | D13: =SUM(D14,D15,D16,D17,D18,D19,D20) | E13: =SUM(E14,E15,E16,E17,E18,E19,E20) | F13: =SUM(F14,F15,F16,F17,F18,F19,F20) | G13: =SUM(G14,G15,G16,G17,G18,G19,G20) | H13: - | I13: =SUM(I14,I15,I16,I17,I18,I19,I20)
A14: Услуги техниги для уборки снега (ПТ) | B14: - | C14: - | D14: - | E14: - | F14: - | G14: - | H14: - | I14: -
A15: Услуги садовника (ПТ) | B15: - | C15: - | D15: - | E15: - | F15: - | G15: - | H15: - | I15: -
A16: Сыпучие материалы (ПТ) | B16: - | C16: - | D16: - | E16: - | F16: - | G16: - | H16: - | I16: -
A17: Расходные материалы и инстументы (МОП) | B17: 8000 | C17: 2000 | D17: 2000 | E17: 2000 | F17: 2000 | G17: - | H17: - | I17: -
A18: Расходные материалы и инстументы (ПТ) | B18: 8000 | C18: 2000 | D18: 2000 | E18: 2000 | F18: 2000 | G18: - | H18: - | I18: -
A19: Арена оборудования (ПТ) | B19: - | C19: - | D19: - | E19: - | F19: - | G19: - | H19: - | I19: -
A20: Арена оборудования (МОП) | B20: - | C20: - | D20: - | E20: - | F20: - | G20: - | H20: - | I20: -
A21: Заработная плата (МОП) | B21: 140000 | C21: 35000 | D21: 35000 | E21: 35000 | F21: 35000 | G21: - | H21: - | I21: -
A22: Заработная плата (ПТ) | B22: 140000 | C22: 35000 | D22: 35000 | E22: 35000 | F22: 35000 | G22: - | H22: - | I22: -
A23: Налоги с ФОТ (МОП) | B23: 42000 | C23: - | D23: 14000 | E23: 14000 | F23: 14000 | G23: - | H23: - | I23: -
A24: Налоги с ФОТ (ПТ) | B24: - | C24: - | D24: - | E24: - | F24: - | G24: - | H24: - | I24: -
A25: Премми (МОП) | B25: - | C25: - | D25: - | E25: - | F25: - | G25: - | H25: - | I25: -
A26: Премми (ПТ) | B26: - | C26: - | D26: - | E26: - | F26: - | G26: - | H26: - | I26: -
A27: Униформа (МОП) | B27: - | C27: - | D27: - | E27: - | F27: - | G27: - | H27: - | I27: -
A28: Униформа (ПТ) | B28: - | C28: - | D28: - | E28: - | F28: - | G28: - | H28: - | I28: -
A29: Ремонт оборудования (МОП) | B29: - | C29: - | D29: - | E29: - | F29: - | G29: - | H29: - | I29: -
A30: Ремонт оборудования (ПТ) | B30: - | C30: - | D30: - | E30: - | F30: - | G30: - | H30: - | I30: -
A31: Вывоз мусора | B31: - | C31: - | D31: - | E31: - | F31: - | G31: - | H31: - | I31: -
A32: Штрафы, пени, неустойки | B32: - | C32: - | D32: - | E32: - | F32: - | G32: - | H32: - | I32: -
A33: Расходы к удержанию | B33: - | C33: - | D33: - | E33: - | F33: - | G33: - | H33: - | I33: -
A34: Общехозяйственные | B34: 12000 | C34: =SUM(C35,C36,C37,C38,C39,C40,C41,C42) | D34: =SUM(D35,D36,D37,D38,D39,D40,D41,D42) | E34: =SUM(E35,E36,E37,E38,E39,E40,E41,E42) | F34: =SUM(F35,F36,F37,F38,F39,F40,F41,F42) | G34: =SUM(G35,G36,G37,G38,G39,G40,G41,G42) | H34: - | I34: =SUM(I35,I36,I37,I38,I39,I40,I41,I42)
A35: Аутсорс (направления) | B35: - | C35: - | D35: - | E35: - | F35: - | G35: - | H35: - | I35: -
A36: Заработная плата МО АУП | B36: - | C36: - | D36: - | E36: - | F36: - | G36: - | H36: - | I36: -
A37: Инструменты: ГСМ | B37: - | C37: - | D37: - | E37: - | F37: - | G37: - | H37: - | I37: -
A38: Медосмотры | B38: - | C38: - | D38: - | E38: - | F38: - | G38: - | H38: - | I38: -
A39: Налоги с ФОТ (ИП) | B39: 12000 | C39: 3000 | D39: 3000 | E39: 3000 | F39: 3000 | G39: - | H39: - | I39: -
A40: Приобритение мебели, бытовой техники | B40: - | C40: - | D40: - | E40: - | F40: - | G40: - | H40: - | I40: -
A41: Комиссия за перевод ЗП | B41: - | C41: - | D41: - | E41: - | F41: - | G41: - | H41: - | I41: -
A42: Аренда квартиры (включая коммуналку) | B42: - | C42: - | D42: - | E42: - | F42: - | G42: - | H42: - | I42: -
A43: Валовая прибыль | B43: 34000 | C43: =C4-C10 | D43: =D4-D10 | E43: =E4-E10 | F43: =F4-F10 | G43: =G4-G10 | H43: - | I43: =I4-I10
A44: Валовая рентабельность | B44: 8.85% | C44: =IFERROR(IF(C4=0,"-",C43/C4),"-") | D44: =IFERROR(IF(D4=0,"-",D43/D4),"-") | E44: =IFERROR(IF(E4=0,"-",E43/E4),"-") | F44: =IFERROR(IF(F4=0,"-",F43/F4),"-") | G44: =IFERROR(IF(G4=0,"-",G43/G4),"-") | H44: - | I44: =IFERROR(IF(I4=0,"-",I43/I4),"-")
A45: Косвенные расходы | B45: - | C45: =SUM(C46,C47,C48,C52,C56,C57,C58,C59,C60,C63,C64,C65,C66,C67,C68,C69,C70,C71,C72,C73,C74,C75,C76,C77,C78,C79) | D45: =SUM(D46,D47,D48,D52,D56,D57,D58,D59,D60,D63,D64,D65,D66,D67,D68,D69,D70,D71,D72,D73,D74,D75,D76,D77,D78,D79) | E45: =SUM(E46,E47,E48,E52,E56,E57,E58,E59,E60,E63,E64,E65,E66,E67,E68,E69,E70,E71,E72,E73,E74,E75,E76,E77,E78,E79) | F45: =SUM(F46,F47,F48,F52,F56,F57,F58,F59,F60,F63,F64,F65,F66,F67,F68,F69,F70,F71,F72,F73,F74,F75,F76,F77,F78,F79) | G45: =SUM(G46,G47,G48,G52,G56,G57,G58,G59,G60,G63,G64,G65,G66,G67,G68,G69,G70,G71,G72,G73,G74,G75,G76,G77,G78,G79) | H45: - | I45: =SUM(I46,I47,I48,I52,I56,I57,I58,I59,I60,I63,I64,I65,I66,I67,I68,I69,I70,I71,I72,I73,I74,I75,I76,I77,I78,I79)
A46: Расход БЭК-ОФИС | B46: - | C46: - | D46: - | E46: - | F46: - | G46: - | H46: - | I46: -
A47: Расходы на бэк-офис | B47: - | C47: - | D47: - | E47: - | F47: - | G47: - | H47: - | I47: -
A48: Автомобиль | B48: - | C48: =SUM(C49,C50,C51) | D48: =SUM(D49,D50,D51) | E48: =SUM(E49,E50,E51) | F48: =SUM(F49,F50,F51) | G48: =SUM(G49,G50,G51) | H48: - | I48: =SUM(I49,I50,I51)
A49: Автомобиль: ГСМ | B49: - | C49: - | D49: - | E49: - | F49: - | G49: - | H49: - | I49: -
A50: Автомобиль: страхование | B50: - | C50: - | D50: - | E50: - | F50: - | G50: - | H50: - | I50: -
A51: Автомобиль: ТО | B51: - | C51: - | D51: - | E51: - | F51: - | G51: - | H51: - | I51: -
A52: Офисные расходы | B52: - | C52: =SUM(C53,C54,C55) | D52: =SUM(D53,D54,D55) | E52: =SUM(E53,E54,E55) | F52: =SUM(F53,F54,F55) | G52: =SUM(G53,G54,G55) | H52: - | I52: =SUM(I53,I54,I55)
A53: Аренда офиса | B53: - | C53: - | D53: - | E53: - | F53: - | G53: - | H53: - | I53: -
A54: Канцелярия и обслуживание | B54: - | C54: - | D54: - | E54: - | F54: - | G54: - | H54: - | I54: -
A55: Интернет и связь | B55: - | C55: - | D55: - | E55: - | F55: - | G55: - | H55: - | I55: -
A56: Банковские услуги | B56: - | C56: - | D56: - | E56: - | F56: - | G56: - | H56: - | I56: -
A57: Заработная плата АУП (БО) | B57: - | C57: - | D57: - | E57: - | F57: - | G57: - | H57: - | I57: -
A58: Заработная плата бухгалтерии (БО) | B58: - | C58: - | D58: - | E58: - | F58: - | G58: - | H58: - | I58: -
A59: Заработная плата СБ (БО) | B59: - | C59: - | D59: - | E59: - | F59: - | G59: - | H59: - | I59: -
A60: Командировочные расходы | B60: - | C60: =SUM(C61,C62) | D60: =SUM(D61,D62) | E60: =SUM(E61,E62) | F60: =SUM(F61,F62) | G60: =SUM(G61,G62) | H60: - | I60: =SUM(I61,I62)
A61: Командировнчеы расходы: билеты (БО) | B61: - | C61: - | D61: - | E61: - | F61: - | G61: - | H61: - | I61: -
A62: Командировнчеы расходы: проживание (БО) | B62: - | C62: - | D62: - | E62: - | F62: - | G62: - | H62: - | I62: -
A63: Комиссия УК ДОМ | B63: - | C63: - | D63: - | E63: - | F63: - | G63: - | H63: - | I63: -
A64: Налоги с ФОТ (ИП)_БО | B64: - | C64: - | D64: - | E64: - | F64: - | G64: - | H64: - | I64: -
A65: Налоги с ФОТ (НДФЛ) БО | B65: - | C65: - | D65: - | E65: - | F65: - | G65: - | H65: - | I65: -
A66: Налоги с ФОТ (страховые взносы) БО | B66: - | C66: - | D66: - | E66: - | F66: - | G66: - | H66: - | I66: -
A67: Нотариальные услуги | B67: - | C67: - | D67: - | E67: - | F67: - | G67: - | H67: - | I67: -
A68: Обслуживание техники (БО) | B68: - | C68: - | D68: - | E68: - | F68: - | G68: - | H68: - | I68: -
A69: Программное обеспечение (БО) | B69: - | C69: - | D69: - | E69: - | F69: - | G69: - | H69: - | I69: -
A70: ПланФакт | B70: - | C70: - | D70: - | E70: - | F70: - | G70: - | H70: - | I70: -
A71: ТБ | B71: - | C71: - | D71: - | E71: - | F71: - | G71: - | H71: - | I71: -
A72: Контур | B72: - | C72: - | D72: - | E72: - | F72: - | G72: - | H72: - | I72: -
... A79: HR (аутсорс) | B79: - | C79: - | D79: - | E79: - | F79: - | G79: - | H79: - | I79: -
A80: Операционная прибыль | B80: 34000 | C80: =C43-C45 | D80: =D43-D45 | E80: =E43-E45 | F80: =F43-F45 | G80: =G43-G45 | H80: - | I80: =I43-I45
A81: Операционная рентабельность | B81: 8.85% | C81: =IFERROR(IF(C4=0,"-",C80/C4),"-") | D81: =IFERROR(IF(D4=0,"-",D80/D4),"-") | E81: =IFERROR(IF(E4=0,"-",E80/E4),"-") | F81: =IFERROR(IF(F4=0,"-",F80/F4),"-") | G81: =IFERROR(IF(G4=0,"-",G80/G4),"-") | H81: - | I81: =IFERROR(IF(I4=0,"-",I80/I4),"-")
A82: Прочие доходы | B82: - | C82: =SUM(C83,C84,C85,C86) | D82: =SUM(D83,D84,D85,D86) | E82: =SUM(E83,E84,E85,E86) | F82: =SUM(F83,F84,F85,F86) | G82: =SUM(G83,G84,G85,G86) | H82: - | I82: =SUM(I83,I84,I85,I86)
A83: Доход БЭК-ОФИС | B83: - | C83: - | D83: - | E83: - | F83: - | G83: - | H83: - | I83: -
A84: Пополненин бэк-офис | B84: - | C84: - | D84: - | E84: - | F84: - | G84: - | H84: - | I84: -
A85: Проценты по вкладам | B85: - | C85: - | D85: - | E85: - | F85: - | G85: - | H85: - | I85: -
A86: Курсовая разница (+) | B86: - | C86: - | D86: - | E86: - | F86: - | G86: - | H86: - | I86: -
A87: Прочие расходы | B87: - | C87: =SUM(C88) | D87: =SUM(D88) | E87: =SUM(E88) | F87: =SUM(F88) | G87: =SUM(G88) | H87: - | I87: =SUM(I88)
A88: Курсовая разница (-) | B88: - | C88: - | D88: - | E88: - | F88: - | G88: - | H88: - | I88: -
A89: EBITDA | B89: 34000 | C89: =C80+IFERROR(C82*1,0)-IFERROR(C87*1,0) | D89: =D80+IFERROR(D82*1,0)-IFERROR(D87*1,0) | E89: =E80+IFERROR(E82*1,0)-IFERROR(E87*1,0) | F89: =F80+IFERROR(F82*1,0)-IFERROR(F87*1,0) | G89: =G80+IFERROR(G82*1,0)-IFERROR(G87*1,0) | H89: - | I89: =I80+IFERROR(I82*1,0)-IFERROR(I87*1,0)
A90: Рентабельность по EBITDA | B90: 8.85% | C90: =IFERROR(IF(C4=0,"-",C89/C4),"-") | D90: =IFERROR(IF(D4=0,"-",D89/D4),"-") | E90: =IFERROR(IF(E4=0,"-",E89/E4),"-") | F90: =IFERROR(IF(F4=0,"-",F89/F4),"-") | G90: =IFERROR(IF(G4=0,"-",G89/G4),"-") | H90: - | I90: =IFERROR(IF(I4=0,"-",I89/I4),"-")
A91: Амортизация | B91: - | C91: =SUM(C92,C93) | D91: =SUM(D92,D93) | E91: =SUM(E92,E93) | F91: =SUM(F92,F93) | G91: =SUM(G92,G93) | H91: - | I91: =SUM(I92,I93)
A92: Амортизация ОС (ПТ) | B92: - | C92: - | D92: - | E92: - | F92: - | G92: - | H92: - | I92: -
A93: Амортизация ОС (МОП) | B93: - | C93: - | D93: - | E93: - | F93: - | G93: - | H93: - | I93: -
A94: Проценты по кредитам и займам | B94: - | C94: - | D94: - | E94: - | F94: - | G94: - | H94: - | I94: -
A95: Налог на прибыль | B95: 26800 | C95: =SUM(C96,C97) | D95: =SUM(D96,D97) | E95: =SUM(E96,E97) | F95: =SUM(F96,F97) | G95: =SUM(G96,G97) | H95: - | I95: =SUM(I96,I97)
A96: Налоги УСН | B96: 26800 | C96: 6700 | D96: 6700 | E96: 6700 | F96: 6700 | G96: - | H96: - | I96: -
A97: Налоги НДС 5% | B97: - | C97: - | D97: - | E97: - | F97: - | G97: - | H97: - | I97: -
A98: Чистая прибыль (убыток) | B98: 7200 | C98: =IFERROR(C89*1,0)-IFERROR(C91*1,0)-IFERROR(C94*1,0)-IFERROR(C95*1,0) | D98: =IFERROR(D89*1,0)-IFERROR(D91*1,0)-IFERROR(D94*1,0)-IFERROR(D95*1,0) | E98: =IFERROR(E89*1,0)-IFERROR(E91*1,0)-IFERROR(E94*1,0)-IFERROR(E95*1,0) | F98: =IFERROR(F89*1,0)-IFERROR(F91*1,0)-IFERROR(F94*1,0)-IFERROR(F95*1,0) | G98: =IFERROR(G89*1,0)-IFERROR(G91*1,0)-IFERROR(G94*1,0)-IFERROR(G95*1,0) | H98: - | I98: =IFERROR(I89*1,0)-IFERROR(I91*1,0)-IFERROR(I94*1,0)-IFERROR(I95*1,0)
A99: Рентабельность чистой прибыли | B99: 1.88% | C99: =IFERROR(IF(C4=0,"-",C98/C4),"-") | D99: =IFERROR(IF(D4=0,"-",D98/D4),"-") | E99: =IFERROR(IF(E4=0,"-",E98/E4),"-") | F99: =IFERROR(IF(F4=0,"-",F98/F4),"-") | G99: =IFERROR(IF(G4=0,"-",G98/G4),"-") | H99: - | I99: =IFERROR(IF(I4=0,"-",I98/I4),"-")

Sheet Милый дом
A1: ПланФакт | B1: Создано с помощью сервиса ПланФакт | I1: =HYPERLINK("https://app.planfact.io/?from=Pf_BDR", "Перейти в сервис")
B2: Итого | C2: июнь` 26 | D2: июль` 26 | E2: август` 26 | F2: сентябрь` 26 | G2: октябрь` 26 | H2: ноябрь` 26 | I2: декабрь` 26
A3: Милый дом | B3: план | C3: план | D3: план | E3: план | F3: план | G3: план | H3: план | I3: план
A4: Выручка | B4: 2451750.6 | C4: =SUM(C5,C6) | D4: =SUM(D5,D6) | E4: =SUM(E5,E6) | F4: =SUM(F5,F6) | G4: =SUM(G5,G6) | H4: - | I4: =SUM(I5,I6)
A5: Нераспределенный доход | B5: - | C5: - | D5: - | E5: - | F5: - | G5: - | H5: - | I5: -
A6: Выручка | B6: 2451750.6 | C6: =SUM(C7,C8,C9) | D6: =SUM(D7,D8,D9) | E6: =SUM(E7,E8,E9) | F6: =SUM(F7,F8,F9) | G6: =SUM(G7,G8,G9) | H6: - | I6: =SUM(I7,I8,I9)
A7: Реализация услуг Клининг (ОД) | B7: 2451750.6 | C7: 373920.6 | D7: 692610 | E7: 692610 | F7: 692610 | G7: - | H7: - | I7: -
A8: Реализация услуг Клининг (Доп.услуги) | B8: - | C8: - | D8: - | E8: - | F8: - | G8: - | H8: - | I8: -
A9: Реализация услуг Клининг (снег) | B9: - | C9: - | D9: - | E9: - | F9: - | G9: - | H9: - | I9: -
A10: Прямые расходы | B10: 1028537.7 | C10: =SUM(C11,C12,C13,C21,C22,C23,C24,C25,C26,C27,C28,C29,C30,C31,C32,C33,C34) | D10: =SUM(D11,D12,D13,D21,D22,D23,D24,D25,D26,D27,D28,D29,D30,D31,D32,D33,D34) | E10: =SUM(E11,E12,E13,E21,E22,E23,E24,E25,E26,E27,E28,E29,E30,E31,E32,E33,E34) | F10: =SUM(F11,F12,F13,F21,F22,F23,F24,F25,F26,F27,F28,F29,F30,F31,F32,F33,F34) | G10: =SUM(G11,G12,G13,G21,G22,G23,G24,G25,G26,G27,G28,G29,G30,G31,G32,G33,G34) | H10: - | I10: =SUM(I11,I12,I13,I21,I22,I23,I24,I25,I26,I27,I28,I29,I30,I31,I32,I33,I34)
A11: Нераспределенный расход | B11: - | C11: - | D11: - | E11: - | F11: - | G11: - | H11: - | I11: -
A12: Транспортные расходы | B12: - | C12: - | D12: - | E12: - | F12: - | G12: - | H12: - | I12: -
A13: Переменные | B13: 170000 | C13: =SUM(C14,C15,C16,C17,C18,C19,C20) | D13: =SUM(D14,D15,D16,D17,D18,D19,D20) | E13: =SUM(E14,E15,E16,E17,E18,E19,E20) | F13: =SUM(F14,F15,F16,F17,F18,F19,F20) | G13: =SUM(G14,G15,G16,G17,G18,G19,G20) | H13: - | I13: =SUM(I14,I15,I16,I17,I18,I19,I20)
A14: Услуги техниги для уборки снега (ПТ) | B14: - | C14: - | D14: - | E14: - | F14: - | G14: - | H14: - | I14: -
A15: Услуги садовника (ПТ) | B15: - | C15: - | D15: - | E15: - | F15: - | G15: - | H15: - | I15: -
A16: Сыпучие материалы (ПТ) | B16: - | C16: - | D16: - | E16: - | F16: - | G16: - | H16: - | I16: -
A17: Расходные материалы и инстументы (МОП) | B17: 120000 | C17: - | D17: 40000 | E17: 40000 | F17: 40000 | G17: - | H17: - | I17: -
A18: Расходные материалы и инстументы (ПТ) | B18: 20000 | C18: 5000 | D18: 5000 | E18: 5000 | F18: 5000 | G18: - | H18: - | I18: -
A19: Арена оборудования (ПТ) | B19: - | C19: - | D19: - | E19: - | F19: - | G19: - | H19: - | I19: -
A20: Арена оборудования (МОП) | B20: 30000 | C20: 30000 | D20: - | E20: - | F20: - | G20: - | H20: - | I20: -
A21: Заработная плата (МОП) | B21: 200000 | C21: 50000 | D21: 50000 | E21: 50000 | F21: 50000 | G21: - | H21: - | I21: -
A22: Заработная плата (ПТ) | B22: 452500 | C22: 62500 | D22: 130000 | E22: 130000 | F22: 130000 | G22: - | H22: - | I22: -
A23: Налоги с ФОТ (МОП) | B23: 45037.68 | C23: 3037.68 | D23: 14000 | E23: 14000 | F23: 14000 | G23: - | H23: - | I23: -
A24: Налоги с ФОТ (ПТ) | B24: - | C24: - | D24: - | E24: - | F24: - | G24: - | H24: - | I24: -
A25: Премми (МОП) | B25: - | C25: - | D25: - | E25: - | F25: - | G25: - | H25: - | I25: -
A26: Премми (ПТ) | B26: - | C26: - | D26: - | E26: - | F26: - | G26: - | H26: - | I26: -
A27: Униформа (МОП) | B27: - | C27: - | D27: - | E27: - | F27: - | G27: - | H27: - | I27: -
A28: Униформа (ПТ) | B28: - | C28: - | D28: - | E28: - | F28: - | G28: - | H28: - | I28: -
A29: Ремонт оборудования (МОП) | B29: - | C29: - | D29: - | E29: - | F29: - | G29: - | H29: - | I29: -
A30: Ремонт оборудования (ПТ) | B30: - | C30: - | D30: - | E30: - | F30: - | G30: - | H30: - | I30: -
A31: Вывоз мусора | B31: - | C31: - | D31: - | E31: - | F31: - | G31: - | H31: - | I31: -
A32: Штрафы, пени, неустойки | B32: - | C32: - | D32: - | E32: - | F32: - | G32: - | H32: - | I32: -
A33: Расходы к удержанию | B33: - | C33: - | D33: - | E33: - | F33: - | G33: - | H33: - | I33: -
A34: Общехозяйственные | B34: 161000 | C34: =SUM(C35,C36,C37,C38,C39,C40,C41,C42) | D34: =SUM(D35,D36,D37,D38,D39,D40,D41,D42) | E34: =SUM(E35,E36,E37,E38,E39,E40,E41,E42) | F34: =SUM(F35,F36,F37,F38,F39,F40,F41,F42) | G34: =SUM(G35,G36,G37,G38,G39,G40,G41,G42) | H34: - | I34: =SUM(I35,I36,I37,I38,I39,I40,I41,I42)
A35: Аутсорс (направления) | B35: - | C35: - | D35: - | E35: - | F35: - | G35: - | H35: - | I35: -
A36: Заработная плата МО АУП | B36: 120000 | C36: 30000 | D36: 30000 | E36: 30000 | F36: 30000 | G36: - | H36: - | I36: -
A37: Инструменты: ГСМ | B37: - | C37: - | D37: - | E37: - | F37: - | G37: - | H37: - | I37: -
A38: Медосмотры | B38: - | C38: - | D38: - | E38: - | F38: - | G38: - | H38: - | I38: -
A39: Налоги с ФОТ (ИП) | B39: 39500 | C39: 3500 | D39: 12000 | E39: 12000 | F39: 12000 | G39: - | H39: - | I39: -
A40: Приобритение мебели, бытовой техники | B40: - | C40: - | D40: - | E40: - | F40: - | G40: - | H40: - | I40: -
A41: Комиссия за перевод ЗП | B41: 1500 | C41: - | D41: 500 | E41: 500 | F41: 500 | G41: - | H41: - | I41: -
A42: Аренда квартиры (включая коммуналку) | B42: - | C42: - | D42: - | E42: - | F42: - | G42: - | H42: - | I42: -
A43: Валовая прибыль | B43: 1423212.9 | C43: =C4-C10 | D43: =D4-D10 | E43: =E4-E10 | F43: =F4-F10 | G43: =G4-G10 | H43: - | I43: =I4-I10
A44: Валовая рентабельность | B44: 58.05% | C44: =IFERROR(IF(C4=0,"-",C43/C4),"-") | D44: =IFERROR(IF(D4=0,"-",D43/D4),"-") | E44: =IFERROR(IF(E4=0,"-",E43/E4),"-") | F44: =IFERROR(IF(F4=0,"-",F43/F4),"-") | G44: =IFERROR(IF(G4=0,"-",G43/G4),"-") | H44: - | I44: =IFERROR(IF(I4=0,"-",I43/I4),"-")
A45: Косвенные расходы | B45: - | C45: =SUM(C46,C47,C48,C52,C56,C57,C58,C59,C60,C63,C64,C65,C66,C67,C68,C69,C70,C71,C72,C73,C74,C75,C76,C77,C78,C79) | D45: =SUM(D46,D47,D48,D52,D56,D57,D58,D59,D60,D63,D64,D65,D66,D67,D68,D69,D70,D71,D72,D73,D74,D75,D76,D77,D78,D79) | E45: =SUM(E46,E47,E48,E52,E56,E57,E58,E59,E60,E63,E64,E65,E66,E67,E68,E69,E70,E71,E72,E73,E74,E75,E76,E77,E78,E79) | F45: =SUM(F46,F47,F48,F52,F56,F57,F58,F59,F60,F63,F64,F65,F66,F67,F68,F69,F70,F71,F72,F73,F74,F75,F76,F77,F78,F79) | G45: =SUM(G46,G47,G48,G52,G56,G57,G58,G59,G60,G63,G64,G65,G66,G67,G68,G69,G70,G71,G72,G73,G74,G75,G76,G77,G78,G79) | H45: - | I45: =SUM(I46,I47,I48,I52,I56,I57,I58,I59,I60,I63,I64,I65,I66,I67,I68,I69,I70,I71,I72,I73,I74,I75,I76,I77,I78,I79)
A46: Расход БЭК-ОФИС | B46: - | C46: - | D46: - | E46: - | F46: - | G46: - | H46: - | I46: -
A47: Расходы на бэк-офис | B47: - | C47: - | D47: - | E47: - | F47: - | G47: - | H47: - | I47: -
A48: Автомобиль | B48: - | C48: =SUM(C49,C50,C51) | D48: =SUM(D49,D50,D51) | E48: =SUM(E49,E50,E51) | F48: =SUM(F49,F50,F51) | G48: =SUM(G49,G50,G51) | H48: - | I48: =SUM(I49,I50,I51)
A49: Автомобиль: ГСМ | B49: - | C49: - | D49: - | E49: - | F49: - | G49: - | H49: - | I49: -
A50: Автомобиль: страхование | B50: - | C50: - | D50: - | E50: - | F50: - | G50: - | H50: - | I50: -
A51: Автомобиль: ТО | B51: - | C51: - | D51: - | E51: - | F51: - | G51: - | H51: - | I51: -
A52: Офисные расходы | B52: - | C52: =SUM(C53,C54,C55) | D52: =SUM(D53,D54,D55) | E52: =SUM(E53,E54,E55) | F52: =SUM(F53,F54,F55) | G52: =SUM(G53,G54,G55) | H52: - | I52: =SUM(I53,I54,I55)
A53: Аренда офиса | B53: - | C53: - | D53: - | E53: - | F53: - | G53: - | H53: - | I53: -
A54: Канцелярия и обслуживание | B54: - | C54: - | D54: - | E54: - | F54: - | G54: - | H54: - | I54: -
A55: Интернет и связь | B55: - | C55: - | D55: - | E55: - | F55: - | G55: - | H55: - | I55: -
A56: Банковские услуги | B56: - | C56: - | D56: - | E56: - | F56: - | G56: - | H56: - | I56: -
A57: Заработная плата АУП (БО) | B57: - | C57: - | D57: - | E57: - | F57: - | G57: - | H57: - | I57: -
A58: Заработная плата бухгалтерии (БО) | B58: - | C58: - | D58: - | E58: - | F58: - | G58: - | H58: - | I58: -
A59: Заработная плата СБ (БО) | B59: - | C59: - | D59: - | E59: - | F59: - | G59: - | H59: - | I59: -
A60: Командировочные расходы | B60: - | C60: =SUM(C61,C62) | D60: =SUM(D61,D62) | E60: =SUM(E61,E62) | F60: =SUM(F61,F62) | G60: =SUM(G61,G62) | H60: - | I60: =SUM(I61,I62)
A61: Командировнчеы расходы: билеты (БО) | B61: - | C61: - | D61: - | E61: - | F61: - | G61: - | H61: - | I61: -
A62: Командировнчеы расходы: проживание (БО) | B62: - | C62: - | D62: - | E62: - | F62: - | G62: - | H62: - | I62: -
A63: Комиссия УК ДОМ | B63: - | C63: - | D63: - | E63: - | F63: - | G63: - | H63: - | I63: -
A64: Налоги с ФОТ (ИП)_БО | B64: - | C64: - | D64: - | E64: - | F64: - | G64: - | H64: - | I64: -
A65: Налоги с ФОТ (НДФЛ) БО | B65: - | C65: - | D65: - | E65: - | F65: - | G65: - | H65: - | I65: -
A66: Налоги с ФОТ (страховые взносы) БО | B66: - | C66: - | D66: - | E66: - | F66: - | G66: - | H66: - | I66: -
A67: Нотариальные услуги | B67: - | C67: - | D67: - | E67: - | F67: - | G67: - | H67: - | I67: -
A68: Обслуживание техники (БО) | B68: - | C68: - | D68: - | E68: - | F68: - | G68: - | H68: - | I68: -
A69: Программное обеспечение (БО) | B69: - | C69: - | D69: - | E69: - | F69: - | G69: - | H69: - | I69: -
A70: ПланФакт | B70: - | C70: - | D70: - | E70: - | F70: - | G70: - | H70: - | I70: -
A71: ТБ | B71: - | C71: - | D71: - | E71: - | F71: - | G71: - | H71: - | I71: -
A72: Контур | B72: - | C72: - | D72: - | E72: - | F72: - | G72: - | H72: - | I72: -
... A79: HR (аутсорс) | B79: - | C79: - | D79: - | E79: - | F79: - | G79: - | H79: - | I79: -
A80: Операционная прибыль | B80: 1423212.9 | C80: =C43-C45 | D80: =D43-D45 | E80: =E43-E45 | F80: =F43-F45 | G80: =G43-G45 | H80: - | I80: =I43-I45
A81: Операционная рентабельность | B81: 58.05% | C81: =IFERROR(IF(C4=0,"-",C80/C4),"-") | D81: =IFERROR(IF(D4=0,"-",D80/D4),"-") | E81: =IFERROR(IF(E4=0,"-",E80/E4),"-") | F81: =IFERROR(IF(F4=0,"-",F80/F4),"-") | G81: =IFERROR(IF(G4=0,"-",G80/G4),"-") | H81: - | I81: =IFERROR(IF(I4=0,"-",I80/I4),"-")
A82: Прочие доходы | B82: - | C82: =SUM(C83,C84,C85,C86) | D82: =SUM(D83,D84,D85,D86) | E82: =SUM(E83,E84,E85,E86) | F82: =SUM(F83,F84,F85,F86) | G82: =SUM(G83,G84,G85,G86) | H82: - | I82: =SUM(I83,I84,I85,I86)
A83: Доход БЭК-ОФИС | B83: - | C83: - | D83: - | E83: - | F83: - | G83: - | H83: - | I83: -
A84: Пополненин бэк-офис | B84: - | C84: - | D84: - | E84: - | F84: - | G84: - | H84: - | I84: -
A85: Проценты по вкладам | B85: - | C85: - | D85: - | E85: - | F85: - | G85: - | H85: - | I85: -
A86: Курсовая разница (+) | B86: - | C86: - | D86: - | E86: - | F86: - | G86: - | H86: - | I86: -
A87: Прочие расходы | B87: - | C87: =SUM(C88) | D87: =SUM(D88) | E87: =SUM(E88) | F87: =SUM(F88) | G87: =SUM(G88) | H87: - | I87: =SUM(I88)
A88: Курсовая разница (-) | B88: - | C88: - | D88: - | E88: - | F88: - | G88: - | H88: - | I88: -
A89: EBITDA | B89: 1423212.9 | C89: =C80+IFERROR(C82*1,0)-IFERROR(C87*1,0) | D89: =D80+IFERROR(D82*1,0)-IFERROR(D87*1,0) | E89: =E80+IFERROR(E82*1,0)-IFERROR(E87*1,0) | F89: =F80+IFERROR(F82*1,0)-IFERROR(F87*1,0) | G89: =G80+IFERROR(G82*1,0)-IFERROR(G87*1,0) | H89: - | I89: =I80+IFERROR(I82*1,0)-IFERROR(I87*1,0)
A90: Рентабельность по EBITDA | B90: 58.05% | C90: =IFERROR(IF(C4=0,"-",C89/C4),"-") | D90: =IFERROR(IF(D4=0,"-",D89/D4),"-") | E90: =IFERROR(IF(E4=0,"-",E89/E4),"-") | F90: =IFERROR(IF(F4=0,"-",F89/F4),"-") | G90: =IFERROR(IF(G4=0,"-",G89/G4),"-") | H90: - | I90: =IFERROR(IF(I4=0,"-",I89/I4),"-")
A91: Амортизация | B91: 225000 | C91: =SUM(C92,C93) | D91: =SUM(D92,D93) | E91: =SUM(E92,E93) | F91: =SUM(F92,F93) | G91: =SUM(G92,G93) | H91: - | I91: =SUM(I92,I93)
A92: Амортизация ОС (ПТ) | B92: - | C92: - | D92: - | E92: - | F92: - | G92: - | H92: - | I92: -
A93: Амортизация ОС (МОП) | B93: 225000 | C93: - | D93: 225000 | E93: - | F93: - | G93: - | H93: - | I93: -
A94: Проценты по кредитам и займам | B94: - | C94: - | D94: - | E94: - | F94: - | G94: - | H94: - | I94: -
A95: Налог на прибыль | B95: 158595.74 | C95: =SUM(C96,C97) | D95: =SUM(D96,D97) | E95: =SUM(E96,E97) | F95: =SUM(F96,F97) | G95: =SUM(G96,G97) | H95: - | I95: =SUM(I96,I97)
A96: Налоги УСН | B96: 36900 | C96: 5700 | D96: 10400 | E96: 10400 | F96: 10400 | G96: - | H96: - | I96: -
A97: Налоги НДС 5% | B97: 121695.74 | C97: 17805.74 | D97: 34630 | E97: 34630 | F97: 34630 | G97: - | H97: - | I97: -
A98: Чистая прибыль (убыток) | B98: 1039617.2 | C98: =IFERROR(C89*1,0)-IFERROR(C91*1,0)-IFERROR(C94*1,0)-IFERROR(C95*1,0) | D98: =IFERROR(D89*1,0)-IFERROR(D91*1,0)-IFERROR(D94*1,0)-IFERROR(D95*1,0) | E98: =IFERROR(E89*1,0)-IFERROR(E91*1,0)-IFERROR(E94*1,0)-IFERROR(E95*1,0) | F98: =IFERROR(F89*1,0)-IFERROR(F91*1,0)-IFERROR(F94*1,0)-IFERROR(F95*1,0) | G98: =IFERROR(G89*1,0)-IFERROR(G91*1,0)-IFERROR(G94*1,0)-IFERROR(G95*1,0) | H98: - | I98: =IFERROR(I89*1,0)-IFERROR(I91*1,0)-IFERROR(I94*1,0)-IFERROR(I95*1,0)
A99: Рентабельность чистой прибыли | B99: 42.40% | C99: =IFERROR(IF(C4=0,"-",C98/C4),"-") | D99: =IFERROR(IF(D4=0,"-",D98/D4),"-") | E99: =IFERROR(IF(E4=0,"-",E98/E4),"-") | F99: =IFERROR(IF(F4=0,"-",F98/F4),"-") | G99: =IFERROR(IF(G4=0,"-",G98/G4),"-") | H99: - | I99: =IFERROR(IF(I4=0,"-",I98/I4),"-")

Sheet River Park
A1: ПланФакт | B1: Создано с помощью сервиса ПланФакт | I1: =HYPERLINK("https://app.planfact.io/?from=Pf_BDR", "Перейти в сервис")
B2: Итого | C2: июнь` 26 | D2: июль` 26 | E2: август` 26 | F2: сентябрь` 26 | G2: октябрь` 26 | H2: ноябрь` 26 | I2: декабрь` 26
A3: River Park | B3: план | C3: план | D3: план | E3: план | F3: план | G3: план | H3: план | I3: план
A4: Выручка | B4: 2539080 | C4: =SUM(C5,C6) | D4: =SUM(D5,D6) | E4: =SUM(E5,E6) | F4: =SUM(F5,F6) | G4: =SUM(G5,G6) | H4: - | I4: =SUM(I5,I6)
A5: Нераспределенный доход | B5: - | C5: - | D5: - | E5: - | F5: - | G5: - | H5: - | I5: -
A6: Выручка | B6: 2539080 | C6: =SUM(C7,C8,C9) | D6: =SUM(D7,D8,D9) | E6: =SUM(E7,E8,E9) | F6: =SUM(F7,F8,F9) | G6: =SUM(G7,G8,G9) | H6: - | I6: =SUM(I7,I8,I9)
A7: Реализация услуг Клининг (ОД) | B7: 2539080 | C7: 846360 | D7: 846360 | E7: 846360 | F7: - | G7: - | H7: - | I7: -
A8: Реализация услуг Клининг (Доп.услуги) | B8: - | C8: - | D8: - | E8: - | F8: - | G8: - | H8: - | I8: -
A9: Реализация услуг Клининг (снег) | B9: - | C9: - | D9: - | E9: - | F9: - | G9: - | H9: - | I9: -
A10: Прямые расходы | B10: 2088109.4 | C10: =SUM(C11,C12,C13,C21,C22,C23,C24,C25,C26,C27,C28,C29,C30,C31,C32,C33,C34) | D10: =SUM(D11,D12,D13,D21,D22,D23,D24,D25,D26,D27,D28,D29,D30,D31,D32,D33,D34) | E10: =SUM(E11,E12,E13,E21,E22,E23,E24,E25,E26,E27,E28,E29,E30,E31,E32,E33,E34) | F10: =SUM(F11,F12,F13,F21,F22,F23,F24,F25,F26,F27,F28,F29,F30,F31,F32,F33,F34) | G10: =SUM(G11,G12,G13,G21,G22,G23,G24,G25,G26,G27,G28,G29,G30,G31,G32,G33,G34) | H10: - | I10: =SUM(I11,I12,I13,I21,I22,I23,I24,I25,I26,I27,I28,I29,I30,I31,I32,I33,I34)
A11: Нераспределенный расход | B11: - | C11: - | D11: - | E11: - | F11: - | G11: - | H11: - | I11: -
A12: Транспортные расходы | B12: 10352 | C12: 10352 | D12: - | E12: - | F12: - | G12: - | H12: - | I12: -
A13: Переменные | B13: 50717.39 | C13: =SUM(C14,C15,C16,C17,C18,C19,C20) | D13: =SUM(D14,D15,D16,D17,D18,D19,D20) | E13: =SUM(E14,E15,E16,E17,E18,E19,E20) | F13: =SUM(F14,F15,F16,F17,F18,F19,F20) | G13: =SUM(G14,G15,G16,G17,G18,G19,G20) | H13: - | I13: =SUM(I14,I15,I16,I17,I18,I19,I20)
A14: Услуги техниги для уборки снега (ПТ) | B14: - | C14: - | D14: - | E14: - | F14: - | G14: - | H14: - | I14: -
A15: Услуги садовника (ПТ) | B15: - | C15: - | D15: - | E15: - | F15: - | G15: - | H15: - | I15: -
A16: Сыпучие материалы (ПТ) | B16: - | C16: - | D16: - | E16: - | F16: - | G16: - | H16: - | I16: -
A17: Расходные материалы и инстументы (МОП) | B17: 32073.9 | C17: 22073.9 | D17: 5000 | E17: 5000 | F17: - | G17: - | H17: - | I17: -
A18: Расходные материалы и инстументы (ПТ) | B18: 18643.49 | C18: 8643.49 | D18: 5000 | E18: 5000 | F18: - | G18: - | H18: - | I18: -
A19: Арена оборудования (ПТ) | B19: - | C19: - | D19: - | E19: - | F19: - | G19: - | H19: - | I19: -
A20: Арена оборудования (МОП) | B20: - | C20: - | D20: - | E20: - | F20: - | G20: - | H20: - | I20: -
A21: Заработная плата (МОП) | B21: 820000 | C21: 260000 | D21: 280000 | E21: 280000 | F21: - | G21: - | H21: - | I21: -
A22: Заработная плата (ПТ) | B22: 810000 | C22: 270000 | D22: 270000 | E22: 270000 | F22: - | G22: - | H22: - | I22: -
A23: Налоги с ФОТ (МОП) | B23: - | C23: - | D23: - | E23: - | F23: - | G23: - | H23: - | I23: -
A24: Налоги с ФОТ (ПТ) | B24: - | C24: - | D24: - | E24: - | F24: - | G24: - | H24: - | I24: -
A25: Премми (МОП) | B25: - | C25: - | D25: - | E25: - | F25: - | G25: - | H25: - | I25: -
A26: Премми (ПТ) | B26: - | C26: - | D26: - | E26: - | F26: - | G26: - | H26: - | I26: -
A27: Униформа (МОП) | B27: - | C27: - | D27: - | E27: - | F27: - | G27: - | H27: - | I27: -
A28: Униформа (ПТ) | B28: - | C28: - | D28: - | E28: - | F28: - | G28: - | H28: - | I28: -
A29: Ремонт оборудования (МОП) | B29: - | C29: - | D29: - | E29: - | F29: - | G29: - | H29: - | I29: -
A30: Ремонт оборудования (ПТ) | B30: 8000 | C30: 2000 | D30: 3000 | E30: 3000 | F30: - | G30: - | H30: - | I30: -
A31: Вывоз мусора | B31: 7920 | C31: 7920 | D31: - | E31: - | F31: - | G31: - | H31: - | I31: -
A32: Штрафы, пени, неустойки | B32: - | C32: - | D32: - | E32: - | F32: - | G32: - | H32: - | I32: -
A33: Расходы к удержанию | B33: - | C33: - | D33: - | E33: - | F33: - | G33: - | H33: - | I33: -
A34: Общехозяйственные | B34: 381120 | C34: =SUM(C35,C36,C37,C38,C39,C40,C41,C42) | D34: =SUM(D35,D36,D37,D38,D39,D40,D41,D42) | E34: =SUM(E35,E36,E37,E38,E39,E40,E41,E42) | F34: =SUM(F35,F36,F37,F38,F39,F40,F41,F42) | G34: =SUM(G35,G36,G37,G38,G39,G40,G41,G42) | H34: - | I34: =SUM(I35,I36,I37,I38,I39,I40,I41,I42)
A35: Аутсорс (направления) | B35: 12500 | C35: 7500 | D35: 2500 | E35: 2500 | F35: - | G35: - | H35: - | I35: -
A36: Заработная плата МО АУП | B36: 195000 | C36: 65000 | D36: 65000 | E36: 65000 | F36: - | G36: - | H36: - | I36: -
A37: Инструменты: ГСМ | B37: 8620 | C37: 2620 | D37: 3000 | E37: 3000 | F37: - | G37: - | H37: - | I37: -
A38: Медосмотры | B38: - | C38: - | D38: - | E38: - | F38: - | G38: - | H38: - | I38: -
A39: Налоги с ФОТ (ИП) | B39: 159000 | C39: 53000 | D39: 53000 | E39: 53000 | F39: - | G39: - | H39: - | I39: -
A40: Приобритение мебели, бытовой техники | B40: - | C40: - | D40: - | E40: - | F40: - | G40: - | H40: - | I40: -
A41: Комиссия за перевод ЗП | B41: 6000 | C41: 2000 | D41: 2000 | E41: 2000 | F41: - | G41: - | H41: - | I41: -
A42: Аренда квартиры (включая коммуналку) | B42: - | C42: - | D42: - | E42: - | F42: - | G42: - | H42: - | I42: -
A43: Валовая прибыль | B43: 450970.61 | C43: =C4-C10 | D43: =D4-D10 | E43: =E4-E10 | F43: =F4-F10 | G43: =G4-G10 | H43: - | I43: =I4-I10
A44: Валовая рентабельность | B44: 17.76% | C44: =IFERROR(IF(C4=0,"-",C43/C4),"-") | D44: =IFERROR(IF(D4=0,"-",D43/D4),"-") | E44: =IFERROR(IF(E4=0,"-",E43/E4),"-") | F44: =IFERROR(IF(F4=0,"-",F43/F4),"-") | G44: =IFERROR(IF(G4=0,"-",G43/G4),"-") | H44: - | I44: =IFERROR(IF(I4=0,"-",I43/I4),"-")
A45: Косвенные расходы | B45: - | C45: =SUM(C46,C47,C48,C52,C56,C57,C58,C59,C60,C63,C64,C65,C66,C67,C68,C69,C70,C71,C72,C73,C74,C75,C76,C77,C78,C79) | D45: =SUM(D46,D47,D48,D52,D56,D57,D58,D59,D60,D63,D64,D65,D66,D67,D68,D69,D70,D71,D72,D73,D74,D75,D76,D77,D78,D79) | E45: =SUM(E46,E47,E48,E52,E56,E57,E58,E59,E60,E63,E64,E65,E66,E67,E68,E69,E70,E71,E72,E73,E74,E75,E76,E77,E78,E79) | F45: =SUM(F46,F47,F48,F52,F56,F57,F58,F59,F60,F63,F64,F65,F66,F67,F68,F69,F70,F71,F72,F73,F74,F75,F76,F77,F78,F79) | G45: =SUM(G46,G47,G48,G52,G56,G57,G58,G59,G60,G63,G64,G65,G66,G67,G68,G69,G70,G71,G72,G73,G74,G75,G76,G77,G78,G79) | H45: - | I45: =SUM(I46,I47,I48,I52,I56,I57,I58,I59,I60,I63,I64,I65,I66,I67,I68,I69,I70,I71,I72,I73,I74,I75,I76,I77,I78,I79)
A46: Расход БЭК-ОФИС | B46: - | C46: - | D46: - | E46: - | F46: - | G46: - | H46: - | I46: -
A47: Расходы на бэк-офис | B47: - | C47: - | D47: - | E47: - | F47: - | G47: - | H47: - | I47: -
A48: Автомобиль | B48: - | C48: =SUM(C49,C50,C51) | D48: =SUM(D49,D50,D51) | E48: =SUM(E49,E50,E51) | F48: =SUM(F49,F50,F51) | G48: =SUM(G49,G50,G51) | H48: - | I48: =SUM(I49,I50,I51)
A49: Автомобиль: ГСМ | B49: - | C49: - | D49: - | E49: - | F49: - | G49: - | H49: - | I49: -
A50: Автомобиль: страхование | B50: - | C50: - | D50: - | E50: - | F50: - | G50: - | H50: - | I50: -
A51: Автомобиль: ТО | B51: - | C51: - | D51: - | E51: - | F51: - | G51: - | H51: - | I51: -
A52: Офисные расходы | B52: - | C52: =SUM(C53,C54,C55) | D52: =SUM(D53,D54,D55) | E52: =SUM(E53,E54,E55) | F52: =SUM(F53,F54,F55) | G52: =SUM(G53,G54,G55) | H52: - | I52: =SUM(I53,I54,I55)
A53: Аренда офиса | B53: - | C53: - | D53: - | E53: - | F53: - | G53: - | H53: - | I53: -
A54: Канцелярия и обслуживание | B54: - | C54: - | D54: - | E54: - | F54: - | G54: - | H54: - | I54: -
A55: Интернет и связь | B55: - | C55: - | D55: - | E55: - | F55: - | G55: - | H55: - | I55: -
A56: Банковские услуги | B56: - | C56: - | D56: - | E56: - | F56: - | G56: - | H56: - | I56: -
A57: Заработная плата АУП (БО) | B57: - | C57: - | D57: - | E57: - | F57: - | G57: - | H57: - | I57: -
A58: Заработная плата бухгалтерии (БО) | B58: - | C58: - | D58: - | E58: - | F58: - | G58: - | H58: - | I58: -
A59: Заработная плата СБ (БО) | B59: - | C59: - | D59: - | E59: - | F59: - | G59: - | H59: - | I59: -
A60: Командировочные расходы | B60: - | C60: =SUM(C61,C62) | D60: =SUM(D61,D62) | E60: =SUM(E61,E62) | F60: =SUM(F61,F62) | G60: =SUM(G61,G62) | H60: - | I60: =SUM(I61,I62)
A61: Командировнчеы расходы: билеты (БО) | B61: - | C61: - | D61: - | E61: - | F61: - | G61: - | H61: - | I61: -
A62: Командировнчеы расходы: проживание (БО) | B62: - | C62: - | D62: - | E62: - | F62: - | G62: - | H62: - | I62: -
A63: Комиссия УК ДОМ | B63: - | C63: - | D63: - | E63: - | F63: - | G63: - | H63: - | I63: -
A64: Налоги с ФОТ (ИП)_БО | B64: - | C64: - | D64: - | E64: - | F64: - | G64: - | H64: - | I64: -
A65: Налоги с ФОТ (НДФЛ) БО | B65: - | C65: - | D65: - | E65: - | F65: - | G65: - | H65: - | I65: -
A66: Налоги с ФОТ (страховые взносы) БО | B66: - | C66: - | D66: - | E66: - | F66: - | G66: - | H66: - | I66: -
A67: Нотариальные услуги | B67: - | C67: - | D67: - | E67: - | F67: - | G67: - | H67: - | I67: -
A68: Обслуживание техники (БО) | B68: - | C68: - | D68: - | E68: - | F68: - | G68: - | H68: - | I68: -
A69: Программное обеспечение (БО) | B69: - | C69: - | D69: - | E69: - | F69: - | G69: - | H69: - | I69: -
A70: ПланФакт | B70: - | C70: - | D70: - | E70: - | F70: - | G70: - | H70: - | I70: -
A71: ТБ | B71: - | C71: - | D71: - | E71: - | F71: - | G71: - | H71: - | I71: -
A72: Контур | B72: - | C72: - | D72: - | E72: - | F72: - | G72: - | H72: - | I72: -
... A79: HR (аутсорс) | B79: - | C79: - | D79: - | E79: - | F79: - | G79: - | H79: - | I79: -
A80: Операционная прибыль | B80: 450970.61 | C80: =C43-C45 | D80: =D43-D45 | E80: =E43-E45 | F80: =F43-F45 | G80: =G43-G45 | H80: - | I80: =I43-I45
A81: Операционная рентабельность | B81: 17.76% | C81: =IFERROR(IF(C4=0,"-",C80/C4),"-") | D81: =IFERROR(IF(D4=0,"-",D80/D4),"-") | E81: =IFERROR(IF(E4=0,"-",E80/E4),"-") | F81: =IFERROR(IF(F4=0,"-",F80/F4),"-") | G81: =IFERROR(IF(G4=0,"-",G80/G4),"-") | H81: - | I81: =IFERROR(IF(I4=0,"-",I80/I4),"-")
A82: Прочие доходы | B82: - | C82: =SUM(C83,C84,C85,C86) | D82: =SUM(D83,D84,D85,D86) | E82: =SUM(E83,E84,E85,E86) | F82: =SUM(F83,F84,F85,F86) | G82: =SUM(G83,G84,G85,G86) | H82: - | I82: =SUM(I83,I84,I85,I86)
A83: Доход БЭК-ОФИС | B83: - | C83: - | D83: - | E83: - | F83: - | G83: - | H83: - | I83: -
A84: Пополненин бэк-офис | B84: - | C84: - | D84: - | E84: - | F84: - | G84: - | H84: - | I84: -
A85: Проценты по вкладам | B85: - | C85: - | D85: - | E85: - | F85: - | G85: - | H85: - | I85: -
A86: Курсовая разница (+) | B86: - | C86: - | D86: - | E86: - | F86: - | G86: - | H86: - | I86: -
A87: Прочие расходы | B87: - | C87: =SUM(C88) | D87: =SUM(D88) | E87: =SUM(E88) | F87: =SUM(F88) | G87: =SUM(G88) | H87: - | I87: =SUM(I88)
A88: Курсовая разница (-) | B88: - | C88: - | D88: - | E88: - | F88: - | G88: - | H88: - | I88: -
A89: EBITDA | B89: 450970.61 | C89: =C80+IFERROR(C82*1,0)-IFERROR(C87*1,0) | D89: =D80+IFERROR(D82*1,0)-IFERROR(D87*1,0) | E89: =E80+IFERROR(E82*1,0)-IFERROR(E87*1,0) | F89: =F80+IFERROR(F82*1,0)-IFERROR(F87*1,0) | G89: =G80+IFERROR(G82*1,0)-IFERROR(G87*1,0) | H89: - | I89: =I80+IFERROR(I82*1,0)-IFERROR(I87*1,0)
A90: Рентабельность по EBITDA | B90: 17.76% | C90: =IFERROR(IF(C4=0,"-",C89/C4),"-") | D90: =IFERROR(IF(D4=0,"-",D89/D4),"-") | E90: =IFERROR(IF(E4=0,"-",E89/E4),"-") | F90: =IFERROR(IF(F4=0,"-",F89/F4),"-") | G90: =IFERROR(IF(G4=0,"-",G89/G4),"-") | H90: - | I90: =IFERROR(IF(I4=0,"-",I89/I4),"-")
A91: Амортизация | B91: - | C91: =SUM(C92,C93) | D91: =SUM(D92,D93) | E91: =SUM(E92,E93) | F91: =SUM(F92,F93) | G91: =SUM(G92,G93) | H91: - | I91: =SUM(I92,I93)
A92: Амортизация ОС (ПТ) | B92: - | C92: - | D92: - | E92: - | F92: - | G92: - | H92: - | I92: -
A93: Амортизация ОС (МОП) | B93: - | C93: - | D93: - | E93: - | F93: - | G93: - | H93: - | I93: -
A94: Проценты по кредитам и займам | B94: - | C94: - | D94: - | E94: - | F94: - | G94: - | H94: - | I94: -
A95: Налог на прибыль | B95: 192000 | C95: =SUM(C96,C97) | D95: =SUM(D96,D97) | E95: =SUM(E96,E97) | F95: =SUM(F96,F97) | G95: =SUM(G96,G97) | H95: - | I95: =SUM(I96,I97)
A96: Налоги УСН | B96: 36000 | C96: 12000 | D96: 12000 | E96: 12000 | F96: - | G96: - | H96: - | I96: -
A97: Налоги НДС 5% | B97: 156000 | C97: 52000 | D97: 52000 | E97: 52000 | F97: - | G97: - | H97: - | I97: -
A98: Чистая прибыль (убыток) | B98: 258970.61 | C98: =IFERROR(C89*1,0)-IFERROR(C91*1,0)-IFERROR(C94*1,0)-IFERROR(C95*1,0) | D98: =IFERROR(D89*1,0)-IFERROR(D91*1,0)-IFERROR(D94*1,0)-IFERROR(D95*1,0) | E98: =IFERROR(E89*1,0)-IFERROR(E91*1,0)-IFERROR(E94*1,0)-IFERROR(E95*1,0) | F98: =IFERROR(F89*1,0)-IFERROR(F91*1,0)-IFERROR(F94*1,0)-IFERROR(F95*1,0) | G98: =IFERROR(G89*1,0)-IFERROR(G91*1,0)-IFERROR(G94*1,0)-IFERROR(G95*1,0) | H98: - | I98: =IFERROR(I89*1,0)-IFERROR(I91*1,0)-IFERROR(I94*1,0)-IFERROR(I95*1,0)
A99: Рентабельность чистой прибыли | B99: 10.20% | C99: =IFERROR(IF(C4=0,"-",C98/C4),"-") | D99: =IFERROR(IF(D4=0,"-",D98/D4),"-") | E99: =IFERROR(IF(E4=0,"-",E98/E4),"-") | F99: =IFERROR(IF(F4=0,"-",F98/F4),"-") | G99: =IFERROR(IF(G4=0,"-",G98/G4),"-") | H99: - | I99: =IFERROR(IF(I4=0,"-",I98/I4),"-")
